Workbook

Sheet 00 Dashboard
A1: TheEduAssist SEO Operations Dashboard
A2: Professional team workspace | Canonical site: https://www.theeduassist.com/ | Update task and performance tabs, not this dashboard.
A4: Work Queue | E4: Performance Snapshot | I4: This Week's Operating Rules
A5: Open tasks | B5: =COUNTIFS('01 Task Board'!$A$5:$A$304,"<>",'01 Task Board'!$J$5:$J$304,"<>Done") -> 14 | E5: Latest organic traffic | F5: =IFERROR(LOOKUP(2,1/('05 Performance'!$A$5:$A$104<>""),'05 Performance'!$B$5:$B$104),0) -> 3900 | I5: 1 | J5: Every task must have an owner, due date and evidence link.
A6: Critical open tasks | B6: =COUNTIFS('01 Task Board'!$A$5:$A$304,"<>",'01 Task Board'!$H$5:$H$304,"Critical",'01 Task Board'!$J$5:$J$304,"<>Done") -> 4 | E6: Latest organic keywords | F6: =IFERROR(LOOKUP(2,1/('05 Performance'!$A$5:$A$104<>""),'05 Performance'!$C$5:$C$104),0) -> 201 | I6: 2 | J6: Use www.theeduassist.com URLs in all active tabs.
A7: Overdue tasks | B7: =COUNTIFS('01 Task Board'!$A$5:$A$304,"<>",'01 Task Board'!$R$5:$R$304,"Overdue") -> 14 | E7: Latest authority score | F7: =IFERROR(LOOKUP(2,1/('05 Performance'!$A$5:$A$104<>""),'05 Performance'!$D$5:$D$104),0) -> 8 | I7: 3 | J7: Do not create or chase irrelevant backlinks just because authority is high.
A8: Open technical issues | B8: =COUNTIFS('04 Technical Issues'!$A$5:$A$204,"<>",'04 Technical Issues'!$K$5:$K$204,"<>Resolved") -> 9 | E8: Latest referring domains | F8: =IFERROR(LOOKUP(2,1/('05 Performance'!$A$5:$A$104<>""),'05 Performance'!$E$5:$E$104),0) -> 0 | I8: 4 | J8: Track clicks, impressions, leads and conversions, not rankings alone.
A9: Content items published | B9: =COUNTIFS('03 Content Pipeline'!$A$5:$A$204,"<>",'03 Content Pipeline'!$J$5:$J$204,"Published") -> 6 | E9: Latest GSC clicks | F9: =IFERROR(LOOKUP(2,1/('05 Performance'!$A$5:$A$104<>""),'05 Performance'!$L$5:$L$104),0) -> 0 | I9: 5 | J9: Mark old workbook findings as Needs Revalidation before acting.
E10: Latest organic leads | F10: =IFERROR(LOOKUP(2,1/('05 Performance'!$A$5:$A$104<>""),'05 Performance'!$Q$5:$Q$104),0) -> 0 | I10: 6 | J10: AR/VR legacy ideas are archived and excluded from the active SEO plan.
E11: Latest conversion rate | F11: =IFERROR(LOOKUP(2,1/('05 Performance'!$A$5:$A$104<>""),'05 Performance'!$R$5:$R$104),0) -> 0
A13: Priority Focus
A14: Priority | B14: Workstream | C14: Action | D14: Why it matters | E14: Owner | F14: Due | G14: Status | H14: Evidence | I14: QA | J14: Expected result | K14: Impact | L14: Notes
A15: P1 | B15: Technical | C15: Validate www canonical, redirect chain and sitemap URLs | D15: Prevents duplicate/canonical confusion | E15: Developer | G15: Not Started | I15: SEO Manager | J15: Only canonical URLs index | K15: High
A16: P1 | B16: Technical | C16: Revalidate legacy 404 case-study URLs and homepage links | D16: Removes broken user journeys and crawl waste | E16: Developer | G16: Not Started | I16: QA | J16: No broken featured-project links | K16: High
A17: P1 | B17: Content | C17: Map each important service page to one primary keyword | D17: Stops keyword cannibalization and speeds briefs | E17: SEO Manager | G17: Not Started | I17: Content Lead | J17: Clear keyword-to-page ownership | K17: High
A18: P2 | B18: Reporting | C18: Add GSC and GA4 leads/conversions to weekly reporting | D18: Connects SEO activity to business outcomes | E18: SEO Manager | G18: Not Started | I18: Management | J18: Lead-focused SEO decisions | K18: High

Sheet 01 Task Board
A1: SEO Daily Task Board
A2: One source of truth for daily work. Add every SEO action here, attach evidence, then send it through QA.
A4: Task ID | B4: Date Added | C4: Due Date | D4: Frequency | E4: Workstream | F4: Task | G4: Page / URL | H4: Priority | I4: Owner | J4: Status | K4: Dependency / Blocker | L4: Evidence / Work Link | M4: Result / Notes | N4: QA Owner | O4: QA Status | P4: Completed Date | Q4: Days Open | R4: SLA
A5: SEO-001 | B5: 46230 | C5: 46232 | D5: One-time | E5: Technical SEO | F5: Validate canonical, redirect and sitemap consistency for www domain | G5: https://www.theeduassist.com/ | H5: Critical | I5: Developer | J5: Not Started | N5: SEO Manager | O5: Not Reviewed | Q5: =IF(B5="","",IF(J5="Done",IF(P5="","",P5-B5),TODAY()-B5)) -> 62 | R5: =IF(B5="","",IF(J5="Done","Closed",IF(C5="","No due date",IF(C5<TODAY(),"Overdue",IF(C5-TODAY()<=2,"Due soon","On track"))))) -> Overdue
A6: SEO-002 | B6: 46230 | C6: 46233 | D6: One-time | E6: Technical SEO | F6: Revalidate legacy 404 case-study URLs and remove any broken homepage links | G6: https://www.theeduassist.com/ | H6: Critical | I6: Developer | J6: Not Started | N6: QA | O6: Not Reviewed | Q6: =IF(B6="","",IF(J6="Done",IF(P6="","",P6-B6),TODAY()-B6)) -> 62 | R6: =IF(B6="","",IF(J6="Done","Closed",IF(C6="","No due date",IF(C6<TODAY(),"Overdue",IF(C6-TODAY()<=2,"Due soon","On track"))))) -> Overdue
A7: SEO-003 | B7: 46230 | C7: 46234 | D7: One-time | E7: On-page SEO | F7: Review Contact page H1, title, meta, Organization/ContactPage schema, internal links and conversion tracking | G7: https://www.theeduassist.com/contact/ | H7: High | I7: SEO Manager | J7: Not Started | N7: QA | O7: Not Reviewed | Q7: =IF(B7="","",IF(J7="Done",IF(P7="","",P7-B7),TODAY()-B7)) -> 62 | R7: =IF(B7="","",IF(J7="Done","Closed",IF(C7="","No due date",IF(C7<TODAY(),"Overdue",IF(C7-TODAY()<=2,"Due soon","On track"))))) -> Overdue
A8: SEO-004 | B8: 46230 | C8: 46235 | D8: One-time | E8: On-page SEO | F8: Review About page for company story, team proof, credentials, internal links and CTA | G8: https://www.theeduassist.com/about/ | H8: High | I8: Content Lead | J8: Not Started | N8: SEO Manager | O8: Not Reviewed | Q8: =IF(B8="","",IF(J8="Done",IF(P8="","",P8-B8),TODAY()-B8)) -> 62 | R8: =IF(B8="","",IF(J8="Done","Closed",IF(C8="","No due date",IF(C8<TODAY(),"Overdue",IF(C8-TODAY()<=2,"Due soon","On track"))))) -> Overdue
A9: SEO-005 | B9: 46230 | C9: 46236 | D9: Weekly | E9: Search Console | F9: Export query and page data; flag high-impression low-CTR opportunities | G9: https://search.google.com/search-console/ | H9: High | I9: SEO Manager | J9: Not Started | N9: Management | O9: Not Reviewed | Q9: =IF(B9="","",IF(J9="Done",IF(P9="","",P9-B9),TODAY()-B9)) -> 62 | R9: =IF(B9="","",IF(J9="Done","Closed",IF(C9="","No due date",IF(C9<TODAY(),"Overdue",IF(C9-TODAY()<=2,"Due soon","On track"))))) -> Overdue
A10: SEO-006 | B10: 46230 | C10: 46236 | D10: Weekly | E10: Content SEO | F10: Map unmapped primary keywords to service or pillar pages | G10: See 02 Keyword Map | H10: High | I10: SEO Manager | J10: Not Started | N10: Content Lead | O10: Not Reviewed | Q10: =IF(B10="","",IF(J10="Done",IF(P10="","",P10-B10),TODAY()-B10)) -> 62 | R10: =IF(B10="","",IF(J10="Done","Closed",IF(C10="","No due date",IF(C10<TODAY(),"Overdue",IF(C10-TODAY()<=2,"Due soon","On track"))))) -> Overdue
A11: SEO-007 | B11: 46230 | C11: 46237 | D11: Weekly | E11: Internal Linking | F11: Add contextual links from new/updated articles to relevant service and case-study pages | G11: See 03 Content Pipeline | H11: Medium | I11: Content Writer | J11: Not Started | N11: SEO Manager | O11: Not Reviewed | Q11: =IF(B11="","",IF(J11="Done",IF(P11="","",P11-B11),TODAY()-B11)) -> 62 | R11: =IF(B11="","",IF(J11="Done","Closed",IF(C11="","No due date",IF(C11<TODAY(),"Overdue",IF(C11-TODAY()<=2,"Due soon","On track"))))) -> Overdue
A12: SEO-008 | B12: 46230 | C12: 46237 | D12: Weekly | E12: Technical SEO | F12: Review coverage/indexing, Core Web Vitals and enhancement reports | G12: Search Console / PageSpeed | H12: High | I12: SEO Manager | J12: Not Started | N12: Developer | O12: Not Reviewed | Q12: =IF(B12="","",IF(J12="Done",IF(P12="","",P12-B12),TODAY()-B12)) -> 62 | R12: =IF(B12="","",IF(J12="Done","Closed",IF(C12="","No due date",IF(C12<TODAY(),"Overdue",IF(C12-TODAY()<=2,"Due soon","On track"))))) -> Overdue
A13: SEO-009 | B13: 46230 | C13: 46238 | D13: Weekly | E13: AI Visibility | F13: Check priority questions in Google AI features, ChatGPT, Gemini and Perplexity | G13: See 08 AI Visibility | H13: Medium | I13: SEO Manager | J13: Not Started | N13: Content Lead | O13: Not Reviewed | Q13: =IF(B13="","",IF(J13="Done",IF(P13="","",P13-B13),TODAY()-B13)) -> 62 | R13: =IF(B13="","",IF(J13="Done","Closed",IF(C13="","No due date",IF(C13<TODAY(),"Overdue",IF(C13-TODAY()<=2,"Due soon","On track"))))) -> Overdue
A14: SEO-010 | B14: 46230 | C14: 46238 | D14: Weekly | E14: Backlinks | F14: Qualify 20 relevant link opportunities; reject irrelevant/high-risk domains | G14: See 07 Link Opportunities | H14: Medium | I14: Outreach | J14: Not Started | N14: SEO Manager | O14: Not Reviewed | Q14: =IF(B14="","",IF(J14="Done",IF(P14="","",P14-B14),TODAY()-B14)) -> 62 | R14: =IF(B14="","",IF(J14="Done","Closed",IF(C14="","No due date",IF(C14<TODAY(),"Overdue",IF(C14-TODAY()<=2,"Due soon","On track"))))) -> Overdue
A15: SEO-011 | B15: 46230 | C15: 46239 | D15: Monthly | E15: Reporting | F15: Update organic traffic, keywords, GSC metrics, leads, conversion rate and CWV | G15: See 05 Performance | H15: Critical | I15: SEO Manager | J15: Not Started | N15: Management | O15: Not Reviewed | Q15: =IF(B15="","",IF(J15="Done",IF(P15="","",P15-B15),TODAY()-B15)) -> 62 | R15: =IF(B15="","",IF(J15="Done","Closed",IF(C15="","No due date",IF(C15<TODAY(),"Overdue",IF(C15-TODAY()<=2,"Due soon","On track"))))) -> Overdue
A16: SEO-012 | B16: 46230 | C16: 46239 | D16: One-time | E16: Content Governance | F16: Remove AR/VR items from active content and keyword planning; retain only in archive | G16: See raw archive tabs | H16: High | I16: SEO Manager | J16: Done | L16: Workbook redesign | M16: Deprecated scope removed | N16: Management | O16: Approved | P16: 46230 | Q16: =IF(B16="","",IF(J16="Done",IF(P16="","",P16-B16),TODAY()-B16)) -> 0 | R16: =IF(B16="","",IF(J16="Done","Closed",IF(C16="","No due date",IF(C16<TODAY(),"Overdue",IF(C16-TODAY()<=2,"Due soon","On track"))))) -> Closed
A17: SEO-013 | B17: 46230 | C17: 46240 | D17: One-time | E17: Backlinks | F17: Clean existing backlink list into relevant, realistic and policy-safe opportunities | G17: See 07 Link Opportunities | H17: High | I17: Outreach | J17: In Progress | N17: SEO Manager | O17: Not Reviewed | Q17: =IF(B17="","",IF(J17="Done",IF(P17="","",P17-B17),TODAY()-B17)) -> 62 | R17: =IF(B17="","",IF(J17="Done","Closed",IF(C17="","No due date",IF(C17<TODAY(),"Overdue",IF(C17-TODAY()<=2,"Due soon","On track"))))) -> Overdue
A18: SEO-014 | B18: 46230 | C18: 46240 | D18: One-time | E18: Analytics | F18: Confirm GA4 key events for review form, contact form and consultation/RFP submissions | G18: GA4 | H18: Critical | I18: Developer | J18: Not Started | N18: SEO Manager | O18: Not Reviewed | Q18: =IF(B18="","",IF(J18="Done",IF(P18="","",P18-B18),TODAY()-B18)) -> 62 | R18: =IF(B18="","",IF(J18="Done","Closed",IF(C18="","No due date",IF(C18<TODAY(),"Overdue",IF(C18-TODAY()<=2,"Due soon","On track"))))) -> Overdue
A19: SEO-015 | B19: 46230 | C19: 46241 | D19: One-time | E19: Schema | F19: Validate Organization, Service, Article, Breadcrumb and applicable FAQ markup | G19: Rich Results Test | H19: High | I19: Developer | J19: Not Started | N19: SEO Manager | O19: Not Reviewed | Q19: =IF(B19="","",IF(J19="Done",IF(P19="","",P19-B19),TODAY()-B19)) -> 62 | R19: =IF(B19="","",IF(J19="Done","Closed",IF(C19="","No due date",IF(C19<TODAY(),"Overdue",IF(C19-TODAY()<=2,"Due soon","On track"))))) -> Overdue
Q20: =IF(B20="","",IF(J20="Done",IF(P20="","",P20-B20),TODAY()-B20)) | R20: =IF(B20="","",IF(J20="Done","Closed",IF(C20="","No due date",IF(C20<TODAY(),"Overdue",IF(C20-TODAY()<=2,"Due soon","On track")))))
Q21: =IF(B21="","",IF(J21="Done",IF(P21="","",P21-B21),TODAY()-B21)) | R21: =IF(B21="","",IF(J21="Done","Closed",IF(C21="","No due date",IF(C21<TODAY(),"Overdue",IF(C21-TODAY()<=2,"Due soon","On track")))))
Q22: =IF(B22="","",IF(J22="Done",IF(P22="","",P22-B22),TODAY()-B22)) | R22: =IF(B22="","",IF(J22="Done","Closed",IF(C22="","No due date",IF(C22<TODAY(),"Overdue",IF(C22-TODAY()<=2,"Due soon","On track")))))
Q23: =IF(B23="","",IF(J23="Done",IF(P23="","",P23-B23),TODAY()-B23)) | R23: =IF(B23="","",IF(J23="Done","Closed",IF(C23="","No due date",IF(C23<TODAY(),"Overdue",IF(C23-TODAY()<=2,"Due soon","On track")))))
Q24: =IF(B24="","",IF(J24="Done",IF(P24="","",P24-B24),TODAY()-B24)) | R24: =IF(B24="","",IF(J24="Done","Closed",IF(C24="","No due date",IF(C24<TODAY(),"Overdue",IF(C24-TODAY()<=2,"Due soon","On track")))))
Q25: =IF(B25="","",IF(J25="Done",IF(P25="","",P25-B25),TODAY()-B25)) | R25: =IF(B25="","",IF(J25="Done","Closed",IF(C25="","No due date",IF(C25<TODAY(),"Overdue",IF(C25-TODAY()<=2,"Due soon","On track")))))
Q26: =IF(B26="","",IF(J26="Done",IF(P26="","",P26-B26),TODAY()-B26)) | R26: =IF(B26="","",IF(J26="Done","Closed",IF(C26="","No due date",IF(C26<TODAY(),"Overdue",IF(C26-TODAY()<=2,"Due soon","On track")))))
Q27: =IF(B27="","",IF(J27="Done",IF(P27="","",P27-B27),TODAY()-B27)) | R27: =IF(B27="","",IF(J27="Done","Closed",IF(C27="","No due date",IF(C27<TODAY(),"Overdue",IF(C27-TODAY()<=2,"Due soon","On track")))))
Q28: =IF(B28="","",IF(J28="Done",IF(P28="","",P28-B28),TODAY()-B28)) | R28: =IF(B28="","",IF(J28="Done","Closed",IF(C28="","No due date",IF(C28<TODAY(),"Overdue",IF(C28-TODAY()<=2,"Due soon","On track")))))
Q29: =IF(B29="","",IF(J29="Done",IF(P29="","",P29-B29),TODAY()-B29)) | R29: =IF(B29="","",IF(J29="Done","Closed",IF(C29="","No due date",IF(C29<TODAY(),"Overdue",IF(C29-TODAY()<=2,"Due soon","On track")))))
Q30: =IF(B30="","",IF(J30="Done",IF(P30="","",P30-B30),TODAY()-B30)) | R30: =IF(B30="","",IF(J30="Done","Closed",IF(C30="","No due date",IF(C30<TODAY(),"Overdue",IF(C30-TODAY()<=2,"Due soon","On track")))))
Q31: =IF(B31="","",IF(J31="Done",IF(P31="","",P31-B31),TODAY()-B31)) | R31: =IF(B31="","",IF(J31="Done","Closed",IF(C31="","No due date",IF(C31<TODAY(),"Overdue",IF(C31-TODAY()<=2,"Due soon","On track")))))
... Q304: =IF(B304="","",IF(J304="Done",IF(P304="","",P304-B304),TODAY()-B304)) | R304: =IF(B304="","",IF(J304="Done","Closed",IF(C304="","No due date",IF(C304<TODAY(),"Overdue",IF(C304-TODAY()<=2,"Due soon","On track")))))

Sheet 02 Keyword Map
A1: Keyword-to-Page Map
A2: Use one primary keyword per page, group close variants, and avoid assigning the same intent to multiple pages.
A4: Keyword ID | B4: Keyword | C4: Local Volume | D4: Global Volume | E4: KD | F4: Intent | G4: Cluster / Service | H4: Target Page | I4: Page Type | J4: Keyword Role | K4: Current URL | L4: Mapping Status | M4: Owner | N4: Opportunity Score | O4: Suggested Title / Brief | P4: Meta Description | Q4: Source | R4: Last Reviewed | S4: Next Action | T4: Notes
A5: KW-001 | B5: designing an online course | C5: 90 | D5: 1900 | E5: 22 | F5: Informational | G5: How We Build High-Impact Online Courses | H5: How We Build High-Impact Online Courses | I5: Service / Pillar | J5: Secondary Keyword | L5: Mapped | M5: SEO Manager | N5: =IF(OR(C5="",E5=""),"",ROUND((C5/(E5+1))*IF(ISNUMBER(SEARCH("Commercial",F5)),1.25,1),1)) -> 3.9 | O5: How to build a course that actually gets results | P5: Build a course that actually gets results with our proven guide. Learn to design lessons that work. Start creating your high-impact program today. | Q5: Kajabi Service Page keywords | R5: 46230 | S5: Confirm current canonical URL and search intent
A6: KW-002 | B6: online course design best practices | C6: 40 | D6: 110 | E6: 23 | F6: Commercial | G6: How We Build High-Impact Online Courses | H6: How We Build High-Impact Online Courses | I6: Service / Pillar | J6: Secondary Keyword | L6: Mapped | M6: SEO Manager | N6: =IF(OR(C6="",E6=""),"",ROUND((C6/(E6+1))*IF(ISNUMBER(SEARCH("Commercial",F6)),1.25,1),1)) -> 2.1 | Q6: Kajabi Service Page keywords | R6: 46230 | S6: Confirm current canonical URL and search intent
A7: KW-003 | B7: online course launch | C7: 40 | D7: 70 | E7: 15 | F7: Informational | G7: How We Build High-Impact Online Courses | H7: How We Build High-Impact Online Courses | I7: Service / Pillar | J7: Secondary Keyword | L7: Mapped | M7: SEO Manager | N7: =IF(OR(C7="",E7=""),"",ROUND((C7/(E7+1))*IF(ISNUMBER(SEARCH("Commercial",F7)),1.25,1),1)) -> 2.5 | Q7: Kajabi Service Page keywords | R7: 46230 | S7: Confirm current canonical URL and search intent
A8: KW-004 | B8: how to create elearning courses | C8: 50 | D8: 160 | E8: 18 | F8: Informational | G8: How We Build High-Impact Online Courses | H8: How We Build High-Impact Online Courses | I8: Service / Pillar | J8: Secondary Keyword | L8: Mapped | M8: SEO Manager | N8: =IF(OR(C8="",E8=""),"",ROUND((C8/(E8+1))*IF(ISNUMBER(SEARCH("Commercial",F8)),1.25,1),1)) -> 2.6 | Q8: Kajabi Service Page keywords | R8: 46230 | S8: Confirm current canonical URL and search intent
A9: KW-005 | B9: building elearning courses | C9: 70 | D9: 240 | E9: 15 | F9: Informational | G9: How We Build High-Impact Online Courses | H9: How We Build High-Impact Online Courses | I9: Service / Pillar | J9: Secondary Keyword | L9: Mapped | M9: SEO Manager | N9: =IF(OR(C9="",E9=""),"",ROUND((C9/(E9+1))*IF(ISNUMBER(SEARCH("Commercial",F9)),1.25,1),1)) -> 4.4 | Q9: Kajabi Service Page keywords | R9: 46230 | S9: Confirm current canonical URL and search intent
A10: KW-006 | B10: how to make training interactive | C10: 30 | D10: 70 | E10: 18 | F10: Informational | G10: How We Build High-Impact Online Courses | H10: How We Build High-Impact Online Courses | I10: Service / Pillar | J10: Secondary Keyword | L10: Mapped | M10: SEO Manager | N10: =IF(OR(C10="",E10=""),"",ROUND((C10/(E10+1))*IF(ISNUMBER(SEARCH("Commercial",F10)),1.25,1),1)) -> 1.6 | Q10: Kajabi Service Page keywords | R10: 46230 | S10: Confirm current canonical URL and search intent
A11: KW-007 | B11: done for you course creation | C11: 70 | D11: 140 | E11: 7 | F11: Informational | G11: How We Build High-Impact Online Courses | H11: How We Build High-Impact Online Courses | I11: Service / Pillar | J11: Secondary Keyword | L11: Mapped | M11: SEO Manager | N11: =IF(OR(C11="",E11=""),"",ROUND((C11/(E11+1))*IF(ISNUMBER(SEARCH("Commercial",F11)),1.25,1),1)) -> 8.8 | Q11: Kajabi Service Page keywords | R11: 46230 | S11: Confirm current canonical URL and search intent
A12: KW-008 | B12: how to create and sell online courses | C12: 90 | D12: 220 | E12: 32 | F12: Informational | G12: How We Build High-Impact Online Courses | H12: How We Build High-Impact Online Courses | I12: Service / Pillar | J12: Secondary Keyword | L12: Mapped | M12: SEO Manager | N12: =IF(OR(C12="",E12=""),"",ROUND((C12/(E12+1))*IF(ISNUMBER(SEARCH("Commercial",F12)),1.25,1),1)) -> 2.7 | Q12: Kajabi Service Page keywords | R12: 46230 | S12: Confirm current canonical URL and search intent
A13: KW-009 | B13: how to create an online course pdf | C13: 70 | D13: 170 | E13: 0 | F13: Informational | G13: How We Build High-Impact Online Courses | H13: How We Build High-Impact Online Courses | I13: Service / Pillar | J13: Secondary Keyword | L13: Mapped | M13: SEO Manager | N13: =IF(OR(C13="",E13=""),"",ROUND((C13/(E13+1))*IF(ISNUMBER(SEARCH("Commercial",F13)),1.25,1),1)) -> 70 | Q13: Kajabi Service Page keywords | R13: 46230 | S13: Confirm current canonical URL and search intent
A14: KW-010 | B14: how to create an online course that sells | C14: 70 | D14: 270 | E14: 25 | F14: Commercial | G14: How We Build High-Impact Online Courses | H14: How We Build High-Impact Online Courses | I14: Service / Pillar | J14: Primary Keyword | L14: Mapped | M14: SEO Manager | N14: =IF(OR(C14="",E14=""),"",ROUND((C14/(E14+1))*IF(ISNUMBER(SEARCH("Commercial",F14)),1.25,1),1)) -> 3.4 | Q14: Kajabi Service Page keywords | R14: 46230 | S14: Confirm current canonical URL and search intent
A15: KW-011 | B15: best selling online courses | C15: 40 | D15: 230 | E15: 27 | F15: Informational | G15: How We Build High-Impact Online Courses | H15: How We Build High-Impact Online Courses | I15: Service / Pillar | J15: Secondary Keyword | L15: Mapped | M15: SEO Manager | N15: =IF(OR(C15="",E15=""),"",ROUND((C15/(E15+1))*IF(ISNUMBER(SEARCH("Commercial",F15)),1.25,1),1)) -> 1.4 | Q15: Kajabi Service Page keywords | R15: 46230 | S15: Confirm current canonical URL and search intent
A16: KW-012 | B16: best platform to create and sell online courses | C16: 30 | D16: 100 | G16: How We Build High-Impact Online Courses | H16: How We Build High-Impact Online Courses | I16: Service / Pillar | J16: Secondary Keyword | L16: Mapped | M16: SEO Manager | N16: =IF(OR(C16="",E16=""),"",ROUND((C16/(E16+1))*IF(ISNUMBER(SEARCH("Commercial",F16)),1.25,1),1)) | Q16: Kajabi Service Page keywords | R16: 46230 | S16: Confirm current canonical URL and search intent
A17: KW-013 | B17: how to create a course to sell | C17: 90 | D17: 250 | E17: 30 | F17: Informational | G17: How We Build High-Impact Online Courses | H17: How We Build High-Impact Online Courses | I17: Service / Pillar | J17: Secondary Keyword | L17: Mapped | M17: SEO Manager | N17: =IF(OR(C17="",E17=""),"",ROUND((C17/(E17+1))*IF(ISNUMBER(SEARCH("Commercial",F17)),1.25,1),1)) -> 2.9 | Q17: Kajabi Service Page keywords | R17: 46230 | S17: Confirm current canonical URL and search intent
A18: KW-014 | B18: online training delivery methods | C18: 40 | D18: 70 | E18: 4 | F18: Informational | G18: How We Deliver course | H18: How We Deliver course | I18: Service / Pillar | J18: Secondary Keyword | L18: Mapped | M18: SEO Manager | N18: =IF(OR(C18="",E18=""),"",ROUND((C18/(E18+1))*IF(ISNUMBER(SEARCH("Commercial",F18)),1.25,1),1)) -> 8 | O18: How We Deliver Professional Courses With Speed and Precision | P18: Get courses delivered with precision and speed. We handle the hard work so you don't have to. See how our professional team gets it done right. Learn more now. | Q18: Kajabi Service Page keywords | R18: 46230 | S18: Confirm current canonical URL and search intent
A19: KW-015 | B19: e-learning delivery methods | C19: 50 | D19: 80 | E19: 1 | F19: Commercial+Informational | I19: Unmapped | J19: Secondary Keyword | L19: Needs Mapping | M19: SEO Manager | N19: =IF(OR(C19="",E19=""),"",ROUND((C19/(E19+1))*IF(ISNUMBER(SEARCH("Commercial",F19)),1.25,1),1)) -> 31.3 | Q19: Kajabi Service Page keywords | R19: 46230 | S19: Assign to a suitable existing or new page
A20: KW-016 | B20: best service delivery courses | C20: 0 | D20: 10 | F20: Informational | I20: Unmapped | J20: Secondary Keyword | L20: Needs Mapping | M20: SEO Manager | N20: =IF(OR(C20="",E20=""),"",ROUND((C20/(E20+1))*IF(ISNUMBER(SEARCH("Commercial",F20)),1.25,1),1)) | Q20: Kajabi Service Page keywords | R20: 46230 | S20: Assign to a suitable existing or new page
A21: KW-017 | B21: deliver a course | C21: 0 | D21: 140 | E21: 9 | F21: Informational | I21: Unmapped | J21: Secondary Keyword | L21: Needs Mapping | M21: SEO Manager | N21: =IF(OR(C21="",E21=""),"",ROUND((C21/(E21+1))*IF(ISNUMBER(SEARCH("Commercial",F21)),1.25,1),1)) -> 0 | Q21: Kajabi Service Page keywords | R21: 46230 | S21: Assign to a suitable existing or new page
A22: KW-018 | B22: elearning delivery | C22: 70 | D22: 110 | E22: 6 | F22: Informational | I22: Unmapped | J22: Secondary Keyword | L22: Needs Mapping | M22: SEO Manager | N22: =IF(OR(C22="",E22=""),"",ROUND((C22/(E22+1))*IF(ISNUMBER(SEARCH("Commercial",F22)),1.25,1),1)) -> 10 | Q22: Kajabi Service Page keywords | R22: 46230 | S22: Assign to a suitable existing or new page
A23: KW-019 | B23: KEYWORD | F23: INTENT | G23: WORD TYPE | H23: WORD TYPE | I23: Service / Pillar | J23: Title | L23: Mapped | M23: SEO Manager | N23: =IF(OR(C23="",E23=""),"",ROUND((C23/(E23+1))*IF(ISNUMBER(SEARCH("Commercial",F23)),1.25,1),1)) | O23: Description | P23: Linking page | Q23: Kajabi Service Page keywords | R23: 46230 | S23: Confirm current canonical URL and search intent
A24: KW-020 | B24: kajabi online course platform | C24: 18100 | D24: 18100 | E24: 28 | F24: Informational | G24: Secondary Keyword | H24: Secondary Keyword | I24: Service / Pillar | J24: Secondary Keyword | L24: Mapped | M24: SEO Manager | N24: =IF(OR(C24="",E24=""),"",ROUND((C24/(E24+1))*IF(ISNUMBER(SEARCH("Commercial",F24)),1.25,1),1)) -> 624.1 | Q24: Kajabi Service Page keywords | R24: 46230 | S24: Confirm current canonical URL and search intent
A25: KW-021 | B25: kajabi online courses | C25: 90 | D25: 310 | F25: Informational | G25: Secondary Keyword | H25: Secondary Keyword | I25: Service / Pillar | J25: Expert Kajabi Course Setup to Scale Your Business-theEduAssist | L25: Mapped | M25: SEO Manager | N25: =IF(OR(C25="",E25=""),"",ROUND((C25/(E25+1))*IF(ISNUMBER(SEARCH("Commercial",F25)),1.25,1),1)) | O25: Scale your business with pro Kajabi course setup. theEduAssist handles the tech so you can teach. Book your setup call and launch your offer now. | P25: https://theeduassist.com/blog/7-powerful-kajabi-course-creation-services/ | Q25: Kajabi Service Page keywords | R25: 46230 | S25: Confirm current canonical URL and search intent
A26: KW-022 | B26: kajabi online course setup | F26: Informational | G26: Secondary Keyword | H26: Secondary Keyword | I26: Service / Pillar | J26: Secondary Keyword | L26: Mapped | M26: SEO Manager | N26: =IF(OR(C26="",E26=""),"",ROUND((C26/(E26+1))*IF(ISNUMBER(SEARCH("Commercial",F26)),1.25,1),1)) | P26: https://theeduassist.com/blog/kajabi-online-course-setup/ | Q26: Kajabi Service Page keywords | R26: 46230 | S26: Confirm current canonical URL and search intent
A27: KW-023 | B27: setup online course kajabi | F27: Informational | G27: Secondary Keyword | H27: Secondary Keyword | I27: Service / Pillar | J27: Secondary Keyword | L27: Mapped | M27: SEO Manager | N27: =IF(OR(C27="",E27=""),"",ROUND((C27/(E27+1))*IF(ISNUMBER(SEARCH("Commercial",F27)),1.25,1),1)) | P27: https://theeduassist.com/blog/kajabi-course-design-explained-how-to-create-online-course-in-2026/ | Q27: Kajabi Service Page keywords | R27: 46230 | S27: Confirm current canonical URL and search intent
A28: KW-024 | B28: kajabi course setup | F28: Informational | G28: Secondary Keyword | H28: Secondary Keyword | I28: Service / Pillar | J28: Secondary Keyword | L28: Mapped | M28: SEO Manager | N28: =IF(OR(C28="",E28=""),"",ROUND((C28/(E28+1))*IF(ISNUMBER(SEARCH("Commercial",F28)),1.25,1),1)) | P28: https://theeduassist.com/blog/kajabi-course-design/ | Q28: Kajabi Service Page keywords | R28: 46230 | S28: Confirm current canonical URL and search intent
A29: KW-025 | B29: online course setup | C29: 20 | D29: 90 | F29: Informational | G29: Secondary Keyword | H29: Secondary Keyword | I29: Service / Pillar | J29: Secondary Keyword | L29: Mapped | M29: SEO Manager | N29: =IF(OR(C29="",E29=""),"",ROUND((C29/(E29+1))*IF(ISNUMBER(SEARCH("Commercial",F29)),1.25,1),1)) | P29: https://theeduassist.com/blog/kajabi-drip-course-setup/ | Q29: Kajabi Service Page keywords | R29: 46230 | S29: Confirm current canonical URL and search intent
A30: KW-026 | B30: how to create a course on kajabi | C30: 30 | D30: 30 | F30: Informational | G30: Secondary Keyword | H30: Secondary Keyword | I30: Service / Pillar | J30: Secondary Keyword | L30: Mapped | M30: SEO Manager | N30: =IF(OR(C30="",E30=""),"",ROUND((C30/(E30+1))*IF(ISNUMBER(SEARCH("Commercial",F30)),1.25,1),1)) | Q30: Kajabi Service Page keywords | R30: 46230 | S30: Confirm current canonical URL and search intent
A31: KW-027 | B31: how to create a course in kajabi | C31: 20 | D31: 100 | F31: Informational | G31: Secondary Keyword | H31: Secondary Keyword | I31: Service / Pillar | J31: Secondary Keyword | L31: Mapped | M31: SEO Manager | N31: =IF(OR(C31="",E31=""),"",ROUND((C31/(E31+1))*IF(ISNUMBER(SEARCH("Commercial",F31)),1.25,1),1)) | Q31: Kajabi Service Page keywords | R31: 46230 | S31: Confirm current canonical URL and search intent
A32: KW-028 | B32: how to create a kajabi course | C32: 20 | D32: 30 | F32: Informational | G32: Secondary Keyword | H32: Secondary Keyword | I32: Service / Pillar | J32: Secondary Keyword | L32: Mapped | M32: SEO Manager | N32: =IF(OR(C32="",E32=""),"",ROUND((C32/(E32+1))*IF(ISNUMBER(SEARCH("Commercial",F32)),1.25,1),1)) | Q32: Kajabi Service Page keywords | R32: 46230 | S32: Confirm current canonical URL and search intent
A33: KW-029 | B33: Kajabi Course Setup Service | G33: Primary Keyword | H33: Primary Keyword | I33: Service / Pillar | J33: Secondary Keyword | L33: Mapped | M33: SEO Manager | N33: =IF(OR(C33="",E33=""),"",ROUND((C33/(E33+1))*IF(ISNUMBER(SEARCH("Commercial",F33)),1.25,1),1)) | Q33: Kajabi Service Page keywords | R33: 46230 | S33: Confirm current canonical URL and search intent
A34: KW-030 | B34: Kajabi services | C34: 40 | D34: 70 | E34: 31 | F34: Navigational | G34: Secondary Keyword | H34: Secondary Keyword | I34: Service / Pillar | J34: Secondary Keyword | L34: Mapped | M34: SEO Manager | N34: =IF(OR(C34="",E34=""),"",ROUND((C34/(E34+1))*IF(ISNUMBER(SEARCH("Commercial",F34)),1.25,1),1)) -> 1.3 | Q34: Kajabi Service Page keywords | R34: 46230 | S34: Confirm current canonical URL and search intent
A35: KW-031 | B35: kajabi funnels | C35: 20 | D35: 220 | F35: Informational | G35: Primary Keyword | H35: Primary Keyword | I35: Service / Pillar | J35: Expert Kajabi Website & Funnel Setup for More Sales | L35: Mapped | M35: SEO Manager | N35: =IF(OR(C35="",E35=""),"",ROUND((C35/(E35+1))*IF(ISNUMBER(SEARCH("Commercial",F35)),1.25,1),1)) | O35: Your Kajabi site should work for you. We build high-converting funnels that boost your revenue. Book your setup call now. | P35: https://theeduassist.com/blog/kajabi-website-funnel-services/ | Q35: Kajabi Service Page keywords | R35: 46230 | S35: Confirm current canonical URL and search intent
A36: KW-032 | B36: kajabi website | C36: 390 | D36: 820 | E36: 21 | F36: Navigational | G36: Primary Keyword | H36: Primary Keyword | I36: Service / Pillar | J36: Secondary Keyword | L36: Mapped | M36: SEO Manager | N36: =IF(OR(C36="",E36=""),"",ROUND((C36/(E36+1))*IF(ISNUMBER(SEARCH("Commercial",F36)),1.25,1),1)) -> 17.7 | P36: https://theeduassist.com/blog/kajabi-website-funnel-services/ | Q36: Kajabi Service Page keywords | R36: 46230 | S36: Confirm current canonical URL and search intent
A37: KW-033 | B37: kajabi website expert | C37: 70 | D37: 70 | E37: 9 | F37: Commercial | G37: Secondary Keyword | H37: Secondary Keyword | I37: Service / Pillar | J37: Secondary Keyword | L37: Mapped | M37: SEO Manager | N37: =IF(OR(C37="",E37=""),"",ROUND((C37/(E37+1))*IF(ISNUMBER(SEARCH("Commercial",F37)),1.25,1),1)) -> 8.8 | Q37: Kajabi Service Page keywords | R37: 46230 | S37: Confirm current canonical URL and search intent
A38: KW-034 | B38: kajabi sales funnel | C38: 20 | D38: 70 | F38: Informational | G38: Secondary Keyword | H38: Secondary Keyword | I38: Service / Pillar | J38: Secondary Keyword | L38: Mapped | M38: SEO Manager | N38: =IF(OR(C38="",E38=""),"",ROUND((C38/(E38+1))*IF(ISNUMBER(SEARCH("Commercial",F38)),1.25,1),1)) | Q38: Kajabi Service Page keywords | R38: 46230 | S38: Confirm current canonical URL and search intent
A39: KW-035 | B39: best funnels to use on kajabi | F39: Informational | G39: Secondary Keyword | H39: Secondary Keyword | I39: Service / Pillar | J39: Secondary Keyword | L39: Mapped | M39: SEO Manager | N39: =IF(OR(C39="",E39=""),"",ROUND((C39/(E39+1))*IF(ISNUMBER(SEARCH("Commercial",F39)),1.25,1),1)) | Q39: Kajabi Service Page keywords | R39: 46230 | S39: Confirm current canonical URL and search intent
A40: KW-036 | B40: kajabi course upload services | G40: Primary Keyword | H40: Primary Keyword | I40: Service / Pillar | J40: Professional Kajabi Course Upload Service | We Value Your Time | L40: Mapped | M40: SEO Manager | N40: =IF(OR(C40="",E40=""),"",ROUND((C40/(E40+1))*IF(ISNUMBER(SEARCH("Commercial",F40)),1.25,1),1)) | O40: Need your course live? Our professional Kajabi course upload service takes the stress away. We build it right the first time. Hire our experts here. | Q40: Kajabi Service Page keywords | R40: 46230 | S40: Confirm current canonical URL and search intent
A41: KW-037 | B41: kajabi.services | G41: Secondary Keyword | H41: Secondary Keyword | I41: Service / Pillar | J41: Secondary Keyword | L41: Mapped | M41: SEO Manager | N41: =IF(OR(C41="",E41=""),"",ROUND((C41/(E41+1))*IF(ISNUMBER(SEARCH("Commercial",F41)),1.25,1),1)) | Q41: Kajabi Service Page keywords | R41: 46230 | S41: Confirm current canonical URL and search intent
A42: KW-038 | B42: kajabi customer service | C42: 50 | D42: 140 | E42: 19 | F42: Informational | G42: Secondary Keyword | H42: Secondary Keyword | I42: Service / Pillar | J42: Secondary Keyword | L42: Mapped | M42: SEO Manager | N42: =IF(OR(C42="",E42=""),"",ROUND((C42/(E42+1))*IF(ISNUMBER(SEARCH("Commercial",F42)),1.25,1),1)) -> 2.5 | Q42: Kajabi Service Page keywords | R42: 46230 | S42: Confirm current canonical URL and search intent
A43: KW-039 | B43: kajabi help | C43: 110 | D43: 390 | E43: 20 | F43: Navigational+Commercial | G43: Secondary Keyword | H43: Secondary Keyword | I43: Service / Pillar | J43: Secondary Keyword | L43: Mapped | M43: SEO Manager | N43: =IF(OR(C43="",E43=""),"",ROUND((C43/(E43+1))*IF(ISNUMBER(SEARCH("Commercial",F43)),1.25,1),1)) -> 6.5 | Q43: Kajabi Service Page keywords | R43: 46230 | S43: Confirm current canonical URL and search intent
A44: KW-040 | B44: kajabi support | C44: 140 | D44: 490 | E44: 17 | F44: Navigational | G44: Secondary Keyword | H44: Secondary Keyword | I44: Service / Pillar | J44: Secondary Keyword | L44: Mapped | M44: SEO Manager | N44: =IF(OR(C44="",E44=""),"",ROUND((C44/(E44+1))*IF(ISNUMBER(SEARCH("Commercial",F44)),1.25,1),1)) -> 7.8 | Q44: Kajabi Service Page keywords | R44: 46230 | S44: Confirm current canonical URL and search intent
A45: KW-041 | B45: Kajabi Migration | C45: 20 | D45: 60 | F45: Informational | G45: Secondary Keyword | H45: Secondary Keyword | I45: Service / Pillar | J45: Move to Kajabi: Expert Migration for Your Growth | L45: Mapped | M45: SEO Manager | N45: =IF(OR(C45="",E45=""),"",ROUND((C45/(E45+1))*IF(ISNUMBER(SEARCH("Commercial",F45)),1.25,1),1)) | O45: Ready to move to Kajabi? Get a clean migration that saves you time. We move your courses and emails fast. Scale your business without the headaches. Call us. | P45: https://theeduassist.com/blog/kajabi-website-funnel-services/ | Q45: Kajabi Service Page keywords | R45: 46230 | S45: Confirm current canonical URL and search intent
A46: KW-042 | B46: Kajabi Migration Services | G46: Primary Keyword | H46: Primary Keyword | I46: Service / Pillar | J46: Secondary Keyword | L46: Mapped | M46: SEO Manager | N46: =IF(OR(C46="",E46=""),"",ROUND((C46/(E46+1))*IF(ISNUMBER(SEARCH("Commercial",F46)),1.25,1),1)) | Q46: Kajabi Service Page keywords | R46: 46230 | S46: Confirm current canonical URL and search intent
A47: KW-043 | B47: migrate from kajabi | C47: 10 | D47: 30 | G47: Secondary Keyword | H47: Secondary Keyword | I47: Service / Pillar | J47: Secondary Keyword | L47: Mapped | M47: SEO Manager | N47: =IF(OR(C47="",E47=""),"",ROUND((C47/(E47+1))*IF(ISNUMBER(SEARCH("Commercial",F47)),1.25,1),1)) | Q47: Kajabi Service Page keywords | R47: 46230 | S47: Confirm current canonical URL and search intent
A48: KW-044 | B48: migrate from kajabi to wordpress | G48: Secondary Keyword | H48: Secondary Keyword | I48: Service / Pillar | J48: Secondary Keyword | L48: Mapped | M48: SEO Manager | N48: =IF(OR(C48="",E48=""),"",ROUND((C48/(E48+1))*IF(ISNUMBER(SEARCH("Commercial",F48)),1.25,1),1)) | Q48: Kajabi Service Page keywords | R48: 46230 | S48: Confirm current canonical URL and search intent
A49: KW-045 | B49: migrate from kajabi to teachable | C49: 20 | D49: 20 | G49: Secondary Keyword | H49: Secondary Keyword | I49: Service / Pillar | J49: Secondary Keyword | L49: Mapped | M49: SEO Manager | N49: =IF(OR(C49="",E49=""),"",ROUND((C49/(E49+1))*IF(ISNUMBER(SEARCH("Commercial",F49)),1.25,1),1)) | Q49: Kajabi Service Page keywords | R49: 46230 | S49: Confirm current canonical URL and search intent
A50: KW-046 | B50: migrate wordpress to kajabi | G50: Secondary Keyword | H50: Secondary Keyword | I50: Service / Pillar | J50: Secondary Keyword | L50: Mapped | M50: SEO Manager | N50: =IF(OR(C50="",E50=""),"",ROUND((C50/(E50+1))*IF(ISNUMBER(SEARCH("Commercial",F50)),1.25,1),1)) | Q50: Kajabi Service Page keywords | R50: 46230 | S50: Confirm current canonical URL and search intent
A51: KW-047 | B51: migrating from kajabi | G51: Secondary Keyword | H51: Secondary Keyword | I51: Service / Pillar | J51: Secondary Keyword | L51: Mapped | M51: SEO Manager | N51: =IF(OR(C51="",E51=""),"",ROUND((C51/(E51+1))*IF(ISNUMBER(SEARCH("Commercial",F51)),1.25,1),1)) | Q51: Kajabi Service Page keywords | R51: 46230 | S51: Confirm current canonical URL and search intent
A52: KW-048 | B52: kajabi va | C52: 20 | D52: 110 | G52: Secondary Keyword | H52: Secondary Keyword | I52: Service / Pillar | J52: Hire a Kajabi VA for Reliable Monthly Management | L52: Mapped | M52: SEO Manager | N52: =IF(OR(C52="",E52=""),"",ROUND((C52/(E52+1))*IF(ISNUMBER(SEARCH("Commercial",F52)),1.25,1),1)) | O52: Stop wasting hours on tech. Hire a Kajabi VA for reliable monthly management. We fix the bugs and automate your site. Start your easy growth plan now. | Q52: Kajabi Service Page keywords | R52: 46230 | S52: Confirm current canonical URL and search intent
A53: KW-049 | B53: hire kajabi experts | C53: 70 | D53: 100 | E53: 8 | F53: Commercial | G53: Secondary Keyword | H53: Secondary Keyword | I53: Service / Pillar | J53: Secondary Keyword | L53: Mapped | M53: SEO Manager | N53: =IF(OR(C53="",E53=""),"",ROUND((C53/(E53+1))*IF(ISNUMBER(SEARCH("Commercial",F53)),1.25,1),1)) -> 9.7 | Q53: Kajabi Service Page keywords | R53: 46230 | S53: Confirm current canonical URL and search intent
A54: KW-050 | B54: virtual teammate client playbook | C54: 50 | D54: 50 | E54: 0 | F54: Navigational | G54: Secondary Keyword | H54: Secondary Keyword | I54: Service / Pillar | J54: Secondary Keyword | L54: Mapped | M54: SEO Manager | N54: =IF(OR(C54="",E54=""),"",ROUND((C54/(E54+1))*IF(ISNUMBER(SEARCH("Commercial",F54)),1.25,1),1)) -> 50 | Q54: Kajabi Service Page keywords | R54: 46230 | S54: Confirm current canonical URL and search intent
A55: KW-051 | B55: kajabi virtual assistant | C55: 20 | D55: 60 | G55: Secondary Keyword | H55: Secondary Keyword | I55: Service / Pillar | J55: Secondary Keyword | L55: Mapped | M55: SEO Manager | N55: =IF(OR(C55="",E55=""),"",ROUND((C55/(E55+1))*IF(ISNUMBER(SEARCH("Commercial",F55)),1.25,1),1)) | Q55: Kajabi Service Page keywords | R55: 46230 | S55: Confirm current canonical URL and search intent
A56: KW-052 | B56: kajabi virtual assistants | G56: Secondary Keyword | H56: Secondary Keyword | I56: Service / Pillar | J56: Secondary Keyword | L56: Mapped | M56: SEO Manager | N56: =IF(OR(C56="",E56=""),"",ROUND((C56/(E56+1))*IF(ISNUMBER(SEARCH("Commercial",F56)),1.25,1),1)) | Q56: Kajabi Service Page keywords | R56: 46230 | S56: Confirm current canonical URL and search intent
A57: KW-053 | B57: virtual assistant kajabi | G57: Secondary Keyword | H57: Secondary Keyword | I57: Service / Pillar | J57: Secondary Keyword | L57: Mapped | M57: SEO Manager | N57: =IF(OR(C57="",E57=""),"",ROUND((C57/(E57+1))*IF(ISNUMBER(SEARCH("Commercial",F57)),1.25,1),1)) | Q57: Kajabi Service Page keywords | R57: 46230 | S57: Confirm current canonical URL and search intent
A58: KW-054 | B58: kajabi virtual assistant for sales page | G58: Secondary Keyword | H58: Secondary Keyword | I58: Service / Pillar | J58: Secondary Keyword | L58: Mapped | M58: SEO Manager | N58: =IF(OR(C58="",E58=""),"",ROUND((C58/(E58+1))*IF(ISNUMBER(SEARCH("Commercial",F58)),1.25,1),1)) | Q58: Kajabi Service Page keywords | R58: 46230 | S58: Confirm current canonical URL and search intent
A59: KW-055 | B59: kajabi virtual assistant for product launch | G59: Secondary Keyword | H59: Secondary Keyword | I59: Service / Pillar | J59: Secondary Keyword | L59: Mapped | M59: SEO Manager | N59: =IF(OR(C59="",E59=""),"",ROUND((C59/(E59+1))*IF(ISNUMBER(SEARCH("Commercial",F59)),1.25,1),1)) | Q59: Kajabi Service Page keywords | R59: 46230 | S59: Confirm current canonical URL and search intent
A60: KW-056 | B60: kajabi packages for the virtual assistant | G60: Secondary Keyword | H60: Secondary Keyword | I60: Service / Pillar | J60: Secondary Keyword | L60: Mapped | M60: SEO Manager | N60: =IF(OR(C60="",E60=""),"",ROUND((C60/(E60+1))*IF(ISNUMBER(SEARCH("Commercial",F60)),1.25,1),1)) | Q60: Kajabi Service Page keywords | R60: 46230 | S60: Confirm current canonical URL and search intent
A61: KW-057 | B61: Kajabi VA services | G61: Primary Keyword | H61: Primary Keyword | I61: Service / Pillar | J61: Secondary Keyword | L61: Mapped | M61: SEO Manager | N61: =IF(OR(C61="",E61=""),"",ROUND((C61/(E61+1))*IF(ISNUMBER(SEARCH("Commercial",F61)),1.25,1),1)) | Q61: Kajabi Service Page keywords | R61: 46230 | S61: Confirm current canonical URL and search intent
A62: KW-058 | B62: Kajabi virtual assistant services | G62: Primary Keyword | H62: Primary Keyword | I62: Service / Pillar | J62: Secondary Keyword | L62: Mapped | M62: SEO Manager | N62: =IF(OR(C62="",E62=""),"",ROUND((C62/(E62+1))*IF(ISNUMBER(SEARCH("Commercial",F62)),1.25,1),1)) | Q62: Kajabi Service Page keywords | R62: 46230 | S62: Confirm current canonical URL and search intent
A63: KW-059 | B63: Custom e-learning Development Services | C63: 30 | D63: 70 | E63: 21 | F63: Commercial | G63: Custom elearnig Development | H63: Custom elearnig Development | I63: Service / Pillar | J63: Secondary Keyword | L63: Mapped | M63: SEO Manager | N63: =IF(OR(C63="",E63=""),"",ROUND((C63/(E63+1))*IF(ISNUMBER(SEARCH("Commercial",F63)),1.25,1),1)) -> 1.7 | Q63: Keywords Research April 2026 | R63: 46230 | S63: Confirm current canonical URL and search intent
A64: KW-060 | B64: Custom elearning development | C64: 1300 | D64: 2700 | E64: 5 | F64: Informational | G64: Custom elearnig Development | H64: Custom elearnig Development | I64: Service / Pillar | J64: Primary Keyword | L64: Mapped | M64: SEO Manager | N64: =IF(OR(C64="",E64=""),"",ROUND((C64/(E64+1))*IF(ISNUMBER(SEARCH("Commercial",F64)),1.25,1),1)) -> 216.7 | Q64: Keywords Research April 2026 | R64: 46230 | S64: Confirm current canonical URL and search intent
A65: KW-061 | B65: custom elearning solutions | C65: 880 | D65: 1600 | E65: 32 | F65: Informational | G65: Custom elearnig Development | H65: Custom elearnig Development | I65: Service / Pillar | J65: Secondary Keyword | L65: Mapped | M65: SEO Manager | N65: =IF(OR(C65="",E65=""),"",ROUND((C65/(E65+1))*IF(ISNUMBER(SEARCH("Commercial",F65)),1.25,1),1)) -> 26.7 | Q65: Keywords Research April 2026 | R65: 46230 | S65: Confirm current canonical URL and search intent
A66: KW-062 | B66: custom elearning | C66: 880 | D66: 2100 | E66: 47 | F66: Informational | G66: Custom elearnig Development | H66: Custom elearnig Development | I66: Service / Pillar | J66: Secondary Keyword | L66: Mapped | M66: SEO Manager | N66: =IF(OR(C66="",E66=""),"",ROUND((C66/(E66+1))*IF(ISNUMBER(SEARCH("Commercial",F66)),1.25,1),1)) -> 18.3 | Q66: Keywords Research April 2026 | R66: 46230 | S66: Confirm current canonical URL and search intent
A67: KW-063 | B67: custom elearning content development | C67: 390 | D67: 720 | E67: 25 | F67: Informational | G67: Custom elearnig Development | H67: Custom elearnig Development | I67: Service / Pillar | J67: Secondary Keyword | L67: Mapped | M67: SEO Manager | N67: =IF(OR(C67="",E67=""),"",ROUND((C67/(E67+1))*IF(ISNUMBER(SEARCH("Commercial",F67)),1.25,1),1)) -> 15 | Q67: Keywords Research April 2026 | R67: 46230 | S67: Confirm current canonical URL and search intent
A68: KW-064 | B68: elearning development | C68: 590 | D68: 1800 | E68: 9 | F68: Informational | G68: Custom elearnig Development | H68: Custom elearnig Development | I68: Service / Pillar | J68: Secondary Keyword | L68: Mapped | M68: SEO Manager | N68: =IF(OR(C68="",E68=""),"",ROUND((C68/(E68+1))*IF(ISNUMBER(SEARCH("Commercial",F68)),1.25,1),1)) -> 59 | Q68: Keywords Research April 2026 | R68: 46230 | S68: Confirm current canonical URL and search intent
A69: KW-065 | B69: custom elearning course development | C69: 390 | D69: 730 | E69: 20 | F69: Informational | G69: Custom elearnig Development | H69: Custom elearnig Development | I69: Service / Pillar | J69: Secondary Keyword | L69: Mapped | M69: SEO Manager | N69: =IF(OR(C69="",E69=""),"",ROUND((C69/(E69+1))*IF(ISNUMBER(SEARCH("Commercial",F69)),1.25,1),1)) -> 18.6 | Q69: Keywords Research April 2026 | R69: 46230 | S69: Confirm current canonical URL and search intent
A70: KW-066 | B70: elearning localization services | C70: 390 | D70: 600 | E70: 6 | F70: Informational | G70: E-learning Localization Services | H70: E-learning Localization Services | I70: Service / Pillar | J70: Primary Keyword | L70: Mapped | M70: SEO Manager | N70: =IF(OR(C70="",E70=""),"",ROUND((C70/(E70+1))*IF(ISNUMBER(SEARCH("Commercial",F70)),1.25,1),1)) -> 55.7 | Q70: Keywords Research April 2026 | R70: 46230 | S70: Confirm current canonical URL and search intent
A71: KW-067 | B71: ai powered learning solutions | C71: 20 | D71: 20 | E71: 0 | F71: Commercial+Informational | G71: AI Powered learning and development Solutions | H71: AI Powered learning and development Solutions | I71: Service / Pillar | J71: Secondary Keyword | L71: Mapped | M71: SEO Manager | N71: =IF(OR(C71="",E71=""),"",ROUND((C71/(E71+1))*IF(ISNUMBER(SEARCH("Commercial",F71)),1.25,1),1)) -> 25 | Q71: Keywords Research April 2026 | R71: 46230 | S71: Confirm current canonical URL and search intent
A72: KW-068 | B72: e-learning solutions | C72: 480 | D72: 2300 | E72: 42 | F72: Informational | G72: AI Powered learning and development Solutions | H72: AI Powered learning and development Solutions | I72: Service / Pillar | J72: Secondary Keyword | L72: Mapped | M72: SEO Manager | N72: =IF(OR(C72="",E72=""),"",ROUND((C72/(E72+1))*IF(ISNUMBER(SEARCH("Commercial",F72)),1.25,1),1)) -> 11.2 | Q72: Keywords Research April 2026 | R72: 46230 | S72: Confirm current canonical URL and search intent
A73: KW-069 | B73: managed learning environment | C73: 3600 | D73: 11400 | E73: 24 | F73: Informational | G73: LMS Implementation & Integration | H73: LMS Implementation & Integration | I73: Service / Pillar | J73: Secondary Keyword | L73: Mapped | M73: SEO Manager | N73: =IF(OR(C73="",E73=""),"",ROUND((C73/(E73+1))*IF(ISNUMBER(SEARCH("Commercial",F73)),1.25,1),1)) -> 144 | Q73: Keywords Research April 2026 | R73: 46230 | S73: Confirm current canonical URL and search intent
A74: KW-070 | B74: training management software | C74: 1900 | D74: 4500 | E74: 17 | F74: Commercial+Informational | G74: LMS Implementation & Integration | H74: LMS Implementation & Integration | I74: Service / Pillar | J74: Secondary Keyword | L74: Mapped | M74: SEO Manager | N74: =IF(OR(C74="",E74=""),"",ROUND((C74/(E74+1))*IF(ISNUMBER(SEARCH("Commercial",F74)),1.25,1),1)) -> 131.9 | Q74: Keywords Research April 2026 | R74: 46230 | S74: Confirm current canonical URL and search intent
... A81: KW-077 | B81: audio and video production | C81: 210 | D81: 590 | E81: 16 | F81: Informational | G81: Audio & Video Production for eLearning | H81: Audio & Video Production for eLearning | I81: Service / Pillar | J81: Secondary Keyword | L81: Mapped | M81: SEO Manager | N81: =IF(OR(C81="",E81=""),"",ROUND((C81/(E81+1))*IF(ISNUMBER(SEARCH("Commercial",F81)),1.25,1),1)) -> 12.4 | Q81: Keywords Research April 2026 | R81: 46230 | S81: Confirm current canonical URL and search intent
A82: KW-078 | B82: voiceover production | C82: 30 | D82: 150 | F82: Informational | G82: Audio & Video Production for eLearning | H82: Audio & Video Production for eLearning | I82: Service / Pillar | J82: Secondary Keyword | L82: Mapped | M82: SEO Manager | N82: =IF(OR(C82="",E82=""),"",ROUND((C82/(E82+1))*IF(ISNUMBER(SEARCH("Commercial",F82)),1.25,1),1)) | Q82: Keywords Research April 2026 | R82: 46230 | S82: Confirm current canonical URL and search intent
A83: KW-079 | B83: 3d animation video production | C83: 390 | D83: 580 | E83: 24 | F83: Informational | G83: Audio & Video Production for eLearning | H83: Audio & Video Production for eLearning | I83: Service / Pillar | J83: Secondary Keyword | L83: Mapped | M83: SEO Manager | N83: =IF(OR(C83="",E83=""),"",ROUND((C83/(E83+1))*IF(ISNUMBER(SEARCH("Commercial",F83)),1.25,1),1)) -> 15.6 | Q83: Keywords Research April 2026 | R83: 46230 | S83: Confirm current canonical URL and search intent
A84: KW-080 | B84: animated videos for elearning | C84: 50 | D84: 90 | E84: 12 | F84: Informational+Transational | G84: Audio & Video Production for eLearning | H84: Audio & Video Production for eLearning | I84: Service / Pillar | J84: Secondary Keyword | L84: Mapped | M84: SEO Manager | N84: =IF(OR(C84="",E84=""),"",ROUND((C84/(E84+1))*IF(ISNUMBER(SEARCH("Commercial",F84)),1.25,1),1)) -> 3.8 | Q84: Keywords Research April 2026 | R84: 46230 | S84: Confirm current canonical URL and search intent
A85: KW-081 | B85: elearning video production services | G85: Audio & Video Production for eLearning | H85: Audio & Video Production for eLearning | I85: Service / Pillar | J85: Primary Keyword | L85: Mapped | M85: SEO Manager | N85: =IF(OR(C85="",E85=""),"",ROUND((C85/(E85+1))*IF(ISNUMBER(SEARCH("Commercial",F85)),1.25,1),1)) | Q85: Keywords Research April 2026 | R85: 46230 | S85: Confirm current canonical URL and search intent
A86: KW-082 | B86: audio in elearning | C86: 20 | D86: 40 | G86: Audio & Video Production for eLearning | H86: Audio & Video Production for eLearning | I86: Service / Pillar | J86: Secondary Keyword | L86: Mapped | M86: SEO Manager | N86: =IF(OR(C86="",E86=""),"",ROUND((C86/(E86+1))*IF(ISNUMBER(SEARCH("Commercial",F86)),1.25,1),1)) | Q86: Keywords Research April 2026 | R86: 46230 | S86: Confirm current canonical URL and search intent
A87: KW-083 | B87: legacy content conversions | C87: 20 | D87: 20 | G87: Legacy Content Conversion | H87: Legacy Content Conversion | I87: Service / Pillar | J87: Secondary Keyword | L87: Mapped | M87: SEO Manager | N87: =IF(OR(C87="",E87=""),"",ROUND((C87/(E87+1))*IF(ISNUMBER(SEARCH("Commercial",F87)),1.25,1),1)) | Q87: Keywords Research April 2026 | R87: 46230 | S87: Confirm current canonical URL and search intent
A88: KW-084 | B88: legacy content conversion services | C88: 20 | D88: 20 | G88: Legacy Content Conversion | H88: Legacy Content Conversion | I88: Service / Pillar | J88: Primary Keyword | L88: Mapped | M88: SEO Manager | N88: =IF(OR(C88="",E88=""),"",ROUND((C88/(E88+1))*IF(ISNUMBER(SEARCH("Commercial",F88)),1.25,1),1)) | Q88: Keywords Research April 2026 | R88: 46230 | S88: Confirm current canonical URL and search intent
A89: KW-085 | B89: eLearning content conversion | F89: Informational | G89: Legacy Content Conversion | H89: Legacy Content Conversion | I89: Service / Pillar | J89: Secondary Keyword | L89: Mapped | M89: SEO Manager | N89: =IF(OR(C89="",E89=""),"",ROUND((C89/(E89+1))*IF(ISNUMBER(SEARCH("Commercial",F89)),1.25,1),1)) | Q89: Keywords Research April 2026 | R89: 46230 | S89: Confirm current canonical URL and search intent
A90: KW-086 | B90: convert flash to html5 | C90: 140 | D90: 770 | E90: 28 | F90: Informational | G90: Legacy Content Conversion | H90: Legacy Content Conversion | I90: Service / Pillar | J90: Secondary Keyword | L90: Mapped | M90: SEO Manager | N90: =IF(OR(C90="",E90=""),"",ROUND((C90/(E90+1))*IF(ISNUMBER(SEARCH("Commercial",F90)),1.25,1),1)) -> 4.8 | Q90: Keywords Research April 2026 | R90: 46230 | S90: Confirm current canonical URL and search intent
A91: KW-087 | B91: ppt to elearning conversion | C91: 90 | D91: 220 | E91: 4 | F91: Informational | G91: Legacy Content Conversion | H91: Legacy Content Conversion | I91: Service / Pillar | J91: Secondary Keyword | L91: Mapped | M91: SEO Manager | N91: =IF(OR(C91="",E91=""),"",ROUND((C91/(E91+1))*IF(ISNUMBER(SEARCH("Commercial",F91)),1.25,1),1)) -> 18 | Q91: Keywords Research April 2026 | R91: 46230 | S91: Confirm current canonical URL and search intent
A92: KW-088 | B92: create interactive elearning | C92: 40 | D92: 70 | E92: 21 | F92: Informational | G92: Legacy Content Conversion | H92: Legacy Content Conversion | I92: Service / Pillar | J92: Secondary Keyword | L92: Mapped | M92: SEO Manager | N92: =IF(OR(C92="",E92=""),"",ROUND((C92/(E92+1))*IF(ISNUMBER(SEARCH("Commercial",F92)),1.25,1),1)) -> 1.8 | Q92: Keywords Research April 2026 | R92: 46230 | S92: Confirm current canonical URL and search intent
A93: KW-089 | B93: how to make powerpoint interactive | C93: 40 | D93: 710 | E93: 27 | F93: Informational | G93: For Blog Post(not to include) | H93: For Blog Post(not to include) | I93: Service / Pillar | J93: Secondary Keyword | L93: Mapped | M93: SEO Manager | N93: =IF(OR(C93="",E93=""),"",ROUND((C93/(E93+1))*IF(ISNUMBER(SEARCH("Commercial",F93)),1.25,1),1)) -> 1.4 | Q93: Keywords Research April 2026 | R93: 46230 | S93: Confirm current canonical URL and search intent
A94: KW-090 | B94: how to convert legacy content to eLearning | G94: For Blog Post(not to include) | H94: For Blog Post(not to include) | I94: Service / Pillar | J94: Secondary Keyword | L94: Mapped | M94: SEO Manager | N94: =IF(OR(C94="",E94=""),"",ROUND((C94/(E94+1))*IF(ISNUMBER(SEARCH("Commercial",F94)),1.25,1),1)) | Q94: Keywords Research April 2026 | R94: 46230 | S94: Confirm current canonical URL and search intent
A95: KW-091 | B95: e learning instructional design | C95: 50 | D95: 610 | E95: 23 | F95: Commercial+Informational | G95: Instructional & UI/UX Design | H95: Instructional & UI/UX Design | I95: Service / Pillar | J95: Secondary Keyword | L95: Mapped | M95: SEO Manager | N95: =IF(OR(C95="",E95=""),"",ROUND((C95/(E95+1))*IF(ISNUMBER(SEARCH("Commercial",F95)),1.25,1),1)) -> 2.6 | Q95: Keywords Research April 2026 | R95: 46230 | S95: Confirm current canonical URL and search intent
A96: KW-092 | B96: elearning and instructional design | C96: 30 | D96: 140 | E96: 26 | F96: Informational | G96: Instructional & UI/UX Design | H96: Instructional & UI/UX Design | I96: Service / Pillar | J96: Secondary Keyword | L96: Mapped | M96: SEO Manager | N96: =IF(OR(C96="",E96=""),"",ROUND((C96/(E96+1))*IF(ISNUMBER(SEARCH("Commercial",F96)),1.25,1),1)) -> 1.1 | Q96: Keywords Research April 2026 | R96: 46230 | S96: Confirm current canonical URL and search intent
A97: KW-093 | B97: instructional design for e learning | C97: 30 | D97: 550 | E97: 16 | F97: Informational | G97: Instructional & UI/UX Design | H97: Instructional & UI/UX Design | I97: Service / Pillar | J97: Secondary Keyword | L97: Mapped | M97: SEO Manager | N97: =IF(OR(C97="",E97=""),"",ROUND((C97/(E97+1))*IF(ISNUMBER(SEARCH("Commercial",F97)),1.25,1),1)) -> 1.8 | Q97: Keywords Research April 2026 | R97: 46230 | S97: Confirm current canonical URL and search intent
A98: KW-094 | B98: elearning design | C98: 390 | D98: 1600 | E98: 26 | F98: Informational | G98: Instructional & UI/UX Design | H98: Instructional & UI/UX Design | I98: Service / Pillar | J98: Secondary Keyword | L98: Mapped | M98: SEO Manager | N98: =IF(OR(C98="",E98=""),"",ROUND((C98/(E98+1))*IF(ISNUMBER(SEARCH("Commercial",F98)),1.25,1),1)) -> 14.4 | Q98: Keywords Research April 2026 | R98: 46230 | S98: Confirm current canonical URL and search intent
A99: KW-095 | B99: custom e learning design | C99: 110 | D99: 190 | E99: 26 | F99: Commercial | G99: Instructional & UI/UX Design | H99: Instructional & UI/UX Design | I99: Service / Pillar | J99: Secondary Keyword | L99: Mapped | M99: SEO Manager | N99: =IF(OR(C99="",E99=""),"",ROUND((C99/(E99+1))*IF(ISNUMBER(SEARCH("Commercial",F99)),1.25,1),1)) -> 5.1 | Q99: Keywords Research April 2026 | R99: 46230 | S99: Confirm current canonical URL and search intent
A100: KW-096 | B100: Instructional Design services | C100: 590 | D100: 2300 | E100: 21 | F100: Informational | G100: Instructional & UI/UX Design | H100: Instructional & UI/UX Design | I100: Service / Pillar | J100: Primary Keyword | L100: Mapped | M100: SEO Manager | N100: =IF(OR(C100="",E100=""),"",ROUND((C100/(E100+1))*IF(ISNUMBER(SEARCH("Commercial",F100)),1.25,1),1)) -> 26.8 | Q100: Keywords Research April 2026 | R100: 46230 | S100: Confirm current canonical URL and search intent
A101: KW-097 | B101: elearning ui/ux design services | F101: Informational | G101: Instructional & UI/UX Design | H101: Instructional & UI/UX Design | I101: Service / Pillar | J101: Secondary Keyword | L101: Mapped | M101: SEO Manager | N101: =IF(OR(C101="",E101=""),"",ROUND((C101/(E101+1))*IF(ISNUMBER(SEARCH("Commercial",F101)),1.25,1),1)) | Q101: Keywords Research April 2026 | R101: 46230 | S101: Confirm current canonical URL and search intent
A102: KW-098 | B102: rapid learning | C102: 210 | D102: 1000 | E102: 18 | F102: Informational | G102: Rapid eLearning Development | H102: Rapid eLearning Development | I102: Service / Pillar | J102: Secondary Keyword | L102: Mapped | M102: SEO Manager | N102: =IF(OR(C102="",E102=""),"",ROUND((C102/(E102+1))*IF(ISNUMBER(SEARCH("Commercial",F102)),1.25,1),1)) -> 11.1 | Q102: Keywords Research April 2026 | R102: 46230 | S102: Confirm current canonical URL and search intent
A103: KW-099 | B103: rapid elearning | C103: 90 | D103: 300 | E103: 23 | F103: Informational | G103: Rapid eLearning Development | H103: Rapid eLearning Development | I103: Service / Pillar | J103: Secondary Keyword | L103: Mapped | M103: SEO Manager | N103: =IF(OR(C103="",E103=""),"",ROUND((C103/(E103+1))*IF(ISNUMBER(SEARCH("Commercial",F103)),1.25,1),1)) -> 3.8 | Q103: Keywords Research April 2026 | R103: 46230 | S103: Confirm current canonical URL and search intent
A104: KW-100 | B104: rapid elearning development | C104: 90 | D104: 200 | E104: 24 | F104: Informational | G104: Rapid eLearning Development | H104: Rapid eLearning Development | I104: Service / Pillar | J104: Secondary Keyword | L104: Mapped | M104: SEO Manager | N104: =IF(OR(C104="",E104=""),"",ROUND((C104/(E104+1))*IF(ISNUMBER(SEARCH("Commercial",F104)),1.25,1),1)) -> 3.6 | Q104: Keywords Research April 2026 | R104: 46230 | S104: Confirm current canonical URL and search intent
A105: KW-101 | B105: rapid elearning services | C105: 30 | D105: 130 | G105: Rapid eLearning Development | H105: Rapid eLearning Development | I105: Service / Pillar | J105: Secondary Keyword | L105: Mapped | M105: SEO Manager | N105: =IF(OR(C105="",E105=""),"",ROUND((C105/(E105+1))*IF(ISNUMBER(SEARCH("Commercial",F105)),1.25,1),1)) | Q105: Keywords Research April 2026 | R105: 46230 | S105: Confirm current canonical URL and search intent
A106: KW-102 | B106: best rapid elearning services | C106: 10 | D106: 10 | G106: Rapid eLearning Development | H106: Rapid eLearning Development | I106: Service / Pillar | J106: Secondary Keyword | L106: Mapped | M106: SEO Manager | N106: =IF(OR(C106="",E106=""),"",ROUND((C106/(E106+1))*IF(ISNUMBER(SEARCH("Commercial",F106)),1.25,1),1)) | Q106: Keywords Research April 2026 | R106: 46230 | S106: Confirm current canonical URL and search intent
A107: KW-103 | B107: rapid elearning development company | C107: 10 | D107: 40 | G107: Rapid eLearning Development | H107: Rapid eLearning Development | I107: Service / Pillar | J107: Secondary Keyword | L107: Mapped | M107: SEO Manager | N107: =IF(OR(C107="",E107=""),"",ROUND((C107/(E107+1))*IF(ISNUMBER(SEARCH("Commercial",F107)),1.25,1),1)) | Q107: Keywords Research April 2026 | R107: 46230 | S107: Confirm current canonical URL and search intent
...

Sheet 03 Content Pipeline
A1: Content and Page Production Pipeline
A2: Track service pages, articles, comparisons, case studies and resources from brief through indexing and refresh.
A4: Content ID | B4: Content / Page | C4: Type | D4: Cluster | E4: Primary Keyword | F4: Intent | G4: Funnel Stage | H4: Current URL | I4: Draft / Brief Link | J4: Status | K4: Priority | L4: Owner | M4: Due Date | N4: Publish Date | O4: Primary CTA | P4: Internal Links to Add | Q4: Schema | R4: Index Status | S4: Last Refresh | T4: Notes
A5: CNT-001 | B5: Homepage | C5: Core Page | D5: Brand / E-learning Agency | E5: eLearning development company | F5: Commercial | G5: Decision | H5: https://www.theeduassist.com/ | J5: Published | K5: Critical | L5: SEO Manager | O5: Get a 24–48 Hour Review | P5: Services; Kajabi; Case Studies; Pricing; Insights | Q5: Organization; WebSite; Breadcrumb | R5: Indexed | T5: Monitor CTR and conversions
A6: CNT-002 | B6: Services Hub | C6: Core Page | D6: Services | E6: eLearning services | F6: Commercial | G6: Consideration | H6: https://www.theeduassist.com/services/ | J6: Published | K6: Critical | L6: SEO Manager | O6: Get a 24–48 Hour Review | P6: All service pages; case studies | Q6: ItemList; Service; Breadcrumb | R6: Needs Review | T6: Confirm current canonical
A7: CNT-003 | B7: Kajabi Services Hub | C7: Core Page | D7: Kajabi | E7: Kajabi services | F7: Commercial | G7: Consideration | H7: https://www.theeduassist.com/kajabi-services/ | J7: Published | K7: High | L7: SEO Manager | O7: Get a Kajabi Review | P7: Kajabi service pages; case studies | Q7: Service; Breadcrumb | R7: Needs Review
A8: CNT-004 | B8: Case Studies Hub | C8: Core Page | D8: Proof / Results | E8: eLearning case studies | F8: Commercial | G8: Decision | H8: https://www.theeduassist.com/case-studies/ | J8: Published | K8: High | L8: Content Lead | O8: Discuss a Project | P8: Relevant services; review CTA | Q8: CollectionPage; Breadcrumb | R8: Needs Review
A9: CNT-005 | B9: Pricing | C9: Core Page | D9: Pricing | E9: eLearning development pricing | F9: Commercial | G9: Decision | H9: https://www.theeduassist.com/pricing/ | J9: Published | K9: High | L9: SEO Manager | O9: Request Review | P9: Services; case studies; contact | Q9: Service; Breadcrumb | R9: Needs Review
A10: CNT-006 | B10: About Us | C10: Core Page | D10: Trust | E10: TheEduAssist | F10: Navigational | G10: Decision | H10: https://www.theeduassist.com/about/ | J10: Needs Review | K10: High | L10: Content Lead | M10: 46235 | O10: Talk to Our Team | P10: Contact; case studies; careers | Q10: AboutPage; Organization; Breadcrumb | R10: Needs Revalidation | T10: Revalidate live page before editing
A11: CNT-007 | B11: Contact Us | C11: Core Page | D11: Conversion | E11: contact TheEduAssist | F11: Navigational | G11: Decision | H11: https://www.theeduassist.com/contact/ | J11: Needs Review | K11: Critical | L11: SEO Manager | M11: 46234 | O11: Submit Enquiry | P11: Services; review pathway | Q11: ContactPage; Organization; Breadcrumb | R11: Needs Revalidation | T11: Confirm form completion and key event tracking
A12: CNT-008 | B12: 24–48 Hour Review | C12: Conversion Page | D12: Lead Generation | E12: eLearning project review | F12: Commercial | G12: Decision | H12: https://www.theeduassist.com/book-free-audit/ | J12: Published | K12: Critical | L12: SEO Manager | O12: Submit Review | P12: Services; pricing; proof | Q12: Service; Breadcrumb | R12: Needs Review | T12: Track form conversion
A13: CNT-009 | B13: Quality Assurance & Testing | C13: Service Page | D13: Quality Assurance & Testing | F13: Commercial | G13: Consideration | I13: https://docs.google.com/document/d/1f56qgIxvQ8BxjrmBfliB3yKROdXTLpazw-3e6_4kuHQ/edit?tab=t.yg0q4iabl9v4 | J13: Brief Available | K13: High | L13: Content Lead | O13: Get a 24–48 Hour Review | P13: Homepage; Services; relevant case study | Q13: Service; Breadcrumb | R13: Not Checked | T13: Legacy source data. Confirm whether page remains in current scope.
A14: CNT-010 | B14: custom elearning Content Development | C14: Service Page | D14: custom elearning Content Development | F14: Commercial | G14: Consideration | I14: https://docs.google.com/document/d/1f56qgIxvQ8BxjrmBfliB3yKROdXTLpazw-3e6_4kuHQ/edit?tab=t.5lutc4nxjx8 | J14: Brief Available | K14: High | L14: Content Lead | O14: Get a 24–48 Hour Review | P14: Homepage; Services; relevant case study | Q14: Service; Breadcrumb | R14: Not Checked | T14: Legacy source data. Confirm whether page remains in current scope.
A15: CNT-011 | B15: Audio & Video Production for eLearning | C15: Service Page | D15: Audio & Video Production for eLearning | F15: Commercial | G15: Consideration | I15: https://docs.google.com/document/d/1f56qgIxvQ8BxjrmBfliB3yKROdXTLpazw-3e6_4kuHQ/edit?tab=t.js459uanpi6m#heading=h.go603l3bm2g | J15: Brief Available | K15: High | L15: Content Lead | O15: Get a 24–48 Hour Review | P15: Homepage; Services; relevant case study | Q15: Service; Breadcrumb | R15: Not Checked | T15: Legacy source data. Confirm whether page remains in current scope.
A16: CNT-012 | B16: Learning Strategy & Consulting | C16: Service Page | D16: Learning Strategy & Consulting | F16: Commercial | G16: Consideration | I16: https://docs.google.com/document/d/1f56qgIxvQ8BxjrmBfliB3yKROdXTLpazw-3e6_4kuHQ/edit?tab=t.ovptwam8j30h#heading=h.d3vlvgz8zawx | J16: Brief Available | K16: High | L16: Content Lead | O16: Get a 24–48 Hour Review | P16: Homepage; Services; relevant case study | Q16: Service; Breadcrumb | R16: Not Checked | T16: Legacy source data. Confirm whether page remains in current scope.
A17: CNT-013 | B17: LMS implementation and migration | C17: Service Page | D17: LMS implementation and migration | F17: Commercial | G17: Consideration | I17: https://docs.google.com/document/d/1f56qgIxvQ8BxjrmBfliB3yKROdXTLpazw-3e6_4kuHQ/edit?tab=t.tohiqah9td47#heading=h.kd718vxvhsby | J17: Brief Available | K17: High | L17: Content Lead | O17: Get a 24–48 Hour Review | P17: Homepage; Services; relevant case study | Q17: Service; Breadcrumb | R17: Not Checked | T17: Legacy source data. Confirm whether page remains in current scope.
A18: CNT-014 | B18: Legacy Content Conversion Services | C18: Service Page | D18: Legacy Content Conversion Services | F18: Commercial | G18: Consideration | I18: https://docs.google.com/document/d/1f56qgIxvQ8BxjrmBfliB3yKROdXTLpazw-3e6_4kuHQ/edit?tab=t.o5zfykc0ue96#heading=h.yzndcpkh5oz9 | J18: Brief Available | K18: High | L18: Content Lead | O18: Get a 24–48 Hour Review | P18: Homepage; Services; relevant case study | Q18: Service; Breadcrumb | R18: Not Checked | T18: Legacy source data. Confirm whether page remains in current scope.
A19: CNT-015 | B19: Dashboard and Analytics | C19: Service Page | D19: Dashboard and Analytics | F19: Commercial | G19: Consideration | I19: https://docs.google.com/document/d/1f56qgIxvQ8BxjrmBfliB3yKROdXTLpazw-3e6_4kuHQ/edit?tab=t.kzfnsxwralxw | J19: Brief Available | K19: High | L19: Content Lead | O19: Get a 24–48 Hour Review | P19: Homepage; Services; relevant case study | Q19: Service; Breadcrumb | R19: Not Checked | T19: Legacy source data. Confirm whether page remains in current scope.
A20: CNT-016 | B20: Instructional & UI/UX Design | C20: Service Page | D20: Instructional & UI/UX Design | F20: Commercial | G20: Consideration | I20: https://theeduassist.com/2508-2/ | J20: Brief Available | K20: High | L20: Content Lead | O20: Get a 24–48 Hour Review | P20: Homepage; Services; relevant case study | Q20: Service; Breadcrumb | R20: Not Checked | T20: Legacy source data. Confirm whether page remains in current scope.
A21: CNT-017 | B21: Microlearning & Microsimulations | C21: Service Page | D21: Microlearning & Microsimulations | F21: Commercial | G21: Consideration | I21: https://docs.google.com/document/d/1f56qgIxvQ8BxjrmBfliB3yKROdXTLpazw-3e6_4kuHQ/edit?tab=t.ux8re1anxvxk | J21: Brief Available | K21: High | L21: Content Lead | O21: Get a 24–48 Hour Review | P21: Homepage; Services; relevant case study | Q21: Service; Breadcrumb | R21: Not Checked | T21: Legacy source data. Confirm whether page remains in current scope.
A22: CNT-018 | B22: Gamification | C22: Service Page | D22: Gamification | F22: Commercial | G22: Consideration | I22: https://docs.google.com/document/d/1f56qgIxvQ8BxjrmBfliB3yKROdXTLpazw-3e6_4kuHQ/edit?tab=t.cxbuvw6ey5v5 | J22: Brief Available | K22: High | L22: Content Lead | O22: Get a 24–48 Hour Review | P22: Homepage; Services; relevant case study | Q22: Service; Breadcrumb | R22: Not Checked | T22: Legacy source data. Confirm whether page remains in current scope.
A23: CNT-019 | B23: Scenario-Based Learning | C23: Service Page | D23: Scenario-Based Learning | F23: Commercial | G23: Consideration | I23: https://docs.google.com/document/d/1f56qgIxvQ8BxjrmBfliB3yKROdXTLpazw-3e6_4kuHQ/edit?tab=t.kb09wkbrauul | J23: Brief Available | K23: High | L23: Content Lead | O23: Get a 24–48 Hour Review | P23: Homepage; Services; relevant case study | Q23: Service; Breadcrumb | R23: Not Checked | T23: Legacy source data. Confirm whether page remains in current scope.
A24: CNT-020 | B24: K-12 Education Services | C24: Service Page | D24: K-12 Education Services | F24: Commercial | G24: Consideration | I24: https://docs.google.com/document/d/1f56qgIxvQ8BxjrmBfliB3yKROdXTLpazw-3e6_4kuHQ/edit?tab=t.79y8aqx5j6vf | J24: Brief Available | K24: High | L24: Content Lead | O24: Get a 24–48 Hour Review | P24: Homepage; Services; relevant case study | Q24: Service; Breadcrumb | R24: Not Checked | T24: Legacy source data. Confirm whether page remains in current scope.
... A38: CNT-034 | B38: Off-the-Shelf Corporate Courses/Ecourses OFF the shelf | C38: Service Page | D38: Off-the-Shelf Corporate Courses/Ecourses OFF the shelf | F38: Commercial | G38: Consideration | I38: https://www.tuvsud.com/en-in/store/academy-in/corporate-subscription-customized-content-solutions/customised-content-creation | J38: Brief Available | K38: Medium | L38: Content Lead | O38: Get a 24–48 Hour Review | P38: Homepage; Services; relevant case study | Q38: Service; Breadcrumb | R38: Not Checked | T38: Legacy source data. Confirm whether page remains in current scope.

Sheet 04 Technical Issues
A1: Technical SEO Issue Log
A2: Log verified issues only. Old findings are marked Needs Revalidation until checked against the current www deployment.
A4: Issue ID | B4: Detected Date | C4: Source | D4: Severity | E4: Category | F4: URL | G4: Issue | H4: SEO / Business Impact | I4: Recommended Fix | J4: Owner | K4: Status | L4: Due Date | M4: Evidence | N4: Validation Method | O4: Resolved Date | P4: Recurrence | Q4: Notes
A5: ISS-001 | B5: 46230 | C5: Legacy workbook | D5: Critical | E5: Canonical / Redirects | F5: https://www.theeduassist.com/ | G5: Active workbook contained many non-www URLs; current canonical is www | H5: Duplicate signals and incorrect reporting if legacy URLs remain in operations | I5: Verify one-hop redirects, canonical tags, sitemap and internal links use www | J5: Developer | K5: Needs Revalidation | L5: 46232 | N5: URL Inspection + curl + sitemap review | P5: One-time
A6: ISS-002 | B6: 46230 | C6: Legacy workbook | D6: Critical | E6: Broken Links | F6: https://theeduassist.com/case-study-1/ | G6: Legacy case study URL previously reported as 404 and visible on homepage | H6: Broken user journey and crawl waste | I6: Revalidate current featured-project cards; fix links or redirects | J6: Developer | K6: Needs Revalidation | L6: 46233 | N6: Crawler + manual click test | P6: One-time | Q6: Also check case-study-2 and case-study-3
A7: ISS-003 | B7: 46230 | C7: Legacy workbook | D7: High | E7: On-page / Conversion | F7: https://www.theeduassist.com/contact/ | G7: Legacy report mentioned missing schema, weak internal linking and no post-submit redirect | H7: May weaken trust, tracking and conversion measurement | I7: Check live page; add appropriate schema, internal links, confirmation state and GA4 key event if missing | J7: SEO Manager | K7: Needs Revalidation | L7: 46234 | N7: Manual test + Rich Results Test + GA4 DebugView | P7: Quarterly
A8: ISS-004 | B8: 46230 | C8: Legacy workbook | D8: High | E8: Trust / On-page | F8: https://www.theeduassist.com/about/ | G8: Legacy report mentioned weak H1, company story, team proof and credentials | H8: Reduced trust and weaker decision-stage support | I8: Review live page and strengthen verifiable company information, team disciplines, proof and CTA | J8: Content Lead | K8: Needs Revalidation | L8: 46235 | N8: Manual content QA + URL Inspection | P8: Quarterly
A9: ISS-005 | B9: 46230 | C9: Workbook audit | D9: High | E9: Content Governance | F9: Active keyword plan | G9: AR/VR keywords remained in old active research although service scope removed | H9: Wastes team time and creates irrelevant content plans | I9: Keep AR/VR only in raw archive; do not create active tasks or pages | J9: SEO Manager | K9: Resolved | L9: 46230 | M9: Redesigned workbook | N9: Review active keyword and content tabs | O9: 46230 | P9: One-time
A10: ISS-006 | B10: 46230 | C10: Workbook audit | D10: High | E10: Backlinks | F10: Legacy backlink export | G10: Raw list contains many high-authority but irrelevant/unrealistic domains | H10: Can cause wasted outreach and link-spam risk | I10: Qualify for topical relevance, editorial fit, realistic route and policy safety before outreach | J10: Outreach | K10: Open | L10: 46240 | N10: Manual relevance and risk review | P10: Monthly
A11: ISS-007 | B11: 46230 | C11: Recommended control | D11: Critical | E11: Analytics | F11: GA4 / forms | G11: SEO reporting does not yet include verified leads and conversion rate in the legacy data | H11: Team may optimize vanity metrics instead of business outcomes | I11: Track review form, contact, consultation and RFP key events; add to monthly performance sheet | J11: Developer | K11: Open | L11: 46239 | N11: GA4 DebugView + form test | P11: Monthly
A12: ISS-008 | B12: 46230 | C12: Recommended control | D12: High | E12: Structured Data | F12: Site templates | G12: Schema must match visible page content and be monitored after deployment | H12: Incorrect markup can lose rich-result eligibility | I12: Validate applicable Organization, Service, Article and Breadcrumb markup; do not mark hidden or irrelevant content | J12: Developer | K12: Open | L12: 46241 | N12: Rich Results Test + Search Console enhancements | P12: On deploy
A13: ISS-009 | B13: 46230 | C13: Recommended control | D13: High | E13: Indexing | F13: XML sitemap | G13: Sitemap should contain only canonical, indexable URLs intended for search | H13: Noncanonical or obsolete URLs slow QA and confuse reporting | I13: Validate sitemap after every routing/content migration; submit in GSC and Bing | J13: Developer | K13: Open | L13: 46236 | N13: Sitemap validation + URL inspection | P13: On deploy
A14: ISS-010 | B14: 46230 | C14: Recommended control | D14: Medium | E14: Core Web Vitals | F14: Key templates | G14: LCP, INP and CLS are not recorded in the legacy performance tracker | H14: Performance regressions may go unnoticed | I14: Record field data monthly and create tasks for poor URL groups | J14: SEO Manager | K14: Open | L14: 46239 | N14: Search Console CWV + PageSpeed Insights | P14: Monthly

Sheet 05 Performance
A1: SEO Performance and Business Outcomes
A2: Enter one row per reporting period. Use the same data source and date range each time. Record leads and conversion rate alongside visibility metrics.
A4: Date | B4: Organic Traffic | C4: Organic Keywords | D4: Authority | E4: Referring Domains | F4: Backlinks | G4: Dofollow | H4: Nofollow | I4: AI Visibility | J4: AI Mentions | K4: Cited Pages | L4: GSC Clicks | M4: GSC Impressions | N4: GSC CTR | O4: Average Position | P4: GA4 Organic Sessions | Q4: Organic Leads | R4: Conversion Rate | S4: LCP (s) | T4: INP (ms) | U4: CLS | V4: Notes
A5: 46149 | B5: 3900 | C5: 201 | D5: 8 | E5: 107 | F5: 246 | G5: 205 | H5: 41 | I5: 14 | J5: 2 | K5: 51 | R5: =IF(OR(P5="",Q5=""),"",Q5/P5) | V5: Legacy snapshot; source details not recorded
A6: 46167 | B6: 2400 | C6: 223 | D6: 11 | E6: 112 | F6: 256 | G6: 210 | H6: 46 | I6: 14 | J6: 2 | K6: 52 | R6: =IF(OR(P6="",Q6=""),"",Q6/P6) | V6: Legacy snapshot; source details not recorded
A7: 46174 | B7: 4400 | C7: 245 | D7: 11 | E7: 113 | F7: 244 | G7: 198 | H7: 46 | I7: 14 | J7: 1 | K7: 53 | R7: =IF(OR(P7="",Q7=""),"",Q7/P7) | V7: Legacy snapshot; source details not recorded
R8: =IF(OR(P8="",Q8=""),"",Q8/P8)
R9: =IF(OR(P9="",Q9=""),"",Q9/P9)
R10: =IF(OR(P10="",Q10=""),"",Q10/P10)
R11: =IF(OR(P11="",Q11=""),"",Q11/P11)
R12: =IF(OR(P12="",Q12=""),"",Q12/P12)
R13: =IF(OR(P13="",Q13=""),"",Q13/P13)
R14: =IF(OR(P14="",Q14=""),"",Q14/P14)
R15: =IF(OR(P15="",Q15=""),"",Q15/P15)
R16: =IF(OR(P16="",Q16=""),"",Q16/P16)
R17: =IF(OR(P17="",Q17=""),"",Q17/P17)
R18: =IF(OR(P18="",Q18=""),"",Q18/P18)
R19: =IF(OR(P19="",Q19=""),"",Q19/P19)
... R104: =IF(OR(P104="",Q104=""),"",Q104/P104)

Sheet 06 Competitors
A1: Competitor Benchmark and Gap Tracker
A2: Metrics below are an April 2026 legacy snapshot. Refresh before making decisions and record a concrete content or link gap, not only numbers.
A4: Competitor ID | B4: Competitor | C4: Organic Traffic | D4: Organic Keywords | E4: Authority | F4: Backlinks | G4: AI Visibility | H4: AI Mentions | I4: Snapshot Date | J4: Refresh Status | K4: Top Strength | L4: Content Gap for TheEduAssist | M4: Link Gap / Source | N4: Priority | O4: Owner | P4: Last Checked | Q4: Next Action | R4: Notes
A5: COM-01 | B5: https://elearning.folio3.com | C5: 325 | D5: 930 | E5: 43 | F5: 374 | G5: 19 | H5: 515 | I5: 46141 | J5: Refresh Needed | N5: Medium | O5: SEO Manager | Q5: Refresh metrics and identify one replicable content advantage
A6: COM-02 | B6: https://www.kytewayelearning.com/ | C6: 763 | D6: 907 | E6: 22 | F6: 42500 | G6: 22 | H6: 32 | I6: 46141 | J6: Refresh Needed | N6: Medium | O6: SEO Manager | Q6: Refresh metrics and identify one replicable content advantage
A7: COM-03 | B7: https://www.eidesign.net/ | C7: 1400 | D7: 2500 | E7: 29 | F7: 21400 | G7: 21 | H7: 40 | I7: 46141 | J7: Refresh Needed | N7: Medium | O7: SEO Manager | Q7: Refresh metrics and identify one replicable content advantage
A8: COM-04 | B8: https://bluecarrot.io/ | C8: 906 | D8: 2000 | E8: 28 | F8: 4000 | G8: 15 | H8: 47 | I8: 46141 | J8: Refresh Needed | N8: Medium | O8: SEO Manager | Q8: Refresh metrics and identify one replicable content advantage
A9: COM-05 | B9: https://elearning.company/ | C9: 575 | D9: 446 | E9: 25 | F9: 1800 | G9: 14 | H9: 3 | I9: 46141 | J9: Refresh Needed | N9: Medium | O9: SEO Manager | Q9: Refresh metrics and identify one replicable content advantage
A10: COM-06 | B10: https://www.acadecraft.com/ | C10: 4700 | D10: 6000 | E10: 31 | F10: 91100 | G10: 25 | H10: 34 | I10: 46141 | J10: Refresh Needed | N10: Medium | O10: SEO Manager | Q10: Refresh metrics and identify one replicable content advantage
A11: COM-07 | B11: https://qquench.ai/our-services/e-learning/ | C11: 4 | D11: 39 | E11: 6 | F11: 257 | G11: 0 | H11: 0 | I11: 46141 | J11: Refresh Needed | N11: Medium | O11: SEO Manager | Q11: Refresh metrics and identify one replicable content advantage
A12: COM-08 | B12: https://redchipsolutions.com/ | C12: 210 | D12: 225 | E12: 20 | F12: 848 | G12: 14 | H12: 0 | I12: 46141 | J12: Refresh Needed | N12: Medium | O12: SEO Manager | Q12: Refresh metrics and identify one replicable content advantage
A13: COM-09 | B13: https://piogroup.net/ | C13: 905 | D13: 1200 | E13: 22 | F13: 2600 | G13: 14 | H13: 2 | I13: 46141 | J13: Refresh Needed | N13: Medium | O13: SEO Manager | Q13: Refresh metrics and identify one replicable content advantage
A14: COM-10 | B14: https://www.learningeverest.com/ | C14: 6800 | D14: 9500 | E14: 31 | F14: 42100 | G14: 16 | H14: 19 | I14: 46141 | J14: Refresh Needed | N14: Medium | O14: SEO Manager | Q14: Refresh metrics and identify one replicable content advantage
A15: COM-11 | B15: https://stratbeans.com/ | C15: 1100 | D15: 2400 | E15: 27 | F15: 2400 | G15: 14 | H15: 21 | I15: 46141 | J15: Refresh Needed | N15: Medium | O15: SEO Manager | Q15: Refresh metrics and identify one replicable content advantage
A16: COM-12 | B16: https://www.swiftelearningservices.com/ | C16: 892 | D16: 4300 | E16: 28 | F16: 41000 | G16: 18 | H16: 37 | I16: 46141 | J16: Refresh Needed | N16: Medium | O16: SEO Manager | Q16: Refresh metrics and identify one replicable content advantage
... A38: COM-34 | B38: https://jupitered.com/ | C38: 789800 | D38: 6000 | E38: 51 | F38: 66900 | G38: 32 | H38: 120 | I38: 46141 | J38: Refresh Needed | N38: Medium | O38: SEO Manager | Q38: Refresh metrics and identify one replicable content advantage

Sheet 07 Link Opportunities
A1: Link Opportunity Qualification
A2: Raw domains are not outreach targets until they pass relevance, realism and risk checks. Avoid link exchanges, paid ranking links and low-quality directories.
A4: Opportunity ID | B4: Domain | C4: Example URL | D4: Authority | E4: Monthly Visits | F4: Why Relevant | G4: Opportunity Type | H4: Target Page | I4: Contact / Submission Route | J4: Risk Check | K4: Status | L4: Owner | M4: Last Checked | N4: Next Step | O4: Notes
A5: LNK-001 | B5: medium.com | C5: https://medium.com/ | D5: 97 | E5: 116000000 | F5: Needs manual topical review | G5: Editorial contribution / resource inclusion | J5: Manual review required | K5: Unqualified | L5: Outreach | N5: Confirm relevance and realistic outreach path | O5: Legacy competitor/export source
A6: LNK-002 | B6: businessinsider.com | C6: www.emarketer.com | D6: 91 | E6: 77300000 | F6: Needs manual topical review | G6: Editorial contribution / resource inclusion | J6: Manual review required | K6: Unqualified | L6: Outreach | N6: Confirm relevance and realistic outreach path | O6: Legacy competitor/export source
A7: LNK-003 | B7: business-standard.com | C7: feedback@business-standard.com | D7: 84 | E7: 6900000 | F7: Needs manual topical review | G7: Editorial contribution / resource inclusion | J7: Manual review required | K7: Unqualified | L7: Outreach | N7: Confirm relevance and realistic outreach path | O7: Legacy competitor/export source
A8: LNK-004 | B8: telkomuniversity.ac.id | D8: 68 | E8: 2700000 | F8: Needs manual topical review | G8: Editorial contribution / resource inclusion | J8: Manual review required | K8: Unqualified | L8: Outreach | N8: Confirm relevance and realistic outreach path | O8: Legacy competitor/export source
A9: LNK-005 | B9: bestcolleges.com | D9: 63 | E9: 959000 | F9: Needs manual topical review | G9: Editorial contribution / resource inclusion | J9: Manual review required | K9: Unqualified | L9: Outreach | N9: Confirm relevance and realistic outreach path | O9: Legacy competitor/export source
A10: LNK-006 | B10: jobsdb.com | D10: 62 | E10: 5400000 | F10: Needs manual topical review | G10: Editorial contribution / resource inclusion | J10: Manual review required | K10: Unqualified | L10: Outreach | N10: Confirm relevance and realistic outreach path | O10: Legacy competitor/export source
A11: LNK-007 | B11: designrush.com | D11: 59 | E11: 639000 | F11: Needs manual topical review | G11: Editorial contribution / resource inclusion | J11: Manual review required | K11: Unqualified | L11: Outreach | N11: Confirm relevance and realistic outreach path | O11: Legacy competitor/export source
A12: LNK-008 | B12: aihr.com | D12: 58 | E12: 537000 | F12: Needs manual topical review | G12: Editorial contribution / resource inclusion | J12: Manual review required | K12: Unqualified | L12: Outreach | N12: Confirm relevance and realistic outreach path | O12: Legacy competitor/export source
A13: LNK-009 | B13: shrm.org | D13: 57 | E13: 2900000 | F13: Needs manual topical review | G13: Editorial contribution / resource inclusion | J13: Manual review required | K13: Unqualified | L13: Outreach | N13: Confirm relevance and realistic outreach path | O13: Legacy competitor/export source
A14: LNK-010 | B14: elearningindustry.com | D14: 54 | E14: 335000 | F14: Needs manual topical review | G14: Editorial contribution / resource inclusion | J14: Manual review required | K14: Unqualified | L14: Outreach | N14: Confirm relevance and realistic outreach path | O14: Legacy competitor/export source
A15: LNK-011 | B15: fortunebusinessinsights.com | D15: 53 | E15: 605000 | F15: Needs manual topical review | G15: Editorial contribution / resource inclusion | J15: Manual review required | K15: Unqualified | L15: Outreach | N15: Confirm relevance and realistic outreach path | O15: Legacy competitor/export source
A16: LNK-012 | B16: 360learning.com | D16: 49 | E16: 906000 | F16: Needs manual topical review | G16: Editorial contribution / resource inclusion | J16: Manual review required | K16: Unqualified | L16: Outreach | N16: Confirm relevance and realistic outreach path | O16: Legacy competitor/export source
A17: LNK-013 | B17: breezy.hr | D17: 47 | E17: 4600000 | F17: Needs manual topical review | G17: Editorial contribution / resource inclusion | J17: Manual review required | K17: Unqualified | L17: Outreach | N17: Confirm relevance and realistic outreach path | O17: Legacy competitor/export source
A18: LNK-014 | B18: trainingmag.com | D18: 45 | E18: 32600 | F18: Needs manual topical review | G18: Editorial contribution / resource inclusion | J18: Manual review required | K18: Unqualified | L18: Outreach | N18: Confirm relevance and realistic outreach path | O18: Legacy competitor/export source
A19: LNK-015 | B19: hotelcareer.de | D19: 45 | E19: 1100000 | F19: Needs manual topical review | G19: Editorial contribution / resource inclusion | J19: Manual review required | K19: Unqualified | L19: Outreach | N19: Confirm relevance and realistic outreach path | O19: Legacy competitor/export source
... A134: LNK-130 | B134: learnpatch.com | D134: 20 | E134: 170 | F134: Needs manual topical review | G134: Editorial contribution / resource inclusion | J134: Manual review required | K134: Unqualified | L134: Outreach | N134: Confirm relevance and realistic outreach path | O134: Legacy competitor/export source
A135: LNK-131 | B135: archylearning.com | D135: 19 | F135: Needs manual topical review | G135: Editorial contribution / resource inclusion | J135: Manual review required | K135: Unqualified | L135: Outreach | N135: Confirm relevance and realistic outreach path | O135: Legacy competitor/export source
A136: LNK-132 | B136: ill-career.co.jp | D136: 19 | F136: Needs manual topical review | G136: Editorial contribution / resource inclusion | J136: Manual review required | K136: Unqualified | L136: Outreach | N136: Confirm relevance and realistic outreach path | O136: Legacy competitor/export source
A137: LNK-133 | B137: peopleopsjobs.io | D137: 19 | E137: 6500 | F137: Needs manual topical review | G137: Editorial contribution / resource inclusion | J137: Manual review required | K137: Unqualified | L137: Outreach | N137: Confirm relevance and realistic outreach path | O137: Legacy competitor/export source
A138: LNK-134 | B138: businessseek.biz | D138: 18 | E138: 19300 | F138: Needs manual topical review | G138: Editorial contribution / resource inclusion | J138: Manual review required | K138: Unqualified | L138: Outreach | N138: Confirm relevance and realistic outreach path | O138: Legacy competitor/export source
A139: LNK-135 | B139: careertown.net | D139: 18 | E139: 856 | F139: Needs manual topical review | G139: Editorial contribution / resource inclusion | J139: Manual review required | K139: Unqualified | L139: Outreach | N139: Confirm relevance and realistic outreach path | O139: Legacy competitor/export source
A140: LNK-136 | B140: frozenfirefilms.com | D140: 18 | F140: Needs manual topical review | G140: Editorial contribution / resource inclusion | J140: Manual review required | K140: Unqualified | L140: Outreach | N140: Confirm relevance and realistic outreach path | O140: Legacy competitor/export source
A141: LNK-137 | B141: southshoreacademyblackpool.co.uk | D141: 18 | F141: Needs manual topical review | G141: Editorial contribution / resource inclusion | J141: Manual review required | K141: Unqualified | L141: Outreach | N141: Confirm relevance and realistic outreach path | O141: Legacy competitor/export source
A142: LNK-138 | B142: globalhrcommunity.com | D142: 17 | E142: 1700 | F142: Needs manual topical review | G142: Editorial contribution / resource inclusion | J142: Manual review required | K142: Unqualified | L142: Outreach | N142: Confirm relevance and realistic outreach path | O142: Legacy competitor/export source
A143: LNK-139 | B143: hranexi.com | D143: 17 | E143: 15200 | F143: Needs manual topical review | G143: Editorial contribution / resource inclusion | J143: Manual review required | K143: Unqualified | L143: Outreach | N143: Confirm relevance and realistic outreach path | O143: Legacy competitor/export source
A144: LNK-140 | B144: qualityservicemarketing.com | D144: 17 | F144: Needs manual topical review | G144: Editorial contribution / resource inclusion | J144: Manual review required | K144: Unqualified | L144: Outreach | N144: Confirm relevance and realistic outreach path | O144: Legacy competitor/export source
A145: LNK-141 | B145: unitedkingdominbusiness.co.uk | D145: 17 | E145: 18900 | F145: Needs manual topical review | G145: Editorial contribution / resource inclusion | J145: Manual review required | K145: Unqualified | L145: Outreach | N145: Confirm relevance and realistic outreach path | O145: Legacy competitor/export source
A146: LNK-142 | B146: usabusinessradio.com | D146: 17 | E146: 1500 | F146: Needs manual topical review | G146: Editorial contribution / resource inclusion | J146: Manual review required | K146: Unqualified | L146: Outreach | N146: Confirm relevance and realistic outreach path | O146: Legacy competitor/export source
A147: LNK-143 | B147: elearning.space | D147: 16 | E147: 23 | F147: Needs manual topical review | G147: Editorial contribution / resource inclusion | J147: Manual review required | K147: Unqualified | L147: Outreach | N147: Confirm relevance and realistic outreach path | O147: Legacy competitor/export source
A148: LNK-144 | B148: businessmad.com | D148: 16 | E148: 29500 | F148: Needs manual topical review | G148: Editorial contribution / resource inclusion | J148: Manual review required | K148: Unqualified | L148: Outreach | N148: Confirm relevance and realistic outreach path | O148: Legacy competitor/export source
A149: LNK-145 | B149: hohmannchris.wordpress.com | D149: 16 | E149: 588 | F149: Needs manual topical review | G149: Editorial contribution / resource inclusion | J149: Manual review required | K149: Unqualified | L149: Outreach | N149: Confirm relevance and realistic outreach path | O149: Legacy competitor/export source
A150: LNK-146 | B150: me-hrl.com | D150: 16 | E150: 360 | F150: Needs manual topical review | G150: Editorial contribution / resource inclusion | J150: Manual review required | K150: Unqualified | L150: Outreach | N150: Confirm relevance and realistic outreach path | O150: Legacy competitor/export source
A151: LNK-147 | B151: omnihrc.com | D151: 16 | E151: 1000 | F151: Needs manual topical review | G151: Editorial contribution / resource inclusion | J151: Manual review required | K151: Unqualified | L151: Outreach | N151: Confirm relevance and realistic outreach path | O151: Legacy competitor/export source
A152: LNK-148 | B152: elearningrobie.pl | D152: 15 | F152: Needs manual topical review | G152: Editorial contribution / resource inclusion | J152: Manual review required | K152: Unqualified | L152: Outreach | N152: Confirm relevance and realistic outreach path | O152: Legacy competitor/export source
A153: LNK-149 | B153: jobsnearme.com.au | D153: 15 | E153: 1200 | F153: Needs manual topical review | G153: Editorial contribution / resource inclusion | J153: Manual review required | K153: Unqualified | L153: Outreach | N153: Confirm relevance and realistic outreach path | O153: Legacy competitor/export source
A154: LNK-150 | B154: dx-learning.com | D154: 14 | E154: 259 | F154: Needs manual topical review | G154: Editorial contribution / resource inclusion | J154: Manual review required | K154: Unqualified | L154: Outreach | N154: Confirm relevance and realistic outreach path | O154: Legacy competitor/export source
A155: LNK-151 | B155: imhvacmarketing.com | D155: 14 | E155: 2800 | F155: Needs manual topical review | G155: Editorial contribution / resource inclusion | J155: Manual review required | K155: Unqualified | L155: Outreach | N155: Confirm relevance and realistic outreach path | O155: Legacy competitor/export source
A156: LNK-152 | B156: leaphr-lifesciences-europe.com | D156: 14 | F156: Needs manual topical review | G156: Editorial contribution / resource inclusion | J156: Manual review required | K156: Unqualified | L156: Outreach | N156: Confirm relevance and realistic outreach path | O156: Legacy competitor/export source
A157: LNK-153 | B157: mypodcastdata.com | D157: 14 | E157: 2900 | F157: Needs manual topical review | G157: Editorial contribution / resource inclusion | J157: Manual review required | K157: Unqualified | L157: Outreach | N157: Confirm relevance and realistic outreach path | O157: Legacy competitor/export source
A158: LNK-154 | B158: openjobs-ai.com | D158: 14 | E158: 4400 | F158: Needs manual topical review | G158: Editorial contribution / resource inclusion | J158: Manual review required | K158: Unqualified | L158: Outreach | N158: Confirm relevance and realistic outreach path | O158: Legacy competitor/export source
A159: LNK-155 | B159: business-dir.co.uk | D159: 13 | E159: 12700 | F159: Needs manual topical review | G159: Editorial contribution / resource inclusion | J159: Manual review required | K159: Unqualified | L159: Outreach | N159: Confirm relevance and realistic outreach path | O159: Legacy competitor/export source
A160: LNK-156 | B160: elearningtags.com | D160: 13 | F160: Needs manual topical review | G160: Editorial contribution / resource inclusion | J160: Manual review required | K160: Unqualified | L160: Outreach | N160: Confirm relevance and realistic outreach path | O160: Legacy competitor/export source
A161: LNK-157 | B161: businesscontacts.io | D161: 12 | E161: 2000 | F161: Needs manual topical review | G161: Editorial contribution / resource inclusion | J161: Manual review required | K161: Unqualified | L161: Outreach | N161: Confirm relevance and realistic outreach path | O161: Legacy competitor/export source
A162: LNK-158 | B162: businessveyor.com | D162: 12 | E162: 19100 | F162: Needs manual topical review | G162: Editorial contribution / resource inclusion | J162: Manual review required | K162: Unqualified | L162: Outreach | N162: Confirm relevance and realistic outreach path | O162: Legacy competitor/export source
A163: LNK-159 | B163: chriscurnow.com | D163: 12 | F163: Needs manual topical review | G163: Editorial contribution / resource inclusion | J163: Manual review required | K163: Unqualified | L163: Outreach | N163: Confirm relevance and realistic outreach path | O163: Legacy competitor/export source
A164: LNK-160 | B164: educationtreeglobal.com | D164: 12 | E164: 984 | F164: Needs manual topical review | G164: Editorial contribution / resource inclusion | J164: Manual review required | K164: Unqualified | L164: Outreach | N164: Confirm relevance and realistic outreach path | O164: Legacy competitor/export source
A165: LNK-161 | B165: ejobscircular.com | D165: 12 | E165: 23000 | F165: Needs manual topical review | G165: Editorial contribution / resource inclusion | J165: Manual review required | K165: Unqualified | L165: Outreach | N165: Confirm relevance and realistic outreach path | O165: Legacy competitor/export source
A166: LNK-162 | B166: learningdevelopment.institute | D166: 12 | F166: Needs manual topical review | G166: Editorial contribution / resource inclusion | J166: Manual review required | K166: Unqualified | L166: Outreach | N166: Confirm relevance and realistic outreach path | O166: Legacy competitor/export source
A167: LNK-163 | B167: learningisthenewworking.org | D167: 12 | E167: 1900 | F167: Needs manual topical review | G167: Editorial contribution / resource inclusion | J167: Manual review required | K167: Unqualified | L167: Outreach | N167: Confirm relevance and realistic outreach path | O167: Legacy competitor/export source
A168: LNK-164 | B168: techmindsoftware.com | D168: 12 | E168: 691 | F168: Needs manual topical review | G168: Editorial contribution / resource inclusion | J168: Manual review required | K168: Unqualified | L168: Outreach | N168: Confirm relevance and realistic outreach path | O168: Legacy competitor/export source
A169: LNK-165 | B169: freshersjobs24.com | D169: 11 | E169: 69500 | F169: Needs manual topical review | G169: Editorial contribution / resource inclusion | J169: Manual review required | K169: Unqualified | L169: Outreach | N169: Confirm relevance and realistic outreach path | O169: Legacy competitor/export source
A170: LNK-166 | B170: learncourses.us | D170: 11 | E170: 301 | F170: Needs manual topical review | G170: Editorial contribution / resource inclusion | J170: Manual review required | K170: Unqualified | L170: Outreach | N170: Confirm relevance and realistic outreach path | O170: Legacy competitor/export source
A171: LNK-167 | B171: qualityservicemarketing.blogs.com | D171: 11 | F171: Needs manual topical review | G171: Editorial contribution / resource inclusion | J171: Manual review required | K171: Unqualified | L171: Outreach | N171: Confirm relevance and realistic outreach path | O171: Legacy competitor/export source
A172: LNK-168 | B172: 1clickeducation.com | D172: 10 | F172: Needs manual topical review | G172: Editorial contribution / resource inclusion | J172: Manual review required | K172: Unqualified | L172: Outreach | N172: Confirm relevance and realistic outreach path | O172: Legacy competitor/export source
A173: LNK-169 | B173: borobudur-training.com | D173: 10 | E173: 261 | F173: Needs manual topical review | G173: Editorial contribution / resource inclusion | J173: Manual review required | K173: Unqualified | L173: Outreach | N173: Confirm relevance and realistic outreach path | O173: Legacy competitor/export source
A174: LNK-170 | B174: schoolscompass.com.ng | D174: 10 | E174: 3500 | F174: Needs manual topical review | G174: Editorial contribution / resource inclusion | J174: Manual review required | K174: Unqualified | L174: Outreach | N174: Confirm relevance and realistic outreach path | O174: Legacy competitor/export source
A175: LNK-171 | B175: indianbusinessdirectory.in | D175: 9 | E175: 3700 | F175: Needs manual topical review | G175: Editorial contribution / resource inclusion | J175: Manual review required | K175: Unqualified | L175: Outreach | N175: Confirm relevance and realistic outreach path | O175: Legacy competitor/export source
A176: LNK-172 | B176: learningplatforms.net | D176: 9 | E176: 237 | F176: Needs manual topical review | G176: Editorial contribution / resource inclusion | J176: Manual review required | K176: Unqualified | L176: Outreach | N176: Confirm relevance and realistic outreach path | O176: Legacy competitor/export source
A177: LNK-173 | B177: liveuaejobs.com | D177: 9 | E177: 186000 | F177: Needs manual topical review | G177: Editorial contribution / resource inclusion | J177: Manual review required | K177: Unqualified | L177: Outreach | N177: Confirm relevance and realistic outreach path | O177: Legacy competitor/export source
A178: LNK-174 | B178: mycareerfair.my | D178: 9 | E178: 1200 | F178: Needs manual topical review | G178: Editorial contribution / resource inclusion | J178: Manual review required | K178: Unqualified | L178: Outreach | N178: Confirm relevance and realistic outreach path | O178: Legacy competitor/export source
A179: LNK-175 | B179: findlocalbusiness.au | D179: 8 | E179: 3400 | F179: Needs manual topical review | G179: Editorial contribution / resource inclusion | J179: Manual review required | K179: Unqualified | L179: Outreach | N179: Confirm relevance and realistic outreach path | O179: Legacy competitor/export source
A180: LNK-176 | B180: hertsbusinessesdirectory.co.uk | D180: 8 | E180: 592 | F180: Needs manual topical review | G180: Editorial contribution / resource inclusion | J180: Manual review required | K180: Unqualified | L180: Outreach | N180: Confirm relevance and realistic outreach path | O180: Legacy competitor/export source
A181: LNK-177 | B181: hrdailywire.com | D181: 8 | F181: Needs manual topical review | G181: Editorial contribution / resource inclusion | J181: Manual review required | K181: Unqualified | L181: Outreach | N181: Confirm relevance and realistic outreach path | O181: Legacy competitor/export source
A182: LNK-178 | B182: kanakadasaschool.in | D182: 8 | E182: 178 | F182: Needs manual topical review | G182: Editorial contribution / resource inclusion | J182: Manual review required | K182: Unqualified | L182: Outreach | N182: Confirm relevance and realistic outreach path | O182: Legacy competitor/export source
A183: LNK-179 | B183: learninglovers.org | D183: 8 | E183: 676 | F183: Needs manual topical review | G183: Editorial contribution / resource inclusion | J183: Manual review required | K183: Unqualified | L183: Outreach | N183: Confirm relevance and realistic outreach path | O183: Legacy competitor/export source
A184: LNK-180 | B184: lxdlearningexperiencedesign.com | D184: 8 | E184: 1000 | F184: Needs manual topical review | G184: Editorial contribution / resource inclusion | J184: Manual review required | K184: Unqualified | L184: Outreach | N184: Confirm relevance and realistic outreach path | O184: Legacy competitor/export source
A185: LNK-181 | B185: proactivetraining.com.au | D185: 8 | E185: 2300 | F185: Needs manual topical review | G185: Editorial contribution / resource inclusion | J185: Manual review required | K185: Unqualified | L185: Outreach | N185: Confirm relevance and realistic outreach path | O185: Legacy competitor/export source
A186: LNK-182 | B186: uschool.asia | D186: 7 | F186: Needs manual topical review | G186: Editorial contribution / resource inclusion | J186: Manual review required | K186: Unqualified | L186: Outreach | N186: Confirm relevance and realistic outreach path | O186: Legacy competitor/export source
A187: LNK-183 | B187: erickswebsdesign.com | D187: 7 | E187: 217 | F187: Needs manual topical review | G187: Editorial contribution / resource inclusion | J187: Manual review required | K187: Unqualified | L187: Outreach | N187: Confirm relevance and realistic outreach path | O187: Legacy competitor/export source
A188: LNK-184 | B188: jobsfind.click | D188: 7 | E188: 95 | F188: Needs manual topical review | G188: Editorial contribution / resource inclusion | J188: Manual review required | K188: Unqualified | L188: Outreach | N188: Confirm relevance and realistic outreach path | O188: Legacy competitor/export source
A189: LNK-185 | B189: leanbusinessclub.com | D189: 7 | E189: 436 | F189: Needs manual topical review | G189: Editorial contribution / resource inclusion | J189: Manual review required | K189: Unqualified | L189: Outreach | N189: Confirm relevance and realistic outreach path | O189: Legacy competitor/export source
A190: LNK-186 | B190: learningoutofthelms.com | D190: 7 | F190: Needs manual topical review | G190: Editorial contribution / resource inclusion | J190: Manual review required | K190: Unqualified | L190: Outreach | N190: Confirm relevance and realistic outreach path | O190: Legacy competitor/export source
A191: LNK-187 | B191: ministryhr.com | D191: 7 | E191: 196 | F191: Needs manual topical review | G191: Editorial contribution / resource inclusion | J191: Manual review required | K191: Unqualified | L191: Outreach | N191: Confirm relevance and realistic outreach path | O191: Legacy competitor/export source
A192: LNK-188 | B192: globalelearningsolution.com | D192: 6 | E192: 53 | F192: Needs manual topical review | G192: Editorial contribution / resource inclusion | J192: Manual review required | K192: Unqualified | L192: Outreach | N192: Confirm relevance and realistic outreach path | O192: Legacy competitor/export source
A193: LNK-189 | B193: amanahru.blogspot.com | D193: 6 | F193: Needs manual topical review | G193: Editorial contribution / resource inclusion | J193: Manual review required | K193: Unqualified | L193: Outreach | N193: Confirm relevance and realistic outreach path | O193: Legacy competitor/export source
A194: LNK-190 | B194: american-podcasts.com | D194: 6 | E194: 4300 | F194: Needs manual topical review | G194: Editorial contribution / resource inclusion | J194: Manual review required | K194: Unqualified | L194: Outreach | N194: Confirm relevance and realistic outreach path | O194: Legacy competitor/export source
A195: LNK-191 | B195: businessperform.com | D195: 6 | E195: 98 | F195: Needs manual topical review | G195: Editorial contribution / resource inclusion | J195: Manual review required | K195: Unqualified | L195: Outreach | N195: Confirm relevance and realistic outreach path | O195: Legacy competitor/export source
A196: LNK-192 | B196: christine-arnaud.com | D196: 6 | F196: Needs manual topical review | G196: Editorial contribution / resource inclusion | J196: Manual review required | K196: Unqualified | L196: Outreach | N196: Confirm relevance and realistic outreach path | O196: Legacy competitor/export source
A197: LNK-193 | B197: communicationbydesign.net | D197: 6 | F197: Needs manual topical review | G197: Editorial contribution / resource inclusion | J197: Manual review required | K197: Unqualified | L197: Outreach | N197: Confirm relevance and realistic outreach path | O197: Legacy competitor/export source
A198: LNK-194 | B198: designsfurnish.com | D198: 6 | E198: 57 | F198: Needs manual topical review | G198: Editorial contribution / resource inclusion | J198: Manual review required | K198: Unqualified | L198: Outreach | N198: Confirm relevance and realistic outreach path | O198: Legacy competitor/export source
A199: LNK-195 | B199: greentechshredding.com | D199: 6 | E199: 171 | F199: Needs manual topical review | G199: Editorial contribution / resource inclusion | J199: Manual review required | K199: Unqualified | L199: Outreach | N199: Confirm relevance and realistic outreach path | O199: Legacy competitor/export source
A200: LNK-196 | B200: leolearning.com | D200: 6 | F200: Needs manual topical review | G200: Editorial contribution / resource inclusion | J200: Manual review required | K200: Unqualified | L200: Outreach | N200: Confirm relevance and realistic outreach path | O200: Legacy competitor/export source
A201: LNK-197 | B201: litesoftware.com | D201: 6 | E201: 394 | F201: Needs manual topical review | G201: Editorial contribution / resource inclusion | J201: Manual review required | K201: Unqualified | L201: Outreach | N201: Confirm relevance and realistic outreach path | O201: Legacy competitor/export source
A202: LNK-198 | B202: onlinelearningconference.com | D202: 6 | F202: Needs manual topical review | G202: Editorial contribution / resource inclusion | J202: Manual review required | K202: Unqualified | L202: Outreach | N202: Confirm relevance and realistic outreach path | O202: Legacy competitor/export source
A203: LNK-199 | B203: buzzshrink.website | D203: 5 | E203: 7200 | F203: Needs manual topical review | G203: Editorial contribution / resource inclusion | J203: Manual review required | K203: Unqualified | L203: Outreach | N203: Confirm relevance and realistic outreach path | O203: Legacy competitor/export source
A204: LNK-200 | B204: businessfreedirectory.com | D204: 5 | E204: 9100 | F204: Needs manual topical review | G204: Editorial contribution / resource inclusion | J204: Manual review required | K204: Unqualified | L204: Outreach | N204: Confirm relevance and realistic outreach path | O204: Legacy competitor/export source

Sheet 08 AI Visibility
A1: AI Search Visibility and Citation Tracking
A2: Track real questions and whether TheEduAssist is mentioned or cited. There is no special AI markup requirement; indexed, crawlable, useful content remains the foundation.
A4: Query ID | B4: Question / Prompt | C4: Topic | D4: Platform | E4: Date Checked | F4: Brand Mentioned | G4: Cited | H4: Cited URL | I4: Prominence | J4: Competitor Cited | K4: Answer Accurate | L4: Sentiment | M4: Opportunity / Missing Information | N4: Owner | O4: Status | P4: Next Check | Q4: Evidence | R4: Notes
A5: AIQ-001 | B5: What is a Learning Management System (LMS) and why is it important for my online course? | C5: LMS Integration & Consulting | D5: Google | F5: Not Checked | G5: Not Checked | K5: Not Checked | L5: Neutral | N5: SEO Manager | O5: Planned | R5: Source/verification note: Google
A6: AIQ-002 | B6: Which LMS is best for launching a small-scale online course — Thinkific, Moodle, or Kajabi? | C6: LMS Integration & Consulting | D6: YouTube | F6: Not Checked | G6: Not Checked | K6: Not Checked | L6: Neutral | N6: SEO Manager | O6: Planned | R6: Source/verification note: YouTube
A7: AIQ-003 | B7: How do I ensure my courses are SCORM-compliant on different LMS platforms? | C7: LMS Integration & Consulting | F7: Not Checked | G7: Not Checked | K7: Not Checked | L7: Neutral | N7: SEO Manager | O7: Planned | R7: Source/verification note: Competitor Blogs
A8: AIQ-004 | B8: How can I make my courses mobile-friendly across LMS platforms? | C8: LMS Integration & Consulting | D8: AI | F8: Not Checked | G8: Not Checked | K8: Not Checked | L8: Neutral | N8: SEO Manager | O8: Planned | R8: Source/verification note: AI
A9: AIQ-005 | B9: What features should I look for in an LMS (quizzes, analytics, payment, integrations)? | C9: LMS Integration & Consulting | D9: Google | F9: Not Checked | G9: Not Checked | K9: Not Checked | L9: Neutral | N9: SEO Manager | O9: Planned | R9: Source/verification note: Google
A10: AIQ-006 | B10: Can I migrate my courses from one LMS to another if needed? | C10: LMS Integration & Consulting | F10: Not Checked | G10: Not Checked | K10: Not Checked | L10: Neutral | N10: SEO Manager | O10: Planned | R10: Source/verification note: Competitor Blogs
A11: AIQ-007 | B11: What are the costs associated with different LMS platforms in 2025? | C11: LMS Integration & Consulting | D11: Google | F11: Not Checked | G11: Not Checked | K11: Not Checked | L11: Neutral | N11: SEO Manager | O11: Planned | R11: Source/verification note: Google
A12: AIQ-008 | B12: LMS What are the pros and cons of open-source LMS (Moodle) vs paid LMS (Thinkific/Kajabi)? | C12: LMS Integration & Consulting | D12: YouTube | F12: Not Checked | G12: Not Checked | K12: Not Checked | L12: Neutral | N12: SEO Manager | O12: Planned | R12: Source/verification note: YouTube
A13: AIQ-009 | B13: How can I integrate videos, quizzes, and interactive modules into an LMS? | C13: LMS Integration & Consulting | D13: AI | F13: Not Checked | G13: Not Checked | K13: Not Checked | L13: Neutral | N13: SEO Manager | O13: Planned | R13: Source/verification note: AI
A14: AIQ-010 | B14: Is LMS suitable for corporate training or only for public courses? | C14: LMS Integration & Consulting | D14: Google | F14: Not Checked | G14: Not Checked | K14: Not Checked | L14: Neutral | N14: SEO Manager | O14: Planned | R14: Source/verification note: Google
A15: AIQ-011 | B15: How secure are LMS platforms for storing course content and user data? | C15: LMS Integration & Consulting | F15: Not Checked | G15: Not Checked | K15: Not Checked | L15: Neutral | N15: SEO Manager | O15: Planned | R15: Source/verification note: Competitor Blogs
A16: AIQ-012 | B16: Can I integrate my LMS with other tools like Zoom, Slack, or Salesforce? | C16: LMS Integration & Consulting | D16: Google | F16: Not Checked | G16: Not Checked | K16: Not Checked | L16: Neutral | N16: SEO Manager | O16: Planned | R16: Source/verification note: Google
A17: AIQ-013 | B17: Can LMS automate course enrollment, reminders, and certificates for learners? | C17: LMS Integration & Consulting | D17: AI | F17: Not Checked | G17: Not Checked | K17: Not Checked | L17: Neutral | N17: SEO Manager | O17: Planned | R17: Source/verification note: AI
A18: AIQ-014 | B18: What kind of support and training do LMS providers offer for course creators? | C18: LMS Integration & Consulting | F18: Not Checked | G18: Not Checked | K18: Not Checked | L18: Neutral | N18: SEO Manager | O18: Planned | R18: Source/verification note: Competitor Blogs
A19: AIQ-015 | B19: Can I brand my LMS interface with my company logo and colors? | C19: LMS Integration & Consulting | D19: Google | F19: Not Checked | G19: Not Checked | K19: Not Checked | L19: Neutral | N19: SEO Manager | O19: Planned | R19: Source/verification note: Google
A20: AIQ-016 | B20: How can LMS help collect feedback and improve courses based on learner input? | C20: LMS Integration & Consulting | D20: AI | F20: Not Checked | G20: Not Checked | K20: Not Checked | L20: Neutral | N20: SEO Manager | O20: Planned | R20: Source/verification note: AI
A21: AIQ-017 | B21: Do LMS platforms allow learners to access content offline? | C21: LMS Integration & Consulting | D21: Google | F21: Not Checked | G21: Not Checked | K21: Not Checked | L21: Neutral | N21: SEO Manager | O21: Planned | R21: Source/verification note: Google
A22: AIQ-018 | B22: Which LMS platforms are best for corporate compliance and certification tracking? | C22: LMS Integration & Consulting | F22: Not Checked | G22: Not Checked | K22: Not Checked | L22: Neutral | N22: SEO Manager | O22: Planned | R22: Source/verification note: Competitor Blogs
A23: AIQ-019 | B23: What does “AI-powered course creation” mean and how does it improve eLearning? | C23: AI-Powered Course Creation | D23: AI | F23: Not Checked | G23: Not Checked | K23: Not Checked | L23: Neutral | N23: SEO Manager | O23: Planned | R23: Source/verification note: AI
A24: AIQ-020 | B24: Can AI generate course outlines, lessons, and modules automatically? | C24: AI-Powered Course Creation | D24: AI | F24: Not Checked | G24: Not Checked | K24: Not Checked | L24: Neutral | N24: SEO Manager | O24: Planned | R24: Source/verification note: AI
A25: AIQ-021 | B25: Can AI help me create quizzes and assessments automatically from course content? | C25: AI-Powered Course Creation | D25: AI | F25: Not Checked | G25: Not Checked | K25: Not Checked | L25: Neutral | N25: SEO Manager | O25: Planned | R25: Source/verification note: AI
A26: AIQ-022 | B26: Is AI-generated content accurate and reliable for professional courses? | C26: AI-Powered Course Creation | D26: Google | F26: Not Checked | G26: Not Checked | K26: Not Checked | L26: Neutral | N26: SEO Manager | O26: Planned | R26: Source/verification note: Google
A27: AIQ-023 | B27: How do I integrate AI-generated content into SCORM-compliant courses? | C27: AI-Powered Course Creation | F27: Not Checked | G27: Not Checked | K27: Not Checked | L27: Neutral | N27: SEO Manager | O27: Planned | R27: Source/verification note: Competitor Blogs
A28: AIQ-024 | B28: Can AI help with content translation, captions, or accessibility features? | C28: AI-Powered Course Creation | D28: AI | F28: Not Checked | G28: Not Checked | K28: Not Checked | L28: Neutral | N28: SEO Manager | O28: Planned | R28: Source/verification note: AI
A29: AIQ-025 | B29: What are the risks of using AI-generated content (plagiarism, inaccuracy, quality)? | C29: AI-Powered Course Creation | D29: Google | F29: Not Checked | G29: Not Checked | K29: Not Checked | L29: Neutral | N29: SEO Manager | O29: Planned | R29: Source/verification note: Google
A30: AIQ-026 | B30: What is the workflow from idea → AI outline → content generation → LMS upload? | C30: AI-Powered Course Creation | D30: AI | F30: Not Checked | G30: Not Checked | K30: Not Checked | L30: Neutral | N30: SEO Manager | O30: Planned | R30: Source/verification note: AI
A31: AIQ-027 | B31: How much faster is course creation using AI-powered tools versus traditional methods? | C31: AI-Powered Course Creation | D31: Google | F31: Not Checked | G31: Not Checked | K31: Not Checked | L31: Neutral | N31: SEO Manager | O31: Planned | R31: Source/verification note: Google
A32: AIQ-028 | B32: Can AI track learner progress, engagement, and completion rates automatically? | C32: AI-Powered Course Creation | D32: AI | F32: Not Checked | G32: Not Checked | K32: Not Checked | L32: Neutral | N32: SEO Manager | O32: Planned | R32: Source/verification note: AI
A33: AIQ-029 | B33: Do I still need instructional designers if I use AI tools for content creation? | C33: AI-Powered Course Creation | D33: AI | F33: Not Checked | G33: Not Checked | K33: Not Checked | L33: Neutral | N33: SEO Manager | O33: Planned | R33: Source/verification note: AI
A34: AIQ-030 | B34: Can AI create videos, animations, or interactive modules for courses? | C34: AI-Powered Course Creation | D34: AI | F34: Not Checked | G34: Not Checked | K34: Not Checked | L34: Neutral | N34: SEO Manager | O34: Planned | R34: Source/verification note: AI
A35: AIQ-031 | B35: Can AI personalize learning paths based on learner performance? | C35: AI-Powered Course Creation | D35: AI | F35: Not Checked | G35: Not Checked | K35: Not Checked | L35: Neutral | N35: SEO Manager | O35: Planned | R35: Source/verification note: AI
A36: AIQ-032 | B36: Which AI tools are best for eLearning content creation in 2025? | C36: AI-Powered Course Creation | D36: Google | F36: Not Checked | G36: Not Checked | K36: Not Checked | L36: Neutral | N36: SEO Manager | O36: Planned | R36: Source/verification note: Google
A37: AIQ-033 | B37: Can AI automatically update course content when new information becomes available? | C37: AI-Powered Course Creation | D37: AI | F37: Not Checked | G37: Not Checked | K37: Not Checked | L37: Neutral | N37: SEO Manager | O37: Planned | R37: Source/verification note: AI
A38: AIQ-034 | B38: Can AI generate automated assessments and grading for learners? | C38: AI-Powered Course Creation | D38: AI | F38: Not Checked | G38: Not Checked | K38: Not Checked | L38: Neutral | N38: SEO Manager | O38: Planned | R38: Source/verification note: AI
A39: AIQ-035 | B39: How do AI tools integrate with popular LMS platforms like Thinkific or Moodle? | C39: AI-Powered Course Creation | F39: Not Checked | G39: Not Checked | K39: Not Checked | L39: Neutral | N39: SEO Manager | O39: Planned | R39: Source/verification note: Competitor Blogs
A40: AIQ-036 | B40: Does AI-powered course creation reduce development costs and time? | C40: AI-Powered Course Creation | D40: Google | F40: Not Checked | G40: Not Checked | K40: Not Checked | L40: Neutral | N40: SEO Manager | O40: Planned | R40: Source/verification note: Google
A41: AIQ-037 | B41: How can I ensure AI-generated content meets quality standards before publishing? | C41: AI-Powered Course Creation | D41: AI | F41: Not Checked | G41: Not Checked | K41: Not Checked | L41: Neutral | N41: SEO Manager | O41: Planned | R41: Source/verification note: AI
A42: AIQ-038 | B42: What trends are emerging for AI in eLearning and course creation? | C42: AI-Powered Course Creation | D42: YouTube | F42: Not Checked | G42: Not Checked | K42: Not Checked | L42: Neutral | N42: SEO Manager | O42: Planned | R42: Source/verification note: YouTube
A43: AIQ-039 | B43: Which corporate courses are best for compliance and regulatory training? | C43: Corporate Upskilling & Employee Training Programs | D43: Google | F43: Not Checked | G43: Not Checked | K43: Not Checked | L43: Neutral | N43: SEO Manager | O43: Planned | R43: Source/verification note: Google
A44: AIQ-040 | B44: How can corporate training improve leadership, communication, and teamwork skills? | C44: Corporate Upskilling & Employee Training Programs | D44: YouTube | F44: Not Checked | G44: Not Checked | K44: Not Checked | L44: Neutral | N44: SEO Manager | O44: Planned | R44: Source/verification note: YouTube
A45: AIQ-041 | B45: What are the best strategies for upskilling employees in a fast-changing industry? | C45: Corporate Upskilling & Employee Training Programs | D45: AI | F45: Not Checked | G45: Not Checked | K45: Not Checked | L45: Neutral | N45: SEO Manager | O45: Planned | R45: Source/verification note: AI
A46: AIQ-042 | B46: How can training programs increase employee engagement and retention? | C46: Corporate Upskilling & Employee Training Programs | D46: Google | F46: Not Checked | G46: Not Checked | K46: Not Checked | L46: Neutral | N46: SEO Manager | O46: Planned | R46: Source/verification note: Google
A47: AIQ-043 | B47: How do I measure the ROI of corporate training programs? | C47: Corporate Upskilling & Employee Training Programs | F47: Not Checked | G47: Not Checked | K47: Not Checked | L47: Neutral | N47: SEO Manager | O47: Planned | R47: Source/verification note: Competitor Blogs
A48: AIQ-044 | B48: Which LMS platforms are most suitable for corporate upskilling programs? | C48: Corporate Upskilling & Employee Training Programs | D48: Google | F48: Not Checked | G48: Not Checked | K48: Not Checked | L48: Neutral | N48: SEO Manager | O48: Planned | R48: Source/verification note: Google
A49: AIQ-045 | B49: How can courses be customized to meet different employee roles and departments? | C49: Corporate Upskilling & Employee Training Programs | D49: AI | F49: Not Checked | G49: Not Checked | K49: Not Checked | L49: Neutral | N49: SEO Manager | O49: Planned | R49: Source/verification note: AI
A50: AIQ-046 | B50: What is blended learning and how does it benefit corporate training? | C50: Corporate Upskilling & Employee Training Programs | F50: Not Checked | G50: Not Checked | K50: Not Checked | L50: Neutral | N50: SEO Manager | O50: Planned | R50: Source/verification note: Competitor Blogs
A51: AIQ-047 | B51: How can microlearning be implemented for busy employees? | C51: Corporate Upskilling & Employee Training Programs | D51: YouTube | F51: Not Checked | G51: Not Checked | K51: Not Checked | L51: Neutral | N51: SEO Manager | O51: Planned | R51: Source/verification note: YouTube
A52: AIQ-048 | B52: How can employers track certifications and course completions for employees? | C52: Corporate Upskilling & Employee Training Programs | D52: Google | F52: Not Checked | G52: Not Checked | K52: Not Checked | L52: Neutral | N52: SEO Manager | O52: Planned | R52: Source/verification note: Google
A53: AIQ-049 | B53: How can employers analyze employee learning data to improve future training programs? | C53: Corporate Upskilling & Employee Training Programs | D53: Google | F53: Not Checked | G53: Not Checked | K53: Not Checked | L53: Neutral | N53: SEO Manager | O53: Planned | R53: Source/verification note: Google
A54: AIQ-050 | B54: How can training programs help identify and close skill gaps in employees? | C54: Corporate Upskilling & Employee Training Programs | F54: Not Checked | G54: Not Checked | K54: Not Checked | L54: Neutral | N54: SEO Manager | O54: Planned | R54: Source/verification note: Competitor Blogs
A55: AIQ-051 | B55: What are best practices for creating engaging video content for eLearning? | C55: Content Development & Multimedia Design | D55: Google | F55: Not Checked | G55: Not Checked | K55: Not Checked | L55: Neutral | N55: SEO Manager | O55: Planned | R55: Source/verification note: Google
A56: AIQ-052 | B56: How can animations enhance learner engagement in online courses? | C56: Content Development & Multimedia Design | D56: YouTube | F56: Not Checked | G56: Not Checked | K56: Not Checked | L56: Neutral | N56: SEO Manager | O56: Planned | R56: Source/verification note: YouTube
A57: AIQ-053 | B57: Why is professional voiceover important in eLearning content? | C57: Content Development & Multimedia Design | F57: Not Checked | G57: Not Checked | K57: Not Checked | L57: Neutral | N57: SEO Manager | O57: Planned | R57: Source/verification note: Competitor Blogs
A58: AIQ-054 | B58: How can interactive modules improve learner retention? | C58: Content Development & Multimedia Design | D58: AI | F58: Not Checked | G58: Not Checked | K58: Not Checked | L58: Neutral | N58: SEO Manager | O58: Planned | R58: Source/verification note: AI
A59: AIQ-055 | B59: How can SMEs and instructional designers collaborate on content development? | C59: Content Development & Multimedia Design | F59: Not Checked | G59: Not Checked | K59: Not Checked | L59: Neutral | N59: SEO Manager | O59: Planned | R59: Source/verification note: Competitor Blogs
A60: AIQ-056 | B60: What is storyboarding and how does it help organize course content? | C60: Content Development & Multimedia Design | D60: AI | F60: Not Checked | G60: Not Checked | K60: Not Checked | L60: Neutral | N60: SEO Manager | O60: Planned | R60: Source/verification note: AI
A61: AIQ-057 | B61: How can I make multimedia content accessible to learners with disabilities? | C61: Content Development & Multimedia Design | D61: Google | F61: Not Checked | G61: Not Checked | K61: Not Checked | L61: Neutral | N61: SEO Manager | O61: Planned | R61: Source/verification note: Google
A62: AIQ-058 | B62: What design practices ensure multimedia content works on mobile devices? | C62: Content Development & Multimedia Design | D62: AI | F62: Not Checked | G62: Not Checked | K62: Not Checked | L62: Neutral | N62: SEO Manager | O62: Planned | R62: Source/verification note: AI
A63: AIQ-059 | B63: How can graphics and visual design improve learning outcomes? | C63: Content Development & Multimedia Design | D63: YouTube | F63: Not Checked | G63: Not Checked | K63: Not Checked | L63: Neutral | N63: SEO Manager | O63: Planned | R63: Source/verification note: YouTube
A64: AIQ-060 | B64: How do I efficiently update multimedia content when information changes? | C64: Content Development & Multimedia Design | F64: Not Checked | G64: Not Checked | K64: Not Checked | L64: Neutral | N64: SEO Manager | O64: Planned | R64: Source/verification note: Competitor Blogs
A65: AIQ-061 | B65: What gamification strategies increase learner engagement in online courses? | C65: Learning Experience Design & Gamification | F65: Not Checked | G65: Not Checked | K65: Not Checked | L65: Neutral | N65: SEO Manager | O65: Planned | R65: Source/verification note: Competitor Blogs
A66: AIQ-062 | B66: How can microlearning improve retention and learner performance? | C66: Learning Experience Design & Gamification | D66: Google | F66: Not Checked | G66: Not Checked | K66: Not Checked | L66: Neutral | N66: SEO Manager | O66: Planned | R66: Source/verification note: Google
A67: AIQ-063 | B67: What types of interactive assessments keep learners engaged? | C67: Learning Experience Design & Gamification | D67: YouTube | F67: Not Checked | G67: Not Checked | K67: Not Checked | L67: Neutral | N67: SEO Manager | O67: Planned | R67: Source/verification note: YouTube
A68: AIQ-064 | B68: How can feedback and analytics improve course design and outcomes? | C68: Learning Experience Design & Gamification | D68: AI | F68: Not Checked | G68: Not Checked | K68: Not Checked | L68: Neutral | N68: SEO Manager | O68: Planned | R68: Source/verification note: AI
A69: AIQ-065 | B69: How can personalized learning paths be designed for different learners? | C69: Learning Experience Design & Gamification | D69: AI | F69: Not Checked | G69: Not Checked | K69: Not Checked | L69: Neutral | N69: SEO Manager | O69: Planned | R69: Source/verification note: AI
A70: AIQ-066 | B70: What motivational strategies help learners complete online courses? | C70: Learning Experience Design & Gamification | D70: Google | F70: Not Checked | G70: Not Checked | K70: Not Checked | L70: Neutral | N70: SEO Manager | O70: Planned | R70: Source/verification note: Google
A71: AIQ-067 | B71: How does storytelling enhance the learning experience? | C71: Learning Experience Design & Gamification | D71: YouTube | F71: Not Checked | G71: Not Checked | K71: Not Checked | L71: Neutral | N71: SEO Manager | O71: Planned | R71: Source/verification note: YouTube
A72: AIQ-068 | B72: Can social learning tools (forums, peer groups) boost engagement? | C72: Learning Experience Design & Gamification | F72: Not Checked | G72: Not Checked | K72: Not Checked | L72: Neutral | N72: SEO Manager | O72: Planned | R72: Source/verification note: Competitor Blogs
A73: AIQ-069 | B73: How can simulations be used effectively in online training? | C73: Learning Experience Design & Gamification | F73: Not Checked | G73: Not Checked | K73: Not Checked | L73: Neutral | N73: SEO Manager | O73: Planned | R73: Source/verification note: Competitor Blogs
A74: AIQ-070 | B74: What is scenario-based learning and how does it improve decision-making skills? | C74: Learning Experience Design & Gamification | D74: Google | F74: Not Checked | G74: Not Checked | K74: Not Checked | L74: Neutral | N74: SEO Manager | O74: Planned | R74: Source/verification note: Google
A75: AIQ-071 | B75: How should courses be tested for quality before launch? | C75: Quality Assurance & Course Evaluation | F75: Not Checked | G75: Not Checked | K75: Not Checked | L75: Neutral | N75: SEO Manager | O75: Planned | R75: Source/verification note: Competitor Blogs
A76: AIQ-072 | B76: How can learner feedback be collected and analyzed effectively? | C76: Quality Assurance & Course Evaluation | D76: Google | F76: Not Checked | G76: Not Checked | K76: Not Checked | L76: Neutral | N76: SEO Manager | O76: Planned | R76: Source/verification note: Google
A77: AIQ-073 | B77: How can courses be continuously improved over time? | C77: Quality Assurance & Course Evaluation | D77: AI | F77: Not Checked | G77: Not Checked | K77: Not Checked | L77: Neutral | N77: SEO Manager | O77: Planned | R77: Source/verification note: AI
A78: AIQ-074 | B78: What processes ensure content accuracy and reliability? | C78: Quality Assurance & Course Evaluation | F78: Not Checked | G78: Not Checked | K78: Not Checked | L78: Neutral | N78: SEO Manager | O78: Planned | R78: Source/verification note: Competitor Blogs
A79: AIQ-075 | B79: How can usability testing improve course navigation and learner experience? | C79: Quality Assurance & Course Evaluation | D79: YouTube | F79: Not Checked | G79: Not Checked | K79: Not Checked | L79: Neutral | N79: SEO Manager | O79: Planned | R79: Source/verification note: YouTube
A80: AIQ-076 | B80: Evaluation Which metrics are most useful to evaluate course effectiveness? | C80: Quality Assurance & Course Evaluation | D80: Google | F80: Not Checked | G80: Not Checked | K80: Not Checked | L80: Neutral | N80: SEO Manager | O80: Planned | R80: Source/verification note: Google
A81: AIQ-077 | B81: How to ensure courses work on multiple LMS platforms? | C81: Quality Assurance & Course Evaluation | F81: Not Checked | G81: Not Checked | K81: Not Checked | L81: Neutral | N81: SEO Manager | O81: Planned | R81: Source/verification note: Competitor Blogs
A82: AIQ-078 | B82: How do I verify courses meet compliance standards? | C82: Quality Assurance & Course Evaluation | D82: Google | F82: Not Checked | G82: Not Checked | K82: Not Checked | L82: Neutral | N82: SEO Manager | O82: Planned | R82: Source/verification note: Google
A83: AIQ-079 | B83: How to ensure courses are accessible to all learners? | C83: Quality Assurance & Course Evaluation | D83: AI | F83: Not Checked | G83: Not Checked | K83: Not Checked | L83: Neutral | N83: SEO Manager | O83: Planned | R83: Source/verification note: AI
A84: AIQ-080 | B84: What are best practices for updating and maintaining online courses? | C84: Quality Assurance & Course Evaluation | F84: Not Checked | G84: Not Checked | K84: Not Checked | L84: Neutral | N84: SEO Manager | O84: Planned | R84: Source/verification note: Competitor Blogs
A108: AI / LLM Action Checklist
A109: Date | B109: Task | C109: Details | D109: Status | E109: Owner | F109: Evidence | G109: Recheck Date | H109: Notes
A110: 45985 | B110: communities platform | C110: groups,forums etc | D110: Done | E110: SEO Manager | H110: Legacy checklist; verify ongoing value
A111: 45986 | B111: AI Questions Research | C111: Collect 150–200 questions from ChatGPT, Claude, Gemini, Perplexity about LMS, e-learning, SCORM, course development. | D111: Done | E111: SEO Manager | H111: Legacy checklist; verify ongoing value
A112: 45987 | B112: Upload llms.txt | C112: Create llms.txt → place it in website root directory. Add homepage, services, industries, about-us, case studies, blog, contact. | D112: Done | E112: SEO Manager | H112: Legacy checklist; verify ongoing value
A113: 45988 | B113: Add Schema Markup | C113: Implement Organization, FAQ, Service, Breadcrumb, Article schema across main pages. | D113: Done | E113: SEO Manager | H113: Legacy checklist; verify ongoing value
A114: 45989 | B114: Content Audit | C114: Review service pages & blogs. Mark each as: Optimize / Expand / Create New. Note missing FAQs. | D114: Done | E114: SEO Manager | H114: Legacy checklist; verify ongoing value
A115: 45990 | B115: Write FAQ Pages (AI Answers Page) | C115: Create /ai-answers page. Add: Who we are, What we do, All services, Clear definitions, FAQs, Links to pillar pages. | D115: Done | E115: SEO Manager | H115: Legacy checklist; verify ongoing value
A116: 45992 | B116: Write How-To Guides (3 Articles) | C116: 3 mini-guides (400–600 words): 1) Build Online Course in 10 Steps, 2) Instructor Training for LMS, 3) Vocational Training Module Design | D116: Done | E116: SEO Manager | H116: Legacy checklist; verify ongoing value
A117: 45993 | B117: Write Comparison Articles (2–3) | C117: Compare: 1) Kajabi vs Thinkific vs TheEduAssist, 2) SCORM vs xAPI vs HTML5 | D117: Done | E117: SEO Manager | H117: Legacy checklist; verify ongoing value
A118: 45994 | B118: Write List Articles (3) | C118: 300–500 words: 1) 5 Ways to Boost Engagement, 2) Gamification Techniques, 3) Accessibility Checklist | D118: Done | E118: SEO Manager | H118: Legacy checklist; verify ongoing value
A119: 45995 | B119: SEO / Schema Implementation | C119: Add FAQPage, HowTo, Article schema. Add internal links to service + pillar pages. Optimize headings/meta. | D119: Done | E119: SEO Manager | H119: Legacy checklist; verify ongoing value
A120: 01–05 Dec-2025 | B120: Internal Linking | C120: Connect all articles → pillar pages → AI Answers page → service pages. | D120: Done | E120: SEO Manager | H120: Legacy checklist; verify ongoing value
A121: 45996 | B121: QA & Review | C121: Check accuracy, clarity, keywords, schema validation, formatting. | D121: Done | E121: SEO Manager | H121: Legacy checklist; verify ongoing value

Sheet 09 SOP Checklists
A1: SEO Operating Checklists
A2: Copy or schedule these repeatable tasks in the Task Board. The evidence column makes the work auditable and easier to review.
A4: Cadence / Trigger | B4: When | C4: Workstream | D4: Checklist Item | E4: Tool / Source | F4: Primary Owner | G4: Evidence Required | H4: QA Check | I4: Escalate When | J4: Notes
A5: Daily | B5: Start of shift | C5: Task Management | D5: Review Critical/High and overdue tasks; update owner, blocker and due date | E5: 01 Task Board | F5: SEO Manager | G5: Updated task rows | H5: No unowned critical task | I5: Blocker remains >1 day
A6: Daily | B6: After work | C6: Task Management | D6: Attach evidence and write outcome, not only 'done' | E6: 01 Task Board | F6: All owners | G6: URL, screenshot, report or document | H6: QA can reproduce result | I6: Evidence is missing
A7: Daily | B7: After publish/update | C7: Indexing | D7: Confirm canonical, status code, indexability and sitemap inclusion | E7: URL Inspection / crawler | F7: SEO Manager | G7: Inspection result | H7: Canonical matches www URL | I7: Wrong canonical, noindex or 4xx
A8: On publish | B8: Immediately | C8: Indexing | D8: Submit changed URL through supported workflow and update sitemap/IndexNow where implemented | E8: GSC / Bing Webmaster | F8: Developer | G8: Submission log | H8: URL is canonical and indexable | I8: Submission errors | J8: Submission does not guarantee indexing
A9: On publish | B9: Before release | C9: Content QA | D9: Check intent match, unique title/meta, one H1, helpful structure, internal links, CTA, author/reviewer proof | E9: Page + brief | F9: Content Lead | G9: QA checklist | H9: No keyword stuffing or unsupported claims | I9: Major mismatch with brief
A10: On publish | B10: Before release | C10: Schema | D10: Validate only applicable visible content in JSON-LD | E10: Rich Results Test | F10: Developer | G10: Test URL/result | H10: No critical errors; markup matches page | I10: Critical errors or misleading markup
A11: Weekly | B11: Monday | C11: Search Console | D11: Compare clicks and impressions to previous period; review pages/queries with largest changes | E11: GSC Performance | F11: SEO Manager | G11: Export link | H11: Focus on trends and page/query causes | I11: Material traffic drop
A12: Weekly | B12: Tuesday | C12: Content SEO | D12: Review high-impression low-CTR queries and pages; test title/snippet improvements | E12: GSC Performance | F12: SEO Manager | G12: Opportunity list | H12: Query intent matches page | I12: CTR decline persists
A13: Weekly | B13: Wednesday | C13: Technical SEO | D13: Review indexing, sitemaps, CWV and enhancement reports | E13: GSC / PageSpeed | F13: SEO Manager | G13: Issue list | H13: Verified issues logged | I13: New critical issue
A14: Weekly | B14: Thursday | C14: Internal Linking | D14: Add relevant links from recent and high-authority pages to priority service pages | E14: Crawler / CMS | F14: Content Writer | G14: Updated URLs | H14: Anchor is natural and useful | I14: Orphan page remains
A15: Weekly | B15: Friday | C15: Backlinks | D15: Qualify prospects by relevance, editorial fit, realistic route and risk | E15: 07 Link Opportunities | F15: Outreach | G15: Qualified rows | H15: Reject spam/irrelevant options | I15: Paid follow link or exchange requested
A16: Weekly | B16: Friday | C16: AI Visibility | D16: Check 10 priority questions across selected AI/search platforms | E16: 08 AI Visibility | F16: SEO Manager | G16: Evidence URLs/screenshots | H16: Citations are recorded consistently | I16: Negative/inaccurate brand answer
A17: Monthly | B17: First week | C17: Reporting | D17: Update organic traffic, keywords, GSC, GA4 leads, conversion and CWV | E17: 05 Performance | F17: SEO Manager | G17: Completed row + source exports | H17: Same date range/source used | I17: Unexplained material change
A18: Monthly | B18: First week | C18: Competitors | D18: Refresh top competitors and capture one content and one link gap each | E18: 06 Competitors | F18: SEO Manager | G18: Updated rows | H18: Gap is actionable and relevant | I18: Metrics are stale >60 days
A19: Quarterly | B19: Quarter start | C19: Content Refresh | D19: Review declining, outdated or strategically important content | E19: GSC + analytics + 03 Pipeline | F19: Content Lead | G19: Refresh decisions | H19: Facts, dates, links and CTA current | I19: Traffic/conversions declining
A20: Quarterly | B20: Quarter start | C20: Governance | D20: Archive out-of-scope keywords/pages and merge duplicate trackers | E20: All tabs | F20: SEO Manager | G20: Change log | H20: No duplicate source of truth | I20: Team keeps separate private trackers

Sheet One Page - Full Strategy
A1: TheEduAssist.com — 1 Month SEO Strategy (All 14 Sections)
A3: 01. Executive Plan
A4: Phase | B4: Current Objective | C4: What We Do | D4: Why
A5: Phase 1 | B5: Migration SEO Stabilization | C5: Publish/restore migrated existing pages; validate URLs, redirects, canonicals, indexability and sitemap | D5: Prevent migration-related ranking/indexation issues
A6: Phase 2 | B6: Existing Content Optimization | C6: Optimize existing pages for keyword intent, titles, headings, content, internal links, CTAs and entities | D6: Improve existing assets before creating new ones
A7: Phase 3 | B7: Indexation & Monitoring | C7: Submit/inspect priority URLs in GSC; monitor coverage, impressions, clicks and rankings | D7: Confirm Google can discover and process pages
A8: Phase 4 | B8: Authority Building | C8: Build relevant editorial backlinks to priority pages | D8: Strengthen authority after optimization
A9: Phase 5 | B9: Content Expansion | C9: Identify genuine gaps and create new pages only after stabilization | D9: Avoid unnecessary content production
A12: 02. Migration SEO Audit
A13: Task | B13: Action | C13: Owner | D13: Priority
A14: URL inventory | B14: Compare old vs new URLs and identify missing/moved pages | C14: SEO + Dev | D14: High
A15: Redirects | B15: Validate 301 redirects for changed URLs | C15: Dev | D15: High
A16: Canonicals | B16: Check canonical targets and self-referencing canonicals | C16: SEO + Dev | D16: High
A17: Indexability | B17: Check robots, noindex, status codes and crawlability | C17: SEO + Dev | D17: High
A18: Sitemap | B18: Update and submit clean XML sitemap | C18: Dev | D18: High
A21: 03. Technical SEO
A22: Area | B22: Action | C22: Owner | D22: Priority
A23: 404/5xx | B23: Find and fix broken/failed URLs | C23: Dev | D23: High
A24: Internal links | B24: Repair broken links and improve contextual linking | C24: SEO + Content | D24: High
A25: Core Web Vitals | B25: Review mobile performance and major page-speed issues | C25: Dev | D25: Medium
A26: Schema | B26: Validate relevant Organization, Article, Breadcrumb and author markup | C26: Dev | D26: Medium
A27: Images | B27: Optimize formats, sizes, filenames and alt text | C27: Content + Dev | D27: Medium
A30: 04. Existing Page Optimization
A31: Element | B31: Action
A32: Title tags | B32: Rewrite around primary intent and improve CTR
A33: H1/H2s | B33: Align headings with search intent and page structure
A34: Content | B34: Refresh outdated/thin sections and improve topical depth
A35: Internal links | B35: Add relevant contextual links to priority pages
A36: CTA | B36: Improve CTA relevance and conversion path
A37: Entities | B37: Add clear brand/topic/entity context where useful
A40: 05. Keyword Mapping
A41: Page Type | B41: Keyword Focus | C41: Intent
A42: Core pages | B42: Primary service/topic terms | C42: Commercial
A43: Existing articles | B43: Primary + secondary terms | C43: Informational
A44: BOFU pages | B44: Comparison, alternatives, pricing, best-fit queries | C44: Transactional
A45: Supporting content | B45: Long-tail and problem-based queries | C45: Informational
A48: 06. Content Audit
A49: Check | B49: Action | C49: Decision
A50: Traffic | B50: Identify pages already receiving impressions/clicks | C50: Optimize first
A51: Conversions | B51: Prioritize pages contributing to leads/signups | C51: High priority
A52: Cannibalization | B52: Find pages targeting overlapping terms | C52: Consolidate or differentiate
A53: Thin content | B53: Improve weak pages before creating replacements | C53: Refresh
A54: Outdated content | B54: Update facts, examples and references | C54: Refresh
A57: 07. Content Optimization Workflow
A58: Step | B58: Action
A59: 1 | B59: Review target keyword and current ranking intent
A60: 2 | B60: Improve title, H1 and headings
A61: 3 | B61: Expand missing subtopics and answer user questions
A62: 4 | B62: Add internal links from/to relevant pages
A63: 5 | B63: Improve CTA and conversion path
A64: 6 | B64: Request indexing after publishing changes
A67: 08. Internal Linking
A68: Source | B68: Target | C68: Purpose
A69: High-authority existing pages | B69: Priority commercial pages | C69: Pass relevance and authority
A70: Related blog articles | B70: Money/service pages | C70: Support conversion
A71: Pillar pages | B71: Cluster articles | C71: Strengthen topical structure
A72: New/updated content | B72: Older relevant content | C72: Distribute internal authority
A75: 09. BOFU Content Opportunities
A76: Opportunity | B76: Purpose | C76: Priority
A77: Alternatives | B77: Capture users comparing solutions | C77: High
A78: Competitor comparisons | B78: Capture solution-selection intent | C78: High
A79: Best tools/resources | B79: Capture commercial investigation | C79: Medium
A80: Pricing/cost queries | B80: Capture high-conversion intent | C80: High
A81: Use-case pages | B81: Match specific user needs | C81: Medium
A84: 10. Content Gaps
A85: Gap Type | B85: Action
A86: Missing topic | B86: Create only where demand and business relevance exist
A87: Weak coverage | B87: Expand existing page instead of duplicating it
A88: Missing comparison | B88: Create comparison/alternative content where justified
A89: Missing supporting topic | B89: Add cluster content to strengthen topical authority
A92: 11. Off-Page SEO / Backlinks
A93: Activity | B93: Action | C93: Priority
A94: Relevant placements | B94: Secure editorial backlinks from relevant sites | C94: High
A95: Priority pages | B95: Point links to optimized pages rather than random URLs | C95: High
A96: Anchor strategy | B96: Keep anchors natural and context-driven | C96: High
A97: Quality control | B97: Review relevance, traffic, indexing and spam signals | C97: High
A98: Link velocity | B98: Build steadily rather than in sudden bursts | C98: Medium
A101: 12. GSC & Indexation
A102: Check | B102: Action | C102: Frequency
A103: URL Inspection | B103: Inspect priority URLs after major changes | C103: Weekly
A104: Coverage | B104: Review indexed/excluded/error URLs | C104: Weekly
A105: Sitemap | B105: Monitor submitted vs indexed URLs | C105: Weekly
A106: Performance | B106: Track clicks, impressions, CTR and position | C106: Weekly
A109: 13. Monthly Execution Timeline
A110: Week | B110: Main Focus | C110: Deliverables
A111: Week 1 | B111: Migration + technical stabilization | C111: URL validation, redirects, canonicals, sitemap, indexability fixes
A112: Week 2 | B112: Existing content optimization | C112: Priority pages refreshed, internal links and on-page fixes
A113: Week 3 | B113: Indexation + authority | C113: GSC checks, indexing requests, backlink outreach/building
A114: Week 4 | B114: Measure + expand | C114: Performance review, BOFU gaps, next-month priorities
A117: 14. Reporting & KPIs
A118: KPI | B118: What to Track
A119: Organic clicks | B119: Weekly/monthly change
A120: Impressions | B120: Visibility growth
A121: Average position | B121: Priority keyword/page movement
A122: Indexed pages | B122: Valid indexed URLs vs submitted URLs
A123: CTR | B123: Improve titles/meta based on performance
A124: Conversions | B124: Leads/signups from organic traffic
A125: Backlinks | B125: Relevant referring domains and quality placements
A126: Next actions | B126: Top fixes/opportunities for the following month

Sheet RAW Ai Prompts
A3: SR No | B3: Page | C3: Page URL | D3: Index status | E3: SEO Improvements
A4: Contact us
B5: Contact us | C5: https://theeduassist.com/contact-us/ | D5: Indexed | E5: 1. Contact form, after filling, doesn't redirect to any page. 2. Schema Missing. 3. Keyword missing. 4. Missing service reference. 5. Less internal links.
A6: About us
B7: About us | C7: https://theeduassist.com/about-us/ | D7: Indexed | E7: 1. Should have a proper H1 like About Edu Assist. 2. Schema Missing. 3. Keyword missing. 4. Missing Authoritative Credentials. . 5. issing company story section.. 6. Add: Talk to our team to redirect to the contact us page. 7, Missing Team Section. 8, Missing certifications or credentials.
A8: Case study
B9: Case study 1 | C9: https://theeduassist.com/case-studies-1/ | D9: Indexed | E9: 1. Should have a proper H1 like About Edu Assist. 2. Schema Missing. 3. Keyword missing. 4. Missing Authoritative Credentials. . 5. issing company story section.. 6. Add: Talk to our team to redirect to the contact us page. 7, Missing Team Section. 8, Missing certifications or credentials.

Sheet RAW Website Issues
A1: SR No | B1: Page | C1: Page URL | D1: Index status | E1: Issue
B2: Home Page
A3: 1 | B3: GOVERNMENT & SKILLS DEVELOPMENT | C3: https://theeduassist.com/case-study-1/ | D3: Not indexed | E3: Page is 404. It is also displaying on home page
A4: 2 | B4: CORPORATE TRAINING | C4: https://theeduassist.com/case-study-2/ | D4: Not indexed | E4: Page is 404. It is also displaying on home page
A5: 3 | B5: EDUCATIONAL | C5: https://theeduassist.com/case-study-3/ | D5: Not indexed | E5: Page is 404. It is also displaying on home page
B6: Contact us
B7: Contact us | C7: https://theeduassist.com/contact-us/ | D7: Indexed | E7: 1. Contact form, after filling, doesn't redirect to any page. 2. Schema Missing. 3. Keyword missing. 4. Missing service reference. 5. Less internal links.
B8: About us
B9: About us | C9: https://theeduassist.com/about-us/ | D9: Indexed | E9: 1. Should have a proper H1 like About Edu Assist. 2. Schema Missing. 3. Keyword missing. 4. Missing Authoritative Credentials. . 5. issing company story section.. 6. Add: Talk to our team to redirect to the contact us page. 7, Missing Team Section. 8, Missing certifications or credentials.

Sheet RAW Kajabi Keywords
A3: SR NO | C3: KEYWORD | D3: VOLUME | E3: GLOBAL VOLUME | F3: DIFFICULTY | G3: INTENT | H3: TARGETED PAGE | I3: WORD TYPE | J3: Title | K3: Description | L3: Page link
A4: 1 | C4: designing an online course | D4: 90 | E4: 1.9k | F4: 22 | G4: Informational | H4: How We Build High-Impact Online Courses | I4: Secondary Keyword | J4: How to build a course that actually gets results | K4: Build a course that actually gets results with our proven guide. Learn to design lessons that work. Start creating your high-impact program today.
A5: 2 | C5: online course design best practices | D5: 40 | E5: 110 | F5: 23 | G5: Commercial | H5: How We Build High-Impact Online Courses | I5: Secondary Keyword
A6: 3 | C6: online course launch | D6: 40 | E6: 70 | F6: 15 | G6: Informational | H6: How We Build High-Impact Online Courses | I6: Secondary Keyword
A7: 4 | C7: how to create elearning courses | D7: 50 | E7: 160 | F7: 18 | G7: Informational | H7: How We Build High-Impact Online Courses | I7: Secondary Keyword
A8: 5 | C8: building elearning courses | D8: 70 | E8: 240 | F8: 15 | G8: Informational | H8: How We Build High-Impact Online Courses | I8: Secondary Keyword
A9: 6 | C9: how to make training interactive | D9: 30 | E9: 70 | F9: 18 | G9: Informational | H9: How We Build High-Impact Online Courses | I9: Secondary Keyword
A10: 7 | C10: done for you course creation | D10: 70 | E10: 140 | F10: 7 | G10: Informational | H10: How We Build High-Impact Online Courses | I10: Secondary Keyword
A11: 8 | C11: how to create and sell online courses | D11: 90 | E11: 220 | F11: 32 | G11: Informational | H11: How We Build High-Impact Online Courses | I11: Secondary Keyword
A12: 9 | C12: how to create an online course pdf | D12: 70 | E12: 170 | F12: 0 | G12: Informational | H12: How We Build High-Impact Online Courses | I12: Secondary Keyword
A13: 10 | C13: how to create an online course that sells​ | D13: 70 | E13: 270 | F13: 25 | G13: Commercial | H13: How We Build High-Impact Online Courses | I13: Primary Keyword
A14: 11 | C14: best selling online courses​ | D14: 40 | E14: 230 | F14: 27 | G14: Informational | H14: How We Build High-Impact Online Courses | I14: Secondary Keyword
A15: 12 | C15: best platform to create and sell online courses​ | D15: 30 | E15: 100 | H15: How We Build High-Impact Online Courses | I15: Secondary Keyword
A16: 13 | C16: how to create a course to sell | D16: 90 | E16: 250 | F16: 30 | G16: Informational | H16: How We Build High-Impact Online Courses | I16: Secondary Keyword
A18: 14 | C18: online training delivery methods | D18: 40 | E18: 70 | F18: 4 | G18: Informational | H18: How We Deliver course | J18: How We Deliver Professional Courses With Speed and Precision | K18: Get courses delivered with precision and speed. We handle the hard work so you don't have to. See how our professional team gets it done right. Learn more now.
A19: 15 | C19: e-learning delivery methods | D19: 50 | E19: 80 | F19: 1 | G19: Commercial+Informational
A20: 16 | C20: best service delivery courses​ | D20: 0 | E20: 10 | G20: Informational
A21: 17 | C21: deliver a course | D21: 0 | E21: 140 | F21: 9 | G21: Informational
A22: 18 | C22: elearning delivery | D22: 70 | E22: 110 | F22: 6 | G22: Informational
G23: Informational
C25: operating systems course online​ | D25: 40 | E25: 250 | G25: Informational | H25: HOW WE OPERATE | J25: The Secret Way We Build High Quality Courses Fast | K25: Discover how we build high quality courses fast. Stop wasting months on planning. Use our proven system to launch your program now. Read the full guide.
C26: online operations management courses​ | D26: 40 | E26: 800 | F26: 43 | G26: Commercial
C27: operating system online course​ | D27: 30 | E27: 310 | F27: 23 | G27: Commercial+Informational
C28: operations research course | D28: 70 | E28: 1.2k | F28: 17 | G28: Informational
C29: operations manager courses | D29: 70 | E29: 6.3k | G29: Commercial+Informational
C30: training and operations | D30: 30 | E30: 190 | F30: 1 | G30: Informational
G31: Commercial+Informational
G32: Commercial+Informational
G33: Commercial+Informational
A35: Kajabi Service Pages Keywords, Titles, Description.
A39: SR NO | B39: TARGETED PAGE | C39: KEYWORD | D39: VOLUME | E39: GLOBAL VOLUME | F39: DIFFICULTY | G39: INTENT | H39: WORD TYPE | I39: Title | J39: Description | K39: Linking page | L39: Keyword in blog
A40: 1 | B40: Kajabi Course Setup Service | C40: kajabi online course platform​ | D40: 18.1k | E40: 18.1k | F40: 28 | G40: Informational | H40: Secondary Keyword
C41: kajabi online courses | D41: 90 | E41: 310 | G41: Informational | H41: Secondary Keyword | I41: Expert Kajabi Course Setup to Scale Your Business-theEduAssist | J41: Scale your business with pro Kajabi course setup. theEduAssist handles the tech so you can teach. Book your setup call and launch your offer now. | K41: https://theeduassist.com/blog/7-powerful-kajabi-course-creation-services/ | L41: Kajabi Course Creation Services
C42: kajabi online course setup | G42: Informational | H42: Secondary Keyword | K42: https://theeduassist.com/blog/kajabi-online-course-setup/ | L42: Setting up your online course on Kajabi | M42: professional Kajabi course setup services
C43: setup online course kajabi | G43: Informational | H43: Secondary Keyword | K43: https://theeduassist.com/blog/kajabi-course-design-explained-how-to-create-online-course-in-2026/ | L43: our Kajabi online course | M43: Kajabi course setup experts
C44: kajabi course setup​ | G44: Informational | H44: Secondary Keyword | K44: https://theeduassist.com/blog/kajabi-course-design/ | L44: Successful Kajabi course creators | M44: Kajabi setup specialists
C45: online course setup​ | D45: 20 | E45: 90 | G45: Informational | H45: Secondary Keyword | K45: https://theeduassist.com/blog/kajabi-drip-course-setup/ | L45: create a Kajabi course | M45: Kajabi course setup strategy
C46: how to create a course on kajabi | D46: 30 | E46: 30 | G46: Informational | H46: Secondary Keyword
C47: how to create a course in kajabi​ | D47: 20 | E47: 100 | G47: Informational | H47: Secondary Keyword
C48: how to create a kajabi course | D48: 20 | E48: 30 | G48: Informational | H48: Secondary Keyword
C49: Kajabi Course Setup Service | H49: Primary Keyword
C50: Kajabi services | D50: 40 | E50: 70 | F50: 31 | G50: Navigational
B52: Kajabi Website & Funnel Setup
C53: kajabi funnels​ | D53: 20 | E53: 220 | G53: Informational | H53: Primary Keyword | I53: Expert Kajabi Website & Funnel Setup for More Sales | J53: Your Kajabi site should work for you. We build high-converting funnels that boost your revenue. Book your setup call now. | K53: https://theeduassist.com/blog/kajabi-website-funnel-services/ | L53: Kajabi website expert services
C54: kajabi website​ | D54: 390 | E54: 820 | F54: 21 | G54: Navigational | H54: Primary Keyword | K54: https://theeduassist.com/blog/kajabi-website-funnel-services/ | L54: Kajabi sales funnel setup
C55: kajabi website expert​ | D55: 70 | E55: 70 | F55: 9 | G55: Commercial | H55: Secondary Keyword
C56: kajabi sales funnel | D56: 20 | E56: 70 | G56: Informational | H56: Secondary Keyword
C57: best funnels to use on kajabi​ | G57: Informational | H57: Secondary Keyword
C58: kajabi funnels​ | G58: Informational | H58: Secondary Keyword
C59: best funnels to use on kajabi​ | G59: Informational | H59: Secondary Keyword
C60: Kajabi services | D60: 40 | E60: 70 | F60: 31 | G60: Navigational
B62: Kajabi Course Upload Service | C62: kajabi course upload services | H62: Primary Keyword | I62: Professional Kajabi Course Upload Service | We Value Your Time | J62: Need your course live? Our professional Kajabi course upload service takes the stress away. We build it right the first time. Hire our experts here.
C63: kajabi.services​ | H63: Secondary Keyword
C64: Kajabi services | D64: 40 | E64: 70 | F64: 31 | G64: Navigational | H64: Secondary Keyword
C65: kajabi customer service | D65: 50 | E65: 140 | F65: 19 | G65: Informational | H65: Secondary Keyword
C66: kajabi help | D66: 110 | E66: 390 | F66: 20 | G66: Navigational+Commercial | H66: Secondary Keyword
C67: kajabi support | D67: 140 | E67: 490 | F67: 17 | G67: Navigational | H67: Secondary Keyword
B71: Kajabi Migration Services
C72: Kajabi Migration | D72: 20 | E72: 60 | G72: Informational | H72: Secondary Keyword | I72: Move to Kajabi: Expert Migration for Your Growth | J72: Ready to move to Kajabi? Get a clean migration that saves you time. We move your courses and emails fast. Scale your business without the headaches. Call us. | K72: https://theeduassist.com/blog/kajabi-website-funnel-services/ | L72: Kajabi website migration
C73: Kajabi Migration Services | H73: Primary Keyword
C74: migrate from kajabi​ | D74: 10 | E74: 30 | H74: Secondary Keyword
C75: migrate from kajabi to wordpress​ | H75: Secondary Keyword
C76: migrate from kajabi to teachable​ | D76: 20 | E76: 20 | H76: Secondary Keyword
C77: migrate wordpress to kajabi​ | H77: Secondary Keyword
C78: migrating from kajabi​ | H78: Secondary Keyword
C79: Kajabi services | D79: 40 | E79: 70 | F79: 31 | G79: Navigational | H79: Secondary Keyword
B81: kajabi virtual assistant/ monthly support services
C82: kajabi va | D82: 20 | E82: 110 | H82: Secondary Keyword | I82: Hire a Kajabi VA for Reliable Monthly Management | J82: Stop wasting hours on tech. Hire a Kajabi VA for reliable monthly management. We fix the bugs and automate your site. Start your easy growth plan now.
C83: Kajabi services | D83: 40 | E83: 70 | F83: 31 | G83: Navigational | H83: Secondary Keyword
C84: hire kajabi experts | D84: 70 | E84: 100 | F84: 8 | G84: Commercial | H84: Secondary Keyword
C85: virtual teammate client playbook | D85: 50 | E85: 50 | F85: 0 | G85: Navigational | H85: Secondary Keyword
C86: kajabi virtual assistant​ | D86: 20 | E86: 60 | H86: Secondary Keyword
C87: kajabi virtual assistants​ | H87: Secondary Keyword
C88: virtual assistant kajabi | H88: Secondary Keyword
C89: kajabi virtual assistant for sales page​ | H89: Secondary Keyword
C90: kajabi virtual assistant for product launch​ | H90: Secondary Keyword
C91: kajabi packages for the virtual assistant​ | H91: Secondary Keyword
C92: Kajabi VA services | H92: Primary Keyword
C93: Kajabi virtual assistant services | H93: Primary Keyword
C94: kajabi help | D94: 110 | E94: 390 | F94: 20 | G94: Navigational+Commercial | H94: Secondary Keyword
C95: kajabi support | D95: 140 | E95: 490 | F95: 17 | G95: Navigational | H95: Secondary Keyword
C96: kajabi customer service | D96: 50 | E96: 140 | F96: 19 | G96: Informational | H96: Secondary Keyword

Sheet RAW Website Metrics
A1: Website matrics
A3: SR NO | B3: DATE | C3: AUTHORITY | D3: ORGANIC TRAFFIC | E3: ORGANIC KEYWORDS | F3: REF. DOMAINS | G3: BACKLINKS | H3: DO FOLLOW | I3: NO FOLLOW | J3: AI VISIBLITY | K3: MENTIONS | L3: CITIED PAGES
A4: 1 | B4: 46149 | C4: 8 | D4: 3.9K | E4: 201 | F4: 107 | G4: 246 | H4: 205 | I4: 41 | J4: 14 | K4: 2 | L4: 51
A5: 2 | B5: 46167 | C5: 11 | D5: 2.4k | E5: 223 | F5: 112 | G5: 256 | H5: 210 | I5: 46 | J5: 14 | K5: 2 | L5: 52
A6: 3 | B6: 46174 | C6: 11 | D6: 4.4k | E6: 245 | F6: 113 | G6: 244 | H6: 198 | I6: 46 | J6: 14 | K6: 1 | L6: 53

Sheet RAW Competitors
A1: Competitor List Updated 29-04-26 | J1: COMPETITOR ANALYSIS
J3: SR NO | K3: COMPETITOR WEBSITE | L3: LINKING WEBSITE | M3: WEBSITE TYPE(LINKING) | N3: BACKLINKS GET (COMPETITOR WEBSITE) | O3: AUTHORITY SCORE (LINKING WEBSITE) | P3: MONTHLY VISITORS(LINKING WEB)
A4: SR. NO | B4: WEBSITE URL | C4: ORGANIC TRAFFIC | D4: ORGANIC KEYWORDS | E4: AUTHORITY | F4: BACKLINKS | G4: AI VISIBLITY | H4: TOTAL MENTIONS BY AI | J4: 1 | K4: https://www.kytewayelearning.com/ | L4: https://www.adobe.com/ | M4: Online Services | N4: 4 | O4: 100 | P4: 461M
A5: 1 | B5: https://elearning.folio3.com | C5: 325 | D5: 930 | E5: 43 | F5: 374 | G5: 19 | H5: 515 | L5: https://www.crunchbase.com/ | M5: Online Services | N5: 1 | O5: 72 | P5: 5.1M
A6: 2 | B6: https://www.kytewayelearning.com/ | C6: 763 | D6: 907 | E6: 22 | F6: 42.5K | G6: 22 | H6: 32 | L6: https://www.articulate.com/ | M6: Distance Learning | N6: 4 | O6: 55 | P6: 3.6M
A7: 3 | B7: https://www.eidesign.net/ | C7: 1.4K | D7: 2.5K | E7: 29 | F7: 21.4K | G7: 21 | H7: 40 | L7: https://elearningindustry.com/ | M7: Distance Learning | N7: 39 | O7: 54 | P7: 335K
A8: 4 | B8: https://bluecarrot.io/ | C8: 906 | D8: 2.0K | E8: 28 | F8: 4K | G8: 15 | H8: 47 | L8: https://peoplemanagingpeople.com/ | M8: Computer Software & Development | N8: 10 | O8: 53 | P8: 105K
A9: 5 | B9: https://elearning.company/ | C9: 575 | D9: 446 | E9: 25 | F9: 1.8K | G9: 14 | H9: 3
A10: 6 | B10: https://www.acadecraft.com/ | C10: 4.7K | D10: 6K | E10: 31 | F10: 91.1K | G10: 25 | H10: 34 | J10: 2 | K10: https://elearning.company/ | L10: https://www.adobe.com/ | M10: Online Services | N10: 2 | O10: 100 | P10: 461M
A11: 7 | B11: https://qquench.ai/our-services/e-learning/ | C11: 4 | D11: 39 | E11: 6 | F11: 257 | G11: 0 | H11: 0 | L11: https://moodle.org/ | M11: Distance Learning | N11: 1 | O11: 73 | P11: 3.1M
A12: 8 | B12: https://redchipsolutions.com/ | C12: 210 | D12: 225 | E12: 20 | F12: 848 | G12: 14 | H12: 0 | L12: https://rocketreach.co/ | M12: Online Services | N12: 1 | O12: 66 | P12: 16M
A13: 9 | B13: https://piogroup.net/ | C13: 905 | D13: 1.2K | E13: 22 | F13: 2.6K | G13: 14 | H13: 2
A14: 10 | B14: https://www.learningeverest.com/ | C14: 6.8K | D14: 9.5K | E14: 31 | F14: 42.1K | G14: 16 | H14: 19
A15: 11 | B15: https://stratbeans.com/ | C15: 1.1K | D15: 2.4K | E15: 27 | F15: 2.4K | G15: 14 | H15: 21 | J15: 3 | K15: https://elearning.folio3.com | L15: https://www.goodfirms.co/ | M15: Computer Software & Development | N15: 1 | O15: 50 | P15: 527K
A16: 12 | B16: https://www.swiftelearningservices.com/ | C16: 892 | D16: 4.3K | E16: 28 | F16: 41K | G16: 18 | H16: 37 | L16: https://coschedule.com/ | M16: Advertising & Marketing | N16: 1 | O16: 46 | P16: 218K
A17: 13 | B17: https://www.allencomm.com/ | C17: 4.5K | D17: 3.6K | E17: 31 | F17: 16.6K | G17: 21 | H17: 189
A18: 14 | B18: https://www.gpstrategies.com/ | C18: 12.3K | D18: 6.4K | E18: 37 | F18: 41.8K | G18: 18 | H18: 280 | J18: 4 | K18: https://www.learningeverest.com/ | L18: pinterest.com | M18: Online Services | N18: 3 | O18: 100 | P18: 1.4B
A19: 15 | B19: https://flearningstudio.com/ | C19: 1K | D19: 4.3K | E19: 27 | F19: 68.3K | G19: 14 | H19: 22 | L19: https://www.osu.edu/ | M19: Education | N19: 1 | O19: 75 | P19: 8.8M
A20: 16 | B20: http://www.jupiter2000.com/training | C20: 241 | D20: 28 | E20: 8 | F20: 503 | G20: 0 | H20: 0 | L20: https://www.fastcompany.com/ | M20: Publishing | N20: 1 | O20: 56 | P20: 5M
A21: 17 | B21: https://legacylearningconsultingllc.com/ | C21: 2 | D21: 4 | E21: 5 | F21: 1.3k | G21: 0 | H21: 0 | L21: https://internshala.com/ | M21: Online Services | N21: 2 | O21: 59 | P21: 5.3M
A22: 18 | B22: https://www.chameleon-agency.com/ | C22: 0 | D22: 7 | E22: 2 | F22: 378 | G22: 14 | H22: 1
A23: 19 | B23: https://www.vivifysol.com/ | C23: 51 | D23: 19 | E23: 7 | F23: 206 | G23: 0 | H23: 0 | J23: 5 | K23: https://www.gpstrategies.com/ | L23: https://www.mynavi.jp/ | M23: Online Services | N23: 1 | O23: 89 | P23: 40.8M
A24: 20 | B24: https://5kwebtech.com/ | C24: 0 | D24: 1 | E24: 2 | F24: 170 | G24: 0 | H24: 0 | L24: https://www.nbcnews.com/ | M24: Mass Media | N24: 1 | O24: 89 | P24: 131M
A25: 21 | B25: https://thelearningedge.eu/ | C25: 613 | D25: 14 | E25: 10 | F25: 570 | G25: 14 | H25: 1 | L25: https://substack.com/ | M25: Mass Media | N25: 6 | O25: 85 | P25: 136M
A26: 22 | B26: https://tidalvisuals.com/ | C26: 0 | D26: 1 | E26: 2 | F26: 138 | G26: 0 | H26: 0 | L26: https://www.behance.net/ | M26: Online Services | N26: 1 | O26: 80 | P26: 52.7M
A27: 23 | B27: https://esparkconsultants.com/ | C27: 313 | D27: 14 | E27: 9 | F27: 4.3k | G27: 14 | H27: 0 | L27: https://libretexts.org/ | M27: Education | N27: 1 | O27: 80 | P27: 9.7M
A28: 24 | B28: https://kaizenlearningservices.com/ | C28: 0 | D28: 0 | E28: 2 | F28: 14 | G28: 14 | H28: 0 | L28: https://www.atlassian.com/# | M28: Computer Software & Development | N28: 1 | O28: 79 | P28: 42.5M
A29: 25 | B29: https://elearn-experts.com/ | C29: 0 | D29: 1 | E29: 2 | F29: 343 | G29: 0 | H29: 0 | L29: https://link.springer.com/brands/springer | M29: Publishing | N29: 1 | O29: 79 | P29: 51.3M
A30: 26 | B30: https://cozyartzmedia.com/ | C30: 51 | D30: 1 | E30: 7 | F30: 327 | G30: 0 | H30: 0 | L30: https://forbesjapan.com/ | M30: Education | N30: 1 | O30: 77 | P30: 5M
A31: 27 | B31: https://ga-training.com/ | C31: 80 | D31: 20 | E31: 8 | F31: 268 | G31: 14 | H31: 0 | L31: https://www.britishcouncil.org/ | M31: Distance Learning | N31: 3 | O31: 76 | P31: 12.3M
A32: 28 | B32: http://palinfocom.com/ | C32: 473 | D32: 64 | E32: 10 | F32: 2.4k | G32: 0 | H32: 0 | L32: https://www.cisco.com/ | M32: Information Technology | N32: 1 | O32: 76 | P32: 15.2M
A33: 29 | B33: https://www.brewersassociation.org/edu/online-courses/ | C33: 49.2k | D33: 35k | E33: 44 | F33: 528k | G33: 26 | H33: 1.6k
A34: 30 | B34: https://maplecollabconsulting.com/ | C34: 0 | D34: 2 | E34: 2 | F34: 166 | G34: 0 | H34: 0
A35: 31 | B35: https://sdlcorp.in/ | C35: 6 | D35: 3 | E35: 5 | F35: 36 | G35: 0 | H35: 0
A36: 32 | B36: https://joyoptions.org/joy-e-learning-courses/ | C36: 3 | D36: 33 | E36: 5 | F36: 191 | G36: 14 | H36: 2
A37: 33 | B37: https://wizcabin.com/ | C37: 0 | D37: 75 | E37: 11 | F37: 5k | G37: 14 | H37: 2
A38: 34 | B38: https://jupitered.com/ | C38: 789.8K | D38: 6k | E38: 51 | F38: 66.9k | G38: 32 | H38: 120

Sheet RAW Keyword Research
A1: KEYWORD RESEARCH
A3: SR NO | B3: KEYWORD | C3: VOLUME | D3: GLOBAL VOLUME | E3: DIFFICULTY | F3: INTENT | G3: TARGETED PAGE | H3: WORD TYPE
A4: 1 | B4: Custom e-learning Development Services​ | C4: 30 | D4: 70 | E4: 21 | F4: Commercial | G4: Custom elearnig Development | H4: Secondary Keyword
A5: 2 | B5: Custom elearning development​ | C5: 1300 | D5: 2.7K | E5: 5 | F5: Informational | G5: Custom elearnig Development | H5: Primary Keyword
A6: 3 | B6: custom elearning solutions​ | C6: 880 | D6: 1.6K | E6: 32 | F6: Informational | G6: Custom elearnig Development | H6: Secondary Keyword
A7: 4 | B7: custom elearning​ | C7: 880 | D7: 2.1K | E7: 47 | F7: Informational | G7: Custom elearnig Development | H7: Secondary Keyword
A8: 5 | B8: custom elearning content development | C8: 390 | D8: 720 | E8: 25 | F8: Informational | G8: Custom elearnig Development | H8: Secondary Keyword
A9: 6 | B9: elearning development​ | C9: 590 | D9: 1.8K | E9: 9 | F9: Informational | G9: Custom elearnig Development | H9: Secondary Keyword
A10: 7 | B10: custom elearning course development​ | C10: 390 | D10: 730 | E10: 20 | F10: Informational | G10: Custom elearnig Development | H10: Secondary Keyword
A11: 8 | B11: elearning localization services | C11: 320 | D11: 530 | E11: 6 | F11: Informational | G11: Custom elearnig Development | H11: Secondary Keyword
A12: 10 | B12: custom elearning content development​ | C12: 390 | D12: 720 | E12: 25 | F12: Informational | G12: Custom elearnig Development | H12: Secondary Keyword
A13: 11 | B13: custom elearning course development​ | C13: 390 | D13: 730 | E13: 20 | F13: Informational | G13: Custom elearnig Development | H13: Secondary Keyword
B14: AI Powered learning and development Solutions
A15: 12 | B15: ai powered learning solutions | C15: 20 | D15: 20 | E15: 0 | F15: Commercial+Informational | G15: AI Powered learning and development Solutions
A16: 13 | B16: e-learning solutions​ | C16: 480 | D16: 2.3K | E16: 42 | F16: Informational | G16: AI Powered learning and development Solutions
B17: LMS Implementation & Integration
A18: 16 | B18: managed learning environment​ | C18: 3.6K | D18: 11.4k | E18: 24 | F18: Informational | G18: LMS Implementation & Integration | H18: Secondary Keyword
A19: 17 | B19: training management software​ | C19: 1.9K | D19: 4.5k | E19: 17 | F19: Commercial+Informational | G19: LMS Implementation & Integration | H19: Secondary Keyword
A20: 18 | B20: lms implementation​ | C20: 590 | D20: 1.2k | E20: 5 | F20: Informational | G20: LMS Implementation & Integration | H20: Primary Keyword
A21: 20 | B21: lms integration​ | C21: 590 | D21: 1.9k | E21: 27 | F21: Informational | G21: LMS Implementation & Integration | H21: Primary Keyword
A22: 21 | B22: learning management system integration​ | C22: 260 | D22: 540 | E22: 23 | F22: Informational | G22: LMS Implementation & Integration | H22: Secondary Keyword
A23: 26 | B23: lms migration​ | C23: 320 | D23: 620 | E23: 18 | F23: Informational | G23: LMS Implementation & Integration | H23: Secondary Keyword
A24: 27 | B24: lms migration services | C24: 90 | D24: 120 | E24: 4 | F24: Informational | G24: LMS Implementation & Integration | H24: Secondary Keyword
B25: AR & VR Solutions
A26: 29 | B26: virtual reality training​ | C26: 1.0K | D26: 4.2k | E26: 26 | F26: Informational | G26: AR & VR Solutions | H26: Secondary Keyword
B27: ark augmented reality​ | C27: 480 | D27: 1.7k | E27: 29 | F27: Informational | G27: AR & VR Solutions | H27: Secondary Keyword
B28: ar vr agency​ | C28: 40.5k | D28: 53.2k | E28: 23 | F28: Informational | G28: AR & VR Solutions | H28: Secondary Keyword
B29: vr development services​ | C29: 140 | D29: 260 | E29: 15 | F29: Informational | G29: AR & VR Solutions | H29: Secondary Keyword
A30: 30 | B30: augmented reality solutions​ | C30: 140 | D30: 380 | E30: 26 | F30: Informational | G30: AR & VR Solutions | H30: Secondary Keyword
A31: 31 | B31: Virtual reality solutions​ | C31: 170 | D31: 960 | E31: 26 | F31: Informational | G31: AR & VR Solutions | H31: Secondary Keyword
A32: 32 | B32: ar and vr solutions​ | C32: 90 | D32: 120 | E32: 19 | F32: Informational | G32: AR & VR Solutions | H32: Primary Keyword
B33: Audio & Video Production for eLearning
A34: 35 | B34: audio production | C34: 1.6k | D34: 4.4k | E34: 28 | F34: Informational | G34: Audio & Video Production for eLearning | H34: Secondary Keyword
A35: 36 | B35: audio and video production​ | C35: 210 | D35: 590 | E35: 16 | F35: Informational | G35: Audio & Video Production for eLearning | H35: Secondary Keyword
A36: 38 | B36: voiceover production​ | C36: 30 | D36: 150 | F36: Informational | G36: Audio & Video Production for eLearning | H36: Secondary Keyword
A37: 39 | B37: 3d animation video production​ | C37: 390 | D37: 580 | E37: 24 | F37: Informational | G37: Audio & Video Production for eLearning | H37: Secondary Keyword
A38: 40 | B38: animated videos for elearning​ | C38: 50 | D38: 90 | E38: 12 | F38: Informational+Transational | G38: Audio & Video Production for eLearning | H38: Secondary Keyword
A39: 41 | B39: elearning video production services | G39: Audio & Video Production for eLearning | H39: Primary Keyword
A40: 42 | B40: audio in elearning​ | C40: 20 | D40: 40 | G40: Audio & Video Production for eLearning | H40: Secondary Keyword
B41: Legacy Content Conversion
A42: 43 | B42: legacy content conversions​ | C42: 20 | D42: 20 | G42: Legacy Content Conversion | H42: Secondary Keyword
A43: 44 | B43: legacy content conversion services | C43: 20 | D43: 20 | G43: Legacy Content Conversion | H43: Primary Keyword
A44: 45 | B44: eLearning content conversion | F44: Informational | G44: Legacy Content Conversion | H44: Secondary Keyword
A45: 46 | B45: convert flash to html5​ | C45: 140 | D45: 770 | E45: 28 | F45: Informational | G45: Legacy Content Conversion | H45: Secondary Keyword
A46: 47 | B46: ppt to elearning conversion​ | C46: 90 | D46: 220 | E46: 4 | F46: Informational | G46: Legacy Content Conversion | H46: Secondary Keyword
A47: 48 | B47: create interactive elearning | C47: 40 | D47: 70 | E47: 21 | F47: Informational | G47: Legacy Content Conversion | H47: Secondary Keyword
A48: 49 | B48: how to make powerpoint interactive | C48: 40 | D48: 710 | E48: 27 | F48: Informational | G48: For Blog Post(not to include) | H48: Secondary Keyword
A49: 50 | B49: how to convert legacy content to eLearning | G49: For Blog Post(not to include) | H49: Secondary Keyword
B50: Instructional & UI/UX Design
A51: 51 | B51: e learning instructional design​ | C51: 50 | D51: 610 | E51: 23 | F51: Commercial+Informational | G51: Instructional & UI/UX Design | H51: Secondary Keyword
A52: 52 | B52: elearning and instructional design | C52: 30 | D52: 140 | E52: 26 | F52: Informational | G52: Instructional & UI/UX Design | H52: Secondary Keyword
A53: 53 | B53: instructional design for e learning | C53: 30 | D53: 550 | E53: 16 | F53: Informational | G53: Instructional & UI/UX Design | H53: Secondary Keyword
A54: 54 | B54: elearning design | C54: 390 | D54: 1.6k | E54: 26 | F54: Informational | G54: Instructional & UI/UX Design | H54: Secondary Keyword
A55: 55 | B55: custom e learning design | C55: 110 | D55: 190 | E55: 26 | F55: Commercial | G55: Instructional & UI/UX Design | H55: Secondary Keyword
A56: 56 | B56: Instructional Design services | C56: 590 | D56: 2.3k | E56: 21 | F56: Informational | G56: Instructional & UI/UX Design | H56: Primary Keyword
A57: 57 | B57: elearning ui/ux design services​ | F57: Informational | G57: Instructional & UI/UX Design | H57: Secondary Keyword
B58: Rapid eLearning Development
A59: 58 | B59: rapid learning​ | C59: 210 | D59: 1.0k | E59: 18 | F59: Informational | G59: Rapid eLearning Development | H59: Secondary Keyword
A60: 59 | B60: rapid elearning | C60: 90 | D60: 300 | E60: 23 | F60: Informational | G60: Rapid eLearning Development | H60: Secondary Keyword
A61: 60 | B61: rapid elearning development​ | C61: 90 | D61: 200 | E61: 24 | F61: Informational | G61: Rapid eLearning Development | H61: Secondary Keyword
A62: 61 | B62: rapid elearning services​ | C62: 30 | D62: 130 | G62: Rapid eLearning Development | H62: Secondary Keyword
A63: 62 | B63: best rapid elearning services​ | C63: 10 | D63: 10 | G63: Rapid eLearning Development | H63: Secondary Keyword
A64: 63 | B64: rapid elearning development company​ | C64: 10 | D64: 40 | G64: Rapid eLearning Development | H64: Secondary Keyword
A65: 64 | B65: rapid elearning content development services​ | G65: Rapid eLearning Development | H65: Secondary Keyword
A66: 65 | B66: rapid elearning development services​ | F66: Informational | G66: Rapid eLearning Development | H66: Primary Keyword
B67: Dashboard and Analytics
A68: 66 | B68: elearning analytics​ | C68: 50 | D68: 130 | E68: 7 | F68: Informational | G68: Dashboard and Analytics | H68: Secondary Keyword
A69: 67 | B69: elearning analytics​ services | C69: 20 | D69: 50 | G69: Dashboard and Analytics | H69: Primary Keyword
A70: 68 | B70: elearning data analytics​ | C70: 20 | D70: 70 | G70: Dashboard and Analytics | H70: Secondary Keyword
A71: 69 | B71: data analytics in elearning​ | G71: Dashboard and Analytics | H71: Secondary Keyword
A72: 70 | B72: lms analytics dashboard​ | C72: 40 | D72: 90 | F72: Informational | G72: Dashboard and Analytics | H72: Secondary Keyword
A73: 71 | B73: learning analytics platform​ | C73: 210 | D73: 490 | E73: 20 | F73: Commercial+Informational | G73: Dashboard and Analytics | H73: Secondary Keyword
A74: 72 | B74: analytical training solutions​ | C74: 20 | D74: 110 | G74: Dashboard and Analytics | H74: Secondary Keyword
B75: Gamified eLearning​
A76: 73 | B76: elearning gamification​ | C76: 210 | D76: 1.2k | E76: 24 | F76: Informational | G76: Gamified eLearning​ | H76: Secondary Keyword
A77: 74 | B77: gamified elearning​ | C77: 170 | D77: 530 | E77: 22 | F77: Informational | G77: Gamified eLearning​ | H77: Secondary Keyword
A78: 75 | B78: gamification in e learning​ | C78: 110 | D78: 910 | E78: 16 | F78: Informational | G78: Gamified eLearning​ | H78: Secondary Keyword
A79: 76 | B79: gamification elearning services​ | G79: Gamified eLearning​ | H79: Primary Keyword
A80: 77 | B80: gamification in elearning​ | C80: 210 | D80: 980 | F80: Informational | G80: Gamified eLearning​ | H80: Secondary Keyword
A81: 78 | B81: gamification in training​ | C81: 140 | D81: 1.1k | E81: 36 | F81: Informational | G81: Gamified eLearning​ | H81: Secondary Keyword
A82: 79 | B82: gamification in employee training​ | C82: 40 | D82: 170 | E82: 30 | F82: Informational | G82: Gamified eLearning​ | H82: Secondary Keyword
B83: L&D Consulting & Advisory Services
A84: 80 | B84: learning and development consulting​ | C84: 320 | D84: 1.3k | E84: 14 | F84: Informational | G84: L&D Consulting & Advisory Services | H84: Secondary Keyword
A85: 81 | B85: learning and development consultant​ | C85: 260 | D85: 1.6k | E85: 6 | F85: Commercial | G85: L&D Consulting & Advisory Services | H85: Secondary Keyword
A86: 82 | B86: learning & development consultant​ | C86: 210 | D86: 700 | E86: 10 | F86: Commercial+Informational | G86: L&D Consulting & Advisory Services | H86: Secondary Keyword
A87: 83 | B87: learning and development consulting services | C87: 70 | D87: 190 | E87: 7 | F87: Informational | G87: L&D Consulting & Advisory Services | H87: Primary Keyword
A88: 84 | B88: l&d consultation services​ | C88: 10 | D88: 10 | G88: L&D Consulting & Advisory Services | H88: Secondary Keyword
A89: 85 | B89: l&d advisory services​ | C89: 10 | D89: 10 | G89: L&D Consulting & Advisory Services | H89: Secondary Keyword
A90: 86 | B90: learning strategy consulting​ | C90: 40 | D90: 60 | G90: L&D Consulting & Advisory Services | H90: Secondary Keyword
A91: 87 | B91: corporate training strategies | C91: 50 | D91: 90 | E91: 28 | F91: Informational | G91: L&D Consulting & Advisory Services | H91: Secondary Keyword
A92: 88 | B92: corporate training strategy​ | C92: 70 | D92: 150 | E92: 32 | F92: Informational | G92: L&D Consulting & Advisory Services | H92: Secondary Keyword
A93: 89 | B93: managed learning transformation services​ | C93: 70 | D93: 130 | E93: 7 | F93: Informational | G93: L&D Consulting & Advisory Services | H93: Secondary Keyword
B94: E-learning Localization Services
A95: 90 | B95: elearning localization services​ | C95: 390 | D95: 600 | E95: 6 | F95: Informational | G95: E-learning Localization Services | H95: Primary Keyword
A96: 91 | B96: elearning localization | C96: 260 | D96: 710 | E96: 13 | F96: Informational | G96: E-learning Localization Services | H96: Secondary Keyword
A97: 92 | B97: elearning content localization​ | C97: 70 | D97: 130 | E97: 11 | F97: Informational | G97: E-learning Localization Services | H97: Secondary Keyword
A98: 93 | B98: elearning translation and localization​ | C98: 70 | D98: 110 | E98: 10 | F98: Informational | G98: E-learning Localization Services | H98: Secondary Keyword
A99: 94 | B99: elearning translation and localization services​ | C99: 50 | D99: 50 | G99: E-learning Localization Services | H99: Secondary Keyword
A100: 95 | B100: elearning localization service​ | C100: 30 | D100: 100 | G100: E-learning Localization Services | H100: Secondary Keyword
A101: 96 | B101: localizing elearning and translation | C101: 90 | D101: 100 | E101: 12 | F101: Informational | G101: E-learning Localization Services | H101: Secondary Keyword
...

Sheet RAW Blog Keywords
A1: Keywords for Blog
A3: SR NO | B3: KEYWORD | C3: VOLUME | D3: GLOBAL VOLUME | E3: DIFFICULTY | F3: INTENT | G3: TARGETED PAGE
A4: Legacy Content Conversion
A5: 1 | B5: how to make powerpoint interactive | C5: 40 | D5: 710 | E5: 27 | F5: Informational | G5: Legacy Content Conversion
A6: 2 | B6: how to convert legacy content to eLearning | F6: Informational | G6: Legacy Content Conversion
A7: Audio & Video Production for eLearning
A8: 3 | B8: what is audio in elearning | F8: Informational | G8: Audio & Video Production for eLearning
A9: 4 | B9: how to create animated elearning videos | F9: Informational | G9: Audio & Video Production for eLearning
A10: AR & VR Solutions
A11: 5 | B11: What Are AR and VR in eLearning? | C11: 590 | D11: 670 | E11: 26 | F11: Informational | G11: AR & VR Solutions
A12: 6 | B12: what is the difference between augmented reality and virtual reality​ | C12: 170 | D12: 1.4k | E12: 28 | F12: Informational | G12: AR & VR Solutions
A13: LMS Implementation & Integration
A14: 7 | B14: key lms features​ | C14: 70 | D14: 140 | E14: 12 | F14: Informational | G14: LMS Implementation & Integration
A15: 8 | B15: benefits of lms​ | C15: 390 | D15: 1.0k | E15: 26 | F15: Informational | G15: LMS Implementation & Integration
A16: 9 | B16: what does lms mean​ | C16: 5.4K | D16: 7.2k | E16: 38 | F16: Informational | G16: LMS Implementation & Integration
A17: 10 | B17: lms implementation checklist​ | C17: 390 | D17: 510 | E17: 19 | F17: Informational | G17: LMS Implementation & Integration
A20: Keyword research for Blog Post
A22: SR NO | B22: KEYWORD | C22: VOLUME | D22: GLOBAL VOLUME | E22: DIFFICULTY | F22: INTENT | G22: TYPE | H22: TARGETED PAGE
A23: 1 | B23: Thinkific | C23: 22.2K | D23: 78.4K | E23: 64 | F23: Commercial+Navigational | G23: Secondary Keyword | H23: Thinkific: Create Strong and Massive Courses that Actually Work
A24: 2 | B24: thinkific pricing​ | C24: 2.4K | D24: 4.8K | E24: 37 | F24: Navigational+Transational | G24: Secondary Keyword | H24: Thinkific: Create Strong and Massive Courses that Actually Work
A25: 3 | B25: thinkific review​ | C25: 260 | D25: 840 | E25: 28 | F25: Commercial | G25: Secondary Keyword | H25: Thinkific: Create Strong and Massive Courses that Actually Work
A26: 4 | B26: thinkific pricing plans​ | C26: 390 | D26: 630 | E26: 24 | F26: Informational | G26: Secondary Keyword | H26: Thinkific: Create Strong and Massive Courses that Actually Work
A27: 5 | B27: thinkific plus pricing​ | C27: 40 | D27: 120 | E27: 17 | F27: Informational | G27: Secondary Keyword | H27: Thinkific: Create Strong and Massive Courses that Actually Work
A28: 6 | B28: thinkific basic plan | C28: 170 | D28: 240 | E28: 29 | F28: Informational | G28: Secondary Keyword | H28: Thinkific: Create Strong and Massive Courses that Actually Work
A29: 7 | B29: how much does thinkific cost​ | C29: 40 | D29: 80 | E29: 19 | F29: Informational | G29: Secondary Keyword | H29: Thinkific: Create Strong and Massive Courses that Actually Work
A30: 8 | B30: how to create a thinkific course​ | C30: 20 | D30: 40 | E30: 0 | F30: Informational | G30: Primary Keyword | H30: Thinkific: Create Strong and Massive Courses that Actually Work
A31: 9 | B31: what is thinkific​ | C31: 210 | D31: 630 | E31: 11 | F31: Informational | G31: Secondary Keyword | H31: Thinkific: Create Strong and Massive Courses that Actually Work
A32: 10 | B32: thinkific vs. teachable​ | C32: 40 | D32: 850 | E32: 11 | F32: Commercial+Informational | G32: Secondary Keyword | H32: Thinkific: Create Strong and Massive Courses that Actually Work
A33: 11 | B33: thinkific pricing plans​ | C33: 390 | D33: 620 | E33: 24 | F33: Informational | G33: Secondary Keyword | H33: Thinkific: Create Strong and Massive Courses that Actually Work
A36: 1 | F36: Informational | G36: Secondary Keyword
A37: 2 | F37: Informational | G37: Secondary Keyword
A38: 3 | F38: Informational | G38: Secondary Keyword
A39: 4 | F39: Informational | G39: Secondary Keyword
A40: 5 | F40: Informational | G40: Secondary Keyword
A41: 6 | F41: Informational | G41: Secondary Keyword
A42: 7 | F42: Informational | G42: Secondary Keyword
A43: 8 | F43: Informational | G43: Secondary Keyword
A44: 9 | F44: Informational | G44: Secondary Keyword
A45: 10 | F45: Informational | G45: Secondary Keyword
A46: 11 | F46: Informational | G46: Secondary Keyword

Sheet RAW April Keywords
A1: Unique Value | B1: Count | E1: Top queries
A2: Instructional Design | B2: 1835 | E2: elearning content development
A3: Course | B3: 1776 | E3: learning retention
A4: Elearning | B4: 1685 | E4: electronic learning
A5: course | B5: 1327 | E5: technical proficiency? | F5: 39
A6: Online Instruction | B6: 1269 | E6: learning strategies | F6: 23
A7: Graphic Design | B7: 1252 | E7: elearning trends 2026 | F7: 22
A8: Content Writing | B8: 1114 | E8: best moocs 2025 | F8: 16 | I8: keywords list | J8: vol | K8: Kd | M8: Google trends
A9: WordPress | B9: 1096 | E9: ai driven content mastery course | F9: 14
B10: 942 | E10: mooc | F10: 8 | I10: instructional system design | J10: 1000 | K10: 27 | Q10: Keyword | R10: Search Volume | S10: KD | T10: Intent
A11: Web Development | B11: 929 | E11: technical skill in cv | I11: masters in instructional design | J11: 880 | K11: 28 | Q11: instructional system design | R11: 1000 | S11: 27 | T11: Informational
A12: Education | B12: 903 | E12: moocs 2025 | F12: 7 | I12: specifically designed instruction | J12: 880 | K12: 22 | Q12: specifically designed instruction | R12: 880 | S12: 22 | T12: Informational
A13: learning | B13: 889 | E13: udemy | F13: 4 | I13: instructional design courses | J13: 590 | K13: 16 | Q13: instructional design course | R13: 390 | S13: 23 | T13: Informational/Commercial
A14: training | B14: 825 | E14: class creator | I14: instructional design course | J14: 390 | K14: 23 | Q14: what do instructional designers do | R14: 390 | S14: 17 | T14: Informational
A15: platform | B15: 823 | E15: teach start | I15: what do instructional designers do | J15: 390 | K15: 17 | Q15: instructional design services | R15: 320 | S15: 18 | T15: Informational
A16: Kajabi | B16: 817 | E16: elearning development services | I16: instructional design services | J16: 320 | K16: 18 | Q16: what does an instructional designer do | R16: 320 | S16: 25 | T16: Informational
A17: Web Design | B17: 784 | E17: learning theories | F17: 1 | I17: what does an instructional designer do | J17: 320 | K17: 25 | Q17: planning and development training | R17: 880 | S17: 17 | T17: Informational/Transactional
A18: Learning Management System | B18: 750 | E18: best elearning tools | I18: what does an instructional designer do | J18: 320 | K18: 25 | Q18: best elearning tools | R18: 110 | S18: 23 | T18: Commercial
A19: courses | B19: 730 | E19: how to learn ai in 2025 | F19: 1 | I19: planning and development training | J19: 880 | K19: 17 | Q19: elearning development | R19: 480 | S19: 15 | T19: Informational
A20: Articulate Storyline | B20: 617 | E20: ed-tech tools for career guidance | F20: 2041 | I20: masters in training and development | J20: 140 | K20: 20 | Q20: custom elearning development | R20: 590 | S20: 29 | T20: Informational
A21: Video Production | B21: 610 | E21: what is technical proficiency | F21: 601 | I21: best elearning tools | J21: 110 | K21: 23 | Q21: elearning content development | R21: 390 | S21: 18 | T21: Informational/Commercial
A22: English | B22: 481 | E22: teachability | I22: elearning development | J22: 480 | K22: 15 | Q22: learning retention | R22: 260 | S22: 27 | T22: Informational
A23: Course Creation | B23: 436 | E23: personal learning environment | I23: custom elearning development | J23: 590 | K23: 29 | Q23: electronic learning | R23: 1000 | S23: 31 | T23: Informational
A24: Curriculum Development | B24: 419 | E24: thinkific logo | I24: elearning content development | J24: 390 | K24: 18 | Q24: research based instructional strategies | R24: 590 | S24: 25 | T24: Informational
A25: Landing Page | B25: 385 | E25: learning strategies | I25: custom elearning development services | J25: 210 | K25: 22 | Q25: terminal learning objective | R25: 590 | S25: 9 | T25: Informational/Commercial
A26: online | B26: 370 | F26: 524 | I26: elearning developer | J26: 210 | K26: 16 | Q26: what is a learning objective | R26: 390 | S26: 28 | T26: Informational
A27: Social Media Marketing | B27: 352 | E27: saas training best practices | F27: 488 | Q27: what are the objectives of learning | R27: 320 | S27: 29 | T27: Informational
A28: Explainer Video | B28: 343 | E28: problem solving expert apps like solve for me 2025 | F28: 469 | I28: custom elearning course development | J28: 210 | K28: 30 | Q28: how to write a learning objective | R28: 210 | S28: 24 | T28: Informational
A29: Lead Generation | B29: 327 | E29: elearning localization services | F29: 340 | I29: learning retention | J29: 260 | K29: 27 | Q29: course outline | R29: 480 | S29: 25 | T29: Informational
A30: PHP | B30: 319 | E30: expert problem solving apps like solve for me 2025 | F30: 319 | I30: elearning development services | J30: 260 | K30: 30 | Q30: course outline template | R30: 170 | S30: 21 | T30: Informational
A31: Training | B31: 307 | E31: best lms platform | I31: custom elearning services | J31: 110 | K31: 29 | Q31: meaning of storyboarding | R31: 480 | S31: 29 | T31: Informational
A32: Learning | B32: 304 | E32: the edu | F32: 280 | I32: electronic learning | J32: 1000 | K32: 31 | Q32: instructional design storyboard | R32: 110 | S32: 18 | T32: Informational
A33: LMS | B33: 300 | E33: elearning translation services | F33: 276 | I33: high content analysis | J33: 210 | K33: 19 | Q33: personal learning environment | R33: 1300 | S33: 15 | T33: Informational
A34: Program Curriculum | B34: 299 | E34: e-learning course creation trends 2026 | F34: 267 | I34: video content analysis | J34: 210 | K34: 28 | Q34: microlearning platforms | R34: 390 | S34: 21 | T34: Informational
A35: Writing | B35: 295 | E35: technical skills resume | I35: course outline | J35: 480 | K35: 25 | Q35: learning strategies | R35: 2400 | S35: 30 | T35: Informational
A36: Communications | B36: 290 | E36: teachability | F36: 524 | I36: course outline template | J36: 170 | K36: 21 | Q36: learning and development strategy | R36: 390 | S36: 20 | T36: Informational
A37: Adobe Illustrator | B37: 275 | E37: saas training best practices | F37: 488 | I37: course outline format | J37: 110 | K37: 19 | Q37: what are learning strategies | R37: 210 | S37: 24 | T37: Informational
A38: LearnWorlds | B38: 266 | E38: problem solving expert apps like solve for me 2025 | F38: 469 | I38: course outline sample | J38: 90 | K38: 15 | Q38: benefits of in person learning | R38: 140 | S38: 27 | T38: Informational
A39: Adobe Premiere Pro | B39: 262 | E39: elearning localization services | F39: 340 | I39: instructional design storyboard | J39: 110 | K39: 18 | Q39: designing a curriculum | R39: 260 | S39: 29 | T39: Informational
A40: Adobe Photoshop | B40: 261 | E40: learning and development strategy | I40: research based instructional strategies | J40: 590 | K40: 25 | Q40: designing curriculum | R40: 140 | S40: 18 | T40: Informational
A41: Marketing Strategy | B41: 258 | E41: digital learning solution | I41: terminal learning objective | J41: 590 | K41: 9 | Q41: what is curriculum development centre | R41: 1300 | S41: 11 | T41: Informational
A42: Moodle | B42: 255 | E42: the edu | F42: 280 | I42: what is a learning objective | J42: 390 | K42: 28 | Q42: curriculum developer work | R42: 320 | S42: 22 | T42: Informational
A43: LearnDash | B43: 253 | E43: elearning translation services | F43: 276 | I43: what are the objectives of learning | J43: 320 | K43: 29
A44: JavaScript | B44: 251 | E44: e-learning course creation trends 2026 | F44: 267 | I44: how to write a learning objective | J44: 210 | K44: 24 | N44: kajabi vs thinkific
A45: Platform | B45: 234 | E45: electronic learning | I45: screen design | J45: 170 | K45: 28
A46: Data Entry | B46: 231 | E46: mobile learning solutions | I46: meaning of storyboarding | J46: 480 | K46: 29
A47: Curriculum Design | B47: 229 | E47: primary and secondary technical domain skills | F47: 168 | I47: full service video production | J47: 260 | K47: 20
A48: Thinkific | B48: 229 | E48: what does technical proficiency mean | F48: 167 | I48: custom learning solutions | J48: 170 | K48: 10
A49: Articulate Rise | B49: 226 | E49: gamified learning solutions | F49: 159 | I49: personal learning environment | J49: 1300 | K49: 15
A50: Video Post-Editing | B50: 214 | E50: kajabi review | I50: personal learning platform | J50: 210 | K50: 24 | Q50: technical skills in it resume | R50: Informational | S50: 1600 | T50: 32 | U50: 0.51 | V50: Sitelinks, AI Overview, Image pack, Video, Video carousel, People also ask, Related searches | W50: 1 month
A51: design | B51: 200 | E51: elearning popularity growth trends 2026 | F51: 145 | I51: benefits of in person learning | J51: 140 | K51: 27 | Q51: define technical skills | R51: Informational | S51: 880 | T51: 31 | U51: 0 | V51: Sitelinks, AI Overview, Video, People also ask, Discussions and forums, Related searches | W51: 1 month
A52: Python | B52: 195 | E52: curriculum development services | I52: learnworlds vs thinkific | J52: 110 | K52: 21 | Q52: sample resume technical skills | R52: Informational | S52: 170 | T52: 30 | U52: 0.53 | V52: Sitelinks, AI Overview, Image, Image pack, Video, Video carousel, Discussions and forums, Related searches | W52: 1 month
A53: Elearning Design | B53: 194 | E53: kajabi vs thinkific | F53: 142 | I53: what is kajabi | J53: 720 | K53: 23 | Q53: technical skills meaning | R53: Informational | S53: 1000 | T53: 35
A54: Synthesia | B54: 190 | E54: elearning developer | I54: kajabi vs teachable | J54: 390 | K54: 21
A55: Canva | B55: 189 | E55: custom learning solutions | J55: 320 | K55: 15 | Q55: coursebox | R55: Navigational, Transactional | S55: People also ask | T55: Sitelinks, Image, Video, People also ask, Knowledge panel, Related searches | U55: 4 | V55: 100 | W55: 480 | X55: 42 | Y55: https://elearningindustry.com/directory/elearning-software/coursebox | Z55: 45938
A56: Teachable | B56: 172 | E56: elearning development services | I56: kajabi templates | J56: 260 | K56: 25 | Q56: coursebox pricing | R56: Navigational, Transactional | S56: 5 | T56: Sitelinks, Video, People also ask, Related searches, Ads middle, Ads bottom | U56: 0 | V56: 0 | W56: 30 | X56: 10 | Y56: https://elearningindustry.com/directory/elearning-software/coursebox/pricing | Z56: 45906
A57: Artificial Intelligence | B57: 169 | E57: creators monetization strategies skool community 2025 | F57: 121 | I57: teachable vs kajabi | J57: 260 | K57: 21 | Q57: coursebox ai | R57: Commercial, Navigational | S57: 3 | T57: Sitelinks, Image pack, Video, Related searches, Ads top, Ads bottom | U57: 3 | V57: 60 | W57: 170 | X57: 25 | Y57: https://www.futurepedia.io/tool/coursebox | Z57: 45895
A58: Virtual Assistance | B58: 169 | E58: skool vs kajabi | F58: 113 | I58: thinkific vs kajabi | J58: 260 | K58: 18 | Q58: ai tool for creating online course
A59: Copywriting | B59: 167 | E59: platform training | I59: platforms like kajabi | J59: 210 | K59: 17 | Q59: coursebox reviews
A60: AI-Generated Video | B60: 167 | E60: teach start | I60: sites like kajabi | J60: 210 | K60: 20
A61: Facebook | B61: 166 | E61: kajabi review | I61: kajabi experts | J61: 170 | K61: 10
A62: instructional | B62: 163 | E62: thinkific vs kajabi | F62: 112 | I62: what is curriculum development centre | J62: 1300 | K62: 11
A63: Email Marketing | B63: 162 | E63: list technical skills resume | F63: 109 | I63: curriculum developer | J63: 720 | K63: 20
A64: Adobe After Effects | B64: 162 | E64: ai for course creation | F64: 109 | I64: curriculum developer work | J64: 320 | K64: 22
A65: Learn | B65: 158 | E65: custom mobile learning solutions | F65: 107 | I65: curriculum development services | J65: 110 | K65: 0
A66: Elearning Video | B66: 155 | E66: top courses for future proofing skills | F66: 106 | I66: designing a curriculum | J66: 260 | K66: 29
A67: digital | B67: 155 | E67: technical skills examples for resume | F67: 105 | I67: curriculum designer | J67: 320 | K67: 20
A68: Microsoft PowerPoint | B68: 149 | E68: best math problem solving app | F68: 103 | I68: designing curriculum | J68: 140 | K68: 18
A69: Animation | B69: 147 | E69: custom elearning content development | F69: 102 | I69: microlearning platforms | J69: 390 | K69: 21 | AA69: construction company website design UAE
A70: HTML | B70: 144 | E70: course creation ai | F70: 101 | I70: learning strategies | J70: 2400 | K70: 30 | AA70: construction company web design UAE
A71: Motion Graphics | B71: 143 | E71: technical skills list for resume | F71: 98 | I71: learning strategy | J71: 480 | K71: 27
A72: Administrative Support | B72: 143 | E72: scorm news december 2025 | F72: 97 | I72: learning and development strategy | J72: 390 | K72: 20
A73: creation | B73: 142 | E73: theedu | F73: 97 | I73: what are learning strategies | J73: 210 | K73: 24
A74: Creative Writing | B74: 138 | E74: should i say education & experience on a resume or experience & education? | F74: 97 | I74: technical content writer | J74: 140 | K74: 24
A75: Training Presentation | B75: 138 | E75: course outline | I75: technical writing services | J75: 480 | K75: 21
A76: Online | B76: 131 | E76: udemy platform description | I76: technical content writing services | J76: 70 | K76: 16
A77: Articulate | B77: 126 | I77: get course | J77: 590 | K77: 27
A78: Training , Development | B78: 124 | I78: best things to sell online | J78: 590 | K78: 28
A79: Social Media Management | B79: 123 | I79: selling content | J79: 480 | K79: 20
A80: eLearning | B80: 121 | I80: best buy e learning | J80: 170 | K80: 19
A81: curriculum | B81: 118 | I81: kajabi review | J81: 320 | K81: 15
A82: Project Management | B82: 114 | I82: best lms for small business | J82: 880 | K82: 26
A83: CSS | B83: 114 | I83: sell designs online | J83: 170 | K83: 20
A84: Marketing Automation | B84: 112 | I84: online sales coaching | J84: 260 | K84: 28
A85: 2D Animation | B85: 111 | I85: kajabi logo | J85: 390 | K85: 21
A86: Presentation Design | B86: 108 | I86: branding courses
A87: Lesson | B87: 106
A88: Sales | B88: 106 | I88: get course | J88: 590 | K88: 27
A89: Shareable Content Object Reference Model | B89: 105 | I89: best things to sell online | J89: 590 | K89: 28
A90: ClickFunnels | B90: 101 | I90: selling content | J90: 480 | K90: 20
A91: Organizational Development | B91: 97 | I91: best buy e learning | J91: 170 | K91: 19
A92: Sales Funnel | B92: 96 | I92: kajabi review | J92: 320 | K92: 15
A93: Website | B93: 95 | I93: best lms for small business | J93: 880 | K93: 26
A94: Elearning LMS Consulting | B94: 94 | I94: sell designs online | J94: 170 | K94: 20
A95: Presentations | B95: 93 | I95: online sales coaching | J95: 260 | K95: 28
A96: Infographic | B96: 90 | I96: kajabi logo | J96: 390 | K96: 21
A97: Synchronous Learning | B97: 90 | I97: branding courses | J97: 210 | K97: 25
A98: Academic K-12 | B98: 89 | I98: course material | J98: 720 | K98: 22
A99: Instructional | B99: 86 | I99: things to sell at school | J99: 260 | K99: 3
... A101: Illustration | B101: 84 | I101: teacher builder | J101: 480 | K101: 25
...

Sheet RAW Backlinks
A1: Referring Domain1 â€“ 100 (4,253) | B1: Link | C1: AS | D1: Monthly Visits | E1: Matches | F1: theeduassist.comtheeduassist.com | G1: gpstrategies.comgpstrategies.com | H1: learningeverest.comlearningeverest.com | I1: elearning.companyelearning.company | K1: thelearningedge.euthelearningedge.eu
A2: adobe.com | B2: https://airtable.com/apphWUswjmwIry4SZ/pagM66mocklT7qYQM/form#sa_src=web-messaging | C2: 100 | D2: 461M | E2: 46086 | F2: 0 | G2: 1 | H2: 12 | I2: 2 | K2: 0
A3: apple.com | C3: 100 | D3: 850M | E3: 46027 | F3: 0 | G3: 17 | H3: 0 | I3: 0 | K3: 0
A4: google.com | C4: 100 | D4: 112B | E4: 46027 | F4: 0 | G4: 2 | H4: 0 | I4: 0 | K4: 0
A5: indeed.com | C5: 100 | D5: 444M | E5: 46027 | F5: 0 | G5: 23 | H5: 0 | I5: 0 | K5: 0
A6: pinterest.com | C6: 100 | D6: 1.4B | E6: 46027 | F6: 0 | G6: 0 | H6: 3 | I6: 0 | K6: 0
A7: theguardian.com | C7: 100 | D7: 333M | E7: 46027 | F7: 0 | G7: 1 | H7: 0 | I7: 0 | K7: 0
A8: wikipedia.org | B8: https://en.wikisource.org/w/index.php?title=Talk:Community_Portal&action=edit&redlink=1 | C8: 100 | D8: 4.9B | E8: 46027 | F8: 0 | G8: 10 | H8: 0 | I8: 0 | K8: 0
A9: investing.com | C9: 98 | D9: 212M | E9: 46027 | F9: 0 | G9: 13 | H9: 0 | I9: 0 | K9: 0
A10: medium.com | B10: https://medium.com/ | C10: 97 | D10: 116M | E10: 46027 | F10: 0 | G10: 5 | H10: 0 | I10: 0 | K10: 0
A11: ca.gov | C11: 96 | D11: 109M | E11: 46027 | F11: 0 | G11: 4 | H11: 0 | I11: 0 | K11: 0
A12: cnbc.com | C12: 96 | D12: 118M | E12: 46027 | F12: 0 | G12: 3 | H12: 0 | I12: 0 | K12: 0
