Workbook

Sheet Daily reports
B1: Title | C1: Written by | D1: Linkedin | E1: Twitter | F1: Instagram | G1: Facebook | H1: website | I1: New Links | J1: old Website linkHow to Convert Legacy Training Content to Modern eLearning | K1: Indexation | L1: Qoura | M1: Reddit | N1: Facbook | O1: Instagram | P1: LinkedIn | Q1: Pinterest | R1: Dev.to | S1: Medium | T1: Tumblr | U1: Substack | Z1: indexation | AC1: Workflow Status | AD1: Priority | AE1: Owner | AF1: Due Date | AG1: Published URL | AH1: Team Support Needed | AI1: Community Sharing Needed | AJ1: Community / Post Link | AK1: Next Action | AL1: Days to Due | AM1: Health | AN1: Last Updated | AO1: Management Notes | AP1: =HYPERLINK("#'Guide'!A1","Open Guide") -> Open Guide
A2: 46023 | B2: Time Management and Productivity Skills students can Master 2025 | C2: C5 | D2: Yes | H2: Yes | J2: https://theeduassist.com/wp-admin/post.php?post=1648&action=edit | Z2: Web content writing | AC2: =IF($B2="","",IF(AND($AB2="Done",$H2="Yes"),"Published",IF($AB2="Done","Ready to Publish","In Progress"))) -> In Progress | AK2: =IF($B2="","",IF($AC2<>"Done","Complete content audit",IF($H2<>"Yes","Publish on website",IF($AH2="Yes","Log and assign team support",IF($AI2="Yes","Share in a relevant community","Complete"))))) -> Complete content audit | AL2: =IF(OR($B2="",$AF2=""),"",INT($AF2-TODAY())) | AM2: =IF($B2="","",IF($AC2="Published","Complete",IF($AL2="","No Deadline",IF($AL2<0,"Overdue",IF($AL2<=2,"Due Soon","On Track"))))) -> No Deadline
A3: 46024 | B3: Complete Guide to SaaS Curriculum Development and Training Best Practices | C3: C5 | D3: Yes | H3: Yes | J3: https://theeduassist.com/wp-admin/post.php?post=1703&action=edit | Z3: Introduction to MOOCs | AC3: =IF($B3="","",IF(AND($AB3="Done",$H3="Yes"),"Published",IF($AB3="Done","Ready to Publish","In Progress"))) -> In Progress | AK3: =IF($B3="","",IF(#REF!<>"Done","Complete content audit",IF($H3<>"Yes","Publish on website",IF($AH3="Yes","Log and assign team support",IF($AI3="Yes","Share in a relevant community","Complete"))))) -> #REF! | AL3: =IF(OR($B3="",$AF3=""),"",INT($AF3-TODAY())) | AM3: =IF($B3="","",IF($AC3="Published","Complete",IF($AL3="","No Deadline",IF($AL3<0,"Overdue",IF($AL3<=2,"Due Soon","On Track"))))) -> No Deadline
A4: 46024 | B4: Continuing Education Creation: How to Develop Effective Programs for Professionals 2026 | C4: C5 | D4: Yes | H4: Yes | J4: https://theeduassist.com/wp-admin/post.php?post=1723&action=edit | AC4: =IF($B4="","",IF(AND($AB4="Done",$H4="Yes"),"Published",IF($AB4="Done","Ready to Publish","In Progress"))) -> In Progress | AK4: =IF($B4="","",IF(#REF!<>"Done","Complete content audit",IF($H4<>"Yes","Publish on website",IF($AH4="Yes","Log and assign team support",IF($AI4="Yes","Share in a relevant community","Complete"))))) -> #REF! | AL4: =IF(OR($B4="",$AF4=""),"",INT($AF4-TODAY())) | AM4: =IF($B4="","",IF($AC4="Published","Complete",IF($AL4="","No Deadline",IF($AL4<0,"Overdue",IF($AL4<=2,"Due Soon","On Track"))))) -> No Deadline
A5: 46025 | B5: Instructional Design in Action: Practical Solutions for Learner Problems | C5: C5 | D5: Yes | H5: Yes | J5: https://theeduassist.com/wp-admin/post.php?post=1885&action=edit | Z5: Content Brief Structure | AC5: =IF($B5="","",IF(AND($AB5="Done",$H5="Yes"),"Published",IF($AB5="Done","Ready to Publish","In Progress"))) -> In Progress | AK5: =IF($B5="","",IF(#REF!<>"Done","Complete content audit",IF($H5<>"Yes","Publish on website",IF($AH5="Yes","Log and assign team support",IF($AI5="Yes","Share in a relevant community","Complete"))))) -> #REF! | AL5: =IF(OR($B5="",$AF5=""),"",INT($AF5-TODAY())) | AM5: =IF($B5="","",IF($AC5="Published","Complete",IF($AL5="","No Deadline",IF($AL5<0,"Overdue",IF($AL5<=2,"Due Soon","On Track"))))) -> No Deadline
A6: 46025 | B6: Thinkific Course Creation and LMS Management: How to Create Online Courses 2026 | C6: C5 | D6: Yes | H6: Yes | J6: https://theeduassist.com/wp-admin/post.php?post=1940&action=edit | L6: https://qr.ae/pFIFOi & https://qr.ae/pFGVFp | M6: https://www.reddit.com/r/elearning/comments/1sm9npn/comment/oi6cc1h/?utm_source=share&utm_medium=web3x&utm_name=web3xcss&utm_term=1&utm_content=share_button | Z6: Content Brief Structure | AC6: =IF($B6="","",IF(AND($AB6="Done",$H6="Yes"),"Published",IF($AB6="Done","Ready to Publish","In Progress"))) -> In Progress | AK6: =IF($B6="","",IF(#REF!<>"Done","Complete content audit",IF($H6<>"Yes","Publish on website",IF($AH6="Yes","Log and assign team support",IF($AI6="Yes","Share in a relevant community","Complete"))))) -> #REF! | AL6: =IF(OR($B6="",$AF6=""),"",INT($AF6-TODAY())) | AM6: =IF($B6="","",IF($AC6="Published","Complete",IF($AL6="","No Deadline",IF($AL6<0,"Overdue",IF($AL6<=2,"Due Soon","On Track"))))) -> No Deadline
A7: 46028 | B7: AI Insights Powering Skills-Based Learning and Professional Growth in 2026 | C7: C5 | D7: Yes | H7: Yes | J7: https://theeduassist.com/wp-admin/post.php?post=2164&action=edit | M7: https://www.reddit.com/r/edtech/comments/1sh9cyz/comment/og3ucfx/?utm_source=share&utm_medium=web3x&utm_name=web3xcss&utm_term=1&utm_content=share_button | Z7: Content Brief Structure | AC7: =IF($B7="","",IF(AND($AB7="Done",$H7="Yes"),"Published",IF($AB7="Done","Ready to Publish","In Progress"))) -> In Progress | AK7: =IF($B7="","",IF(#REF!<>"Done","Complete content audit",IF($H7<>"Yes","Publish on website",IF($AH7="Yes","Log and assign team support",IF($AI7="Yes","Share in a relevant community","Complete"))))) -> #REF! | AL7: =IF(OR($B7="",$AF7=""),"",INT($AF7-TODAY())) | AM7: =IF($B7="","",IF($AC7="Published","Complete",IF($AL7="","No Deadline",IF($AL7<0,"Overdue",IF($AL7<=2,"Due Soon","On Track"))))) -> No Deadline
A8: 46029 | B8: Udemy Made Simple: How the Platform Works for Learners and Instructors | C8: C5 | D8: Yes | H8: Yes | J8: https://theeduassist.com/wp-admin/post.php?post=2241&action=edit | L8: https://qr.ae/pFhUsp | Z8: Web content writing | AC8: =IF($B8="","",IF(AND($AB8="Done",$H8="Yes"),"Published",IF($AB8="Done","Ready to Publish","In Progress"))) -> In Progress | AK8: =IF($B8="","",IF(#REF!<>"Done","Complete content audit",IF($H8<>"Yes","Publish on website",IF($AH8="Yes","Log and assign team support",IF($AI8="Yes","Share in a relevant community","Complete"))))) -> #REF! | AL8: =IF(OR($B8="",$AF8=""),"",INT($AF8-TODAY())) | AM8: =IF($B8="","",IF($AC8="Published","Complete",IF($AL8="","No Deadline",IF($AL8<0,"Overdue",IF($AL8<=2,"Due Soon","On Track"))))) -> No Deadline
A9: 46029 | B9: Strategic Digital Product Architecture for Wealth Systems: A Simple Guide | C9: C5 | D9: Yes | H9: Yes | J9: https://theeduassist.com/wp-admin/post.php?post=2245&action=edit | Z9: Content Brief Structure | AC9: =IF($B9="","",IF(AND($AB9="Done",$H9="Yes"),"Published",IF($AB9="Done","Ready to Publish","In Progress"))) -> In Progress | AK9: =IF($B9="","",IF(#REF!<>"Done","Complete content audit",IF($H9<>"Yes","Publish on website",IF($AH9="Yes","Log and assign team support",IF($AI9="Yes","Share in a relevant community","Complete"))))) -> #REF! | AL9: =IF(OR($B9="",$AF9=""),"",INT($AF9-TODAY())) | AM9: =IF($B9="","",IF($AC9="Published","Complete",IF($AL9="","No Deadline",IF($AL9<0,"Overdue",IF($AL9<=2,"Due Soon","On Track"))))) -> No Deadline
A10: 46030 | B10: A Practical 2026 Guide in Using Skool for Real Estate Lending Sales Training | C10: C5 | D10: Yes | H10: Yes | J10: https://theeduassist.com/wp-admin/post.php?post=4021&action=edit | AC10: =IF($B10="","",IF(AND($AB10="Done",$H10="Yes"),"Published",IF($AB10="Done","Ready to Publish","In Progress"))) -> In Progress | AK10: =IF($B10="","",IF(#REF!<>"Done","Complete content audit",IF($H10<>"Yes","Publish on website",IF($AH10="Yes","Log and assign team support",IF($AI10="Yes","Share in a relevant community","Complete"))))) -> #REF! | AL10: =IF(OR($B10="",$AF10=""),"",INT($AF10-TODAY())) | AM10: =IF($B10="","",IF($AC10="Published","Complete",IF($AL10="","No Deadline",IF($AL10<0,"Overdue",IF($AL10<=2,"Due Soon","On Track"))))) -> No Deadline
A11: 46031 | B11: Why Learners Skip Pop-Ups and How Better Design Changes That | C11: C5 | D11: Yes | H11: Yes | J11: https://theeduassist.com/wp-admin/post.php?post=2324&action=edit | AC11: =IF($B11="","",IF(AND($AB11="Done",$H11="Yes"),"Published",IF($AB11="Done","Ready to Publish","In Progress"))) -> In Progress | AK11: =IF($B11="","",IF(#REF!<>"Done","Complete content audit",IF($H11<>"Yes","Publish on website",IF($AH11="Yes","Log and assign team support",IF($AI11="Yes","Share in a relevant community","Complete"))))) -> #REF! | AL11: =IF(OR($B11="",$AF11=""),"",INT($AF11-TODAY())) | AM11: =IF($B11="","",IF($AC11="Published","Complete",IF($AL11="","No Deadline",IF($AL11<0,"Overdue",IF($AL11<=2,"Due Soon","On Track"))))) -> No Deadline
A12: 46031 | B12: MOOCs and IT Education: A Practical Guide for Learners in 2026 | C12: C5 | D12: Yes | H12: Yes | J12: https://theeduassist.com/wp-admin/post.php?post=2328&action=edit | AC12: =IF($B12="","",IF(AND($AB12="Done",$H12="Yes"),"Published",IF($AB12="Done","Ready to Publish","In Progress"))) -> In Progress | AK12: =IF($B12="","",IF(#REF!<>"Done","Complete content audit",IF($H12<>"Yes","Publish on website",IF($AH12="Yes","Log and assign team support",IF($AI12="Yes","Share in a relevant community","Complete"))))) -> #REF! | AL12: =IF(OR($B12="",$AF12=""),"",INT($AF12-TODAY())) | AM12: =IF($B12="","",IF($AC12="Published","Complete",IF($AL12="","No Deadline",IF($AL12<0,"Overdue",IF($AL12<=2,"Due Soon","On Track"))))) -> No Deadline
A13: 46032 | B13: How to Apply SETA Standards in Digital and Blended Learning Environments | C13: C5 | D13: Yes | H13: Yes | J13: https://theeduassist.com/wp-admin/post.php?post=2417&action=edit | AC13: =IF($B13="","",IF(AND($AB13="Done",$H13="Yes"),"Published",IF($AB13="Done","Ready to Publish","In Progress"))) -> In Progress | AK13: =IF($B13="","",IF(#REF!<>"Done","Complete content audit",IF($H13<>"Yes","Publish on website",IF($AH13="Yes","Log and assign team support",IF($AI13="Yes","Share in a relevant community","Complete"))))) -> #REF! | AL13: =IF(OR($B13="",$AF13=""),"",INT($AF13-TODAY())) | AM13: =IF($B13="","",IF($AC13="Published","Complete",IF($AL13="","No Deadline",IF($AL13<0,"Overdue",IF($AL13<=2,"Due Soon","On Track"))))) -> No Deadline
A14: 46032 | B14: Education Is The Key Of Success, its future 2026 | C14: C5 | D14: Yes | H14: Yes | J14: https://theeduassist.com/wp-admin/post.php?post=2423&action=edit | AC14: =IF($B14="","",IF(AND($AB14="Done",$H14="Yes"),"Published",IF($AB14="Done","Ready to Publish","In Progress"))) -> In Progress | AK14: =IF($B14="","",IF(#REF!<>"Done","Complete content audit",IF($H14<>"Yes","Publish on website",IF($AH14="Yes","Log and assign team support",IF($AI14="Yes","Share in a relevant community","Complete"))))) -> #REF! | AL14: =IF(OR($B14="",$AF14=""),"",INT($AF14-TODAY())) | AM14: =IF($B14="","",IF($AC14="Published","Complete",IF($AL14="","No Deadline",IF($AL14<0,"Overdue",IF($AL14<=2,"Due Soon","On Track"))))) -> No Deadline
A15: 46034 | B15: Gamification 2026: How to Boost Engagement, Learning, and Productivity | C15: C5 | D15: Yes | H15: Yes | J15: https://theeduassist.com/wp-admin/post.php?post=2482&action=edit | L15: https://qr.ae/pF25dm | AC15: =IF($B15="","",IF(AND($AB15="Done",$H15="Yes"),"Published",IF($AB15="Done","Ready to Publish","In Progress"))) -> In Progress | AK15: =IF($B15="","",IF(#REF!<>"Done","Complete content audit",IF($H15<>"Yes","Publish on website",IF($AH15="Yes","Log and assign team support",IF($AI15="Yes","Share in a relevant community","Complete"))))) -> #REF! | AL15: =IF(OR($B15="",$AF15=""),"",INT($AF15-TODAY())) | AM15: =IF($B15="","",IF($AC15="Published","Complete",IF($AL15="","No Deadline",IF($AL15<0,"Overdue",IF($AL15<=2,"Due Soon","On Track"))))) -> No Deadline
A16: 46034 | B16: What Are Terminal Learning Objectives? | C16: C5 | D16: Yes | H16: Yes | J16: https://theeduassist.com/wp-admin/post.php?post=2501&action=edit | AC16: =IF($B16="","",IF(AND($AB16="Done",$H16="Yes"),"Published",IF($AB16="Done","Ready to Publish","In Progress"))) -> In Progress | AK16: =IF($B16="","",IF(#REF!<>"Done","Complete content audit",IF($H16<>"Yes","Publish on website",IF($AH16="Yes","Log and assign team support",IF($AI16="Yes","Share in a relevant community","Complete"))))) -> #REF! | AL16: =IF(OR($B16="",$AF16=""),"",INT($AF16-TODAY())) | AM16: =IF($B16="","",IF($AC16="Published","Complete",IF($AL16="","No Deadline",IF($AL16<0,"Overdue",IF($AL16<=2,"Due Soon","On Track"))))) -> No Deadline
A17: 46035 | B17: How to Promote Your Online Course by Using Teachability Principles 2026 | C17: C5 | D17: Yes | H17: Yes | J17: https://theeduassist.com/wp-admin/post.php?post=2514&action=edit | L17: https://qr.ae/pFTUpe | AC17: =IF($B17="","",IF(AND($AB17="Done",$H17="Yes"),"Published",IF($AB17="Done","Ready to Publish","In Progress"))) -> In Progress | AK17: =IF($B17="","",IF(#REF!<>"Done","Complete content audit",IF($H17<>"Yes","Publish on website",IF($AH17="Yes","Log and assign team support",IF($AI17="Yes","Share in a relevant community","Complete"))))) -> #REF! | AL17: =IF(OR($B17="",$AF17=""),"",INT($AF17-TODAY())) | AM17: =IF($B17="","",IF($AC17="Published","Complete",IF($AL17="","No Deadline",IF($AL17<0,"Overdue",IF($AL17<=2,"Due Soon","On Track"))))) -> No Deadline
A18: 46035 | B18: Teachability: How to Improve Learning and Retention in Education | C18: C5 | D18: Yes | H18: Yes | J18: https://theeduassist.com/blog/teachability/ | AC18: =IF($B18="","",IF(AND($AB18="Done",$H18="Yes"),"Published",IF($AB18="Done","Ready to Publish","In Progress"))) -> In Progress | AK18: =IF($B18="","",IF(#REF!<>"Done","Complete content audit",IF($H18<>"Yes","Publish on website",IF($AH18="Yes","Log and assign team support",IF($AI18="Yes","Share in a relevant community","Complete"))))) -> #REF! | AL18: =IF(OR($B18="",$AF18=""),"",INT($AF18-TODAY())) | AM18: =IF($B18="","",IF($AC18="Published","Complete",IF($AL18="","No Deadline",IF($AL18<0,"Overdue",IF($AL18<=2,"Due Soon","On Track"))))) -> No Deadline
A19: 46036 | B19: AI-Driven Online Learning: From Content Creation to Skill Mastery | C19: C5 | D19: Yes | H19: Yes | J19: https://theeduassist.com/wp-admin/post.php?post=2588&action=edit | AC19: =IF($B19="","",IF(AND($AB19="Done",$H19="Yes"),"Published",IF($AB19="Done","Ready to Publish","In Progress"))) -> In Progress | AK19: =IF($B19="","",IF(#REF!<>"Done","Complete content audit",IF($H19<>"Yes","Publish on website",IF($AH19="Yes","Log and assign team support",IF($AI19="Yes","Share in a relevant community","Complete"))))) -> #REF! | AL19: =IF(OR($B19="",$AF19=""),"",INT($AF19-TODAY())) | AM19: =IF($B19="","",IF($AC19="Published","Complete",IF($AL19="","No Deadline",IF($AL19<0,"Overdue",IF($AL19<=2,"Due Soon","On Track"))))) -> No Deadline
A20: 46036 | B20: eLearning 2026: How Technology is Reshaping Education | C20: C5 | D20: Yes | H20: Yes | J20: https://theeduassist.com/wp-admin/post.php?post=2620&action=edit | AC20: =IF($B20="","",IF(AND($AB20="Done",$H20="Yes"),"Published",IF($AB20="Done","Ready to Publish","In Progress"))) -> In Progress | AK20: =IF($B20="","",IF(#REF!<>"Done","Complete content audit",IF($H20<>"Yes","Publish on website",IF($AH20="Yes","Log and assign team support",IF($AI20="Yes","Share in a relevant community","Complete"))))) -> #REF! | AL20: =IF(OR($B20="",$AF20=""),"",INT($AF20-TODAY())) | AM20: =IF($B20="","",IF($AC20="Published","Complete",IF($AL20="","No Deadline",IF($AL20<0,"Overdue",IF($AL20<=2,"Due Soon","On Track"))))) -> No Deadline
A21: 46037 | B21: Go High Level for Education Businesses: What Actually Works | C21: C5 | D21: Yes | H21: Yes | J21: https://theeduassist.com/wp-admin/post.php?post=2628&action=edit | AC21: =IF($B21="","",IF(AND($AB21="Done",$H21="Yes"),"Published",IF($AB21="Done","Ready to Publish","In Progress"))) -> In Progress | AK21: =IF($B21="","",IF(#REF!<>"Done","Complete content audit",IF($H21<>"Yes","Publish on website",IF($AH21="Yes","Log and assign team support",IF($AI21="Yes","Share in a relevant community","Complete"))))) -> #REF! | AL21: =IF(OR($B21="",$AF21=""),"",INT($AF21-TODAY())) | AM21: =IF($B21="","",IF($AC21="Published","Complete",IF($AL21="","No Deadline",IF($AL21<0,"Overdue",IF($AL21<=2,"Due Soon","On Track"))))) -> No Deadline
A22: 46038 | B22: What Is a Personal Learning Environment? And Why It Really Helps You Learn | C22: C5 | D22: Yes | H22: Yes | J22: https://theeduassist.com/wp-admin/post.php?post=2678&action=edit | AC22: =IF($B22="","",IF(AND($AB22="Done",$H22="Yes"),"Published",IF($AB22="Done","Ready to Publish","In Progress"))) -> In Progress | AK22: =IF($B22="","",IF(#REF!<>"Done","Complete content audit",IF($H22<>"Yes","Publish on website",IF($AH22="Yes","Log and assign team support",IF($AI22="Yes","Share in a relevant community","Complete"))))) -> #REF! | AL22: =IF(OR($B22="",$AF22=""),"",INT($AF22-TODAY())) | AM22: =IF($B22="","",IF($AC22="Published","Complete",IF($AL22="","No Deadline",IF($AL22<0,"Overdue",IF($AL22<=2,"Due Soon","On Track"))))) -> No Deadline
A23: 46039 | B23: How Customized Safety Training Reduces Risks in Oil & Gas | C23: C5 | D23: Yes | H23: Yes | J23: https://theeduassist.com/blog/ai-customized-safety-training/ | AC23: =IF($B23="","",IF(AND($AB23="Done",$H23="Yes"),"Published",IF($AB23="Done","Ready to Publish","In Progress"))) -> In Progress | AK23: =IF($B23="","",IF(#REF!<>"Done","Complete content audit",IF($H23<>"Yes","Publish on website",IF($AH23="Yes","Log and assign team support",IF($AI23="Yes","Share in a relevant community","Complete"))))) -> #REF! | AL23: =IF(OR($B23="",$AF23=""),"",INT($AF23-TODAY())) | AM23: =IF($B23="","",IF($AC23="Published","Complete",IF($AL23="","No Deadline",IF($AL23<0,"Overdue",IF($AL23<=2,"Due Soon","On Track"))))) -> No Deadline
A24: 46049 | B24: How FERPA Protects Student Privacy | C24: C5 | D24: Yes | H24: Yes | J24: https://theeduassist.com/blog/what-is-ferpa/ | AC24: =IF($B24="","",IF(AND($AB24="Done",$H24="Yes"),"Published",IF($AB24="Done","Ready to Publish","In Progress"))) -> In Progress | AK24: =IF($B24="","",IF(#REF!<>"Done","Complete content audit",IF($H24<>"Yes","Publish on website",IF($AH24="Yes","Log and assign team support",IF($AI24="Yes","Share in a relevant community","Complete"))))) -> #REF! | AL24: =IF(OR($B24="",$AF24=""),"",INT($AF24-TODAY())) | AM24: =IF($B24="","",IF($AC24="Published","Complete",IF($AL24="","No Deadline",IF($AL24<0,"Overdue",IF($AL24<=2,"Due Soon","On Track"))))) -> No Deadline
A25: 46050 | B25: Instructional Design Services for Custom eLearning Development | C25: C5 | D25: Yes | H25: Yes | J25: https://theeduassist.com/wp-admin/post.php?post=2992&action=edit | AC25: =IF($B25="","",IF(AND($AB25="Done",$H25="Yes"),"Published",IF($AB25="Done","Ready to Publish","In Progress"))) -> In Progress | AK25: =IF($B25="","",IF(#REF!<>"Done","Complete content audit",IF($H25<>"Yes","Publish on website",IF($AH25="Yes","Log and assign team support",IF($AI25="Yes","Share in a relevant community","Complete"))))) -> #REF! | AL25: =IF(OR($B25="",$AF25=""),"",INT($AF25-TODAY())) | AM25: =IF($B25="","",IF($AC25="Published","Complete",IF($AL25="","No Deadline",IF($AL25<0,"Overdue",IF($AL25<=2,"Due Soon","On Track"))))) -> No Deadline
A26: 46051 | B26: A Practical Guide to Planning and Development Training | C26: C5 | D26: Yes | H26: Yes | J26: https://theeduassist.com/wp-admin/post.php?post=3144&action=edit | AC26: =IF($B26="","",IF(AND($AB26="Done",$H26="Yes"),"Published",IF($AB26="Done","Ready to Publish","In Progress"))) -> In Progress | AK26: =IF($B26="","",IF(#REF!<>"Done","Complete content audit",IF($H26<>"Yes","Publish on website",IF($AH26="Yes","Log and assign team support",IF($AI26="Yes","Share in a relevant community","Complete"))))) -> #REF! | AL26: =IF(OR($B26="",$AF26=""),"",INT($AF26-TODAY())) | AM26: =IF($B26="","",IF($AC26="Published","Complete",IF($AL26="","No Deadline",IF($AL26<0,"Overdue",IF($AL26<=2,"Due Soon","On Track"))))) -> No Deadline
A27: 46053 | B27: What Are Terminal Learning Objectives? | C27: C5 | D27: Yes | H27: Yes | J27: https://theeduassist.com/wp-admin/post.php?post=3252&action=edit | AC27: =IF($B27="","",IF(AND($AB27="Done",$H27="Yes"),"Published",IF($AB27="Done","Ready to Publish","In Progress"))) -> In Progress | AK27: =IF($B27="","",IF(#REF!<>"Done","Complete content audit",IF($H27<>"Yes","Publish on website",IF($AH27="Yes","Log and assign team support",IF($AI27="Yes","Share in a relevant community","Complete"))))) -> #REF! | AL27: =IF(OR($B27="",$AF27=""),"",INT($AF27-TODAY())) | AM27: =IF($B27="","",IF($AC27="Published","Complete",IF($AL27="","No Deadline",IF($AL27<0,"Overdue",IF($AL27<=2,"Due Soon","On Track"))))) -> No Deadline
A28: 46054 | C28: C5 | D28: Yes | H28: Yes | J28: https://theeduassist.com/wp-admin/post.php?post=3252&action=edit | AC28: =IF($B28="","",IF(AND($AB28="Done",$H28="Yes"),"Published",IF($AB28="Done","Ready to Publish","In Progress"))) | AK28: =IF($B28="","",IF(#REF!<>"Done","Complete content audit",IF($H28<>"Yes","Publish on website",IF($AH28="Yes","Log and assign team support",IF($AI28="Yes","Share in a relevant community","Complete"))))) | AL28: =IF(OR($B28="",$AF28=""),"",INT($AF28-TODAY())) | AM28: =IF($B28="","",IF($AC28="Published","Complete",IF($AL28="","No Deadline",IF($AL28<0,"Overdue",IF($AL28<=2,"Due Soon","On Track")))))
A29: 46055 | B29: Kajabi Course Design Explained | C29: C5 | D29: Yes | H29: Yes | J29: https://theeduassist.com/wp-admin/post.php?post=3353&action=edit | L29: https://qr.ae/pFIwwD https://qr.ae/pFIxPX | AC29: =IF($B29="","",IF(AND($AB29="Done",$H29="Yes"),"Published",IF($AB29="Done","Ready to Publish","In Progress"))) -> In Progress | AK29: =IF($B29="","",IF(#REF!<>"Done","Complete content audit",IF($H29<>"Yes","Publish on website",IF($AH29="Yes","Log and assign team support",IF($AI29="Yes","Share in a relevant community","Complete"))))) -> #REF! | AL29: =IF(OR($B29="",$AF29=""),"",INT($AF29-TODAY())) | AM29: =IF($B29="","",IF($AC29="Published","Complete",IF($AL29="","No Deadline",IF($AL29<0,"Overdue",IF($AL29<=2,"Due Soon","On Track"))))) -> No Deadline
A30: 46056 | B30: What Is a Curriculum Development Centre? | C30: C5 | D30: Yes | H30: Yes | J30: https://theeduassist.com/wp-admin/post.php?post=3430&action=edit | AC30: =IF($B30="","",IF(AND($AB30="Done",$H30="Yes"),"Published",IF($AB30="Done","Ready to Publish","In Progress"))) -> In Progress | AK30: =IF($B30="","",IF(#REF!<>"Done","Complete content audit",IF($H30<>"Yes","Publish on website",IF($AH30="Yes","Log and assign team support",IF($AI30="Yes","Share in a relevant community","Complete"))))) -> #REF! | AL30: =IF(OR($B30="",$AF30=""),"",INT($AF30-TODAY())) | AM30: =IF($B30="","",IF($AC30="Published","Complete",IF($AL30="","No Deadline",IF($AL30<0,"Overdue",IF($AL30<=2,"Due Soon","On Track"))))) -> No Deadline
A31: 46058 | B31: Why Learning Is the Strongest Skill You Can Build | C31: C5 | D31: Yes | H31: Yes | J31: https://theeduassist.com/wp-admin/post.php?post=3496&action=edit | AC31: =IF($B31="","",IF(AND($AB31="Done",$H31="Yes"),"Published",IF($AB31="Done","Ready to Publish","In Progress"))) -> In Progress | AK31: =IF($B31="","",IF(#REF!<>"Done","Complete content audit",IF($H31<>"Yes","Publish on website",IF($AH31="Yes","Log and assign team support",IF($AI31="Yes","Share in a relevant community","Complete"))))) -> #REF! | AL31: =IF(OR($B31="",$AF31=""),"",INT($AF31-TODAY())) | AM31: =IF($B31="","",IF($AC31="Published","Complete",IF($AL31="","No Deadline",IF($AL31<0,"Overdue",IF($AL31<=2,"Due Soon","On Track"))))) -> No Deadline
A32: 46059 | B32: Why Kajabi Works Better Than Multiple Tools for Coaching Businesses | C32: C5 | D32: Yes | H32: Yes | J32: https://theeduassist.com/wp-admin/post.php?post=3506&action=edit | L32: https://qr.ae/pFIFOi & https://qr.ae/pFnco4 | AC32: =IF($B32="","",IF(AND($AB32="Done",$H32="Yes"),"Published",IF($AB32="Done","Ready to Publish","In Progress"))) -> In Progress | AK32: =IF($B32="","",IF(#REF!<>"Done","Complete content audit",IF($H32<>"Yes","Publish on website",IF($AH32="Yes","Log and assign team support",IF($AI32="Yes","Share in a relevant community","Complete"))))) -> #REF! | AL32: =IF(OR($B32="",$AF32=""),"",INT($AF32-TODAY())) | AM32: =IF($B32="","",IF($AC32="Published","Complete",IF($AL32="","No Deadline",IF($AL32<0,"Overdue",IF($AL32<=2,"Due Soon","On Track"))))) -> No Deadline
A33: 46060 | B33: The Essential Guide to AI-Generated Course Quality 2026 | C33: C5 | D33: Yes | H33: Yes | J33: https://theeduassist.com/wp-admin/post.php?post=3545&action=edit | M33: https://www.reddit.com/r/Learning/comments/1sfd4d0/comment/of2xs3o/?utm_source=share&utm_medium=web3x&utm_name=web3xcss&utm_term=1&utm_content=share_button | AC33: =IF($B33="","",IF(AND($AB33="Done",$H33="Yes"),"Published",IF($AB33="Done","Ready to Publish","In Progress"))) -> In Progress | AK33: =IF($B33="","",IF(#REF!<>"Done","Complete content audit",IF($H33<>"Yes","Publish on website",IF($AH33="Yes","Log and assign team support",IF($AI33="Yes","Share in a relevant community","Complete"))))) -> #REF! | AL33: =IF(OR($B33="",$AF33=""),"",INT($AF33-TODAY())) | AM33: =IF($B33="","",IF($AC33="Published","Complete",IF($AL33="","No Deadline",IF($AL33<0,"Overdue",IF($AL33<=2,"Due Soon","On Track"))))) -> No Deadline
A34: 46065 | B34: Choosing the Right Authoring Tool: Affordable Alternatives to Articulate Storyline | C34: C5 | D34: Yes | H34: Yes | J34: https://theeduassist.com/wp-admin/post.php?post=3711&action=edit | L34: https://qr.ae/pFTy9k | AC34: =IF($B34="","",IF(AND($AB34="Done",$H34="Yes"),"Published",IF($AB34="Done","Ready to Publish","In Progress"))) -> In Progress | AK34: =IF($B34="","",IF(#REF!<>"Done","Complete content audit",IF($H34<>"Yes","Publish on website",IF($AH34="Yes","Log and assign team support",IF($AI34="Yes","Share in a relevant community","Complete"))))) -> #REF! | AL34: =IF(OR($B34="",$AF34=""),"",INT($AF34-TODAY())) | AM34: =IF($B34="","",IF($AC34="Published","Complete",IF($AL34="","No Deadline",IF($AL34<0,"Overdue",IF($AL34<=2,"Due Soon","On Track"))))) -> No Deadline
A35: 46069 | B35: How to Overcome LMS Course Editing | C35: C5 | D35: Yes | H35: Yes | J35: https://theeduassist.com/wp-admin/post.php?post=3895&action=edit | AC35: =IF($B35="","",IF(AND($AB35="Done",$H35="Yes"),"Published",IF($AB35="Done","Ready to Publish","In Progress"))) -> In Progress | AK35: =IF($B35="","",IF(#REF!<>"Done","Complete content audit",IF($H35<>"Yes","Publish on website",IF($AH35="Yes","Log and assign team support",IF($AI35="Yes","Share in a relevant community","Complete"))))) -> #REF! | AL35: =IF(OR($B35="",$AF35=""),"",INT($AF35-TODAY())) | AM35: =IF($B35="","",IF($AC35="Published","Complete",IF($AL35="","No Deadline",IF($AL35<0,"Overdue",IF($AL35<=2,"Due Soon","On Track"))))) -> No Deadline
A36: 46070 | B36: Training Coordination Made Easy | C36: C5 | D36: Yes | H36: Yes | J36: https://theeduassist.com/wp-admin/post.php?post=3914&action=edit | AC36: =IF($B36="","",IF(AND($AB36="Done",$H36="Yes"),"Published",IF($AB36="Done","Ready to Publish","In Progress"))) -> In Progress | AK36: =IF($B36="","",IF(#REF!<>"Done","Complete content audit",IF($H36<>"Yes","Publish on website",IF($AH36="Yes","Log and assign team support",IF($AI36="Yes","Share in a relevant community","Complete"))))) -> #REF! | AL36: =IF(OR($B36="",$AF36=""),"",INT($AF36-TODAY())) | AM36: =IF($B36="","",IF($AC36="Published","Complete",IF($AL36="","No Deadline",IF($AL36<0,"Overdue",IF($AL36<=2,"Due Soon","On Track"))))) -> No Deadline
A37: 46071 | B37: Beyond Gamification: How to Make Interactive Learning Truly Effective | C37: C5 | H37: Yes | J37: https://theeduassist.com/wp-admin/post.php?post=3921&action=edit | AC37: =IF($B37="","",IF(AND($AB37="Done",$H37="Yes"),"Published",IF($AB37="Done","Ready to Publish","In Progress"))) -> In Progress | AK37: =IF($B37="","",IF(#REF!<>"Done","Complete content audit",IF($H37<>"Yes","Publish on website",IF($AH37="Yes","Log and assign team support",IF($AI37="Yes","Share in a relevant community","Complete"))))) -> #REF! | AL37: =IF(OR($B37="",$AF37=""),"",INT($AF37-TODAY())) | AM37: =IF($B37="","",IF($AC37="Published","Complete",IF($AL37="","No Deadline",IF($AL37<0,"Overdue",IF($AL37<=2,"Due Soon","On Track"))))) -> No Deadline
A38: 46071 | B38: Quest 3 for Sim Racing: Can It Be Made Reliable? | C38: C5 | H38: Yes | J38: https://theeduassist.com/wp-admin/post.php?post=3928&action=edit | AC38: =IF($B38="","",IF(AND($AB38="Done",$H38="Yes"),"Published",IF($AB38="Done","Ready to Publish","In Progress"))) -> In Progress | AK38: =IF($B38="","",IF(#REF!<>"Done","Complete content audit",IF($H38<>"Yes","Publish on website",IF($AH38="Yes","Log and assign team support",IF($AI38="Yes","Share in a relevant community","Complete"))))) -> #REF! | AL38: =IF(OR($B38="",$AF38=""),"",INT($AF38-TODAY())) | AM38: =IF($B38="","",IF($AC38="Published","Complete",IF($AL38="","No Deadline",IF($AL38<0,"Overdue",IF($AL38<=2,"Due Soon","On Track"))))) -> No Deadline
A39: 46072 | B39: Instructional Design Checklist: Make Your Online Courses More Engaging | C39: C5 | H39: Yes | J39: https://theeduassist.com/wp-admin/post.php?post=3939&action=edit | AC39: =IF($B39="","",IF(AND($AB39="Done",$H39="Yes"),"Published",IF($AB39="Done","Ready to Publish","In Progress"))) -> In Progress | AK39: =IF($B39="","",IF(#REF!<>"Done","Complete content audit",IF($H39<>"Yes","Publish on website",IF($AH39="Yes","Log and assign team support",IF($AI39="Yes","Share in a relevant community","Complete"))))) -> #REF! | AL39: =IF(OR($B39="",$AF39=""),"",INT($AF39-TODAY())) | AM39: =IF($B39="","",IF($AC39="Published","Complete",IF($AL39="","No Deadline",IF($AL39<0,"Overdue",IF($AL39<=2,"Due Soon","On Track"))))) -> No Deadline
A40: 46072 | B40: AI + Microlearning: The Ultimate Formula for Corporate training 2026 - | C40: C5 | H40: Yes | J40: https://theeduassist.com/wp-admin/post.php?post=3990&action=edit | AC40: =IF($B40="","",IF(AND($AB40="Done",$H40="Yes"),"Published",IF($AB40="Done","Ready to Publish","In Progress"))) -> In Progress | AK40: =IF($B40="","",IF(#REF!<>"Done","Complete content audit",IF($H40<>"Yes","Publish on website",IF($AH40="Yes","Log and assign team support",IF($AI40="Yes","Share in a relevant community","Complete"))))) -> #REF! | AL40: =IF(OR($B40="",$AF40=""),"",INT($AF40-TODAY())) | AM40: =IF($B40="","",IF($AC40="Published","Complete",IF($AL40="","No Deadline",IF($AL40<0,"Overdue",IF($AL40<=2,"Due Soon","On Track"))))) -> No Deadline
A41: 46073 | B41: The Tool Trap: When Technology Overshadows Learning Strategy | C41: C5 | H41: Yes | J41: https://theeduassist.com/wp-admin/post.php?post=3996&action=edit | AC41: =IF($B41="","",IF(AND($AB41="Done",$H41="Yes"),"Published",IF($AB41="Done","Ready to Publish","In Progress"))) -> In Progress | AK41: =IF($B41="","",IF(#REF!<>"Done","Complete content audit",IF($H41<>"Yes","Publish on website",IF($AH41="Yes","Log and assign team support",IF($AI41="Yes","Share in a relevant community","Complete"))))) -> #REF! | AL41: =IF(OR($B41="",$AF41=""),"",INT($AF41-TODAY())) | AM41: =IF($B41="","",IF($AC41="Published","Complete",IF($AL41="","No Deadline",IF($AL41<0,"Overdue",IF($AL41<=2,"Due Soon","On Track"))))) -> No Deadline
A42: 46074 | B42: SCORM Construction Courses for LMS: Compliance Made Simple 2026 | C42: C5 | H42: Yes | J42: https://theeduassist.com/wp-admin/post.php?post=4021&action=edit | AC42: =IF($B42="","",IF(AND($AB42="Done",$H42="Yes"),"Published",IF($AB42="Done","Ready to Publish","In Progress"))) -> In Progress | AK42: =IF($B42="","",IF(#REF!<>"Done","Complete content audit",IF($H42<>"Yes","Publish on website",IF($AH42="Yes","Log and assign team support",IF($AI42="Yes","Share in a relevant community","Complete"))))) -> #REF! | AL42: =IF(OR($B42="",$AF42=""),"",INT($AF42-TODAY())) | AM42: =IF($B42="","",IF($AC42="Published","Complete",IF($AL42="","No Deadline",IF($AL42<0,"Overdue",IF($AL42<=2,"Due Soon","On Track"))))) -> No Deadline
A43: 46074 | B43: Practical AI Learning in 2026: How to Build Real-World Skills That MatteR | C43: C5 | H43: Yes | J43: https://theeduassist.com/wp-admin/post.php?post=4026&action=edit | AC43: =IF($B43="","",IF(AND($AB43="Done",$H43="Yes"),"Published",IF($AB43="Done","Ready to Publish","In Progress"))) -> In Progress | AK43: =IF($B43="","",IF(#REF!<>"Done","Complete content audit",IF($H43<>"Yes","Publish on website",IF($AH43="Yes","Log and assign team support",IF($AI43="Yes","Share in a relevant community","Complete"))))) -> #REF! | AL43: =IF(OR($B43="",$AF43=""),"",INT($AF43-TODAY())) | AM43: =IF($B43="","",IF($AC43="Published","Complete",IF($AL43="","No Deadline",IF($AL43<0,"Overdue",IF($AL43<=2,"Due Soon","On Track"))))) -> No Deadline
A44: 46093 | B44: Leadership training program design in 2026 (New Generation) | C44: C1 | D44: Yes | H44: Yes | J44: https://theeduassist.com/wp-admin/post.php?post=4149&action=edit | AC44: =IF($B44="","",IF(AND($AB44="Done",$H44="Yes"),"Published",IF($AB44="Done","Ready to Publish","In Progress"))) -> In Progress | AK44: =IF($B44="","",IF(#REF!<>"Done","Complete content audit",IF($H44<>"Yes","Publish on website",IF($AH44="Yes","Log and assign team support",IF($AI44="Yes","Share in a relevant community","Complete"))))) -> #REF! | AL44: =IF(OR($B44="",$AF44=""),"",INT($AF44-TODAY())) | AM44: =IF($B44="","",IF($AC44="Published","Complete",IF($AL44="","No Deadline",IF($AL44<0,"Overdue",IF($AL44<=2,"Due Soon","On Track"))))) -> No Deadline
A45: 46094 | B45: Webinar to online course:A complete guide | C45: C1 | D45: Yes | H45: Yes | J45: https://theeduassist.com/wp-admin/post.php?post=4162&action=edit | AC45: =IF($B45="","",IF(AND($AB45="Done",$H45="Yes"),"Published",IF($AB45="Done","Ready to Publish","In Progress"))) -> In Progress | AK45: =IF($B45="","",IF(#REF!<>"Done","Complete content audit",IF($H45<>"Yes","Publish on website",IF($AH45="Yes","Log and assign team support",IF($AI45="Yes","Share in a relevant community","Complete"))))) -> #REF! | AL45: =IF(OR($B45="",$AF45=""),"",INT($AF45-TODAY())) | AM45: =IF($B45="","",IF($AC45="Published","Complete",IF($AL45="","No Deadline",IF($AL45<0,"Overdue",IF($AL45<=2,"Due Soon","On Track"))))) -> No Deadline
A46: 46097 | B46: How to Create Executive Assistant eLearning ? | C46: C1 | D46: Yes | H46: Yes | J46: https://theeduassist.com/wp-admin/post.php?post=4186&action=edit | AC46: =IF($B46="","",IF(AND($AB46="Done",$H46="Yes"),"Published",IF($AB46="Done","Ready to Publish","In Progress"))) -> In Progress | AK46: =IF($B46="","",IF(#REF!<>"Done","Complete content audit",IF($H46<>"Yes","Publish on website",IF($AH46="Yes","Log and assign team support",IF($AI46="Yes","Share in a relevant community","Complete"))))) -> #REF! | AL46: =IF(OR($B46="",$AF46=""),"",INT($AF46-TODAY())) | AM46: =IF($B46="","",IF($AC46="Published","Complete",IF($AL46="","No Deadline",IF($AL46<0,"Overdue",IF($AL46<=2,"Due Soon","On Track"))))) -> No Deadline
A47: 46098 | B47: How to Design Interactive Learning Content for Corporate Training Programs | C47: C1 | D47: Yes | H47: Yes | J47: https://theeduassist.com/wp-admin/post.php?post=4209&action=edit | AC47: =IF($B47="","",IF(AND($AB47="Done",$H47="Yes"),"Published",IF($AB47="Done","Ready to Publish","In Progress"))) -> In Progress | AK47: =IF($B47="","",IF(#REF!<>"Done","Complete content audit",IF($H47<>"Yes","Publish on website",IF($AH47="Yes","Log and assign team support",IF($AI47="Yes","Share in a relevant community","Complete"))))) -> #REF! | AL47: =IF(OR($B47="",$AF47=""),"",INT($AF47-TODAY())) | AM47: =IF($B47="","",IF($AC47="Published","Complete",IF($AL47="","No Deadline",IF($AL47<0,"Overdue",IF($AL47<=2,"Due Soon","On Track"))))) -> No Deadline
A48: 46095 | B48: High-Impact Sales Training Slides in: Visual Storytelling for Better Engagement | C48: C1 | D48: Yes | H48: Yes | J48: https://theeduassist.com/wp-admin/post.php?post=4227&action=edit | AC48: =IF($B48="","",IF(AND($AB48="Done",$H48="Yes"),"Published",IF($AB48="Done","Ready to Publish","In Progress"))) -> In Progress | AK48: =IF($B48="","",IF(#REF!<>"Done","Complete content audit",IF($H48<>"Yes","Publish on website",IF($AH48="Yes","Log and assign team support",IF($AI48="Yes","Share in a relevant community","Complete"))))) -> #REF! | AL48: =IF(OR($B48="",$AF48=""),"",INT($AF48-TODAY())) | AM48: =IF($B48="","",IF($AC48="Published","Complete",IF($AL48="","No Deadline",IF($AL48<0,"Overdue",IF($AL48<=2,"Due Soon","On Track"))))) -> No Deadline
A49: 46099 | B49: Hire an Expert to Create an Entrepreneurship Training Program from Scratch( | C49: C1 | D49: Yes | H49: Yes | J49: https://theeduassist.com/?p=4241&preview=true&_thumbnail_id=4247 | AC49: =IF($B49="","",IF(AND($AB49="Done",$H49="Yes"),"Published",IF($AB49="Done","Ready to Publish","In Progress"))) -> In Progress | AK49: =IF($B49="","",IF(#REF!<>"Done","Complete content audit",IF($H49<>"Yes","Publish on website",IF($AH49="Yes","Log and assign team support",IF($AI49="Yes","Share in a relevant community","Complete"))))) -> #REF! | AL49: =IF(OR($B49="",$AF49=""),"",INT($AF49-TODAY())) | AM49: =IF($B49="","",IF($AC49="Published","Complete",IF($AL49="","No Deadline",IF($AL49<0,"Overdue",IF($AL49<=2,"Due Soon","On Track"))))) -> No Deadline
A50: 46104 | B50: Miami eLearning Services: LearnWorlds Course Design Made Easy | C50: C1 | D50: Yes | H50: Yes | J50: https://theeduassist.com/?p=4263&preview=true&_thumbnail_id=4291 | L50: https://qr.ae/pFGVFp | AC50: =IF($B50="","",IF(AND($AB50="Done",$H50="Yes"),"Published",IF($AB50="Done","Ready to Publish","In Progress"))) -> In Progress | AK50: =IF($B50="","",IF(#REF!<>"Done","Complete content audit",IF($H50<>"Yes","Publish on website",IF($AH50="Yes","Log and assign team support",IF($AI50="Yes","Share in a relevant community","Complete"))))) -> #REF! | AL50: =IF(OR($B50="",$AF50=""),"",INT($AF50-TODAY())) | AM50: =IF($B50="","",IF($AC50="Published","Complete",IF($AL50="","No Deadline",IF($AL50<0,"Overdue",IF($AL50<=2,"Due Soon","On Track"))))) -> No Deadline
A51: 46098 | B51: 2026 Coaching Reality Check: Scaling Online Without the Hype – Latest Trends & Strategies in North Dakota | C51: C2 | H51: Yes | J51: https://theeduassist.com/blog/2026-coaching-reality-check-scaling-online-without-the-hype-latest-trends-strategies-in-north-dakota/ | AC51: =IF($B51="","",IF(AND($AB51="Done",$H51="Yes"),"Published",IF($AB51="Done","Ready to Publish","In Progress"))) -> In Progress | AK51: =IF($B51="","",IF(#REF!<>"Done","Complete content audit",IF($H51<>"Yes","Publish on website",IF($AH51="Yes","Log and assign team support",IF($AI51="Yes","Share in a relevant community","Complete"))))) -> #REF! | AL51: =IF(OR($B51="",$AF51=""),"",INT($AF51-TODAY())) | AM51: =IF($B51="","",IF($AC51="Published","Complete",IF($AL51="","No Deadline",IF($AL51<0,"Overdue",IF($AL51<=2,"Due Soon","On Track"))))) -> No Deadline
A52: 46105 | B52: Build a Health and Wealth Online Course with US-focused Content Expert | C52: C1 | D52: Yes | H52: Yes | J52: https://theeduassist.com/wp-admin/post.php?post=4299&action=edit | AC52: =IF($B52="","",IF(AND($AB52="Done",$H52="Yes"),"Published",IF($AB52="Done","Ready to Publish","In Progress"))) -> In Progress | AK52: =IF($B52="","",IF(#REF!<>"Done","Complete content audit",IF($H52<>"Yes","Publish on website",IF($AH52="Yes","Log and assign team support",IF($AI52="Yes","Share in a relevant community","Complete"))))) -> #REF! | AL52: =IF(OR($B52="",$AF52=""),"",INT($AF52-TODAY())) | AM52: =IF($B52="","",IF($AC52="Published","Complete",IF($AL52="","No Deadline",IF($AL52<0,"Overdue",IF($AL52<=2,"Due Soon","On Track"))))) -> No Deadline
A53: 46101 | B53: Busy Course Creators: DIY vs Pro Slide Design – Compare Costs, Time & Outsourcing Tips | C53: C2 | H53: Yes | J53: https://theeduassist.com/blog/busy-course-creators-diy-vs-pro-slide-design-compare-costs-time-outsourcing-tips/ | AC53: =IF($B53="","",IF(AND($AB53="Done",$H53="Yes"),"Published",IF($AB53="Done","Ready to Publish","In Progress"))) -> In Progress | AK53: =IF($B53="","",IF(#REF!<>"Done","Complete content audit",IF($H53<>"Yes","Publish on website",IF($AH53="Yes","Log and assign team support",IF($AI53="Yes","Share in a relevant community","Complete"))))) -> #REF! | AL53: =IF(OR($B53="",$AF53=""),"",INT($AF53-TODAY())) | AM53: =IF($B53="","",IF($AC53="Published","Complete",IF($AL53="","No Deadline",IF($AL53<0,"Overdue",IF($AL53<=2,"Due Soon","On Track"))))) -> No Deadline
A54: 46102 | B54: Phlebotomy Curriculum Design: Guide to Building an AI Future-Ready Training Program for 2026 | C54: C2 | H54: Yes | J54: https://theeduassist.com/blog/phlebotomy-curriculum-design-guide-to-building-an-ai-future-ready-training-program-for-2026/ | L54: https://qr.ae/pFpDRk | AC54: =IF($B54="","",IF(AND($AB54="Done",$H54="Yes"),"Published",IF($AB54="Done","Ready to Publish","In Progress"))) -> In Progress | AK54: =IF($B54="","",IF(#REF!<>"Done","Complete content audit",IF($H54<>"Yes","Publish on website",IF($AH54="Yes","Log and assign team support",IF($AI54="Yes","Share in a relevant community","Complete"))))) -> #REF! | AL54: =IF(OR($B54="",$AF54=""),"",INT($AF54-TODAY())) | AM54: =IF($B54="","",IF($AC54="Published","Complete",IF($AL54="","No Deadline",IF($AL54<0,"Overdue",IF($AL54<=2,"Due Soon","On Track"))))) -> No Deadline
A55: 46102 | B55: Busy E-Learning Teams in New York: How AI Video Creation Can Speed Up Their Training Module Production | C55: C2 | H55: Yes | J55: https://theeduassist.com/blog/busy-e-learning-teams-in-new-york-how-ai-video-creation-can-speed-up-their-training-module-production/ | AC55: =IF($B55="","",IF(AND($AB55="Done",$H55="Yes"),"Published",IF($AB55="Done","Ready to Publish","In Progress"))) -> In Progress | AK55: =IF($B55="","",IF(#REF!<>"Done","Complete content audit",IF($H55<>"Yes","Publish on website",IF($AH55="Yes","Log and assign team support",IF($AI55="Yes","Share in a relevant community","Complete"))))) -> #REF! | AL55: =IF(OR($B55="",$AF55=""),"",INT($AF55-TODAY())) | AM55: =IF($B55="","",IF($AC55="Published","Complete",IF($AL55="","No Deadline",IF($AL55<0,"Overdue",IF($AL55<=2,"Due Soon","On Track"))))) -> No Deadline
A56: 46104 | B56: GHL Development and Setup: A Complete Guide for EdTech and Coaching Businesses in New Jersey | C56: C2 | H56: Yes | J56: https://theeduassist.com/blog/ghl-development-and-setup-a-complete-guide-for-edtech-and-coaching-businesses-in-new-jersey/ | L56: https://qr.ae/pFhns0 & https://qr.ae/pFhqxF | AC56: =IF($B56="","",IF(AND($AB56="Done",$H56="Yes"),"Published",IF($AB56="Done","Ready to Publish","In Progress"))) -> In Progress | AK56: =IF($B56="","",IF(#REF!<>"Done","Complete content audit",IF($H56<>"Yes","Publish on website",IF($AH56="Yes","Log and assign team support",IF($AI56="Yes","Share in a relevant community","Complete"))))) -> #REF! | AL56: =IF(OR($B56="",$AF56=""),"",INT($AF56-TODAY())) | AM56: =IF($B56="","",IF($AC56="Published","Complete",IF($AL56="","No Deadline",IF($AL56<0,"Overdue",IF($AL56<=2,"Due Soon","On Track"))))) -> No Deadline
A57: 46105 | B57: Creating Interactive eLearning Videos with Pre-Recorded Voiceovers: A Guide for EdTech Startups in New York | C57: C2 | H57: Yes | J57: https://theeduassist.com/blog/creating-interactive-elearning-videos-with-pre-recorded-voiceovers-a-guide-for-edtech-startups-in-new-york/ | AC57: =IF($B57="","",IF(AND($AB57="Done",$H57="Yes"),"Published",IF($AB57="Done","Ready to Publish","In Progress"))) -> In Progress | AK57: =IF($B57="","",IF(#REF!<>"Done","Complete content audit",IF($H57<>"Yes","Publish on website",IF($AH57="Yes","Log and assign team support",IF($AI57="Yes","Share in a relevant community","Complete"))))) -> #REF! | AL57: =IF(OR($B57="",$AF57=""),"",INT($AF57-TODAY())) | AM57: =IF($B57="","",IF($AC57="Published","Complete",IF($AL57="","No Deadline",IF($AL57<0,"Overdue",IF($AL57<=2,"Due Soon","On Track"))))) -> No Deadline
A58: 46106 | B58: Leadership Course Creation on Kajabi for Coaching Businesses in Miami | C58: C2 | H58: Yes | J58: https://theeduassist.com/blog/leadership-course-creation-on-kajabi-for-coaching-businesses-in-miami/ | AC58: =IF($B58="","",IF(AND($AB58="Done",$H58="Yes"),"Published",IF($AB58="Done","Ready to Publish","In Progress"))) -> In Progress | AK58: =IF($B58="","",IF(#REF!<>"Done","Complete content audit",IF($H58<>"Yes","Publish on website",IF($AH58="Yes","Log and assign team support",IF($AI58="Yes","Share in a relevant community","Complete"))))) -> #REF! | AL58: =IF(OR($B58="",$AF58=""),"",INT($AF58-TODAY())) | AM58: =IF($B58="","",IF($AC58="Published","Complete",IF($AL58="","No Deadline",IF($AL58<0,"Overdue",IF($AL58<=2,"Due Soon","On Track"))))) -> No Deadline
A59: 46106 | B59: Professional Kajabi Designers in Perth for Scalable eLearning | C59: C1 | D59: Yes | H59: Yes | J59: https://theeduassist.com/wp-admin/post.php?post=4311&action=edit | AC59: =IF($B59="","",IF(AND($AB59="Done",$H59="Yes"),"Published",IF($AB59="Done","Ready to Publish","In Progress"))) -> In Progress | AK59: =IF($B59="","",IF(#REF!<>"Done","Complete content audit",IF($H59<>"Yes","Publish on website",IF($AH59="Yes","Log and assign team support",IF($AI59="Yes","Share in a relevant community","Complete"))))) -> #REF! | AL59: =IF(OR($B59="",$AF59=""),"",INT($AF59-TODAY())) | AM59: =IF($B59="","",IF($AC59="Published","Complete",IF($AL59="","No Deadline",IF($AL59<0,"Overdue",IF($AL59<=2,"Due Soon","On Track"))))) -> No Deadline
A60: 46106 | B60: Ultimate LearnWorlds LMS Guide: How eLearning Businesses in Chicago Can Design Microlearning Courses | C60: C2 | D60: Yes | H60: Yes | J60: https://theeduassist.com/blog/ultimate-learnworlds-lms-guide-how-elearning-businesses-in-chicago-can-design-microlearning-courses/ | AC60: =IF($B60="","",IF(AND($AB60="Done",$H60="Yes"),"Published",IF($AB60="Done","Ready to Publish","In Progress"))) -> In Progress | AK60: =IF($B60="","",IF(#REF!<>"Done","Complete content audit",IF($H60<>"Yes","Publish on website",IF($AH60="Yes","Log and assign team support",IF($AI60="Yes","Share in a relevant community","Complete"))))) -> #REF! | AL60: =IF(OR($B60="",$AF60=""),"",INT($AF60-TODAY())) | AM60: =IF($B60="","",IF($AC60="Published","Complete",IF($AL60="","No Deadline",IF($AL60<0,"Overdue",IF($AL60<=2,"Due Soon","On Track"))))) -> No Deadline
A61: 46106 | B61: Ultimate Guide to AI Content Automation for Melbourne Course Creators | C61: C1 | D61: Yes | H61: Yes | J61: https://theeduassist.com/wp-admin/post.php?post=4341&action=edit | M61: https://www.reddit.com/r/instructionaldesign/comments/1dzcwo2/comment/oeow4n3/?utm_source=share&utm_medium=web3x&utm_name=web3xcss&utm_term=1&utm_content=share_button | AC61: =IF($B61="","",IF(AND($AB61="Done",$H61="Yes"),"Published",IF($AB61="Done","Ready to Publish","In Progress"))) -> In Progress | AK61: =IF($B61="","",IF(#REF!<>"Done","Complete content audit",IF($H61<>"Yes","Publish on website",IF($AH61="Yes","Log and assign team support",IF($AI61="Yes","Share in a relevant community","Complete"))))) -> #REF! | AL61: =IF(OR($B61="",$AF61=""),"",INT($AF61-TODAY())) | AM61: =IF($B61="","",IF($AC61="Published","Complete",IF($AL61="","No Deadline",IF($AL61<0,"Overdue",IF($AL61<=2,"Due Soon","On Track"))))) -> No Deadline
A62: 46107 | B62: How to Design a Life & Health Insurance Course: | C62: C1 | D62: Yes | H62: Yes | J62: https://theeduassist.com/wp-admin/post.php?post=4368&action=edit | AC62: =IF($B62="","",IF(AND($AB62="Done",$H62="Yes"),"Published",IF($AB62="Done","Ready to Publish","In Progress"))) -> In Progress | AK62: =IF($B62="","",IF(#REF!<>"Done","Complete content audit",IF($H62<>"Yes","Publish on website",IF($AH62="Yes","Log and assign team support",IF($AI62="Yes","Share in a relevant community","Complete"))))) -> #REF! | AL62: =IF(OR($B62="",$AF62=""),"",INT($AF62-TODAY())) | AM62: =IF($B62="","",IF($AC62="Published","Complete",IF($AL62="","No Deadline",IF($AL62<0,"Overdue",IF($AL62<=2,"Due Soon","On Track"))))) -> No Deadline
A63: 46107 | B63: Ultimate Guide to Curriculum Design for Supply Chain Courses | C63: C1 | D63: Yes | H63: Yes | J63: https://theeduassist.com/wp-admin/post.php?post=4377&action=edit | AC63: =IF($B63="","",IF(AND($AB63="Done",$H63="Yes"),"Published",IF($AB63="Done","Ready to Publish","In Progress"))) -> In Progress | AK63: =IF($B63="","",IF(#REF!<>"Done","Complete content audit",IF($H63<>"Yes","Publish on website",IF($AH63="Yes","Log and assign team support",IF($AI63="Yes","Share in a relevant community","Complete"))))) -> #REF! | AL63: =IF(OR($B63="",$AF63=""),"",INT($AF63-TODAY())) | AM63: =IF($B63="","",IF($AC63="Published","Complete",IF($AL63="","No Deadline",IF($AL63<0,"Overdue",IF($AL63<=2,"Due Soon","On Track"))))) -> No Deadline
A64: 46107 | B64: Instructional Design Strategies for Course Creation for Real Estate Investors in New York | C64: C2 | D64: Yes | H64: Yes | J64: https://theeduassist.com/blog/instructional-design-strategies-for-course-creation-for-real-estate-investors-in-new-york/ | AC64: =IF($B64="","",IF(AND($AB64="Done",$H64="Yes"),"Published",IF($AB64="Done","Ready to Publish","In Progress"))) -> In Progress | AK64: =IF($B64="","",IF(#REF!<>"Done","Complete content audit",IF($H64<>"Yes","Publish on website",IF($AH64="Yes","Log and assign team support",IF($AI64="Yes","Share in a relevant community","Complete"))))) -> #REF! | AL64: =IF(OR($B64="",$AF64=""),"",INT($AF64-TODAY())) | AM64: =IF($B64="","",IF($AC64="Published","Complete",IF($AL64="","No Deadline",IF($AL64<0,"Overdue",IF($AL64<=2,"Due Soon","On Track"))))) -> No Deadline
A65: 46108 | B65: Build Profitable Kajabi Courses in Canberra with Instructional Design(Part 1) | C65: C1 | D65: Yes | H65: Yes | J65: https://theeduassist.com/wp-admin/post.php?post=4395&action=edit | AC65: =IF($B65="","",IF(AND($AB65="Done",$H65="Yes"),"Published",IF($AB65="Done","Ready to Publish","In Progress"))) -> In Progress | AK65: =IF($B65="","",IF(#REF!<>"Done","Complete content audit",IF($H65<>"Yes","Publish on website",IF($AH65="Yes","Log and assign team support",IF($AI65="Yes","Share in a relevant community","Complete"))))) -> #REF! | AL65: =IF(OR($B65="",$AF65=""),"",INT($AF65-TODAY())) | AM65: =IF($B65="","",IF($AC65="Published","Complete",IF($AL65="","No Deadline",IF($AL65<0,"Overdue",IF($AL65<=2,"Due Soon","On Track"))))) -> No Deadline
A66: 46108 | B66: Kajabi Course Creation Guide for EdTech Startups in Miami: Why Hiring a Kajabi Expert Matters | C66: C2 | D66: Yes | H66: Yes | J66: https://theeduassist.com/blog/kajabi-course-creation-guide-for-edtech-startups-in-miami-why-hiring-a-kajabi-expert-matters/ | AC66: =IF($B66="","",IF(AND($AB66="Done",$H66="Yes"),"Published",IF($AB66="Done","Ready to Publish","In Progress"))) -> In Progress | AK66: =IF($B66="","",IF(#REF!<>"Done","Complete content audit",IF($H66<>"Yes","Publish on website",IF($AH66="Yes","Log and assign team support",IF($AI66="Yes","Share in a relevant community","Complete"))))) -> #REF! | AL66: =IF(OR($B66="",$AF66=""),"",INT($AF66-TODAY())) | AM66: =IF($B66="","",IF($AC66="Published","Complete",IF($AL66="","No Deadline",IF($AL66<0,"Overdue",IF($AL66<=2,"Due Soon","On Track"))))) -> No Deadline
A67: 46109 | B67: Build Profitable Kajabi Courses in Canberra with Instructional Design(Part 2) | C67: C1 | D67: Yes | H67: Yes | J67: https://theeduassist.com/wp-admin/post.php?post=4465&action=edit | AC67: =IF($B67="","",IF(AND($AB67="Done",$H67="Yes"),"Published",IF($AB67="Done","Ready to Publish","In Progress"))) -> In Progress | AK67: =IF($B67="","",IF(#REF!<>"Done","Complete content audit",IF($H67<>"Yes","Publish on website",IF($AH67="Yes","Log and assign team support",IF($AI67="Yes","Share in a relevant community","Complete"))))) -> #REF! | AL67: =IF(OR($B67="",$AF67=""),"",INT($AF67-TODAY())) | AM67: =IF($B67="","",IF($AC67="Published","Complete",IF($AL67="","No Deadline",IF($AL67<0,"Overdue",IF($AL67<=2,"Due Soon","On Track"))))) -> No Deadline
A68: 46109 | B68: How to Launch a Kajabi Online Course in Florida: Best Practices for Video Editing and e-Learning Course Creation | C68: C2 | D68: Yes | H68: Yes | J68: https://theeduassist.com/blog/how-to-launch-a-kajabi-online-course-in-florida-best-practices-for-video-editing-and-e-learning-course-creation/ | AC68: =IF($B68="","",IF(AND($AB68="Done",$H68="Yes"),"Published",IF($AB68="Done","Ready to Publish","In Progress"))) -> In Progress | AK68: =IF($B68="","",IF(#REF!<>"Done","Complete content audit",IF($H68<>"Yes","Publish on website",IF($AH68="Yes","Log and assign team support",IF($AI68="Yes","Share in a relevant community","Complete"))))) -> #REF! | AL68: =IF(OR($B68="",$AF68=""),"",INT($AF68-TODAY())) | AM68: =IF($B68="","",IF($AC68="Published","Complete",IF($AL68="","No Deadline",IF($AL68<0,"Overdue",IF($AL68<=2,"Due Soon","On Track"))))) -> No Deadline
A69: 46111 | B69: Sales Training Workbook vs Presentation Deck: Which Drives Better Results? | C69: C1 | D69: Yes | H69: Yes | J69: https://theeduassist.com/wp-admin/post.php?post=4475&action=editt | AC69: =IF($B69="","",IF(AND($AB69="Done",$H69="Yes"),"Published",IF($AB69="Done","Ready to Publish","In Progress"))) -> In Progress | AK69: =IF($B69="","",IF(#REF!<>"Done","Complete content audit",IF($H69<>"Yes","Publish on website",IF($AH69="Yes","Log and assign team support",IF($AI69="Yes","Share in a relevant community","Complete"))))) -> #REF! | AL69: =IF(OR($B69="",$AF69=""),"",INT($AF69-TODAY())) | AM69: =IF($B69="","",IF($AC69="Published","Complete",IF($AL69="","No Deadline",IF($AL69<0,"Overdue",IF($AL69<=2,"Due Soon","On Track"))))) -> No Deadline
A70: 46111 | B70: How to Build Engaging eLearning Courses in Sydney | C70: C1 | D70: Yes | H70: Yes | J70: https://theeduassist.com/wp-admin/post.php?post=4504&action=edit | AC70: =IF($B70="","",IF(AND($AB70="Done",$H70="Yes"),"Published",IF($AB70="Done","Ready to Publish","In Progress"))) -> In Progress | AK70: =IF($B70="","",IF(#REF!<>"Done","Complete content audit",IF($H70<>"Yes","Publish on website",IF($AH70="Yes","Log and assign team support",IF($AI70="Yes","Share in a relevant community","Complete"))))) -> #REF! | AL70: =IF(OR($B70="",$AF70=""),"",INT($AF70-TODAY())) | AM70: =IF($B70="","",IF($AC70="Published","Complete",IF($AL70="","No Deadline",IF($AL70<0,"Overdue",IF($AL70<=2,"Due Soon","On Track"))))) -> No Deadline
A71: 46111 | B71: Ultimate Guide for Queensland Course Creators: eLearning Screencast Video Creation | C71: C2 | D71: Yes | H71: Yes | J71: https://theeduassist.com/blog/ultimate-guide-for-queensland-course-creators-elearning-screencast-video-creation/ | AC71: =IF($B71="","",IF(AND($AB71="Done",$H71="Yes"),"Published",IF($AB71="Done","Ready to Publish","In Progress"))) -> In Progress | AK71: =IF($B71="","",IF(#REF!<>"Done","Complete content audit",IF($H71<>"Yes","Publish on website",IF($AH71="Yes","Log and assign team support",IF($AI71="Yes","Share in a relevant community","Complete"))))) -> #REF! | AL71: =IF(OR($B71="",$AF71=""),"",INT($AF71-TODAY())) | AM71: =IF($B71="","",IF($AC71="Published","Complete",IF($AL71="","No Deadline",IF($AL71<0,"Overdue",IF($AL71<=2,"Due Soon","On Track"))))) -> No Deadline
A72: 46111 | B72: How to Design eLearning Workbooks for Masterclasses: Ultimate 2026 Curriculum Guide for California Course Creators | C72: C2 | D72: Yes | H72: Yes | J72: https://theeduassist.com/blog/how-to-design-elearning-workbooks-for-masterclasses-ultimate-2026-curriculum-guide-for-california-course-creators/ | AC72: =IF($B72="","",IF(AND($AB72="Done",$H72="Yes"),"Published",IF($AB72="Done","Ready to Publish","In Progress"))) -> In Progress | AK72: =IF($B72="","",IF(#REF!<>"Done","Complete content audit",IF($H72<>"Yes","Publish on website",IF($AH72="Yes","Log and assign team support",IF($AI72="Yes","Share in a relevant community","Complete"))))) -> #REF! | AL72: =IF(OR($B72="",$AF72=""),"",INT($AF72-TODAY())) | AM72: =IF($B72="","",IF($AC72="Published","Complete",IF($AL72="","No Deadline",IF($AL72<0,"Overdue",IF($AL72<=2,"Due Soon","On Track"))))) -> No Deadline
A73: 46112 | B73: How to Create Coaching Content Systems for Influencer Brands of Dallas,US | C73: C1 | D73: Yes | H73: Yes | J73: https://theeduassist.com/wp-admin/post.php?post=4543&action=edit | AC73: =IF($B73="","",IF(AND($AB73="Done",$H73="Yes"),"Published",IF($AB73="Done","Ready to Publish","In Progress"))) -> In Progress | AK73: =IF($B73="","",IF(#REF!<>"Done","Complete content audit",IF($H73<>"Yes","Publish on website",IF($AH73="Yes","Log and assign team support",IF($AI73="Yes","Share in a relevant community","Complete"))))) -> #REF! | AL73: =IF(OR($B73="",$AF73=""),"",INT($AF73-TODAY())) | AM73: =IF($B73="","",IF($AC73="Published","Complete",IF($AL73="","No Deadline",IF($AL73<0,"Overdue",IF($AL73<=2,"Due Soon","On Track"))))) -> No Deadline
A74: 46112 | B74: Ultimate TalentLMS Onboarding Framework for eLearning Creators in Ohio | C74: C2 | H74: Yes | J74: https://theeduassist.com/blog/ultimate-talentlms-onboarding-framework-for-elearning-creators-in-ohio/ | AC74: =IF($B74="","",IF(AND($AB74="Done",$H74="Yes"),"Published",IF($AB74="Done","Ready to Publish","In Progress"))) -> In Progress | AK74: =IF($B74="","",IF(#REF!<>"Done","Complete content audit",IF($H74<>"Yes","Publish on website",IF($AH74="Yes","Log and assign team support",IF($AI74="Yes","Share in a relevant community","Complete"))))) -> #REF! | AL74: =IF(OR($B74="",$AF74=""),"",INT($AF74-TODAY())) | AM74: =IF($B74="","",IF($AC74="Published","Complete",IF($AL74="","No Deadline",IF($AL74<0,"Overdue",IF($AL74<=2,"Due Soon","On Track"))))) -> No Deadline
A75: 46112 | B75: Creating Self-Help Online Courses in Ohio: The Ultimate Guide | C75: C2 | D75: Yes | H75: Yes | J75: https://theeduassist.com/blog/creating-self-help-online-courses-in-ohio-the-ultimate-guide/ | AC75: =IF($B75="","",IF(AND($AB75="Done",$H75="Yes"),"Published",IF($AB75="Done","Ready to Publish","In Progress"))) -> In Progress | AK75: =IF($B75="","",IF(#REF!<>"Done","Complete content audit",IF($H75<>"Yes","Publish on website",IF($AH75="Yes","Log and assign team support",IF($AI75="Yes","Share in a relevant community","Complete"))))) -> #REF! | AL75: =IF(OR($B75="",$AF75=""),"",INT($AF75-TODAY())) | AM75: =IF($B75="","",IF($AC75="Published","Complete",IF($AL75="","No Deadline",IF($AL75<0,"Overdue",IF($AL75<=2,"Due Soon","On Track"))))) -> No Deadline
A76: 46113 | B76: How to Launch a 6-Week Online Course on a New LMS: Step-by-Step Setup Guide for Texas Creators | C76: C2 | H76: Yes | J76: https://theeduassist.com/blog/how-to-launch-a-6-week-online-course-on-a-new-lms-step-by-step-setup-guide-for-texas-creators/ | AC76: =IF($B76="","",IF(AND($AB76="Done",$H76="Yes"),"Published",IF($AB76="Done","Ready to Publish","In Progress"))) -> In Progress | AK76: =IF($B76="","",IF(#REF!<>"Done","Complete content audit",IF($H76<>"Yes","Publish on website",IF($AH76="Yes","Log and assign team support",IF($AI76="Yes","Share in a relevant community","Complete"))))) -> #REF! | AL76: =IF(OR($B76="",$AF76=""),"",INT($AF76-TODAY())) | AM76: =IF($B76="","",IF($AC76="Published","Complete",IF($AL76="","No Deadline",IF($AL76<0,"Overdue",IF($AL76<=2,"Due Soon","On Track"))))) -> No Deadline
A77: 46113 | B77: How to Turn Raw Videos into an Online Course Content: Stepwise Guide for California Creators | C77: C2 | D77: Yes | H77: Yes | J77: https://theeduassist.com/blog/how-to-turn-raw-videos-into-an-online-course-content-stepwise-guide-for-california-creators/ | M77: https://www.reddit.com/r/onlinecourses/comments/1sssora/comment/ohwkblp/?utm_source=share&utm_medium=web3x&utm_name=web3xcss&utm_term=1&utm_content=share_button | AC77: =IF($B77="","",IF(AND($AB77="Done",$H77="Yes"),"Published",IF($AB77="Done","Ready to Publish","In Progress"))) -> In Progress | AK77: =IF($B77="","",IF(#REF!<>"Done","Complete content audit",IF($H77<>"Yes","Publish on website",IF($AH77="Yes","Log and assign team support",IF($AI77="Yes","Share in a relevant community","Complete"))))) -> #REF! | AL77: =IF(OR($B77="",$AF77=""),"",INT($AF77-TODAY())) | AM77: =IF($B77="","",IF($AC77="Published","Complete",IF($AL77="","No Deadline",IF($AL77<0,"Overdue",IF($AL77<=2,"Due Soon","On Track"))))) -> No Deadline
A78: 46113 | B78: Most hybrid yoga courses fail, and it's not the content | C78: C4 | D78: Yes | J78: https://www.linkedin.com/posts/theeduassist_hybridlearning-yogateachertraining-instructionaldesign-activity-7445091989370519552--AW-?utm_source=share&utm_medium=member_android&rcm=ACoAAF_8k9UBKnS3dFz-4VY8K3yCcAZIFgLF49M | AC78: =IF($B78="","",IF(AND($AB78="Done",$H78="Yes"),"Published",IF($AB78="Done","Ready to Publish","In Progress"))) -> In Progress | AK78: =IF($B78="","",IF(#REF!<>"Done","Complete content audit",IF($H78<>"Yes","Publish on website",IF($AH78="Yes","Log and assign team support",IF($AI78="Yes","Share in a relevant community","Complete"))))) -> #REF! | AL78: =IF(OR($B78="",$AF78=""),"",INT($AF78-TODAY())) | AM78: =IF($B78="","",IF($AC78="Published","Complete",IF($AL78="","No Deadline",IF($AL78<0,"Overdue",IF($AL78<=2,"Due Soon","On Track"))))) -> No Deadline
A79: 46113 | B79: Canva Video Tutorials for Digital Products: A Complete Guide | C79: C1 | D79: Yes | H79: Yes | J79: https://theeduassist.com/wp-admin/post.php?post=4574&action=edit | AC79: =IF($B79="","",IF(AND($AB79="Done",$H79="Yes"),"Published",IF($AB79="Done","Ready to Publish","In Progress"))) -> In Progress | AK79: =IF($B79="","",IF(#REF!<>"Done","Complete content audit",IF($H79<>"Yes","Publish on website",IF($AH79="Yes","Log and assign team support",IF($AI79="Yes","Share in a relevant community","Complete"))))) -> #REF! | AL79: =IF(OR($B79="",$AF79=""),"",INT($AF79-TODAY())) | AM79: =IF($B79="","",IF($AC79="Published","Complete",IF($AL79="","No Deadline",IF($AL79<0,"Overdue",IF($AL79<=2,"Due Soon","On Track"))))) -> No Deadline
A80: 46113 | B80: Educational HTML & CSS Video Tutorials: A Complete Guide for Coaches: | C80: C1 | D80: Yes | H80: Yes | J80: https://theeduassist.com/wp-admin/post.php?post=4590&action=edit | AC80: =IF($B80="","",IF(AND($AB80="Done",$H80="Yes"),"Published",IF($AB80="Done","Ready to Publish","In Progress"))) -> In Progress | AK80: =IF($B80="","",IF(#REF!<>"Done","Complete content audit",IF($H80<>"Yes","Publish on website",IF($AH80="Yes","Log and assign team support",IF($AI80="Yes","Share in a relevant community","Complete"))))) -> #REF! | AL80: =IF(OR($B80="",$AF80=""),"",INT($AF80-TODAY())) | AM80: =IF($B80="","",IF($AC80="Published","Complete",IF($AL80="","No Deadline",IF($AL80<0,"Overdue",IF($AL80<=2,"Due Soon","On Track"))))) -> No Deadline
A81: 46114 | B81: Affiliate Marketing Strategy for Agencies in Orlando: Full Guide | C81: C1 | D81: Yes | H81: Yes | J81: https://theeduassist.com/wp-admin/post.php?post=4603&action=edit | AC81: =IF($B81="","",IF(AND($AB81="Done",$H81="Yes"),"Published",IF($AB81="Done","Ready to Publish","In Progress"))) -> In Progress | AK81: =IF($B81="","",IF(#REF!<>"Done","Complete content audit",IF($H81<>"Yes","Publish on website",IF($AH81="Yes","Log and assign team support",IF($AI81="Yes","Share in a relevant community","Complete"))))) -> #REF! | AL81: =IF(OR($B81="",$AF81=""),"",INT($AF81-TODAY())) | AM81: =IF($B81="","",IF($AC81="Published","Complete",IF($AL81="","No Deadline",IF($AL81<0,"Overdue",IF($AL81<=2,"Due Soon","On Track"))))) -> No Deadline
A82: 46114 | B82: “How to Produce 20–40 Minute Coaching Videos from Long Scripts” | C82: C1 | D82: Yes | H82: Yes | J82: https://theeduassist.com/wp-admin/post.php?post=4612&action=edit | L82: https://qr.ae/pFIwwD | M82: https://www.reddit.com/r/elearning/comments/1sqtsbe/comment/ohlf10i/?utm_source=share&utm_medium=web3x&utm_name=web3xcss&utm_term=1&utm_content=share_button & https://www.reddit.com/r/onlinecourses/comments/1sxvxns/comment/oipw7je/?utm_source=share&utm_medium=web3x&utm_name=web3xcss&utm_term=1&utm_content=share_button | AC82: =IF($B82="","",IF(AND($AB82="Done",$H82="Yes"),"Published",IF($AB82="Done","Ready to Publish","In Progress"))) -> In Progress | AK82: =IF($B82="","",IF(#REF!<>"Done","Complete content audit",IF($H82<>"Yes","Publish on website",IF($AH82="Yes","Log and assign team support",IF($AI82="Yes","Share in a relevant community","Complete"))))) -> #REF! | AL82: =IF(OR($B82="",$AF82=""),"",INT($AF82-TODAY())) | AM82: =IF($B82="","",IF($AC82="Published","Complete",IF($AL82="","No Deadline",IF($AL82<0,"Overdue",IF($AL82<=2,"Due Soon","On Track"))))) -> No Deadline
A83: 46114 | B83: Ultimate Guide to Developing an eLearning Curriculum in Victoria | C83: C2 | D83: Yes | H83: Yes | J83: Ultimate Guide to Developing an eLearning Curriculum in Victoria | AC83: =IF($B83="","",IF(AND($AB83="Done",$H83="Yes"),"Published",IF($AB83="Done","Ready to Publish","In Progress"))) -> In Progress | AK83: =IF($B83="","",IF(#REF!<>"Done","Complete content audit",IF($H83<>"Yes","Publish on website",IF($AH83="Yes","Log and assign team support",IF($AI83="Yes","Share in a relevant community","Complete"))))) -> #REF! | AL83: =IF(OR($B83="",$AF83=""),"",INT($AF83-TODAY())) | AM83: =IF($B83="","",IF($AC83="Published","Complete",IF($AL83="","No Deadline",IF($AL83<0,"Overdue",IF($AL83<=2,"Due Soon","On Track"))))) -> No Deadline
A84: 3/4/0226 | B84: How to Create Course Pop-Ups in Chicago & Perth (Best Practices) | C84: C1 | D84: Yes | H84: Yes | J84: https://theeduassist.com/wp-admin/post.php?post=4636&action=edit | AC84: =IF($B84="","",IF(AND($AB84="Done",$H84="Yes"),"Published",IF($AB84="Done","Ready to Publish","In Progress"))) -> In Progress | AK84: =IF($B84="","",IF(#REF!<>"Done","Complete content audit",IF($H84<>"Yes","Publish on website",IF($AH84="Yes","Log and assign team support",IF($AI84="Yes","Share in a relevant community","Complete"))))) -> #REF! | AL84: =IF(OR($B84="",$AF84=""),"",INT($AF84-TODAY())) | AM84: =IF($B84="","",IF($AC84="Published","Complete",IF($AL84="","No Deadline",IF($AL84<0,"Overdue",IF($AL84<=2,"Due Soon","On Track"))))) -> No Deadline
A85: 46115 | B85: Ultimate Guide to Udemy Video Editing with Canva & Doodly | C85: C1 | D85: Yes | H85: Yes | J85: https://theeduassist.com/wp-admin/post.php?post=4648&action=edit | AC85: =IF($B85="","",IF(AND($AB85="Done",$H85="Yes"),"Published",IF($AB85="Done","Ready to Publish","In Progress"))) -> In Progress | AK85: =IF($B85="","",IF(#REF!<>"Done","Complete content audit",IF($H85<>"Yes","Publish on website",IF($AH85="Yes","Log and assign team support",IF($AI85="Yes","Share in a relevant community","Complete"))))) -> #REF! | AL85: =IF(OR($B85="",$AF85=""),"",INT($AF85-TODAY())) | AM85: =IF($B85="","",IF($AC85="Published","Complete",IF($AL85="","No Deadline",IF($AL85<0,"Overdue",IF($AL85<=2,"Due Soon","On Track"))))) -> No Deadline
A86: 46115 | B86: AI Automation Course Creation Guide for New York EdTech Startups | C86: C2 | D86: Yes | H86: Yes | J86: https://theeduassist.com/blog/ai-automation-course-creation-guide-for-new-york-edtech-startups/ | AC86: =IF($B86="","",IF(AND($AB86="Done",$H86="Yes"),"Published",IF($AB86="Done","Ready to Publish","In Progress"))) -> In Progress | AK86: =IF($B86="","",IF(#REF!<>"Done","Complete content audit",IF($H86<>"Yes","Publish on website",IF($AH86="Yes","Log and assign team support",IF($AI86="Yes","Share in a relevant community","Complete"))))) -> #REF! | AL86: =IF(OR($B86="",$AF86=""),"",INT($AF86-TODAY())) | AM86: =IF($B86="","",IF($AC86="Published","Complete",IF($AL86="","No Deadline",IF($AL86<0,"Overdue",IF($AL86<=2,"Due Soon","On Track"))))) -> No Deadline
A87: 46116 | B87: Philosophy to Practice: Interactive Leadership Mastery with AI & Technology | C87: C1 | D87: Yes | H87: Yes | J87: https://theeduassist.com/wp-admin/post.php?post=4672&action=edit | AC87: =IF($B87="","",IF(AND($AB87="Done",$H87="Yes"),"Published",IF($AB87="Done","Ready to Publish","In Progress"))) -> In Progress | AK87: =IF($B87="","",IF(#REF!<>"Done","Complete content audit",IF($H87<>"Yes","Publish on website",IF($AH87="Yes","Log and assign team support",IF($AI87="Yes","Share in a relevant community","Complete"))))) -> #REF! | AL87: =IF(OR($B87="",$AF87=""),"",INT($AF87-TODAY())) | AM87: =IF($B87="","",IF($AC87="Published","Complete",IF($AL87="","No Deadline",IF($AL87<0,"Overdue",IF($AL87<=2,"Due Soon","On Track"))))) -> No Deadline
A88: 46115 | B88: How to design a Hybrid Yoga Training Guide | C88: C4 | H88: Yes | J88: https://theeduassist.com/blog/how-to-design-a-hybrid-yoga-training-guide/ | AC88: =IF($B88="","",IF(AND($AB88="Done",$H88="Yes"),"Published",IF($AB88="Done","Ready to Publish","In Progress"))) -> In Progress | AK88: =IF($B88="","",IF(#REF!<>"Done","Complete content audit",IF($H88<>"Yes","Publish on website",IF($AH88="Yes","Log and assign team support",IF($AI88="Yes","Share in a relevant community","Complete"))))) -> #REF! | AL88: =IF(OR($B88="",$AF88=""),"",INT($AF88-TODAY())) | AM88: =IF($B88="","",IF($AC88="Published","Complete",IF($AL88="","No Deadline",IF($AL88<0,"Overdue",IF($AL88<=2,"Due Soon","On Track"))))) -> No Deadline
A89: 46116 | B89: Ultimate Excel Course Video Guide in Sydney, LA with TheEduAssist | C89: C1 | D89: Yes | H89: Yes | J89: https://theeduassist.com/uncategorized/ultimate-excel-course-video-guide-in-sydney-la-with-theeduassist/ | AC89: =IF($B89="","",IF(AND($AB89="Done",$H89="Yes"),"Published",IF($AB89="Done","Ready to Publish","In Progress"))) -> In Progress | AK89: =IF($B89="","",IF(#REF!<>"Done","Complete content audit",IF($H89<>"Yes","Publish on website",IF($AH89="Yes","Log and assign team support",IF($AI89="Yes","Share in a relevant community","Complete"))))) -> #REF! | AL89: =IF(OR($B89="",$AF89=""),"",INT($AF89-TODAY())) | AM89: =IF($B89="","",IF($AC89="Published","Complete",IF($AL89="","No Deadline",IF($AL89<0,"Overdue",IF($AL89<=2,"Due Soon","On Track"))))) -> No Deadline
A90: 46116 | B90: Ultimate Guide to Promoting Ohio eLearning Business via YouTube | C90: C2 | D90: Yes | G90: Yes | H90: Yes | J90: https://theeduassist.com/blog/how-to-create-a-youtube-channel-for-promoting-elearning-business-in-ohio-complete-2026-guide/ | N90: https://web.facebook.com/groups/onlinecoursecommunityfornewbiesandbeginners/posts/4621895844704787/?comment_id=4628874590673579 | AC90: =IF($B90="","",IF(AND($AB90="Done",$H90="Yes"),"Published",IF($AB90="Done","Ready to Publish","In Progress"))) -> In Progress | AK90: =IF($B90="","",IF(#REF!<>"Done","Complete content audit",IF($H90<>"Yes","Publish on website",IF($AH90="Yes","Log and assign team support",IF($AI90="Yes","Share in a relevant community","Complete"))))) -> #REF! | AL90: =IF(OR($B90="",$AF90=""),"",INT($AF90-TODAY())) | AM90: =IF($B90="","",IF($AC90="Published","Complete",IF($AL90="","No Deadline",IF($AL90<0,"Overdue",IF($AL90<=2,"Due Soon","On Track"))))) -> No Deadline
A91: 46118 | B91: Professional Video Workshops for Kajabi, Skool & Funnels in Australia | C91: C1 | D91: Yes | H91: Yes | J91: https://theeduassist.com/blog/professional-video-workshops-for-kajabi-skool-funnels-in-australia/ | AC91: =IF($B91="","",IF(AND($AB91="Done",$H91="Yes"),"Published",IF($AB91="Done","Ready to Publish","In Progress"))) -> In Progress | AK91: =IF($B91="","",IF(#REF!<>"Done","Complete content audit",IF($H91<>"Yes","Publish on website",IF($AH91="Yes","Log and assign team support",IF($AI91="Yes","Share in a relevant community","Complete"))))) -> #REF! | AL91: =IF(OR($B91="",$AF91=""),"",INT($AF91-TODAY())) | AM91: =IF($B91="","",IF($AC91="Published","Complete",IF($AL91="","No Deadline",IF($AL91<0,"Overdue",IF($AL91<=2,"Due Soon","On Track"))))) -> No Deadline
A92: 46118 | B92: 2026 Teachable Guide: How to Build & Sell Online Courses as a California Creator | C92: C2 | D92: Yes | H92: Yes | J92: https://theeduassist.com/blog/2026-teachable-guide-how-to-build-sell-online-courses-as-a-california-creator/ | L92: https://qr.ae/pFhqxF | AC92: =IF($B92="","",IF(AND($AB92="Done",$H92="Yes"),"Published",IF($AB92="Done","Ready to Publish","In Progress"))) -> In Progress | AK92: =IF($B92="","",IF(#REF!<>"Done","Complete content audit",IF($H92<>"Yes","Publish on website",IF($AH92="Yes","Log and assign team support",IF($AI92="Yes","Share in a relevant community","Complete"))))) -> #REF! | AL92: =IF(OR($B92="",$AF92=""),"",INT($AF92-TODAY())) | AM92: =IF($B92="","",IF($AC92="Published","Complete",IF($AL92="","No Deadline",IF($AL92<0,"Overdue",IF($AL92<=2,"Due Soon","On Track"))))) -> No Deadline
A93: 46119 | B93: Ultimate Opigno LMS Course Development Tips for Businesses in Adelaide | C93: C1 | D93: Yes | H93: Yes | J93: https://theeduassist.com/wp-admin/post.php?post=4719&action=edit | P93: https://www.linkedin.com/feed/update/urn:li:activity:7447433098369359873 | AC93: =IF($B93="","",IF(AND($AB93="Done",$H93="Yes"),"Published",IF($AB93="Done","Ready to Publish","In Progress"))) -> In Progress | AK93: =IF($B93="","",IF(#REF!<>"Done","Complete content audit",IF($H93<>"Yes","Publish on website",IF($AH93="Yes","Log and assign team support",IF($AI93="Yes","Share in a relevant community","Complete"))))) -> #REF! | AL93: =IF(OR($B93="",$AF93=""),"",INT($AF93-TODAY())) | AM93: =IF($B93="","",IF($AC93="Published","Complete",IF($AL93="","No Deadline",IF($AL93<0,"Overdue",IF($AL93<=2,"Due Soon","On Track"))))) -> No Deadline
A94: 46119 | B94: AI Product Training Video Blueprint for Businesses in New York | C94: C1 | D94: Yes | H94: Yes | J94: https://theeduassist.com/wp-admin/post.php?post=4748&action=edit | P94: https://www.linkedin.com/feed/update/urn:li:activity:7448142709212696576 | AC94: =IF($B94="","",IF(AND($AB94="Done",$H94="Yes"),"Published",IF($AB94="Done","Ready to Publish","In Progress"))) -> In Progress | AK94: =IF($B94="","",IF(#REF!<>"Done","Complete content audit",IF($H94<>"Yes","Publish on website",IF($AH94="Yes","Log and assign team support",IF($AI94="Yes","Share in a relevant community","Complete"))))) -> #REF! | AL94: =IF(OR($B94="",$AF94=""),"",INT($AF94-TODAY())) | AM94: =IF($B94="","",IF($AC94="Published","Complete",IF($AL94="","No Deadline",IF($AL94<0,"Overdue",IF($AL94<=2,"Due Soon","On Track"))))) -> No Deadline
A95: 46119 | B95: Skool Community Growth: 2026 Blueprint for High Engagement & Management | C95: C4 | D95: Yes | H95: Yes | J95: https://theeduassist.com/blog/how-to-build-and-manage-a-high-engagement-skool-community-complete-2026-blueprint/ | L95: https://qr.ae/pFppId | M95: https://www.reddit.com/r/elearning/comments/1sdy0yf/comment/oes1cbu/?utm_source=share&utm_medium=mweb3x&utm_name=mweb3xcss&utm_term=1&utm_content=share_button | AC95: =IF($B95="","",IF(AND($AB95="Done",$H95="Yes"),"Published",IF($AB95="Done","Ready to Publish","In Progress"))) -> In Progress | AK95: =IF($B95="","",IF(#REF!<>"Done","Complete content audit",IF($H95<>"Yes","Publish on website",IF($AH95="Yes","Log and assign team support",IF($AI95="Yes","Share in a relevant community","Complete"))))) -> #REF! | AL95: =IF(OR($B95="",$AF95=""),"",INT($AF95-TODAY())) | AM95: =IF($B95="","",IF($AC95="Published","Complete",IF($AL95="","No Deadline",IF($AL95<0,"Overdue",IF($AL95<=2,"Due Soon","On Track"))))) -> No Deadline
A96: 46119 | B96: How to Turn a Video Creation Course Into a Handbook: Instructional Design Guide for 2026 | C96: C2 | D96: Yes | H96: Yes | J96: https://theeduassist.com/blog/how-to-turn-a-video-creation-course-into-a-handbook-instructional-design-guide-for-2026/ | AC96: =IF($B96="","",IF(AND($AB96="Done",$H96="Yes"),"Published",IF($AB96="Done","Ready to Publish","In Progress"))) -> In Progress | AK96: =IF($B96="","",IF(#REF!<>"Done","Complete content audit",IF($H96<>"Yes","Publish on website",IF($AH96="Yes","Log and assign team support",IF($AI96="Yes","Share in a relevant community","Complete"))))) -> #REF! | AL96: =IF(OR($B96="",$AF96=""),"",INT($AF96-TODAY())) | AM96: =IF($B96="","",IF($AC96="Published","Complete",IF($AL96="","No Deadline",IF($AL96<0,"Overdue",IF($AL96<=2,"Due Soon","On Track"))))) -> No Deadline
A97: 46120 | B97: Craft Training Modules for Ohio’s eLearning Academies: 2026 Focused Complete Guide | C97: C2 | D97: Yes | H97: Yes | J97: https://theeduassist.com/blog/training-modules-design-for-elearning-in-ohio-2026/ | AC97: =IF($B97="","",IF(AND($AB97="Done",$H97="Yes"),"Published",IF($AB97="Done","Ready to Publish","In Progress"))) -> In Progress | AK97: =IF($B97="","",IF(#REF!<>"Done","Complete content audit",IF($H97<>"Yes","Publish on website",IF($AH97="Yes","Log and assign team support",IF($AI97="Yes","Share in a relevant community","Complete"))))) -> #REF! | AL97: =IF(OR($B97="",$AF97=""),"",INT($AF97-TODAY())) | AM97: =IF($B97="","",IF($AC97="Published","Complete",IF($AL97="","No Deadline",IF($AL97<0,"Overdue",IF($AL97<=2,"Due Soon","On Track"))))) -> No Deadline
A98: 46121 | B98: Digital marketing curriculum on Skool: How to build high value | C98: C4 | D98: Yes | H98: Yes | J98: https://theeduassist.com/uncategorized/digital-marketing-curriculum-on-skool-how-to-build-high-value/ | L98: https://qr.ae/pFTB7f https://qr.ae/pFTBNi https://qr.ae/pFT3kk | M98: https://www.reddit.com/r/elearning/comments/1sgkwdv/comment/of5wn7s/?utm_source=share&utm_medium=web3x&utm_name=web3xcss&utm_term=1&utm_content=share_button https://www.reddit.com/r/instructionaldesign/comments/1sfx2d0/comment/of631od/?utm_source=share&utm_medium=web3x&utm_name=web3xcss&utm_term=1&utm_content=share_buttonn | AC98: =IF($B98="","",IF(AND($AB98="Done",$H98="Yes"),"Published",IF($AB98="Done","Ready to Publish","In Progress"))) -> In Progress | AK98: =IF($B98="","",IF(#REF!<>"Done","Complete content audit",IF($H98<>"Yes","Publish on website",IF($AH98="Yes","Log and assign team support",IF($AI98="Yes","Share in a relevant community","Complete"))))) -> #REF! | AL98: =IF(OR($B98="",$AF98=""),"",INT($AF98-TODAY())) | AM98: =IF($B98="","",IF($AC98="Published","Complete",IF($AL98="","No Deadline",IF($AL98<0,"Overdue",IF($AL98<=2,"Due Soon","On Track"))))) -> No Deadline
A99: 46121 | B99: n8n Automation Course Creation Opportunity for Creators in Florida | C99: C2 | D99: Yes | H99: Yes | J99: https://theeduassist.com/blog/guide-for-creating-an-n8n-automation-online-course-2026-in-florida/ | AC99: =IF($B99="","",IF(AND($AB99="Done",$H99="Yes"),"Published",IF($AB99="Done","Ready to Publish","In Progress"))) -> In Progress | AK99: =IF($B99="","",IF(#REF!<>"Done","Complete content audit",IF($H99<>"Yes","Publish on website",IF($AH99="Yes","Log and assign team support",IF($AI99="Yes","Share in a relevant community","Complete"))))) -> #REF! | AL99: =IF(OR($B99="",$AF99=""),"",INT($AF99-TODAY())) | AM99: =IF($B99="","",IF($AC99="Published","Complete",IF($AL99="","No Deadline",IF($AL99<0,"Overdue",IF($AL99<=2,"Due Soon","On Track"))))) -> No Deadline
A100: 46122 | B100: How to Become a Training Coordinator in 2026: Content and LMS Management Guide for Course Creators in Texas | C100: C2 | D100: Yes | H100: Yes | J100: https://theeduassist.com/blog/how-to-become-a-training-coordinator-in-2026-content-and-lms-management-guide-for-course-creators-in-texas/ | L100: https://qr.ae/pFhTKo | Q100: https://pin.it/XCOeQ7kq6 | AC100: =IF($B100="","",IF(AND($AB100="Done",$H100="Yes"),"Published",IF($AB100="Done","Ready to Publish","In Progress"))) -> In Progress | AK100: =IF($B100="","",IF(#REF!<>"Done","Complete content audit",IF($H100<>"Yes","Publish on website",IF($AH100="Yes","Log and assign team support",IF($AI100="Yes","Share in a relevant community","Complete"))))) -> #REF! | AL100: =IF(OR($B100="",$AF100=""),"",INT($AF100-TODAY())) | AM100: =IF($B100="","",IF($AC100="Published","Complete",IF($AL100="","No Deadline",IF($AL100<0,"Overdue",IF($AL100<=2,"Due Soon","On Track"))))) -> No Deadline
...

Sheet Kajabi service pages and Kajabi
R1: Kajabi Tree Keywords and FAQ's | AG1: =HYPERLINK("#'Guide'!A1","Open Guide") -> Open Guide
A3: Kajabi Service Pages Keywords, Titles, Description. | R3: Page | S3: KEYWORD | T3: VOLUME | U3: GLOBAL VOLUME | V3: DIFFICULTY | W3: INTENT | X3: TARGETED PAGE | Y3: WORD TYPE | Z3: FAQ's | AD3: FAQ with Answers
R5: Kajabi Course Creation Services | S5: kajabi online course platform​ | T5: 18.1k | U5: 18.1k | V5: 28 | W5: Informational | X5: Kajabi Course Creation Services | Y5: Secondary Keyword | Z5: How do I create a course in Kajabi? | AA5: What is the best platform for course creation? | AD5: All the answers are import from Google. These are for the key idea. Make sure to rewrite the answer that should be appealing before going ahead.
S6: kajabi courses​ | T6: 260 | U6: 640 | V6: 23 | W6: Informational | X6: Kajabi Course Creation Services | Y6: Secondary Keyword | Z6: Is Kajabi good for course creators? | AA6: Do you own your content on Kajabi?
A7: SR NO | B7: TARGETED PAGE | C7: KEYWORD | D7: VOLUME | E7: GLOBAL VOLUME | F7: DIFFICULTY | G7: INTENT | H7: WORD TYPE | I7: Title | J7: Description | K7: Linking page | L7: Keyword in blog | M7: Anchor text | N7: Add Section in blog for link | O7: Backlinks | S7: how to create a course on kajabi | T7: 30 | U7: 30 | X7: Kajabi Course Creation Services | Y7: Secondary Keyword | Z7: Can you sell courses directly through Kajabi? | AD7: FAQ | AE7: Answer | AF7: Topic
A8: 1 | B8: Kajabi Course Setup Service | C8: kajabi online course platform​ | D8: 18.1k | E8: 18.1k | F8: 28 | G8: Informational | H8: Secondary Keyword | S8: how to create a course in kajabi​ | T8: 20 | U8: 100 | X8: Kajabi Course Creation Services | Y8: Secondary Keyword | Z8: Do I need a website if I use Kajabi? | AD8: What types of digital products can I create using Kajabi? | AE8: With Kajabi, you can create a variety of digital products, including online courses, coaching programs, membership sites, digital downloads, and webinars.The platform offers customizable templates to help you design and deliver your content effectively. | AF8: kajabi digital product creation
C9: kajabi online courses | D9: 90 | E9: 310 | G9: Informational | H9: Secondary Keyword | I9: Expert Kajabi Course Setup to Scale Your Business-theEduAssist | J9: Scale your business with pro Kajabi course setup. theEduAssist handles the tech so you can teach. Book your setup call and launch your offer now. | K9: https://theeduassist.com/blog/7-powerful-kajabi-course-creation-services/ | L9: Kajabi Course Creation Services | S9: how to create a kajabi course | T9: 20 | U9: 30 | X9: Kajabi Course Creation Services | Y9: Secondary Keyword | Z9: Is Kajabi difficult to learn? | AD9: Do I need any technical skills to create digital products on Kajabi? | AE9: No, you do not need advanced technical skills to create digital products on Kajabi.The platform is user-friendly and designed for ease of use, with drag-and-drop features and step-by-step guides to help you set up your products and website. | AF9: kajabi digital product creation
C10: kajabi online course setup | G10: Informational | H10: Secondary Keyword | K10: https://theeduassist.com/blog/kajabi-online-course-setup/ | L10: Setting up your online course on Kajabi | M10: professional Kajabi course setup services | S10: kajabi course creation | T10: 20 | U10: 80 | X10: Kajabi Course Creation Services | Y10: Secondary Keyword | Z10: Can someone build my Kajabi course for me? | AD10: Can I sell my digital products on Kajabi? | AE10: es, Kajabi provides built-in sales and marketing tools that allow you to sell your digital products directly from your site.You can set up payment gateways, offer subscription plans, and create marketing funnels to attract and convert customers. | AF10: kajabi digital product creation
C11: setup online course kajabi | G11: Informational | H11: Secondary Keyword | K11: https://theeduassist.com/blog/kajabi-course-design-explained-how-to-create-online-course-in-2026/ | L11: our Kajabi online course | M11: Kajabi course setup experts | S11: Kajabi Course Creation Services | X11: Kajabi Course Creation Services | Y11: Primary Keyword | Z11: Should I hire a Kajabi consultant? | AD11: Is there customer support available if I encounter issues while creating products on Kajabi? | AE11: Yes, Kajabi offers customer support through various channels, including live chat, email, and a comprehensive help center with tutorials and resources.This ensures you can get assistance whenever you need it while creating your digital products. | AF11: kajabi digital product creation
C12: kajabi course setup​ | G12: Informational | H12: Secondary Keyword | K12: https://theeduassist.com/blog/kajabi-course-design/ | L12: Successful Kajabi course creators | M12: Kajabi setup specialists
C13: online course setup​ | D13: 20 | E13: 90 | G13: Informational | H13: Secondary Keyword | K13: https://theeduassist.com/blog/kajabi-drip-course-setup/ | L13: create a Kajabi course | M13: Kajabi course setup strategy | R13: kajabi online course setup | S13: kajabi online course platform​ | T13: 18.1k | U13: 18.1k | V13: 28 | W13: Informational | X13: kajabi online course setup | Y13: Secondary Keyword | Z13: How do I set up an online course in Kajabi? | AA13: How do I create a student-friendly Kajabi course? | AD13: What is Kajabi, and why use it for a membership site? | AE13: Kajabi is an all-in-one platform designed to help you create, market, and sell online courses, memberships, and digital products easily. It’s great for membership sites because it handles everything—from content hosting to payments—all in one place, so you don't need to juggle multiple tools. | AF13: kajabi membership site development
C14: how to create a course on kajabi | D14: 30 | E14: 30 | G14: Informational | H14: Secondary Keyword | S14: kajabi online courses | T14: 90 | U14: 310 | X14: kajabi online course setup | Y14: Secondary Keyword | Z14: How long does Kajabi setup take? | AA14: How do I create a coaching program in Kajabi? | AD14: How do I get started with building a membership site on Kajabi? | AE14: First, sign up for a Kajabi account and choose a plan that fits your needs. Then, you can use their pre-built templates or customize your own site. Set up your membership by creating product categories, uploading your content, and organizing it into member-exclusive access areas. | AF14: kajabi membership site development
C15: how to create a course in kajabi​ | D15: 20 | E15: 100 | G15: Informational | H15: Secondary Keyword | S15: kajabi online course setup | X15: kajabi online course setup | Y15: Primary Keyword | Z15: Is Kajabi hard to set up? | AA15: How do I create a client onboarding course in Kajabi? | AD15: Can I customize the look and feel of my Kajabi membership site? | AE15: Absolutely! Kajabi offers a variety of themes and customization options so you can match your site to your brand. You can change colors, fonts, layout styles, and add your own logo and images to create a professional and unique experience for your members. | AF15: kajabi membership site development
C16: how to create a kajabi course | D16: 20 | E16: 30 | G16: Informational | H16: Secondary Keyword | S16: setup online course kajabi | Z16: What do I need before creating a Kajabi course? | AD16: How do I protect my content so only members can see it? | AE16: Kajabi lets you set access rules easily. When you create your membership product, you choose which content is available to paying members. This way, your videos, downloads, and courses are securely locked behind a login. | AF16: kajabi membership site development
C17: Kajabi Course Setup Service | H17: Primary Keyword | AD17: Do I need technical skills to create a membership site on Kajabi? | AE17: No need to be a tech expert. Kajabi is designed with user-friendliness in mind, offering step-by-step guides and customer support. If you run into any trouble, their help team and community forums are great resources. | AF17: kajabi membership site development
C18: Kajabi services | D18: 40 | E18: 70 | F18: 31 | G18: Navigational | R18: kajabi course design | S18: kajabi course design best practices for engagement | X18: kajabi course design | Y18: Secondary Keyword | Z18: Does Kajabi market your course? | AA18: What is Kajabi and why should I use it for my course? | AD18: Can I track how my membership is performing? | AE18: Definitely. Kajabi provides analytics to monitor member engagement, sales, and other key metrics so you can see what’s working and make improvements where needed. | AF18: kajabi membership site development
S19: kajabi course design | X19: kajabi course design | Y19: Primary Keyword | Z19: How do I start designing a course on Kajabi?
B20: Kajabi Website & Funnel Setup | S20: done for you kajabi course design | X20: kajabi course design | Y20: Secondary Keyword | Z20: Can I customize the look and feel of my course? | AD20: can you upload course modules to kajabi via api​ | AF20: kajabi course upload services
C21: kajabi funnels​ | D21: 20 | E21: 220 | G21: Informational | H21: Primary Keyword | I21: Expert Kajabi Website & Funnel Setup for More Sales | J21: Your Kajabi site should work for you. We build high-converting funnels that boost your revenue. Book your setup call now. | K21: https://theeduassist.com/blog/kajabi-website-funnel-services/ | L21: Kajabi website expert services | S21: kajabi course designer | X21: kajabi course design | Y21: Secondary Keyword | Z21: How do I organize my course materials effectively? | AD21: Why should I use a Kajabi course upload service? | AE21: Save time, ensure a polished, scalable course structure, proper tagging and sequencing, and fewer technical hiccups during launch | AF21: kajabi course upload services
C22: kajabi website​ | D22: 390 | E22: 820 | F22: 21 | G22: Navigational | H22: Primary Keyword | K22: https://theeduassist.com/blog/kajabi-online-course-setup/ | L22: sales pipelines and funnels | M22: Kajabi funnel setup | AD22: What files can you upload to Kajabi? | AE22: Videos (MP4), audio, PDFs, slides, quizzes, downloadable resources, and text content. We’ll format and organize them for best learner flow. | AF22: kajabi course upload services
C23: kajabi website expert​ | D23: 70 | E23: 70 | F23: 9 | G23: Commercial | H23: Secondary Keyword | K23: https://theeduassist.com/blog/discover-kajabi-the-most-popular-platform-of-elearning-world/ | L23: website creation | M23: Kajabi website setup | R23: kajabi membership site development | S23: kajabi membership site​ | T23: 70 | U23: 330 | V23: 23 | W23: Informational | X23: kajabi membership site development | Y23: Secondary Keyword | Z23: What is Kajabi, and why use it for a membership site? | AD23: How long does a typical Kajabi upload project take? | AE23: It depends on course length, but most projects range from 3–10 business days. Exact timeline is confirmed in a project brief. | AF23: kajabi course upload services
C24: kajabi sales funnel | D24: 20 | E24: 70 | G24: Informational | H24: Secondary Keyword | K24: https://theeduassist.com/blog/kajabi-course-design/ | L24: Kajabi funnels | M24: custom Kajabi website and funnel setup | S24: kajabi membership | T24: 20 | U24: 190 | W24: Informational | X24: kajabi membership site development | Y24: Secondary Keyword | Z24: How do I get started with building a membership site on Kajabi? | AD24: Can you set up quizzes, assignments, and certificates? | AE24: Absolutely. We configure quizzes, graded tasks, and completion certificates where Kajabi supports them. | AF24: kajabi course upload services
C25: best funnels to use on kajabi​ | G25: Informational | H25: Secondary Keyword | K25: https://theeduassist.com/blog/7-powerful-kajabi-course-creation-services/ | L25: Funnel setup | M25: Kajabi funnel setup services | S25: how to create a membership in kajabi | T25: 20 | U25: 30 | X25: kajabi membership site development | Y25: Secondary Keyword | Z25: Can I customize the look and feel of my Kajabi membership site? | AD25: Will you customize templates and pages for my course? | AE25: Yes. We tailor landing pages, sales pages, and course templates to match your branding and voice. | AF25: kajabi course upload services
C26: kajabi funnels​ | G26: Informational | H26: Secondary Keyword | S26: kajabi membership site examples​ | T26: 70 | U26: 150 | V26: 0 | W26: Informational | X26: kajabi membership site development | Y26: Secondary Keyword | Z26: How do I protect my content so only members can see it? | AD26: Can you optimize SEO and discoverability on Kajabi? | AE26: We optimize titles, descriptions, keywords, hero images, and meta data to improve search visibility inside and outside Kajabi. | AF26: kajabi course upload services
C27: best funnels to use on kajabi​ | G27: Informational | H27: Secondary Keyword | S27: how to cancel kajabi membership​ | T27: 20 | U27: 20 | X27: kajabi membership site development | Y27: Secondary Keyword | Z27: Do I need technical skills to create a membership site on Kajabi? | AD27: Do you handle revisions or edits after uploads? | AE27: Yes. Most services include a revision window. Additional edits may incur a small fee depending on scope. | AF27: kajabi course upload services
C28: Kajabi services | D28: 40 | E28: 70 | F28: 31 | G28: Navigational | S28: kajabi membership site development | X28: kajabi membership site development | Y28: Primary Keyword | Z28: Can I track how my membership is performing? | AD28: How do you protect my content and confidentiality? | AE28: Share a brief of your course assets and goals (video count, resources, pages). We’ll propose a plan, timeline, and quote, then begin after approval. | AF28: kajabi course upload services
B30: Kajabi Course Upload Service | C30: . | H30: Primary Keyword | I30: Professional Kajabi Course Upload Service | We Value Your Time | J30: Need your course live? Our professional Kajabi course upload service takes the stress away. We build it right the first time. Hire our experts here. | K30: https://theeduassist.com/blog/kajabi-online-course-setup/ | L30: Upload videos, add text, PDFs, audio files, or external embeds | M30: Kajabi Course Upload Services | R30: kajabi coaching program setup | S30: kajabi coaching program setup guide | X30: kajabi coaching program setup | Y30: Secondary Keyword | Z30: How Do I Set Up a Kajabi Coaching Program? | AA30: What are the 5 C's in coaching? | AD30: What are some best practices for Kajabi training? | AE30: Start with a clear product and pricing plan, use pipelines to bootstrap launches, automate welcome emails, segment your audience, and regularly update content based on student feedback. | AF30: kajabi training platform
C31: kajabi.services​ | H31: Secondary Keyword | K31: https://theeduassist.com/blog/7-powerful-kajabi-course-creation-services/ | L31: Course structure | M31: professional Kajabi course upload services | S31: kajabi coaching program setup for beginners | X31: kajabi coaching program setup | Y31: Secondary Keyword | Z31: How Long Does It Take to Set Up Kajabi Coaching? | AA31: What are the 3 C's of coaching? | AD31: What type of platform is Kajabi? | AE31: Kajabi was built as a business platform for knowledge entrepreneurs. Courses are one product type among several. On Kajabi, you also build your website, send email campaigns, create sales funnels, run a coaching practice, host a community, manage affiliates, and accept payments. | AF31: kajabi training platform
C32: Kajabi services | D32: 40 | E32: 70 | F32: 31 | G32: Navigational | H32: Secondary Keyword | K32: https://theeduassist.com/blog/kajabi-course-design-explained-how-to-create-online-course-in-2026/ | L32: upload your content | M32: upload your course to Kajabi | S32: kajabi coaching program | T32: 20 | U32: 40 | W32: Informational | X32: kajabi coaching program setup | Y32: Secondary Keyword | Z32: What Features Should My Kajabi Coaching Program Have? | AA32: What is the golden triangle of coaching? | AD32: Which is better, Kajabi or teachable? | AE32: Kajabi has more tools and product types. Teachable offers more courses per tier. Kajabi has more expensive plans, but it gives you access to extra products like podcasts in addition to multiple integrations and advanced email marketing tools. However, product numbers and customers are limited per tier. | AF32: kajabi training platform
C33: kajabi customer service | D33: 50 | E33: 140 | F33: 19 | G33: Informational | H33: Secondary Keyword | K33: https://theeduassist.com/blog/kajabi-course-design/ | L33: Kajabi content upload services | M33: Kajabi content upload services | N33: A well-designed course also requires proper implementation, which is why many creators use Kajabi content upload services to organize lessons and learning materials efficiently. | S33: kajabi coaching​ | T33: 30 | U33: 180 | V33: 12 | W33: Informational + navigational | X33: kajabi coaching program setup | Y33: Secondary Keyword | Z33: Can I Customize My Kajabi Coaching Program?
C34: kajabi help | D34: 110 | E34: 390 | F34: 20 | G34: Navigational+Commercial | H34: Secondary Keyword | K34: https://theeduassist.com/blog/kajabi-drip-course-setup/ | L34: Kajabi course content upload | M34: Kajabi course content upload | N34: Before configuring drip schedules, ensure your Kajabi course content upload process is completed correctly with structured modules and lesson assets. | S34: coaching kajabi​ | T34: 20 | U34: 50 | W34: Informational | X34: kajabi coaching program setup | Y34: Secondary Keyword | Z34: How to set up a coaching program? | AD34: Are there different types of templates in Kajabi? | AE34: Yes: course templates (structure), landing/page templates (for sales and branding), email sequence templates, and funnel/templates for onboarding. | AF34: kajabi course templates
C35: kajabi support | D35: 140 | E35: 490 | F35: 17 | G35: Navigational | H35: Secondary Keyword | S35: kajabi coaching platform​ | T35: 70 | U35: 100 | V35: 13 | W35: Informational + navigational | X35: kajabi coaching program setup | Y35: Secondary Keyword | Z35: What is the 70 30 rule in coaching? | AD35: Can I customize a Kajabi course template after applying it? | AE35: Absolutely. Templates are starting points and can be edited, renamed, reorganized, and re-styled to fit your brand | AF35: kajabi course templates
S36: kajabi coaching program setup | X36: kajabi coaching program setup | Y36: Primary Keyword | AD36: Can I import a template from another course? | AE36: Yes, you can clone or import course content from one product into another, which often includes templates as a base. | AF36: kajabi course templates
AD37: Do templates work with mobile and responsive design? | AE37: Yes, Kajabi templates are designed to be responsive, but you should still test on mobile devices. | AF37: kajabi course templates
R38: kajabi digital product creation | S38: kajabi digital products​ | T38: 20 | U38: 50 | X38: kajabi digital product creation | Y38: Secondary Keyword | Z38: What types of digital products can I create using Kajabi? | AD38: Can I use a template for a new niche or language? | AE38: Yes, templates are adaptable. You may need to update copy, media, and localization to fit your niche or language. | AF38: kajabi course templates
B39: Kajabi Migration Services | S39: kajabi digital products​ creation guide | X39: kajabi digital product creation | Y39: Secondary Keyword | Z39: Do I need any technical skills to create digital products on Kajabi? | AD39: How do I update or modify a template after launching? | AE39: You can edit the course pages, modules, and blocks anytime; changes apply to your live course without breaking students’ progress. | AF39: kajabi course templates
C40: Kajabi Migration | D40: 20 | E40: 60 | G40: Informational | H40: Secondary Keyword | I40: Move to Kajabi: Expert Migration for Your Growth | J40: Ready to move to Kajabi? Get a clean migration that saves you time. We move your courses and emails fast. Scale your business without the headaches. Call us. | K40: https://theeduassist.com/blog/kajabi-website-funnel-services/ | L40: Kajabi website migration | S40: kajabi digital products​ creation program | X40: kajabi digital product creation | Y40: Secondary Keyword | Z40: Can I sell my digital products on Kajabi? | AD40: What's the best way to choose a Kajabi template? | AE40: Consider your course goals, desired student flow, branding, and whether the template supports your media (video, downloads), assessments, and marketing pages. Test a sample to ensure it meets your needs. | AF40: kajabi course templates
C41: Kajabi Migration Services | H41: Primary Keyword | K41: https://theeduassist.com/blog/kajabi-online-course-setup/ | L41: migrate your course to Kajabi | M41: migrate your course to Kajabi | N41: If your course already exists on another platform, you can migrate your course to Kajabi while preserving your content structure, lessons, downloads, and learner experience. Add the above sentence. After this, Why Choose Kajabi for Your Online Course? | S41: how to sell digital products on kajabi | X41: kajabi digital product creation | Y41: Secondary Keyword | Z41: Is there customer support available if I encounter issues while creating products on Kajabi? | AD41: Are there limitations or downsides to using templates? | AE41: Templates can speed setup but may require reworking if your course structure is very unique; ensure the template fits your learning path. | AF41: kajabi course templates
C42: migrate from kajabi​ | D42: 10 | E42: 30 | H42: Secondary Keyword | K42: https://theeduassist.com/blog/discover-kajabi-the-most-popular-platform-of-elearning-world/ | L42: Kajabi migration experts | M42: Kajabi migration experts | N42: Kajabi vs Competitors section, Add. Many businesses work with Kajabi migration experts when moving from platforms like Thinkific, Teachable, or LearnWorlds to avoid data loss and technical issues. | S42: kajabi digital product setup | X42: kajabi digital product creation | Y42: Secondary Keyword
C43: migrate from kajabi to wordpress​ | H43: Secondary Keyword | K43: https://theeduassist.com/blog/7-powerful-kajabi-course-creation-services/ | L43: Kajabi course migration services | M43: Kajabi course migration services | N43: In the Kajabi course creation services section. Add, Many creators also require Kajabi course migration services when moving existing content from other learning platforms into Kajabi. | X43: kajabi digital product creation | Y43: Primary Keyword | AD43: What services are included in Kajabi Website & Funnel Services? | AE43: Website and landing page design, funnel planning, product and payment setup, email sequences, automation, lead magnets, SEO basics, and ongoing optimization. | AF43: Kajabi Website & Funnel Services
C44: migrate from kajabi to teachable​ | D44: 20 | E44: 20 | H44: Secondary Keyword | K44: https://theeduassist.com/blog/kajabi-course-design-explained-how-to-create-online-course-in-2026/ | L44: transfer your course to Kajabi | M44: transfer your course to Kajabi | N44: After, We do not simply upload your content to Kajabi. Add, Whether you're launching a new course or need to transfer your course to Kajabi, proper course design and structure remain essential. | AD44: How long does a typical Kajabi website or funnel project take? | AE44: Most projects take 2–6 weeks, depending on scope and the number of funnels/pages required. | AF44: Kajabi Website & Funnel Services
C45: migrate wordpress to kajabi​ | H45: Secondary Keyword | R45: kajabi drip course setup | S45: kajabi drip content | T45: 20 | U45: 120 | X45: kajabi drip course setup | Y45: Secondary Keyword | AD45: Do you offer funnel strategy and mapping? | AE45: Absolutely. We design a customer journey, map touchpoints, and create automated email/sequences to maximize conversions. | AF45: Kajabi Website & Funnel Services
C46: migrating from kajabi​ | H46: Secondary Keyword | S46: drip content kajabi​ | T46: 20 | U46: 30 | X46: kajabi drip course setup | Y46: Secondary Keyword | Z46: How to drip content in Kajabi? | AA46: How long should a drip take? | AD46: How do I start a Kajabi Website & Funnel Services project? | AE46: Contact us for a discovery call, share your goals, and we’ll propose a tailored plan and timeline | AF46: Kajabi Website & Funnel Services
C47: Kajabi services | D47: 40 | E47: 70 | F47: 31 | G47: Navigational | H47: Secondary Keyword | S47: kajabi drip​ | T47: 20 | U47: 30 | X47: kajabi drip course setup | Y47: Secondary Keyword | Z47: What is drip course content? | AA47: How to set up a drip campaign? | AD47: How do Kajabi funnels work? | AE47: A Funnel brings marketing and sales together through the power of automation. A Funnel can help drive traffic to your opt-in page, capture lead information, send follow-up content, and ultimately convert visitors into paying customers. With Kajabi, Funnels are designed with pre-built landing pages and email copy. | AF47: Kajabi Website & Funnel Services
S48: kajabi drip course setup | X48: kajabi drip course setup | Y48: Primary Keyword | Z48: How long should a drip campaign last? | AA48: What is the 30/30 rule for drip irrigation? | AD48: What are Kajabi websites? | AE48: A Powerful All in one Website Builder. Build a website to connect everything in your business. Create a no code website simply and easily on Kajabi's all in one website builder platform. | AF48: Kajabi Website & Funnel Services
B49: kajabi virtual assistant/ monthly support services | AD49: Can I build a website with Kajabi? | AE49: With Kajabi, you can create and design your website with streamlined templates and highly-customizable page editing features. | AF49: Kajabi Website & Funnel Services
C50: kajabi va | D50: 20 | E50: 110 | H50: Secondary Keyword | I50: Hire a Kajabi VA for Reliable Monthly Management | J50: Stop wasting hours on tech. Hire a Kajabi VA for reliable monthly management. We fix the bugs and automate your site. Start your easy growth plan now. | K50: https://theeduassist.com/blog/discover-kajabi-the-most-popular-platform-of-elearning-world/ | L50: Kajabi monthly support services | M50: Kajabi monthly support services | N50: In the 3rd paragraph from the start. Replace with,At TheEduAssist, we help clients fully leverage Kajabi through expert services including course creation, website & funnel building, marketing automation, SEO & growth, and Kajabi monthly support services. | R50: kajabi course upload services | S50: kajabi course upload services | X50: kajabi course upload services | Y50: Primary Keyword | Z50: Why should I use a Kajabi course upload service? | AA50: How do I get started? | AD50: Do website owners get paid? | AE50: Websites can generate income in various ways, depending on what they offer and who they serve. Some rely on advertising, while others earn money through product sales, subscriptions, or partnerships. Many successful sites use a combination of these methods to generate revenue through more than one source | AF50: Kajabi Website & Funnel Services
C51: Kajabi services | D51: 40 | E51: 70 | F51: 31 | G51: Navigational | H51: Secondary Keyword | K51: https://theeduassist.com/blog/kajabi-website-funnel-services/ | L51: ongoing Kajabi support services | M51: ongoing Kajabi support services | N51: In Final CTA or conclusion. Add, After your website and funnel are launched, our ongoing Kajabi support services help maintain pages, optimize automations, update content, and improve performance over time. | S51: kajabi course upload services Free | X51: kajabi course upload services | Y51: Secondary Keyword | Z51: What files can you upload to Kajabi? | AD51: What are Kajabi "Funnel Services"? | AF51: Kajabi Website & Funnel Services
C52: hire kajabi experts | D52: 70 | E52: 100 | F52: 8 | G52: Commercial | H52: Secondary Keyword | K52: https://theeduassist.com/blog/7-powerful-kajabi-course-creation-services/ | L52: Kajabi virtual assistant support | M52: Kajabi virtual assistant support | N52: Near: Buying Kajabi does not automatically create a successful online course business. Add, Many course creators rely on Kajabi virtual assistant support to manage content updates, student resources, automations, and ongoing platform maintenance. | S52: kajabi course upload services for beginner | X52: kajabi course upload services | Y52: Secondary Keyword | Z52: How long does a typical Kajabi upload project take? | AD52: Do I need to hire a Kajabi Expert? | AF52: Kajabi Website & Funnel Services
C53: virtual teammate client playbook | D53: 50 | E53: 50 | F53: 0 | G53: Navigational | H53: Secondary Keyword | K53: https://theeduassist.com/blog/kajabi-membership-sites-development/ | L53: monthly Kajabi management services | M53: monthly Kajabi management services | N53: Under: Inconsistent content rhythm. Add, Many membership owners use monthly Kajabi management services to keep content updated, maintain community engagement, and ensure a consistent publishing schedule. | S53: kajabi course upload services blog | X53: kajabi course upload services | Y53: Secondary Keyword | Z53: Can you set up quizzes, assignments, and certificates? | AD53: Where can I find Kajabi Website & Funnel Services? | AF53: Kajabi Website & Funnel Services
C54: kajabi virtual assistant​ | D54: 20 | E54: 60 | H54: Secondary Keyword | K54: https://theeduassist.com/blog/kajabi-online-course-setup/ | L54: ongoing Kajabi assistance | M54: ongoing Kajabi assistance | N54: Near conclusion or FAQ. Add, Launching your course is only the beginning. Many creators benefit from ongoing Kajabi assistance to manage updates, uploads, automations, and learner support. | S54: kajabi course upload services complete | X54: kajabi course upload services | Y54: Secondary Keyword | Z54: Will you customize templates and pages for my course?
C55: kajabi virtual assistants​ | H55: Secondary Keyword | S55: kajabi course upload services cost | X55: kajabi course upload services | Y55: Secondary Keyword | Z55: Can you optimize SEO and discoverability on Kajabi? | AD55: Do I need a designer for Kajabi? | AE55: No, Kajabi features a drag-and-drop builder and offers a large library of industry-specific templates, making it accessible even without coding experience. However, many creators hire professionals for custom branding, complex sales funnels, and advanced page layouts. | AF55: kajabi website design services
C56: virtual assistant kajabi | H56: Secondary Keyword | S56: kajabi course upload services Documentation | X56: kajabi course upload services | Y56: Secondary Keyword | Z56: Do you handle revisions or edits after uploads? | AD56: What should a Kajabi website include? | AE56: A high-converting Kajabi site should feature a clear homepage, an "About" page, a dedicated storefront for courses/memberships, lead-generation landing pages, and seamlessly integrated checkout pages | AF56: kajabi website design services
C57: kajabi virtual assistant for sales page​ | H57: Secondary Keyword | S57: kajabi course upload services dashboard | X57: kajabi course upload services | Y57: Secondary Keyword | Z57: How do you protect my content and confidentiality? | AD57: What is included in Kajabi website design services? | AE57: Custom website design on Kajabi, theme/setup, page templates (home, about, courses, blog), funnels, landing pages, checkout setup, and basic brand alignment | AF57: kajabi website design services
C58: kajabi virtual assistant for product launch​ | H58: Secondary Keyword | AD58: Do you design full Kajabi sites or just pages? | AE58: we can design a full site (home, about, courses, blog, contact) or optimize/design specific pages and funnels as needed. | AF58: kajabi website design services
C59: kajabi packages for the virtual assistant​ | H59: Secondary Keyword | R59: kajabi training platform | S59: kajabi training platform | X59: kajabi training platform | Y59: Primary Keyword | Z59: What are some best practices for Kajabi training?
C60: Kajabi VA services | H60: Primary Keyword | S60: kajabi learning platform | X60: kajabi training platform | Y60: Secondary Keyword | Z60: What type of platform is Kajabi? | AD60: What Kajabi templates should I use for courses? | AE60: For selling a course, use the Product Launch funnel blueprint or the Simple Sales Page funnel. These automatically route prospects from a value-driven video or sales page directly to your course checkout | AF60: kajabi sales funnel setup
C61: Kajabi virtual assistant services | H61: Primary Keyword | S61: kajabi course platform | X61: kajabi training platform | Y61: Secondary Keyword | Z61: Which is better, Kajabi or teachable? | AD61: How do I test my funnel before going live? | AE61: Before launching, copy the funnel URL and paste it into a Chrome Incognito window. Click through the pages, fill out the form, and run a test transaction to make sure the checkout process and email automations work exactly as intended | AF61: kajabi sales funnel setup
C62: kajabi help | D62: 110 | E62: 390 | F62: 20 | G62: Navigational+Commercial | H62: Secondary Keyword | S62: kajabi online training platform | X62: kajabi training platform | Y62: Secondary Keyword | AD62: How many funnels can I create? | AE62: Your funnel limit is tied to your Kajabi plan. The Basic plan allows for 3 active funnels, while the Growth plan offers up to 15. However, you can always build an infinite amount of standalone landing pages, forms, and offers through your website tab and link them together manually. | AF62: kajabi sales funnel setup
C63: kajabi support | D63: 140 | E63: 490 | F63: 17 | G63: Navigational | H63: Secondary Keyword | S63: kajabi employee training platform | X63: kajabi training platform | Y63: Secondary Keyword | AD63: Can I attach multiple offers to one sales funnel? | AE63: Yes, you can include tiered pricing or multiple offers on a single page. You can add a Pricing Cards section to your funnel's sales page and set the CTA blocks in those cards to link to the corresponding checkout pages. | AF63: kajabi sales funnel setup
C64: kajabi customer service | D64: 50 | E64: 140 | F64: 19 | G64: Informational | H64: Secondary Keyword | AD64: What is a Kajabi sales funnel? | AE64: A guided sequence of pages, emails, and automations designed to convert visitors into customers and upsell them over time. | AF64: kajabi sales funnel setup
C65: new kajabi help | D65: 50 | E65: 90 | F65: 12 | G65: Navigational | H65: Secondary Keyword | R65: kajabi course templates | S65: kajabi course templates | T65: 30 | U65: 170 | V65: 14 | W65: Informational | X65: kajabi course templates | Y65: Primary Keyword | Z65: Are there different types of templates in Kajabi? | AD65: Where do I start when building a funnel in Kajabi? | AE65: Define your goal, map the customer journey, create a pipeline (funnel) with a landing page, checkout, and follow-up emails, then connect automations. | AF65: kajabi sales funnel setup
S66: kajabi course templates free | X66: kajabi course templates | Y66: Secondary Keyword | Z66: Can I customize a Kajabi course template after applying it? | AD66: What is a Kajabi Pipeline? | AE66: A pre-built funnel blueprint in Kajabi (e.g., Newsletter, Launch, or Product Launch) you can customize to fit your offer. | AF66: kajabi sales funnel setup
S67: best kajabi course templates | X67: kajabi course templates | Y67: Secondary Keyword | Z67: Can I import a template from another course?
S68: kajabi templates | T68: 260 | U68: 690 | V68: 23 | W68: Commerical | X68: kajabi course templates | Y68: Secondary Keyword | Z68: Do templates work with mobile and responsive design? | AD68: What is the first step to optimize my Kajabi landing page for conversions? | AE68: Define your goal and target audience, then map your message to that audience—clear value proposition, benefits, and a single, prominent CTA. | AF68: kajabi landing page design
S69: kajabi course template | T69: 20 | U69: 20 | X69: kajabi course templates | Y69: Secondary Keyword | Z69: Are there limitations or downsides to using templates? | AD69: What makes a strong CTA on a Kajabi landing page? | AE69: Clarity, urgency, and relevance. Use action verbs, specify the outcome (e.g., “Get the Guide,” “Start Free Trial”), and place the CTA above the fold with a contrasting color. | AF69: kajabi landing page design
S70: kajabi themes | T70: 30 | U70: 300 | V70: 17 | W70: navigational | X70: kajabi course templates | Y70: Secondary Keyword | Z70: Can I use a template for a new niche or language? | AD70: Should I use video on my landing page, and where? | AE70: Yes. Place a short explainer video near the top or in the hero, with a transcribed caption option. Videos should quickly convey value and demonstrate results. | AF70: kajabi landing page design
S71: kajabi website templates | T71: 140 | U71: 320 | V71: 20 | W71: Informational | X71: kajabi course templates | Y71: Secondary Keyword | Z71: How do I update or modify a template after launching? | AD71: How do I design a landing page in Kajabi? | AE71: Navigate: From your Kajabi Dashboard, go to Website > Pages > Landing Pages.Choose a Template: Select from Kajabi’s free library (sales pages, opt-ins, podcast links, waitlists) or start with a Blank Canvas.Customize: Click on any element (headlines, buttons, videos) to edit text, colors, and spacing in the drag-and-drop editor.Optimize: Always toggle to mobile view to adjust sizes and ensure it looks clean on mobile devices | AF71: kajabi landing page design
S72: kajabi website themes​ | T72: 20 | U72: 40 | X72: kajabi course templates | Y72: Secondary Keyword | Z72: What's the best way to choose a Kajabi template? | AD72: How do I increase conversions on a Kajabi landing page? | AE72: Remove Distractions: Hide the standard site header and footer on sales and opt-in pages so visitors focus solely on your goal.Craft a Strong Headline: Use a formula like "How to [Desired Outcome] without [Undesired Action]".Include Trust Signals: Add testimonials, guarantee badges, or social proof right before your final Call to Action (CTA) button.Make CTAs Stand Out: Use high-contrast colors for your buttons and use actionable text (e.g., "Start Your Free Trial" instead of "Submit") | AF72: kajabi landing page design
S73: kajabi email templates | T73: 50 | U73: 130 | V73: 14 | W73: Informational | X73: kajabi course templates | Y73: Secondary Keyword | AD73: How do I set a landing page as my homepage? | AE73: If you want visitors to see your new landing page immediately when they go to your URL:Go to Settings from your Kajabi Dashboard.Click Site Details.Scroll down to the Homepage dropdown menu.Select the landing page you want to display, then click Save | AF73: kajabi landing page design
R75: Kajabi Website & Funnel Services | S75: kajabi funnels​ | T75: 20 | U75: 220 | X75: Kajabi Website & Funnel Services | Y75: Primary Keyword
S76: sales funnel website template | T76: 40 | U76: 190 | V76: 4 | W76: Transactional
S77: difference between click funnels and kajabi​ | X77: Kajabi Website & Funnel Services | Y77: Secondary Keyword
S78: kajabi funnel templates​ | X78: Kajabi Website & Funnel Services | Y78: Secondary Keyword
S79: kajabi funnel page templates​ | X79: Kajabi Website & Funnel Services | Y79: Secondary Keyword
S80: kajabi mini-course funnel templates​ | X80: Kajabi Website & Funnel Services | Y80: Secondary Keyword
S81: add kajabi product to click funnels​ | X81: Kajabi Website & Funnel Services | Y81: Secondary Keyword
S82: how to add a kajabi product to click funnels​ | X82: Kajabi Website & Funnel Services | Y82: Secondary Keyword
S83: add a kajabi product to click funnels | X83: Kajabi Website & Funnel Services | Y83: Secondary Keyword
S84: kajabi sales funnel | T84: 20 | U84: 70 | X84: Kajabi Website & Funnel Services | Y84: Secondary Keyword
S85: sales funnel kajabi​ | X85: Kajabi Website & Funnel Services | Y85: Secondary Keyword
S86: kajabi sales funnel template​ | X86: Kajabi Website & Funnel Services | Y86: Secondary Keyword
S87: using kajabi for sales funnel​ | X87: Kajabi Website & Funnel Services | Y87: Secondary Keyword
S88: best funnels to use on kajabi​ | X88: Kajabi Website & Funnel Services | Y88: Secondary Keyword
S89: how to use kajabi like deadline funnel​ | X89: Kajabi Website & Funnel Services | Y89: Secondary Keyword
S90: kajabi website expert​ | T90: 70 | U90: 70 | V90: 9 | W90: Commercial | X90: Kajabi Website & Funnel Services | Y90: Secondary Keyword
S91: kajabi website template​ | T91: 40 | U91: 60 | V91: 9 | X91: Kajabi Website & Funnel Services | Y91: Secondary Keyword
S92: kajabi website​ | T92: 390 | U92: 820 | V92: 21 | W92: Navigational | X92: Kajabi Website & Funnel Services | Y92: Primary Keyword
S93: kajabi website themes​ | T93: 20 | U93: 40 | X93: Kajabi Website & Funnel Services | Y93: Secondary Keyword
S94: kajabi change website theme​ | X94: Kajabi Website & Funnel Services | Y94: Secondary Keyword
S95: how do you change your website theme on kajabi​ | X95: Kajabi Website & Funnel Services | Y95: Secondary Keyword
R97: kajabi website design services | S97: kajabi website design​ | T97: 0 | U97: 30 | X97: kajabi website design services | Y97: Secondary Keyword
S98: new kajabi website designers | X98: kajabi website design services | Y98: Secondary Keyword
S99: design kajabi website​ | X99: kajabi website design services | Y99: Secondary Keyword
S100: kajabi website design templates​ | T100: 20 | U100: 20 | X100: kajabi website design services | Y100: Secondary Keyword
S101: kajabi website designer​ | T101: 20 | U101: 130 | X101: kajabi website design services | Y101: Secondary Keyword
S102: kajabi website design for coaches​ | X102: kajabi website design services | Y102: Secondary Keyword
S103: kajabi website design templates​ | T103: 20 | U103: 20 | X103: kajabi website design services | Y103: Secondary Keyword
S104: kajabi website examples | T104: 260 | U104: 510 | V104: 7 | W104: Commercial | X104: kajabi website design services | Y104: Secondary Keyword
S105: kajabi website developer | T105: 40 | U105: 40 | V105: 7 | W105: Informational | X105: kajabi website design services | Y105: Secondary Keyword
...

Sheet Kajabi Tree
B1: How to write an article : Pillar content should be at least 2000 words. Include every detail about topic. This page link to all it's cluster pages. Cluster content should to 800 to 1000 words. These content should be link to pilar content | K1: suggestion by Content wirtier | L1: Feedback | M1: Suggeestions by SEO | N1: Everyone Make sure to remove these preadded tags in the bottom of AISEO SEO settings and add your own title anddescription and focus words help improve the seo of the website
A2: Pillar Content | B2: Cluster Content | C2: Search Intent | D2: Suggested Title | E2: Suggested URL Slug | F2: keyword difficulty | G2: Description | H2: Written by | I2: Add Link here for linking | J2: new link | M2: Description incorrect.
A3: Kajabi Course Creation Services | D3: 7 Powerful Kajabi Course Creation Services That Skyrocket Sales | G3: Discover how Kajabi Course Creation Services help coaches and creators build stunning, high-converting online courses that boost engagement, sales, and growth. | H3: C2 | I3: https://theeduassist.com/blog/7-powerful-kajabi-course-creation-services-to-skyrocket-sales/ | K3: Rechecked and corrected. | M3: Description incorrect.
B4: kajabi online course setup | C4: transactional | D4: How to Set Up an Online Course on Kajabi | E4: kajabi-online-course-setup | F4: Medium | G4: Discover the ultimate Kajabi Online Course Setup guide to build, launch, and scale a high-converting course that boosts engagement, trust, and sales fast. | H4: C1 | I4: https://theeduassist.com/blog/kajabi-online-course-setup/ | K4: Rechecked and corrected.
B5: kajabi course design | C5: commercial | D5: Master Kajabi Course Design With These Simple steps | E5: kajabi-course-design | F5: Medium | G5: Master Kajabi Course Design with proven strategies to create stunning, engaging, and high-converting online courses that captivate learners and grow sales. | H5: C2 | I5: https://theeduassist.com/blog/kajabi-course-design/ | K5: Rechecked and corrected. | M5: Description incorrect.
B6: kajabi membership site development | C6: commercial | D6: What Are the Best Practices for Kajabi Membership Sites? | E6: kajabi-membership-site-development | F6: Medium | G6: Discover expert Kajabi membership site development services to create, manage, and grow your online community effortlessly. Start your journey today! | H6: C1 | I6: https://theeduassist.com/blog/kajabi-membership-sites-development/ | K6: Rechecked and corrected. | M6: Description incorrect.
B7: kajabi coaching program setup | C7: commercial | D7: Quick Tips for Setting Up Kajabi Coaching | E7: kajabi-coaching-program-setup | F7: Low | G7: Transform your ideas into income with our Kajabi coaching program setup. Get expert guidance to launch and grow your online business successfully! | H7: C2 | I7: https://theeduassist.com/blog/kajabi-coaching-program-setup/
B8: kajabi digital product creation | C8: informational | D8: How to Create Digital Products with Kajabi | E8: kajabi-digital-product-creation | F8: Low | G8: Ready to create and sell digital products? Kajabi offers everything you need to build, market, and grow your online business. Start your success story now! | H8: C1 | I8: https://theeduassist.com/blog/kajabi-digital-product-creation/
B9: kajabi drip course setup | C9: informational | D9: What Are the Best Practices for Kajabi Drip Courses? | E9: kajabi-drip-course-setup | F9: Low | G9: Discover how to set up a successful Kajabi drip course. Our expert tips will help you enhance user experience and maximize course engagement. | H9: C2 | I9: https://theeduassist.com/blog/kajabi-drip-course-setup/ | K9: Rechecked and corrected. | M9: Description incorrect.
B10: kajabi course upload services | C10: transactional | D10: 7 Common Mistakes In Kajabi Course Uploading To Avoid | E10: kajabi-course-upload-services | F10: Low | G10: Avoid these 7 common mistakes in Kajabi course uploading. Get your lessons right the first time for a better student experience. Click to learn more | H10: C1 | I10: https://theeduassist.com/uncategorized/kajabi-course-upload-services/ | K10: Rechecked and corrected. | L10: Rewrite it. Please Check. | M10: Description incorrect.
B11: kajabi training platform | C11: navigational | D11: how to create a training portal in kajabi | E11: kajabi-training-platform | F11: High | G11: Join our Kajabi training program and turn your passion into profit! Learn to create and market online courses with ease. Get started today! | H11: C4 | I11: https://theeduassist.com/blog/how-to-create-a-kajabi-training-platform/
B12: kajabi course templates | C12: informational | D12: Best Free and Paid Kajabi Course Templates & Themes for 2026 | E12: kajabi-course-templates | F12: Medium | G12: Find the ultimate collection of Kajabi course templates and themes for 2026. Boost your course's appeal with our curated selection of free and paid designs! | H12: C2 | I12: https://theeduassist.com/blog/kajabi-course-templates/
A14: Kajabi Website & Funnel Services | D14: Best Kajabi Funnel and Website Setup Services for 2026 Growth | G14: Boost your online presence with our Kajabi website and funnel services. We specialize in e-learning solutions to help you engage your audience effectively. | H14: C1 | I14: https://theeduassist.com/blog/kajabi-website-funnel-services/
B15: kajabi website design services | C15: commercial | D15: A Step-by-Step Guide to Finding the Best Kajabi Design Services | E15: kajabi-website-design-services | F15: High | G15: Hire the right Kajabi design services with these simple steps. We show you how to pick a designer who delivers results. Click to start now. | H15: C4 | I15: https://theeduassist.com/uncategorized/kajabi-website-design-services/
B16: kajabi sales funnel setup | C16: commercial | D16: The Future Of Sales Funnels: Leveraging Kajabi For Growth | E16: kajabi-sales-funnel-setup | F16: Medium | G16: Use Kajabi to build smart sales funnels that actually work. Stop losing leads and start making more sales. See how to grow your brand now. | H16: C2 | I16: https://theeduassist.com/blog/kajabi-sales-funnel-setup/
B17: kajabi landing page design | C17: commercial | D17: How to Optimize Your Kajabi Landing Page for Conversions | E17: kajabi-landing-page-design | F17: Medium | G17: Turn your visitors into buyers. We show you how to optimize your Kajabi landing page for conversions quickly. Boost your ROI with these proven steps. | H17: C1 | I17: https://theeduassist.com/blog/kajabi-landing-page-design/
B18: kajabi funnel builder | C18: informational | D18: How to Maximize Your Sales with the Kajabi Funnel Builder | E18: kajabi-funnel-builder | F18: High | G18: Learn how to use the Kajabi funnel builder to grow your revenue. Stop losing leads. Build high-converting pages and start selling more today. | H18: C4 | I18: https://theeduassist.com/blog/kajabi-webinar-funnel/
B19: kajabi webinar funnel | C19: informational | D19: How to build your first Kajabi webinar funnel | E19: kajabi-webinar-funnel | F19: Low | G19: Learn how to build your first Kajabi webinar funnel and turn your webinar into an effective tool for attracting, engaging, and converting your audience. | H19: C3 | I19: https://www.theeduassist.com/blog/how-to-build-your-first-kajabi-webinar-funnel/
B20: kajabi email marketing funnels | C20: commercial | D20: Stop losing leads with these simple Kajabi email tweaks | E20: kajabi-email-marketing-funnels | F20: Low | H20: C4 | I20: https://theeduassist.com/blog/kajabi-email-marketing-funnels/
B21: kajabi website migration | C21: transactional | D21: Why You Should Switch to Kajabi Right Now | E21: kajabi-website-migration | F21: Medium | H21: C3 | I21: https://theeduassist.com/blog/why-you-should-switch-to-kajabi-the-ultimate-website-migration-guide/
B22: kajabi checkout page optimization | C22: commercial | D22: Kajabi Checkout Page Optimization Strategies | E22: kajabi-checkout-page-optimization | F22: Low | H22: C2 | I22: https://theeduassist.com/blog/kajabi-checkout-page-optimization/
B23: kajabi website templates | C23: navigational | D23: How to Pick a Kajabi Template That Actually Sells | E23: kajabi-website-templates | F23: Medium | H23: C2 | I23: https://theeduassist.com/uncategorized/best-kajabi-website-templates/
B24: kajabi lead generation funnels | C24: commercial | D24: 5 easy ways to get more leads with Kajabi | E24: kajabi-lead-generation-funnels | F24: Medium | H24: C4 | I24: https://theeduassist.com/blog/kajabi-lead-generation-funnels/
A26: Kajabi Marketing & Automation Services
B27: kajabi marketing services | C27: commercial | D27: How to find the best Kajabi marketing pros | E27: kajabi-marketing-services | F27: High | H27: C1 | I27: https://theeduassist.com/blog/kajabi-marketing-services/
B28: kajabi email automation | C28: commercial | D28: Make More Money While You Sleep With Kajabi Automation | E28: kajabi-email-automation | F28: Medium | H28: C3 | I28: https://theeduassist.com/blog/make-more-money-while-you-sleep-with-kajabi-email-automation/
B29: kajabi crm integration | C29: commercial | D29: Best ways to link your CRM to Kajabi right now | E29: kajabi-crm-integration | F29: Low | H29: C4 | I29: https://theeduassist.com/uncategorized/kajabi-crm-integration/
B30: kajabi sales automation | C30: informational | D30: Your Kajabi Sales Funnel is Broken: Here is the Fix | E30: kajabi-sales-automation | F30: Low | H30: C3 | I30: https://theeduassist.com/blog/kajabi-sales-automation-why-your-sales-funnel-is-broken-and-how-to-fix-it/
B31: kajabi affiliate marketing setup | C31: transactional | D31: The easy guide to finding your first Kajabi affiliates | E31: kajabi-affiliate-marketing-setup | F31: Medium | H31: C4 | I31: https://theeduassist.com/blog/kajabi-affiliate-marketing-setup/
B32: kajabi pipeline setup | C32: informational | D32: The Simple Way to Automate Your Sales With Kajabi Pipelines | E32: kajabi-pipeline-setup | F32: Medium | H32: C2 | I32: https://theeduassist.com/blog/kajabi-pipeline-setup/
B33: kajabi email campaigns | C33: informational | D33: Your guide to Kajabi emails that people love to read | E33: kajabi-email-campaigns | F33: Low | H33: C1 | I33: https://theeduassist.com/uncategorized/kajabi-email-campaigns/
B34: kajabi automation workflows | C34: commercial | D34: The best way to welcome new members on autopilot | kajabi automation workflows | E34: kajabi-automation-workflows | F34: Low | H34: C5
B35: kajabi vs clickfunnels | C35: navigational | D35: Kajabi vs ClickFunnels: Which One Actually Makes You Money | E35: kajabi-vs-clickfunnels | F35: High | H35: C5
B36: kajabi launch strategy | C36: commercial | D36: How to launch your Kajabi course without the stress | E36: kajabi-launch-strategy | F36: Low | H36: C4 | I36: https://theeduassist.com/uncategorized/kajabi-launch-strategy/
A38: Kajabi SEO & Growth Services | B38: kajabi seo services | C38: commercial | D38: Kajabi SEO Services to Grow Organic Traffic | E38: kajabi-seo-services | F38: Medium | H38: C5
B39: kajabi seo optimization | C39: informational | D39: Kajabi SEO Optimization Guide for Beginners | E39: kajabi-seo-optimization | F39: Medium | H39: C3
B40: kajabi blogging strategy | C40: informational | D40: Kajabi Blogging Strategy for Course Creators | E40: kajabi-blogging-strategy | F40: Low | H40: C4
B41: kajabi website speed optimization | C41: commercial | D41: Kajabi Website Speed Optimization Tips | E41: kajabi-website-speed-optimization | F41: Low | H41: C1
B42: kajabi keyword research | C42: informational | D42: Kajabi Keyword Research for Higher Rankings | E42: kajabi-keyword-research | F42: Low | H42: C4
B43: kajabi organic traffic growth | C43: commercial | D43: How to Grow Organic Traffic on Kajabi | E43: kajabi-organic-traffic-growth | F43: Low | H43: C1
B44: kajabi conversion optimization | C44: commercial | D44: Kajabi Conversion Optimization Best Practices | E44: kajabi-conversion-optimization | F44: Medium | H44: C4
B45: kajabi seo audit | C45: transactional | D45: Kajabi SEO Audit Services for Online Businesses | E45: kajabi-seo-audit | F45: Low | H45: C3
B46: kajabi google analytics integration | C46: navigational | D46: Kajabi Google Analytics Integration Guide | E46: kajabi-google-analytics-integration | F46: Medium | H46: C4
B47: kajabi content marketing | C47: commercial | D47: Kajabi Content Marketing Strategies That Work | E47: kajabi-content-marketing | F47: Low
A50: Kajabi Support & Management Services
B51: kajabi virtual assistant services | C51: commercial | D51: Kajabi Virtual Assistant Services for Creators | E51: kajabi-virtual-assistant-services | F51: Low | G51: Learn what a Kajabi Virtual Assistant does, the tasks they can handle, and how to find, evaluate, and hire the right VA for your online course business. | H51: C3 | I51: https://www.theeduassist.com/blog/kajabi-virtual-assistant/
B52: kajabi technical support | C52: transactional | D52: Kajabi Technical Support for Online Businesses | E52: kajabi-technical-support | F52: Medium | G52: Learn how to get Kajabi technical support and troubleshoot common issues with payments, course access, email delivery, websites, and integrations. | H52: C3 | I52: https://www.theeduassist.com/blog/kajabi-technical-support/
B53: kajabi maintenance services | C53: commercial | D53: Kajabi Maintenance Services for Smooth Operations | E53: kajabi-maintenance-services | F53: Low
B54: kajabi account setup | C54: transactional | D54: Kajabi Account Setup Guide for Beginners | E54: kajabi-account-setup | F54: Low
B55: kajabi integration services | C55: commercial | D55: Kajabi Integration Services for Business Automation | E55: kajabi-integration-services | F55: Medium
B56: kajabi troubleshooting | C56: informational | D56: Common Kajabi Troubleshooting Issues and Fixes | E56: kajabi-troubleshooting | F56: Low
B57: kajabi customer support outsourcing | C57: commercial | D57: Kajabi Customer Support Outsourcing Benefits | E57: kajabi-customer-support-outsourcing | F57: Low
B58: kajabi admin support | C58: commercial | D58: Kajabi Admin Support for Scaling Businesses | E58: kajabi-admin-support | F58: Low
B59: kajabi help center | C59: navigational | D59: How to Use the Kajabi Help Center Efficiently | E59: kajabi-help-center | F59: High
B60: kajabi migration services | C60: transactional | D60: Kajabi Migration Services for Course Platforms | E60: kajabi-migration-services | F60: Medium
A108: Keywords
A109: Keywords | B109: Intent | C109: Volumn | D109: KD % | E109: CPC | F109: Com. | I109: Results | M109: updated
A110: kajabi | B110: Navigational | C110: 40500 | D110: 73 | E110: 2.95 | F110: 0.62 | H110: Sitelinks, Video, Video carousel, People also ask, Related searches, Ads top, Ads bottom | I110: 2090000 | M110: Last week
A111: kajabi online course platform | B111: Informational | C111: 18100 | D111: 28 | E111: 0 | F111: 0 | H111: Sitelinks, Video, Video carousel, People also ask, Discussions and forums, Related searches, Ads bottom | I111: 429000 | M111: 2 weeks
A112: kajabi login | B112: Navigational, Transactional | C112: 14800 | D112: 44 | E112: 0.04 | F112: 0.09 | H112: Sitelinks, Video, People also ask, Related searches | I112: 152 | M112: Last week
A113: kajabi pricing | B113: Navigational | C113: 3600 | D113: 29 | E113: 6.78 | F113: 0.77 | H113: Sitelinks, AI Overview, Video, Video carousel, People also ask, Related searches | I113: 117 | M113: 2 weeks
A114: kajabi news | B114: Informational | C114: 2400 | D114: 22 | E114: 5.08 | F114: 0.16 | H114: AI Overview, Video, Video carousel, People also ask, Related searches | I114: 228000 | M114: 2 weeks
A115: why does kajabi say 0 delivered emails | B115: Informational | C115: 1900 | D115: 22 | E115: 0 | F115: 0 | H115: AI Overview, Video, Related searches | I115: 95600 | M115: 1 month
A116: manychat kajabi integration | C116: 1600 | E116: 0 | F116: 0
A117: kajabi app | B117: Informational | C117: 1000 | D117: 30 | E117: 2.42 | F117: 0.35 | H117: AI Overview, Video, Related searches, See results about | I117: 155 | M117: 1 month
A118: kajabi log in | B118: Navigational, Transactional | C118: 1000 | D118: 29 | E118: 0.04 | F118: 0.09 | H118: Sitelinks, Video, Related searches | I118: 2220000 | M118: 1 month
A119: kajabi application | B119: Informational | C119: 720 | D119: 48 | E119: 2.42 | F119: 0.35 | H119: AI Overview, Video, Video carousel, Related searches, See results about, Ads top | M119: 1 month
A120: what is kajabi | B120: Informational, Navigational | C120: 720 | D120: 15 | E120: 2.79 | F120: 0.32 | H120: Sitelinks, AI Overview, Video, Video carousel, Related searches | M120: 1 month
A121: kajabi alternatives | B121: Informational, Commercial | C121: 590 | D121: 17 | E121: 10.81 | F121: 0.85 | H121: Sitelinks, AI Overview, Video, Video carousel, People also ask, Discussions and forums, Related searches | I121: 114 | M121: 1 month
A122: kajabi community | B122: Informational | C122: 590 | D122: 24 | E122: 1.98 | F122: 0.2 | H122: AI Overview, Video, Video carousel, Short videos, Related searches, Ads bottom | I122: 1400000 | M122: 1 month
A123: how much is it to use kajabi branded app | B123: Informational | C123: 480 | D123: 18 | E123: 0 | F123: 0 | H123: Sitelinks, AI Overview, Video, Video carousel, People also ask, Related searches | I123: 585000 | M123: 3 weeks
A124: kajabi alternative | B124: Informational, Commercial | C124: 480 | D124: 6 | E124: 10.81 | F124: 0.85 | H124: Sitelinks, AI Overview, Video, Video carousel, Discussions and forums, Related searches | M124: 1 month
A125: kajabi product definition basic plan limitations | B125: Informational | C125: 480 | D125: 13 | E125: 0 | F125: 0 | H125: Sitelinks, AI Overview, Video, Related searches | M125: 1 month
A126: kajabi review | B126: Informational, Commercial | C126: 480 | D126: 10 | E126: 5.08 | F126: 0.48 | H126: Sitelinks, AI Overview, Video, Video carousel, People also ask, Discussions and forums, Related searches | I126: 988000 | M126: 2 weeks
A127: kajabi.com | B127: Navigational | C127: 480 | D127: 63 | E127: 2.56 | F127: 0.43 | H127: Sitelinks, Video, Video carousel, Ads bottom | I127: 2150000 | M127: 3 weeks
A128: kajabi careers | B128: Commercial | C128: 390 | D128: 15 | E128: 0 | F128: 0.02 | H128: Video, Jobs, Related searches | I128: 79 | M128: 3 weeks
A129: kajabi experts | B129: Commercial | C129: 390 | D129: 6 | E129: 9.76 | F129: 0.01 | H129: Video, Video carousel, People also ask, Related searches | I129: 114 | M129: 4 weeks
A130: kajabi vs clickfunnels | B130: Informational, Commercial | C130: 390 | D130: 5 | E130: 8.77 | F130: 0.52 | H130: Sitelinks, AI Overview, Image pack, Video, Video carousel, Related searches, Ads bottom | I130: 150000 | M130: 3 weeks
A131: kajabi vs teachable | B131: Informational, Commercial | C131: 390 | D131: 14 | E131: 7.49 | F131: 0.63 | H131: Sitelinks, AI Overview, Video, Video carousel, Related searches, Ads bottom, Ads middle | I131: 244000 | M131: 3 weeks
A132: kajabi vs thinkific | B132: Informational, Commercial | C132: 390 | D132: 17 | E132: 7.61 | F132: 0.76 | H132: Sitelinks, AI Overview, Video, Video carousel, Discussions and forums, Related searches | I132: 238000 | M132: 1 month
A133: kajabi website | B133: Navigational | C133: 390 | D133: 21 | E133: 6.62 | F133: 0.73 | H133: Video, Video carousel, Related searches, Ads bottom | M133: 1 month
A134: thinkific vs kajabi | B134: Informational, Commercial | C134: 390 | D134: 25 | E134: 7.61 | F134: 0.76 | H134: Sitelinks, AI Overview, Image pack, Video, People also ask, Discussions and forums, Related searches, Ads bottom | I134: 218000 | M134: 3 weeks
A135: kajabi competitors | B135: Informational | C135: 320 | D135: 19 | E135: 10.93 | F135: 0.88 | H135: Sitelinks, AI Overview, Video, Video carousel, Discussions and forums, Related searches, Ads bottom | I135: 84400 | M135: 3 weeks
A136: kajabi expert | B136: Informational | C136: 320 | D136: 13 | E136: 9.76 | F136: 0.01 | H136: Sitelinks, AI Overview, Video, Video carousel, Related searches | I136: 890000 | M136: 3 weeks
A137: kajabi logo | B137: Navigational | C137: 320 | D137: 18 | E137: 0 | F137: 0 | H137: Sitelinks, Image, Image pack, Video, Video carousel, Related searches, Ads bottom | M137: 1 month
A138: kartra vs kajabi | B138: Informational, Commercial | C138: 320 | D138: 3 | E138: 9.38 | F138: 0.61 | H138: Sitelinks, AI Overview, Video, Video carousel, People also ask, Related searches | I138: 94 | M138: 2 weeks
A139: my kajabi | B139: Navigational | C139: 320 | D139: 34 | E139: 3.18 | F139: 0.32 | H139: Video, Related searches | I139: 123 | M139: 1 month
A140: teachable vs kajabi | B140: Informational, Commercial | C140: 320 | D140: 5 | E140: 7.49 | F140: 0.63 | H140: Sitelinks, AI Overview, Video, Video carousel, Related searches | I140: 101 | M140: 1 month
A141: kajabi apps | B141: Informational | C141: 260 | D141: 26 | E141: 2.42 | F141: 0.35 | H141: AI Overview, Video, Video carousel, Related searches, Ads bottom | I141: 2030000 | M141: 1 month
A142: kajabi communities | B142: Navigational | C142: 260 | D142: 26 | E142: 1.98 | F142: 0.2 | H142: Image pack, Video, Video carousel, People also ask, Related searches, Ads bottom | I142: 1600000 | M142: 3 weeks
A143: kajabi cost | B143: Informational, Navigational | C143: 260 | D143: 28 | E143: 5.72 | F143: 0.72 | H143: Sitelinks, AI Overview, Video, Video carousel, People also ask, Related searches, Ads top, Ads middle | I143: 901000 | M143: 2 weeks
A144: kajabi courses | B144: Informational | C144: 260 | D144: 23 | E144: 5.91 | F144: 0.63 | H144: AI Overview, Video, Video carousel, Related searches | I144: 1360000 | M144: 3 weeks
A145: kajabi plans | B145: Informational, Navigational | C145: 260 | D145: 43 | E145: 5.18 | F145: 0.75 | H145: AI Overview, Video, Video carousel, People also ask, Related searches | I145: 119 | M145: 1 month
A146: kajabi promo code | B146: Informational, Transactional | C146: 260 | D146: 7 | E146: 3.98 | F146: 0.73 | H146: AI Overview, Video, Video carousel, Related searches | I146: 99 | M146: 1 month
A147: kajabi sign in | B147: Navigational, Transactional | C147: 260 | D147: 33 | E147: 0.07 | F147: 0.16 | H147: Sitelinks, Video, Related searches | I147: 106 | M147: 1 month
A148: kajabi templates | B148: Commercial | C148: 260 | D148: 23 | E148: 4.82 | F148: 1 | H148: Sitelinks, Image, Image pack, Video, Related searches | I148: 546000 | M148: 1 month
A149: kajabi website examples | B149: Commercial | C149: 260 | D149: 7 | E149: 6.45 | F149: 0.52 | H149: Sitelinks, Video, Related searches, Ads bottom | I149: 301000 | M149: 3 weeks
... A155: podia vs kajabi | B155: Informational, Commercial | C155: 210 | D155: 9 | E155: 10.19 | F155: 0.68 | H155: Sitelinks, AI Overview, Video, Video carousel, Discussions and forums, Related searches, Ads bottom | I155: 87300 | M155: 1 month
A156: sites like kajabi | B156: Informational, Commercial | C156: 210 | D156: 6 | E156: 18.84 | F156: 0.71 | H156: Sitelinks, AI Overview, Video, Video carousel, Discussions and forums, Related searches | M156: 1 month
A157: circle vs kajabi | B157: Informational, Commercial | C157: 170 | D157: 0 | E157: 9.15 | F157: 0.69 | H157: Sitelinks, AI Overview, Video, Video carousel, Related searches | I157: 105 | M157: 1 month
...

Sheet Backlinks
A1: TOP EDUCATIONAL GUEST POST SITES | S1: Broken Links
M3: everyone kind write article on th ebacklinks and then mention belows
A4: SR NO | B4: WEBSITE | C4: Email/ Website | D4: DOMAIN AUTHORITY | E4: Monthly Traffic | F4: Link Type | G4: Date Sent | H4: Status | I4: Follow-up Date | J4: Notes | K4: Anchor text | L4: Link | M4: article written by | N4: article written by | O4: article written by | P4: article written by | Q4: article written by | S4: Sr. No | T4: Referring Website | U4: To Competitor website | V4: Link type | W4: Reach out | X4: Status
A5: 1 | B5: empowerly.com | C5: jose.a@empowerly.com | D5: 53 | E5: 125K | G5: 45957 | H5: Pending | I5: 45964 | J5: Guest post form on site, AI learning niche | S5: 1 | T5: https://blog.flipsnack.com/how-to-create-a-product-catalog/ | U5: https://ecommerce.folio3.com/wordpress-development-services/ | V5: Removed by reffering website
A6: 2 | B6: mediapost.com | C6: joe@mediapost.com | D6: 53 | E6: 97.8k | F6: Maybe no follow | J6: Focus on AI video tools, | S6: 2 | T6: https://www.fuseuniversal.com/ | U6: https://elearningindustry.com/directory/elearning-software/fuse/reviews | V6: Removed by reffering website
A7: 3 | B7: https://elearningindustry.com/ | C7: https://elearningindustry.com/post-here | D7: 54 | E7: 233.7k | G7: 46186 | H7: Published | I7: 1st July 2026 | J7: Business / tech audience, DA 40+ | K7: Framework on eLearning Technology and Data Trends | L7: https://www.theeduassist.com/blog/elearning-2026-how-technology-is-reshaping-education/ | M7: C2 | N7: C4
A8: 4 | B8: https://trainingindustry.com/ | C8: editor@trainingindustry.com | D8: 45 | E8: 37.9k | J8: AI tools niche
A9: 5 | B9: https://www.edsurge.com/ | C9: https://www.edsurge.com/submission-guidelines | D9: 46 | E9: 44.1k | H9: Pending | J9: Check “Write for Us” page
A10: 6 | B10: https://medium.com | C10: https://medium.com/new-story | D10: 97 | E10: 54.2M | G10: 46200 | H10: Published | J10: Education / eLearning niche, write-for-us page | K10: this comprehensive comparison by TheEduAssist. | L10: https://medium.com/@sofiaarif73/stop-comparing-learndash-and-kajabi-like-theyre-the-same-product-b95b577748fc?sharedUserId=sofiaarif73 | M10: C2
A11: 7 | B11: https://bigthink.com/ | C11: info@bigthink.com | D11: 58 | E11: 303.3k | J11: eLearning, online courses, professional development
A12: 8 | B12: smartbrief.com/ | C12: https://www.smartbrief.com/write-for-us | D12: 44 | E12: 18.1k | H12: Pending | J12: Education innovation / EdTech audience | M12: C1
A13: 9 | B13: https://www.greatschoolspartnership.org/news/write-for-us/ | C13: info@greatschoolspartnership.org | D13: 35 | E13: 12.3k | J13: Instructional design / eLearning, use submission form
A14: 10 | B14: https://www.oneeducation.org.uk/write-for-us/ | C14: partner@oneeducation.org.uk | D14: 38 | E14: 68.3k | J14: Pakistani education / eLearning niche
A15: 11 | B15: https://educationhq.com/ | C15: https://educationhq.com/write-for-us/ | D15: 32 | E15: 3.1k | G15: 45966 | H15: Submitted | J15: Article: How The EduAssist Is Empowering Pakistan’s Students Through Smarter E-Learning Solutions
A16: 12 | B16: https://www.proprofs.com/ | C16: https://www.proprofs.com/c/write-for-us/ | D16: 53 | E16: 652.6k | F16: Maybe no follow
A17: 13 | B17: https://help.ezycourse.com/ | C17: https://help.ezycourse.com/blogging-guidelines | D17: 30 | E17: 2.9k
A18: 14 | B18: https://testfellow.com/write-for-us/ | C18: info@testfellow.com | D18: 19 | E18: 4.7k
A19: 15 | B19: https://education.clickdo.co.uk/ | C19: https://education.clickdo.co.uk/write-for-us/ | D19: 34 | E19: 15.9K | F19: Do Follow
A20: 16 | B20: https://www.efrontlearning.com/blog/contribute-to-the-elearning-community | C20: efronters [at] gmail.com | D20: 35 | E20: 4.7k | H20: Pending | M20: C1
A21: 17 | B21: https://bridgingpointsmedia.com/ | C21: https://www.rightpatient.com/guest-posting-content-submission-guidelines/ | D21: 32 | E21: 8k | F21: 2 Do follow
A22: 18 | B22: https://www.unboundb2b.com/ | C22: https://www.unboundb2b.com/write-for-us/ | D22: 36 | E22: 7.1k
A23: 19 | B23: https://trainingexpress.org.uk/ | C23: partner@trainingexpress.org.uk | D23: 35 | E23: 33.3k
A24: 20 | B24: https://teslontario.org/ | C24: https://teslontario.org/publications/write-for-us/ | D24: 31 | E24: 4.7k
A25: 21 | B25: https://learningforward.org/the-learning-professional | C25: https://learningforward.org/the-learning-professional/write-for-us/ | D25: 39 | E25: 8.6k
A26: 22 | B26: https://www.mygreatlearning.com/ | C26: https://www.mygreatlearning.com/blog/become-a-contributor/ | D26: 64 | E26: 95.2k
A27: 23 | B27: https://www.classcentral.com/write-for-us | C27: careers@classcentral.com | D27: 55 | E27: 379.8k
A28: 24 | B28: https://studentsforliberty.org/ | C28: https://studentsforliberty.org/write-for-us/ | D28: 39 | E28: 24.2k
A29: 25 | B29: https://articlereword.com/write-for-us/ | C29: contact@articlereword.com. | D29: 23 | E29: 9.5k
A30: 26 | B30: https://www.sitepoint.com/ | C30: https://www.sitepoint.com/write-for-us/ | D30: 53 | E30: 166.8k
A31: 27 | B31: https://expd.uw.edu/write-for-us-sponsored-posts/ | C31: netherlandsmark@proton.me | D31: 69 | E31: 2M | F31: Check Paid or unpaid
A32: 28 | B32: https://blogarena360.com/ | C32: https://blogarena360.com/write-for-us/ | D32: 20 | E32: 548 | F32: Do follow
A33: 29 | B33: https://360learning.com/ | C33: https://360learning.com/blog/write-for-us/ | D33: 46 | E33: 68.5k | F33: Do follow
A34: 30 | B34: https://express247.home.blog/ | C34: pepelancer7@gmail.com | D34: 64 | E34: 1.6M | H34: Pending | M34: C1
A35: 31 | B35: https://www.english-efl.com/submit-guest-post/ | C35: info@english-efl.com | D35: 26 | E35: 27.2k | F35: Do follow
A36: 32 | B36: https://www.proprofs.com/ | C36: https://www.proprofs.com/c/submit-an-article-on-training/ | D36: 54 | E36: 761.2k
A37: 33 | B37: https://bemoacademicconsulting.com/ | C37: https://bemoacademicconsulting.com/write-for-us | D37: 39 | E37: 63k
A38: 34 | B38: https://empowerly.com/guest-post-program/ | C38: jose.a@empowerly.com. | D38: 43 | E38: 113.3k | F38: 2 Do folow
A39: 35 | B39: https://www.janets.org.uk/ | C39: https://www.janets.org.uk/write-for-us/ | D39: 31 | E39: 8.7k | H39: Pending | M39: C1
A69: Referring Domain1 â€“ 100 (4,253) | B69: Link | C69: AS | D69: Monthly Visits | E69: Matches | F69: theeduassist.comtheeduassist.com | G69: gpstrategies.comgpstrategies.com | H69: learningeverest.comlearningeverest.com | I69: elearning.companyelearning.company | K69: thelearningedge.euthelearningedge.eu | N69: article written by | O69: article written by | P69: article written by | Q69: article written by | R69: article written by
A70: adobe.com | B70: https://airtable.com/apphWUswjmwIry4SZ/pagM66mocklT7qYQM/form#sa_src=web-messaging | C70: 100 | D70: 461M | E70: 46086 | F70: 0 | G70: 1 | H70: 12 | I70: 2 | K70: 0
A71: apple.com | C71: 100 | D71: 850M | E71: 46027 | F71: 0 | G71: 17 | H71: 0 | I71: 0 | K71: 0
A72: google.com | C72: 100 | D72: 112B | E72: 46027 | F72: 0 | G72: 2 | H72: 0 | I72: 0 | K72: 0
A73: indeed.com | C73: 100 | D73: 444M | E73: 46027 | F73: 0 | G73: 23 | H73: 0 | I73: 0 | K73: 0
A74: pinterest.com | C74: 100 | D74: 1.4B | E74: 46027 | F74: 0 | G74: 0 | H74: 3 | I74: 0 | K74: 0
A75: theguardian.com | C75: 100 | D75: 333M | E75: 46027 | F75: 0 | G75: 1 | H75: 0 | I75: 0 | K75: 0
A76: wikipedia.org | B76: https://en.wikisource.org/w/index.php?title=Talk:Community_Portal&action=edit&redlink=1 | C76: 100 | D76: 4.9B | E76: 46027 | F76: 0 | G76: 10 | H76: 0 | I76: 0 | K76: 0
A77: investing.com | C77: 98 | D77: 212M | E77: 46027 | F77: 0 | G77: 13 | H77: 0 | I77: 0 | K77: 0
A78: medium.com | B78: https://medium.com/ | C78: 97 | D78: 116M | E78: 46027 | F78: 0 | G78: 5 | H78: 0 | I78: 0 | K78: 0 | N78: C1 | O78: C5 | P78: C3 | Q78: C5
A79: ca.gov | C79: 96 | D79: 109M | E79: 46027 | F79: 0 | G79: 4 | H79: 0 | I79: 0 | K79: 0
A80: cnbc.com | C80: 96 | D80: 118M | E80: 46027 | F80: 0 | G80: 3 | H80: 0 | I80: 0 | K80: 0
A81: blog.naver.com | C81: 95 | D81: 155M | E81: 46027 | F81: 0 | G81: 1 | H81: 0 | I81: 0 | K81: 0
A82: forbes.com | C82: 94 | D82: 83.4M | E82: 46027 | F82: 0 | G82: 5 | H82: 0 | I82: 0 | K82: 0
A83: businessinsider.com | B83: www.emarketer.com | C83: 91 | D83: 77.3M | E83: 46027 | F83: 0 | G83: 8 | H83: 0 | I83: 0 | K83: 0
A84: nasa.gov | C84: 91 | D84: 31.4M | E84: 46027 | F84: 0 | G84: 1 | H84: 0 | I84: 0 | K84: 0
A85: slideshare.net | B85: https://www.slideshare.net/login | C85: 91 | D85: 37.3M | E85: 46027 | F85: 0 | G85: 13 | H85: 0 | I85: 0 | K85: 0 | N85: C5 | O85: C3 | P85: C5
A86: mynavi.jp | C86: 89 | D86: 40.8M | E86: 46027 | F86: 0 | G86: 1 | H86: 0 | I86: 0 | K86: 0
A87: nbcnews.com | B87: https://together.nbcuni.com/nbcu-content/ | C87: 89 | D87: 131M | E87: 46027 | F87: 0 | G87: 1 | H87: 0 | I87: 0 | K87: 0
A88: substack.com | B88: https://substack.com/ | C88: 85 | D88: 136M | E88: 46086 | F88: 0 | G88: 6 | H88: 10 | I88: 4 | K88: 0 | N88: C3 | O88: C5 | P88: C5
A89: business-standard.com | B89: feedback@business-standard.com | C89: 84 | D89: 6.9M | E89: 46027 | F89: 0 | G89: 3 | H89: 0 | I89: 0 | K89: 0
A90: rbc.ru | C90: 81 | D90: 40.7M | E90: 46027 | F90: 0 | G90: 0 | H90: 1 | I90: 0 | K90: 0
A91: behance.net | C91: 80 | D91: 52.7M | E91: 46027 | F91: 0 | G91: 1 | H91: 0 | I91: 0 | K91: 0 | N91: C3
A92: libretexts.org | C92: 80 | D92: 9.7M | E92: 46027 | F92: 0 | G92: 1 | H92: 0 | I92: 0 | K92: 0
A93: atlassian.com | C93: 79 | D93: 42.5M | E93: 46027 | F93: 0 | G93: 1 | H93: 0 | I93: 0 | K93: 0
A94: springer.com | C94: 79 | D94: 51.3M | E94: 46027 | F94: 0 | G94: 1 | H94: 0 | I94: 0 | K94: 0
A95: bbb.org | C95: 78 | D95: 17.6M | E95: 46027 | F95: 0 | G95: 1 | H95: 0 | I95: 0 | K95: 0
A96: michigan.gov | C96: 78 | D96: 28.6M | E96: 46027 | F96: 0 | G96: 2 | H96: 0 | I96: 0 | K96: 0
A97: glassdoor.com | C97: 77 | D97: 32.9M | E97: 46058 | F97: 0 | G97: 7 | H97: 0 | I97: 2 | K97: 0
A98: forbesjapan.com | C98: 77 | D98: 5M | E98: 46027 | F98: 0 | G98: 1 | H98: 0 | I98: 0 | K98: 0
A99: pixnet.net | C99: 77 | D99: 10.3M | E99: 46027 | F99: 0 | G99: 3 | H99: 0 | I99: 0 | K99: 0
A100: osu.edu | C100: 76 | D100: 8.8M | E100: 46058 | F100: 0 | G100: 5 | H100: 1 | I100: 0 | K100: 0
A101: aptoide.com | C101: 76 | D101: 35.5M | E101: 46027 | F101: 0 | G101: 3 | H101: 0 | I101: 0 | K101: 0
A102: britishcouncil.org | C102: 76 | D102: 12.3M | E102: 46027 | F102: 0 | G102: 3 | H102: 0 | I102: 0 | K102: 0
A103: cisco.com | C103: 76 | D103: 15.2M | E103: 46027 | F103: 0 | G103: 1 | H103: 0 | I103: 0 | K103: 0
... A109: nextdoor.com | C109: 73 | D109: 151M | E109: 46027 | F109: 0 | G109: 3 | H109: 0 | I109: 0 | K109: 0
A110: crunchbase.com | C110: 72 | D110: 5.1M | E110: 46058 | F110: 0 | G110: 9 | H110: 0 | I110: 1 | K110: 0 | N110: C5 | O110: C3
A111: ieee.org | C111: 72 | D111: 20.6M | E111: 46027 | F111: 0 | G111: 1 | H111: 0 | I111: 0 | K111: 0
A112: marketbeat.com | C112: 72 | D112: 6.7M | E112: 46027 | F112: 0 | G112: 1 | H112: 0 | I112: 0 | K112: 0
A113: marketscreener.com | C113: 72 | D113: 8.8M | E113: 46027 | F113: 0 | G113: 14 | H113: 0 | I113: 0 | K113: 0
A114: sketchfab.com | C114: 72 | D114: 20.6M | E114: 46027 | F114: 0 | G114: 1 | H114: 0 | I114: 0 | K114: 0
A115: wikibooks.org | C115: 72 | D115: 2.9M | E115: 46027 | F115: 0 | G115: 2 | H115: 0 | I115: 0 | K115: 0
A116: yell.com | C116: 72 | D116: 3.2M | E116: 46027 | F116: 0 | G116: 2 | H116: 0 | I116: 0 | K116: 0
A117: glassdoor.co.in | C117: 71 | D117: 6.8M | E117: 46027 | F117: 0 | G117: 4 | H117: 0 | I117: 0 | K117: 0
A118: lww.com | C118: 70 | D118: 7.4M | E118: 46027 | F118: 0 | G118: 1 | H118: 0 | I118: 0 | K118: 0
A119: zoominfo.com | C119: 70 | D119: 17.5M | E119: 46027 | F119: 0 | G119: 1 | H119: 0 | I119: 0 | K119: 0
A120: amazonaws.com | C120: 69 | D120: 132M | E120: 46027 | F120: 0 | G120: 6 | H120: 0 | I120: 0 | K120: 0
A121: findlaw.com | C121: 69 | D121: 5.5M | E121: 46027 | F121: 0 | G121: 3 | H121: 0 | I121: 0 | K121: 0
A122: steemit.com | C122: 69 | D122: 3.5M | E122: 46027 | F122: 0 | G122: 1 | H122: 0 | I122: 0 | K122: 0 | N122: C3
A123: telkomuniversity.ac.id | C123: 68 | D123: 2.7M | E123: 46027 | F123: 0 | G123: 1 | H123: 0 | I123: 0 | K123: 0
A124: barchart.com | C124: 67 | D124: 8M | E124: 46027 | F124: 0 | G124: 1 | H124: 0 | I124: 0 | K124: 0
A125: dev.to | C125: 67 | D125: 9.3M | E125: 46027 | F125: 0 | G125: 0 | H125: 17 | I125: 0 | K125: 0
A126: tunein.com | C126: 67 | D126: 4M | E126: 46027 | F126: 0 | G126: 1 | H126: 0 | I126: 0 | K126: 0
A127: updatestar.com | C127: 67 | D127: 8.5M | E127: 46027 | F127: 0 | G127: 27 | H127: 0 | I127: 0 | K127: 0
A128: ankara.edu.tr | C128: 66 | D128: 2.5M | E128: 46027 | F128: 0 | G128: 0 | H128: 0 | I128: 1 | K128: 0
A129: builtin.com | C129: 66 | D129: 3.3M | E129: 46027 | F129: 0 | G129: 2 | H129: 0 | I129: 0 | K129: 0
A130: entrepreneur.com | C130: 66 | D130: 3.2M | E130: 46027 | F130: 0 | G130: 2 | H130: 0 | I130: 0 | K130: 0
A131: g2.com | C131: 66 | D131: 3.9M | E131: 46027 | F131: 0 | G131: 4 | H131: 0 | I131: 0 | K131: 0
A132: glassdoor.co.uk | C132: 66 | D132: 6.2M | E132: 46027 | F132: 0 | G132: 5 | H132: 0 | I132: 0 | K132: 0
A133: iaea.org | C133: 66 | D133: 1.3M | E133: 46027 | F133: 0 | G133: 4 | H133: 0 | I133: 0 | K133: 0
A134: informer.com | C134: 66 | D134: 6M | E134: 46027 | F134: 0 | G134: 3 | H134: 0 | I134: 0 | K134: 0
... A170: boston.gov | C170: 56 | D170: 1.2M | E170: 46027 | F170: 0 | G170: 2 | H170: 0 | I170: 0 | K170: 0
...

Sheet communitiesforumsgroups
A1: Group Name | B1: Platform | C1: Category | D1: Region | E1: Link | F1: Members/ Visitors | G1: Post Count | H1: Legacy list — use the new “Communities & Forums” sheet for ongoing work. | I1: =HYPERLINK("#'Guide'!A1","Open Guide") -> Open Guide
A2: Articulate Storyline Community | B2: Articulate | C2: EdTech Communities | D2: Global | E2: https://community.articulate.com
A3: Adobe Captivate Community | B3: Adobe | C3: EdTech Communities | D3: Global | E3: https://elearning.adobe.com
A4: Moodle Community Forum | B4: Moodle | C4: EdTech Communities | D4: Global | E4: https://moodle.org/community
A5: Canvas LMS Community | B5: Canvas | C5: EdTech Communities | D5: Global | E5: https://community.canvaslms.com
A6: Thinkific Instructor Community | B6: Thinkific | C6: EdTech Communities | D6: Global | E6: https://www.thinkific.com/community
A7: Udemy Instructor Community | B7: Udemy | C7: EdTech Communities | D7: Global | E7: https://community.udemy.com
A8: Coursera Instructor Hub | B8: Coursera | C8: EdTech Communities | D8: Global | E8: https://teach.coursera.org
A9: IDOL Courses Community | B9: IDOL | C9: EdTech Communities | D9: Global | E9: https://www.idolcourses.com
A10: ATD (Association for Talent Development) | B10: ATD | C10: Professional Group | D10: Global | E10: https://www.td.org
A11: eLearning Guild | B11: LSG | C11: Professional Group | D11: Global | E11: https://www.learningguild.com
A12: Skillshare Teachers Community | B12: Skillshare | C12: Professional Platform | D12: Global | E12: https://community.skillshare.com | F12: Site not reachable
A13: Dribbble (Course Designers) | B13: Dribbble | C13: Professional Platform | D13: Global | E13: https://dribbble.com/tags/elearning
A14: Behance — eLearning & UX | B14: Behance | C14: Professional Platform | D14: Global | E14: https://www.behance.net/search/projects?search=elearning
A15: Thinkific Global Community | B15: Facebook | C15: Social Media Groups | D15: Global | E15: https://www.facebook.com/groups/thinkific | F15: 31.4K Members | G15: 60 in the last month
A16: Instructional Design and eLearning Community: Upskilling and Job Transition | B16: Facebook | C16: Social Media Groups | D16: Global | E16: https://www.facebook.com/groups/438158560473425 | F16: 6.6K Members | G16: 36 in last month
A17: Kajabi Support Community | B17: Facebook | C17: Social Media Groups | D17: Global | E17: https://www.facebook.com/groups/kajabisupportcommunity | F17: 1.6K Members | G17: 20 in last month
A18: coaches and online course creators | B18: Facebook | C18: Social Media Groups | D18: Global | E18: https://www.facebook.com/groups/535521845015700 | F18: 1.2K Members | G18: 147 in last month
A19: Teaching & Learning with AI | B19: Facebook | C19: Social Media Groups | D19: Global | E19: https://www.facebook.com/groups/teachandlearnwithai | F19: 28.2K Members | G19: 49 in the last month
A20: Learning + Development/Corporate Training Professionals | B20: Facebook | C20: Social Media Groups | D20: Global | E20: https://www.facebook.com/groups/158392293687215 | F20: 561 Members | G20: 53 in the last month
A21: Instructional Designers' Hub | B21: LinkedIn | C21: LinkedIn Groups | D21: Global | E21: https://www.linkedin.com/groups/14405354/ | F21: 4.3K Members | G21: 51 in the last month
A22: eLearning Companies | B22: LinkedIn | C22: LinkedIn Groups | D22: Global | E22: https://www.linkedin.com/groups/2623646/ | F22: 43K Members | G22: 480 in the last month
A23: Online Course Builders 🎓 (Udemy, Teachable, Thinkific, Skillshare + Online Learning Platforms) | B23: LinkedIn | C23: LinkedIn Groups | D23: Global | E23: https://www.linkedin.com/groups/7021598/ | F23: 1,811 Members | G23: Request pending
A24: The LDC's Learning and Development Forum | B24: LinkedIn | C24: LinkedIn Groups | D24: Global | E24: https://www.linkedin.com/groups/14028689/ | F24: 889 Members | G24: Request pending
A25: Education Technology & eLearning Professionals: Tips & Best Teaching Practices | B25: LinkedIn | C25: LinkedIn Groups | D25: Global | E25: https://www.linkedin.com/groups/2127994/ | F25: 19,709 Members | G25: Request pending
A26: AI‑Powered Interactive & Immersive eLearning | B26: LinkedIn | C26: LinkedIn Groups | D26: Global | E26: https://www.linkedin.com/groups/12597037/ | F26: 1874 Members | G26: 31 in the last month
... A34: Quora — Online Course Creation | B34: Quora | C34: Discussion Communities | D34: Global | E34: https://www.quora.com/topic/Online-Courses | F34: 72.8K followers | G34: not available
A35: r/Canva | B35: Reddit | C35: Discussion Communities | D35: Global | E35: https://www.reddit.com/r/canva/ | F35: 163 k followers | G35: 801
A36: r/InstructionalDesign | B36: Reddit | C36: Discussion Communities | D36: global | E36: https://www.reddit.com/r/instructionaldesign/ | F36: 20 k followers | G36: 609

Sheet Competitor List
A1: Competitor List Updated 12-9-26 | I1: =HYPERLINK("#'Guide'!A1","Open Guide") -> Open Guide
A4: SR. NO | B4: WEBSITE URL | C4: ORGANIC TRAFFIC | D4: ORGANIC KEYWORDS | E4: DR | F4: BACKLINKS | G4: AI VISIBLITY | H4: TOTAL MENTIONS BY AI
A5: 1 | B5: https://elearning.folio3.com | C5: 338 | D5: 930 | E5: 74 | F5: 385 | G5: 19 | H5: 515
A6: 2 | B6: https://www.kytewayelearning.com/ | C6: 347 | D6: 907 | E6: 21 | F6: 15K | G6: 22 | H6: 32
A7: 3 | B7: https://www.eidesign.net/ | C7: 0 | D7: 2.5K | E7: 56 | F7: 19K | G7: 21 | H7: 40
A8: 4 | B8: https://bluecarrot.io/ | C8: 1.6k | D8: 2.0K | E8: 51 | F8: 2.7K | G8: 15 | H8: 47
A9: 5 | B9: https://elearning.company/ | C9: 122 | D9: 446 | E9: 35 | F9: 2.5K | G9: 14 | H9: 3
A10: 6 | B10: https://www.acadecraft.com/ | C10: 1.4k | D10: 6K | E10: 38 | F10: 9.9K | G10: 25 | H10: 34
A11: 7 | B11: https://qquench.ai/our-services/e-learning/ | C11: 0 | D11: 39 | E11: 2.3 | F11: 242 | G11: 0 | H11: 0
A12: 8 | B12: https://redchipsolutions.com/ | C12: 4 | D12: 225 | E12: 19 | F12: 1.4K | G12: 14 | H12: 0
A13: 9 | B13: https://piogroup.net/ | C13: 14 | D13: 1.2K | E13: 29 | F13: 1.9K | G13: 14 | H13: 2
A14: 10 | B14: https://www.learningeverest.com/ | C14: 3.4k | D14: 9.5K | E14: 35 | F14: 8.1K | G14: 16 | H14: 19
A15: 11 | B15: https://stratbeans.com/ | C15: 587 | D15: 2.4K | E15: 46 | F15: 11K | G15: 14 | H15: 21
A16: 12 | B16: https://www.swiftelearningservices.com/ | C16: 1.4k | D16: 4.3K | E16: 37 | F16: 19K | G16: 18 | H16: 37
A17: 13 | B17: https://www.allencomm.com/ | C17: 7.4k | D17: 3.6K | E17: 65 | F17: 9.7K | G17: 21 | H17: 189
A18: 14 | B18: https://www.gpstrategies.com/ | C18: 4.5k | D18: 6.4K | E18: 69 | F18: 237K | G18: 18 | H18: 280
A19: 15 | B19: https://flearningstudio.com/ | C19: 1.1k | D19: 4.3K | E19: 38 | F19: 6.6K | G19: 14 | H19: 22
A20: 16 | B20: http://www.jupiter2000.com/training | C20: 0 | D20: 28 | E20: 1.7 | F20: 100 | G20: 0 | H20: 0
A21: 17 | B21: https://legacylearningconsultingllc.com/ | C21: 0 | D21: 4 | E21: 0 | F21: 1.3k | G21: 0 | H21: 0
A22: 18 | B22: https://www.chameleon-agency.com/ | C22: 0 | D22: 7 | E22: 37 | F22: 747 | G22: 14 | H22: 1
A23: 19 | B23: https://www.vivifysol.com/ | C23: 0 | D23: 19 | E23: 0.6 | F23: 214 | G23: 0 | H23: 0
A24: 20 | B24: https://5kwebtech.com/ | C24: 0 | D24: 1 | E24: 0.1 | F24: 445 | G24: 0 | H24: 0
A25: 21 | B25: https://thelearningedge.eu/ | C25: 3 | D25: 14 | E25: 16 | F25: 622 | G25: 14 | H25: 1
A26: 22 | B26: https://tidalvisuals.com/ | C26: 0 | D26: 1 | E26: 0 | F26: 587 | G26: 0 | H26: 0
A27: 23 | B27: https://esparkconsultants.com/ | C27: 54 | D27: 14 | E27: 3.3 | F27: 0 | G27: 14 | H27: 0
A28: 24 | B28: https://kaizenlearningservices.com/ | C28: 0 | D28: 0 | E28: 0 | F28: 373 | G28: 14 | H28: 0
A29: 25 | B29: https://elearn-experts.com/ | C29: 0 | D29: 1 | E29: 0 | F29: 414 | G29: 0 | H29: 0
A30: 26 | B30: https://cozyartzmedia.com/ | C30: 0 | D30: 1 | E30: 38 | F30: 491 | G30: 0 | H30: 0
A31: 27 | B31: https://ga-training.com/ | C31: 57 | D31: 20 | E31: 2.4 | F31: 564 | G31: 14 | H31: 0
A32: 28 | B32: http://palinfocom.com/ | C32: 473 | D32: 64 | E32: 10 | F32: 2.4k | G32: 0 | H32: 0
A33: 29 | B33: https://www.brewersassociation.org/edu/online-courses/ | C33: 345 | D33: 35k | E33: 78 | F33: 1.6M | G33: 26 | H33: 1.6k
A34: 30 | B34: https://maplecollabconsulting.com/ | C34: 0 | D34: 2 | E34: 0 | F34: 378 | G34: 0 | H34: 0
A35: 31 | B35: https://sdlcorp.in/ | C35: 0 | D35: 3 | E35: 10 | F35: 371 | G35: 0 | H35: 0
A36: 32 | B36: https://joyoptions.org/joy-e-learning-courses/ | C36: 0 | D36: 33 | E36: 6 | F36: 487 | G36: 14 | H36: 2
A37: 33 | B37: https://wizcabin.com/ | C37: 0 | D37: 75 | E37: 6 | F37: 1.8K | G37: 14 | H37: 2
A38: 34 | B38: https://jupitered.com/ | C38: 261.8K | D38: 6k | E38: 69 | F38: 87K | G38: 32 | H38: 120

Sheet Research Paper Links
A1: Name | B1: Link | C1: =HYPERLINK("#'Guide'!A1","Open Guide") -> Open Guide
A2: ScienceDirect | B2: https://www.sciencedirect.com/
A3: SpringerLink | B3: https://link.springer.com/journals
A4: Australasian Journal of Educational Technology | B4: https://ajet.org.au/index.php/AJET/search
A5: Journal of Research on Technology in Education | B5: https://www.tandfonline.com/toc/ujrt20/current
A6: British Journal of Educational Technology | B6: https://bera-journals.onlinelibrary.wiley.com/journal/14678535
A7: Educational Technology & Society | B7: https://www.j-ets.net/home
A8: Internet and Higher Education | B8: https://www.sciencedirect.com/journal/the-internet-and-higher-education
A9: Distance Education | B9: https://www.tandfonline.com/journals/cdie20
A10: EdTech Journal Directory | B10: https://www.edtechjournals.org/
A11: Academia | B11: https://www.academia.edu/
A12: JSTOR | B12: https://www.jstor.org/
A13: DOAJ | B13: https://doaj.org/
... A57: Generative AI in Learning Analytics Systems | B57: https://arxiv.org/abs/2312.00087

Sheet Kajabi tree keywords
A1: Page | B1: KEYWORD | C1: VOLUME | D1: GLOBAL VOLUME | E1: DIFFICULTY | F1: INTENT | G1: TARGETED PAGE | H1: WORD TYPE | I1: FAQ's | M1: FAQ with Answers | P1: =HYPERLINK("#'Guide'!A1","Open Guide") -> Open Guide
A3: Kajabi Course Creation Services | B3: kajabi online course platform​ | C3: 18.1k | D3: 18.1k | E3: 28 | F3: Informational | G3: Kajabi Course Creation Services | H3: Secondary Keyword | I3: How do I create a course in Kajabi? | J3: What is the best platform for course creation? | M3: All the answers are import from Google. These are for the key idea. Make sure to rewrite the answer that should be appealing before going ahead.
B4: kajabi courses​ | C4: 260 | D4: 640 | E4: 23 | F4: Informational | G4: Kajabi Course Creation Services | H4: Secondary Keyword | I4: Is Kajabi good for course creators? | J4: Do you own your content on Kajabi?
B5: how to create a course on kajabi | C5: 30 | D5: 30 | G5: Kajabi Course Creation Services | H5: Secondary Keyword | I5: Can you sell courses directly through Kajabi? | M5: FAQ | N5: Answer | O5: Topic
B6: how to create a course in kajabi​ | C6: 20 | D6: 100 | G6: Kajabi Course Creation Services | H6: Secondary Keyword | I6: Do I need a website if I use Kajabi? | M6: What types of digital products can I create using Kajabi? | N6: With Kajabi, you can create a variety of digital products, including online courses, coaching programs, membership sites, digital downloads, and webinars.The platform offers customizable templates to help you design and deliver your content effectively. | O6: kajabi digital product creation
B7: how to create a kajabi course | C7: 20 | D7: 30 | G7: Kajabi Course Creation Services | H7: Secondary Keyword | I7: Is Kajabi difficult to learn? | M7: Do I need any technical skills to create digital products on Kajabi? | N7: No, you do not need advanced technical skills to create digital products on Kajabi.The platform is user-friendly and designed for ease of use, with drag-and-drop features and step-by-step guides to help you set up your products and website. | O7: kajabi digital product creation
B8: kajabi course creation | C8: 20 | D8: 80 | G8: Kajabi Course Creation Services | H8: Secondary Keyword | I8: Can someone build my Kajabi course for me? | M8: Can I sell my digital products on Kajabi? | N8: es, Kajabi provides built-in sales and marketing tools that allow you to sell your digital products directly from your site.You can set up payment gateways, offer subscription plans, and create marketing funnels to attract and convert customers. | O8: kajabi digital product creation
B9: Kajabi Course Creation Services | G9: Kajabi Course Creation Services | H9: Primary Keyword | I9: Should I hire a Kajabi consultant? | M9: Is there customer support available if I encounter issues while creating products on Kajabi? | N9: Yes, Kajabi offers customer support through various channels, including live chat, email, and a comprehensive help center with tutorials and resources.This ensures you can get assistance whenever you need it while creating your digital products. | O9: kajabi digital product creation
A11: kajabi online course setup | B11: kajabi online course platform​ | C11: 18.1k | D11: 18.1k | E11: 28 | F11: Informational | G11: kajabi online course setup | H11: Secondary Keyword | I11: How do I set up an online course in Kajabi? | J11: How do I create a student-friendly Kajabi course? | M11: What is Kajabi, and why use it for a membership site? | N11: Kajabi is an all-in-one platform designed to help you create, market, and sell online courses, memberships, and digital products easily. It’s great for membership sites because it handles everything—from content hosting to payments—all in one place, so you don't need to juggle multiple tools. | O11: kajabi membership site development
B12: kajabi online courses | C12: 90 | D12: 310 | G12: kajabi online course setup | H12: Secondary Keyword | I12: How long does Kajabi setup take? | J12: How do I create a coaching program in Kajabi? | M12: How do I get started with building a membership site on Kajabi? | N12: First, sign up for a Kajabi account and choose a plan that fits your needs. Then, you can use their pre-built templates or customize your own site. Set up your membership by creating product categories, uploading your content, and organizing it into member-exclusive access areas. | O12: kajabi membership site development
B13: kajabi online course setup | G13: kajabi online course setup | H13: Primary Keyword | I13: Is Kajabi hard to set up? | J13: How do I create a client onboarding course in Kajabi? | M13: Can I customize the look and feel of my Kajabi membership site? | N13: Absolutely! Kajabi offers a variety of themes and customization options so you can match your site to your brand. You can change colors, fonts, layout styles, and add your own logo and images to create a professional and unique experience for your members. | O13: kajabi membership site development
B14: setup online course kajabi | I14: What do I need before creating a Kajabi course? | M14: How do I protect my content so only members can see it? | N14: Kajabi lets you set access rules easily. When you create your membership product, you choose which content is available to paying members. This way, your videos, downloads, and courses are securely locked behind a login. | O14: kajabi membership site development
M15: Do I need technical skills to create a membership site on Kajabi? | N15: No need to be a tech expert. Kajabi is designed with user-friendliness in mind, offering step-by-step guides and customer support. If you run into any trouble, their help team and community forums are great resources. | O15: kajabi membership site development
A16: kajabi course design | B16: kajabi course design best practices for engagement | G16: kajabi course design | H16: Secondary Keyword | I16: Does Kajabi market your course? | J16: What is Kajabi and why should I use it for my course? | M16: Can I track how my membership is performing? | N16: Definitely. Kajabi provides analytics to monitor member engagement, sales, and other key metrics so you can see what’s working and make improvements where needed. | O16: kajabi membership site development
B17: kajabi course design | G17: kajabi course design | H17: Primary Keyword | I17: How do I start designing a course on Kajabi?
B18: done for you kajabi course design | G18: kajabi course design | H18: Secondary Keyword | I18: Can I customize the look and feel of my course? | M18: can you upload course modules to kajabi via api​ | O18: kajabi course upload services
B19: kajabi course designer | G19: kajabi course design | H19: Secondary Keyword | I19: How do I organize my course materials effectively? | M19: Why should I use a Kajabi course upload service? | N19: Save time, ensure a polished, scalable course structure, proper tagging and sequencing, and fewer technical hiccups during launch | O19: kajabi course upload services
M20: What files can you upload to Kajabi? | N20: Videos (MP4), audio, PDFs, slides, quizzes, downloadable resources, and text content. We’ll format and organize them for best learner flow. | O20: kajabi course upload services
A21: kajabi membership site development | B21: kajabi membership site​ | C21: 70 | D21: 330 | E21: 23 | F21: Informational | G21: kajabi membership site development | H21: Secondary Keyword | I21: What is Kajabi, and why use it for a membership site? | M21: How long does a typical Kajabi upload project take? | N21: It depends on course length, but most projects range from 3–10 business days. Exact timeline is confirmed in a project brief. | O21: kajabi course upload services
B22: kajabi membership | C22: 20 | D22: 190 | F22: Informational | G22: kajabi membership site development | H22: Secondary Keyword | I22: How do I get started with building a membership site on Kajabi? | M22: Can you set up quizzes, assignments, and certificates? | N22: Absolutely. We configure quizzes, graded tasks, and completion certificates where Kajabi supports them. | O22: kajabi course upload services
B23: how to create a membership in kajabi | C23: 20 | D23: 30 | G23: kajabi membership site development | H23: Secondary Keyword | I23: Can I customize the look and feel of my Kajabi membership site? | M23: Will you customize templates and pages for my course? | N23: Yes. We tailor landing pages, sales pages, and course templates to match your branding and voice. | O23: kajabi course upload services
B24: kajabi membership site examples​ | C24: 70 | D24: 150 | E24: 0 | F24: Informational | G24: kajabi membership site development | H24: Secondary Keyword | I24: How do I protect my content so only members can see it? | M24: Can you optimize SEO and discoverability on Kajabi? | N24: We optimize titles, descriptions, keywords, hero images, and meta data to improve search visibility inside and outside Kajabi. | O24: kajabi course upload services
B25: how to cancel kajabi membership​ | C25: 20 | D25: 20 | G25: kajabi membership site development | H25: Secondary Keyword | I25: Do I need technical skills to create a membership site on Kajabi? | M25: Do you handle revisions or edits after uploads? | N25: Yes. Most services include a revision window. Additional edits may incur a small fee depending on scope. | O25: kajabi course upload services
B26: kajabi membership site development | G26: kajabi membership site development | H26: Primary Keyword | I26: Can I track how my membership is performing? | M26: How do you protect my content and confidentiality? | N26: Share a brief of your course assets and goals (video count, resources, pages). We’ll propose a plan, timeline, and quote, then begin after approval. | O26: kajabi course upload services
A28: kajabi coaching program setup | B28: kajabi coaching program setup guide | G28: kajabi coaching program setup | H28: Secondary Keyword | I28: How Do I Set Up a Kajabi Coaching Program? | J28: What are the 5 C's in coaching? | M28: What are some best practices for Kajabi training? | N28: Start with a clear product and pricing plan, use pipelines to bootstrap launches, automate welcome emails, segment your audience, and regularly update content based on student feedback. | O28: kajabi training platform
B29: kajabi coaching program setup for beginners | G29: kajabi coaching program setup | H29: Secondary Keyword | I29: How Long Does It Take to Set Up Kajabi Coaching? | J29: What are the 3 C's of coaching? | M29: What type of platform is Kajabi? | N29: Kajabi was built as a business platform for knowledge entrepreneurs. Courses are one product type among several. On Kajabi, you also build your website, send email campaigns, create sales funnels, run a coaching practice, host a community, manage affiliates, and accept payments. | O29: kajabi training platform
B30: kajabi coaching program | C30: 20 | D30: 40 | F30: Informational | G30: kajabi coaching program setup | H30: Secondary Keyword | I30: What Features Should My Kajabi Coaching Program Have? | J30: What is the golden triangle of coaching? | M30: Which is better, Kajabi or teachable? | N30: Kajabi has more tools and product types. Teachable offers more courses per tier. Kajabi has more expensive plans, but it gives you access to extra products like podcasts in addition to multiple integrations and advanced email marketing tools. However, product numbers and customers are limited per tier. | O30: kajabi training platform
B31: kajabi coaching​ | C31: 30 | D31: 180 | E31: 12 | F31: Informational + navigational | G31: kajabi coaching program setup | H31: Secondary Keyword | I31: Can I Customize My Kajabi Coaching Program?
B32: coaching kajabi​ | C32: 20 | D32: 50 | F32: Informational | G32: kajabi coaching program setup | H32: Secondary Keyword | I32: How to set up a coaching program? | M32: Are there different types of templates in Kajabi? | N32: Yes: course templates (structure), landing/page templates (for sales and branding), email sequence templates, and funnel/templates for onboarding. | O32: kajabi course templates
B33: kajabi coaching platform​ | C33: 70 | D33: 100 | E33: 13 | F33: Informational + navigational | G33: kajabi coaching program setup | H33: Secondary Keyword | I33: What is the 70 30 rule in coaching? | M33: Can I customize a Kajabi course template after applying it? | N33: Absolutely. Templates are starting points and can be edited, renamed, reorganized, and re-styled to fit your brand | O33: kajabi course templates
B34: kajabi coaching program setup | G34: kajabi coaching program setup | H34: Primary Keyword | M34: Can I import a template from another course? | N34: Yes, you can clone or import course content from one product into another, which often includes templates as a base. | O34: kajabi course templates
M35: Do templates work with mobile and responsive design? | N35: Yes, Kajabi templates are designed to be responsive, but you should still test on mobile devices. | O35: kajabi course templates
A36: kajabi digital product creation | B36: kajabi digital products​ | C36: 20 | D36: 50 | G36: kajabi digital product creation | H36: Secondary Keyword | I36: What types of digital products can I create using Kajabi? | M36: Can I use a template for a new niche or language? | N36: Yes, templates are adaptable. You may need to update copy, media, and localization to fit your niche or language. | O36: kajabi course templates
B37: kajabi digital products​ creation guide | G37: kajabi digital product creation | H37: Secondary Keyword | I37: Do I need any technical skills to create digital products on Kajabi? | M37: How do I update or modify a template after launching? | N37: You can edit the course pages, modules, and blocks anytime; changes apply to your live course without breaking students’ progress. | O37: kajabi course templates
B38: kajabi digital products​ creation program | G38: kajabi digital product creation | H38: Secondary Keyword | I38: Can I sell my digital products on Kajabi? | M38: What's the best way to choose a Kajabi template? | N38: Consider your course goals, desired student flow, branding, and whether the template supports your media (video, downloads), assessments, and marketing pages. Test a sample to ensure it meets your needs. | O38: kajabi course templates
B39: how to sell digital products on kajabi | G39: kajabi digital product creation | H39: Secondary Keyword | I39: Is there customer support available if I encounter issues while creating products on Kajabi? | M39: Are there limitations or downsides to using templates? | N39: Templates can speed setup but may require reworking if your course structure is very unique; ensure the template fits your learning path. | O39: kajabi course templates
B40: kajabi digital product setup | G40: kajabi digital product creation | H40: Secondary Keyword
G41: kajabi digital product creation | H41: Primary Keyword | M41: What services are included in Kajabi Website & Funnel Services? | N41: Website and landing page design, funnel planning, product and payment setup, email sequences, automation, lead magnets, SEO basics, and ongoing optimization. | O41: Kajabi Website & Funnel Services
M42: How long does a typical Kajabi website or funnel project take? | N42: Most projects take 2–6 weeks, depending on scope and the number of funnels/pages required. | O42: Kajabi Website & Funnel Services
A43: kajabi drip course setup | B43: kajabi drip content | C43: 20 | D43: 120 | G43: kajabi drip course setup | H43: Secondary Keyword | M43: Do you offer funnel strategy and mapping? | N43: Absolutely. We design a customer journey, map touchpoints, and create automated email/sequences to maximize conversions. | O43: Kajabi Website & Funnel Services
B44: drip content kajabi​ | C44: 20 | D44: 30 | G44: kajabi drip course setup | H44: Secondary Keyword | I44: How to drip content in Kajabi? | J44: How long should a drip take? | M44: How do I start a Kajabi Website & Funnel Services project? | N44: Contact us for a discovery call, share your goals, and we’ll propose a tailored plan and timeline | O44: Kajabi Website & Funnel Services
B45: kajabi drip​ | C45: 20 | D45: 30 | G45: kajabi drip course setup | H45: Secondary Keyword | I45: What is drip course content? | J45: How to set up a drip campaign? | M45: How do Kajabi funnels work? | N45: A Funnel brings marketing and sales together through the power of automation. A Funnel can help drive traffic to your opt-in page, capture lead information, send follow-up content, and ultimately convert visitors into paying customers. With Kajabi, Funnels are designed with pre-built landing pages and email copy. | O45: Kajabi Website & Funnel Services
B46: kajabi drip course setup | G46: kajabi drip course setup | H46: Primary Keyword | I46: How long should a drip campaign last? | J46: What is the 30/30 rule for drip irrigation? | M46: What are Kajabi websites? | N46: A Powerful All in one Website Builder. Build a website to connect everything in your business. Create a no code website simply and easily on Kajabi's all in one website builder platform. | O46: Kajabi Website & Funnel Services
M47: Can I build a website with Kajabi? | N47: With Kajabi, you can create and design your website with streamlined templates and highly-customizable page editing features. | O47: Kajabi Website & Funnel Services
A48: kajabi course upload services | B48: kajabi course upload services | G48: kajabi course upload services | H48: Primary Keyword | I48: Why should I use a Kajabi course upload service? | J48: How do I get started? | M48: Do website owners get paid? | N48: Websites can generate income in various ways, depending on what they offer and who they serve. Some rely on advertising, while others earn money through product sales, subscriptions, or partnerships. Many successful sites use a combination of these methods to generate revenue through more than one source | O48: Kajabi Website & Funnel Services
B49: kajabi course upload services Free | G49: kajabi course upload services | H49: Secondary Keyword | I49: What files can you upload to Kajabi? | M49: What are Kajabi "Funnel Services"? | O49: Kajabi Website & Funnel Services
B50: kajabi course upload services for beginner | G50: kajabi course upload services | H50: Secondary Keyword | I50: How long does a typical Kajabi upload project take? | M50: Do I need to hire a Kajabi Expert? | O50: Kajabi Website & Funnel Services
B51: kajabi course upload services blog | G51: kajabi course upload services | H51: Secondary Keyword | I51: Can you set up quizzes, assignments, and certificates? | M51: Where can I find Kajabi Website & Funnel Services? | O51: Kajabi Website & Funnel Services
B52: kajabi course upload services complete | G52: kajabi course upload services | H52: Secondary Keyword | I52: Will you customize templates and pages for my course?
B53: kajabi course upload services cost | G53: kajabi course upload services | H53: Secondary Keyword | I53: Can you optimize SEO and discoverability on Kajabi? | M53: Do I need a designer for Kajabi? | N53: No, Kajabi features a drag-and-drop builder and offers a large library of industry-specific templates, making it accessible even without coding experience. However, many creators hire professionals for custom branding, complex sales funnels, and advanced page layouts. | O53: kajabi website design services
B54: kajabi course upload services Documentation | G54: kajabi course upload services | H54: Secondary Keyword | I54: Do you handle revisions or edits after uploads? | M54: What should a Kajabi website include? | N54: A high-converting Kajabi site should feature a clear homepage, an "About" page, a dedicated storefront for courses/memberships, lead-generation landing pages, and seamlessly integrated checkout pages | O54: kajabi website design services
B55: kajabi course upload services dashboard | G55: kajabi course upload services | H55: Secondary Keyword | I55: How do you protect my content and confidentiality? | M55: What is included in Kajabi website design services? | N55: Custom website design on Kajabi, theme/setup, page templates (home, about, courses, blog), funnels, landing pages, checkout setup, and basic brand alignment | O55: kajabi website design services
M56: Do you design full Kajabi sites or just pages? | N56: we can design a full site (home, about, courses, blog, contact) or optimize/design specific pages and funnels as needed. | O56: kajabi website design services
A57: kajabi training platform | B57: kajabi training platform | G57: kajabi training platform | H57: Primary Keyword | I57: What are some best practices for Kajabi training?
B58: kajabi learning platform | G58: kajabi training platform | H58: Secondary Keyword | I58: What type of platform is Kajabi? | M58: What Kajabi templates should I use for courses? | N58: For selling a course, use the Product Launch funnel blueprint or the Simple Sales Page funnel. These automatically route prospects from a value-driven video or sales page directly to your course checkout | O58: kajabi sales funnel setup
B59: kajabi course platform | G59: kajabi training platform | H59: Secondary Keyword | I59: Which is better, Kajabi or teachable? | M59: How do I test my funnel before going live? | N59: Before launching, copy the funnel URL and paste it into a Chrome Incognito window. Click through the pages, fill out the form, and run a test transaction to make sure the checkout process and email automations work exactly as intended | O59: kajabi sales funnel setup
B60: kajabi online training platform | G60: kajabi training platform | H60: Secondary Keyword | M60: How many funnels can I create? | N60: Your funnel limit is tied to your Kajabi plan. The Basic plan allows for 3 active funnels, while the Growth plan offers up to 15. However, you can always build an infinite amount of standalone landing pages, forms, and offers through your website tab and link them together manually. | O60: kajabi sales funnel setup
B61: kajabi employee training platform | G61: kajabi training platform | H61: Secondary Keyword | M61: Can I attach multiple offers to one sales funnel? | N61: Yes, you can include tiered pricing or multiple offers on a single page. You can add a Pricing Cards section to your funnel's sales page and set the CTA blocks in those cards to link to the corresponding checkout pages. | O61: kajabi sales funnel setup
M62: What is a Kajabi sales funnel? | N62: A guided sequence of pages, emails, and automations designed to convert visitors into customers and upsell them over time. | O62: kajabi sales funnel setup
A63: kajabi course templates | B63: kajabi course templates | C63: 30 | D63: 170 | E63: 14 | F63: Informational | G63: kajabi course templates | H63: Primary Keyword | I63: Are there different types of templates in Kajabi? | M63: Where do I start when building a funnel in Kajabi? | N63: Define your goal, map the customer journey, create a pipeline (funnel) with a landing page, checkout, and follow-up emails, then connect automations. | O63: kajabi sales funnel setup
B64: kajabi course templates free | G64: kajabi course templates | H64: Secondary Keyword | I64: Can I customize a Kajabi course template after applying it? | M64: What is a Kajabi Pipeline? | N64: A pre-built funnel blueprint in Kajabi (e.g., Newsletter, Launch, or Product Launch) you can customize to fit your offer. | O64: kajabi sales funnel setup
B65: best kajabi course templates | G65: kajabi course templates | H65: Secondary Keyword | I65: Can I import a template from another course?
B66: kajabi templates | C66: 260 | D66: 690 | E66: 23 | F66: Commerical | G66: kajabi course templates | H66: Secondary Keyword | I66: Do templates work with mobile and responsive design? | M66: What is the first step to optimize my Kajabi landing page for conversions? | N66: Define your goal and target audience, then map your message to that audience—clear value proposition, benefits, and a single, prominent CTA. | O66: kajabi landing page design
B67: kajabi course template | C67: 20 | D67: 20 | G67: kajabi course templates | H67: Secondary Keyword | I67: Are there limitations or downsides to using templates? | M67: What makes a strong CTA on a Kajabi landing page? | N67: Clarity, urgency, and relevance. Use action verbs, specify the outcome (e.g., “Get the Guide,” “Start Free Trial”), and place the CTA above the fold with a contrasting color. | O67: kajabi landing page design
B68: kajabi themes | C68: 30 | D68: 300 | E68: 17 | F68: navigational | G68: kajabi course templates | H68: Secondary Keyword | I68: Can I use a template for a new niche or language? | M68: Should I use video on my landing page, and where? | N68: Yes. Place a short explainer video near the top or in the hero, with a transcribed caption option. Videos should quickly convey value and demonstrate results. | O68: kajabi landing page design
B69: kajabi website templates | C69: 140 | D69: 320 | E69: 20 | F69: Informational | G69: kajabi course templates | H69: Secondary Keyword | I69: How do I update or modify a template after launching? | M69: How do I design a landing page in Kajabi? | N69: Navigate: From your Kajabi Dashboard, go to Website > Pages > Landing Pages.Choose a Template: Select from Kajabi’s free library (sales pages, opt-ins, podcast links, waitlists) or start with a Blank Canvas.Customize: Click on any element (headlines, buttons, videos) to edit text, colors, and spacing in the drag-and-drop editor.Optimize: Always toggle to mobile view to adjust sizes and ensure it looks clean on mobile devices | O69: kajabi landing page design
B70: kajabi website themes​ | C70: 20 | D70: 40 | G70: kajabi course templates | H70: Secondary Keyword | I70: What's the best way to choose a Kajabi template? | M70: How do I increase conversions on a Kajabi landing page? | N70: Remove Distractions: Hide the standard site header and footer on sales and opt-in pages so visitors focus solely on your goal.Craft a Strong Headline: Use a formula like "How to [Desired Outcome] without [Undesired Action]".Include Trust Signals: Add testimonials, guarantee badges, or social proof right before your final Call to Action (CTA) button.Make CTAs Stand Out: Use high-contrast colors for your buttons and use actionable text (e.g., "Start Your Free Trial" instead of "Submit") | O70: kajabi landing page design
B71: kajabi email templates | C71: 50 | D71: 130 | E71: 14 | F71: Informational | G71: kajabi course templates | H71: Secondary Keyword | M71: How do I set a landing page as my homepage? | N71: If you want visitors to see your new landing page immediately when they go to your URL:Go to Settings from your Kajabi Dashboard.Click Site Details.Scroll down to the Homepage dropdown menu.Select the landing page you want to display, then click Save | O71: kajabi landing page design
A73: Kajabi Website & Funnel Services | B73: kajabi funnels​ | C73: 20 | D73: 220 | G73: Kajabi Website & Funnel Services | H73: Primary Keyword
B74: sales funnel website template | C74: 40 | D74: 190 | E74: 4 | F74: Transactional
B75: difference between click funnels and kajabi​ | G75: Kajabi Website & Funnel Services | H75: Secondary Keyword
B76: kajabi funnel templates​ | G76: Kajabi Website & Funnel Services | H76: Secondary Keyword
B77: kajabi funnel page templates​ | G77: Kajabi Website & Funnel Services | H77: Secondary Keyword
B78: kajabi mini-course funnel templates​ | G78: Kajabi Website & Funnel Services | H78: Secondary Keyword
B79: add kajabi product to click funnels​ | G79: Kajabi Website & Funnel Services | H79: Secondary Keyword
B80: how to add a kajabi product to click funnels​ | G80: Kajabi Website & Funnel Services | H80: Secondary Keyword
B81: add a kajabi product to click funnels | G81: Kajabi Website & Funnel Services | H81: Secondary Keyword
B82: kajabi sales funnel | C82: 20 | D82: 70 | G82: Kajabi Website & Funnel Services | H82: Secondary Keyword
B83: sales funnel kajabi​ | G83: Kajabi Website & Funnel Services | H83: Secondary Keyword
B84: kajabi sales funnel template​ | G84: Kajabi Website & Funnel Services | H84: Secondary Keyword
B85: using kajabi for sales funnel​ | G85: Kajabi Website & Funnel Services | H85: Secondary Keyword
B86: best funnels to use on kajabi​ | G86: Kajabi Website & Funnel Services | H86: Secondary Keyword
B87: how to use kajabi like deadline funnel​ | G87: Kajabi Website & Funnel Services | H87: Secondary Keyword
B88: kajabi website expert​ | C88: 70 | D88: 70 | E88: 9 | F88: Commercial | G88: Kajabi Website & Funnel Services | H88: Secondary Keyword
B89: kajabi website template​ | C89: 40 | D89: 60 | E89: 9 | G89: Kajabi Website & Funnel Services | H89: Secondary Keyword
B90: kajabi website​ | C90: 390 | D90: 820 | E90: 21 | F90: Navigational | G90: Kajabi Website & Funnel Services | H90: Primary Keyword
B91: kajabi website themes​ | C91: 20 | D91: 40 | G91: Kajabi Website & Funnel Services | H91: Secondary Keyword
B92: kajabi change website theme​ | G92: Kajabi Website & Funnel Services | H92: Secondary Keyword
B93: how do you change your website theme on kajabi​ | G93: Kajabi Website & Funnel Services | H93: Secondary Keyword
A95: kajabi website design services | B95: kajabi website design​ | C95: 0 | D95: 30 | G95: kajabi website design services | H95: Secondary Keyword
B96: new kajabi website designers | G96: kajabi website design services | H96: Secondary Keyword
B97: design kajabi website​ | G97: kajabi website design services | H97: Secondary Keyword
B98: kajabi website design templates​ | C98: 20 | D98: 20 | G98: kajabi website design services | H98: Secondary Keyword
B99: kajabi website designer​ | C99: 20 | D99: 130 | G99: kajabi website design services | H99: Secondary Keyword
B100: kajabi website design for coaches​ | G100: kajabi website design services | H100: Secondary Keyword
B101: kajabi website design templates​ | C101: 20 | D101: 20 | G101: kajabi website design services | H101: Secondary Keyword
B102: kajabi website examples | C102: 260 | D102: 510 | E102: 7 | F102: Commercial | G102: kajabi website design services | H102: Secondary Keyword
B103: kajabi website developer | C103: 40 | D103: 40 | E103: 7 | F103: Informational | G103: kajabi website design services | H103: Secondary Keyword
B104: kajabi website design services | G104: kajabi website design services | H104: Primary Keyword
A106: kajabi sales funnel setup | B106: kajabi sales funnel setup | C106: 20 | D106: 70 | G106: kajabi sales funnel setup | H106: Primary Keyword
...

Sheet Ai Qs
A1: Topic | B1: Question | C1: Source / Reference | D1: =HYPERLINK("#'Guide'!A1","Open Guide") -> Open Guide
A2: Course Building | B2: What is the step-by-step process to build an online course? | C2: Quora Online Course Creation
A3: Course Building | B3: Should I use Storyline, Rise, or Canva to create my course? | C3: Reddit r/InstructionalDesign
A4: Course Building | B4: How many modules should a good online course have? | C4: Facebook Course Creator Community
A5: Course Building | B5: How do I turn a PowerPoint into a fully interactive course? | C5: LinkedIn eLearning Groups
A6: Course Building | B6: How can I write strong learning objectives for my course? | C6: Quora Instructional Design Discussions
A7: Course Building | B7: How do I choose the right course format—video, slides, or interactive? | C7: LinkedIn Course Creator Groups
A8: Course Building | B8: How do I script content for an online training module? | C8: Quora Instructional Design Discussions
A9: Course Building | B9: How do I design assessments and quizzes for my online course? | C9: Reddit r/InstructionalDesign
A10: Course Building | B10: How do I create scenario-based learning in a course? | C10: Facebook L&D Community
